Workbook
Name Hols: Static!$A$1:$A$29

Sheet H
A1: Entity Name | B1: Valuation First Level | C1: Valuation Second Level | D1: i Issue Name | E1: PrimaryAssetID | F1: Issue Description | G1: Original Nominal | H1: Clean Book Value | I1: Clean Market Value | J1: Accrued Income | K1: Dividend Receivable | L1: Sum of Market Value Income | M1: Market Price /Yield | N1: % of Total Market Value | O1: Next Coupon Date | P1: Maturity Date | Q1: Coupon | R1: Duration | S1: Modified Duration | T1: Investment Type | U1: Security Type | V1: Sub Security Type | W1: CCY | X1: Sector | Y1: Supersector | Z1: Industry | AA1: Issuer Rating | AB1: Security Rating | AC1: NACA Yield | AD1: NACM Yield | AE1: Weighted Avg NACA Yield | AF1: Weighted Avg NACM Yield | AG1: Market Value % | AH1: Current Exposure | AI1: Current Exposure % | AJ1: i Position Effective Date | AK1: Entity ID | AL1: Weighted Average NACS Yield | AM1: Weighted Average Coupon | AN1: Weighted Modified Duration | AO1: Issuer | AP1: ISIN Code | AQ1: Ticker
A2: 27four Life - Pos Ret | B2: BONDS | C2: Bonds (3 - 7 Years) | D2: LBK28 10.565% 150528 | E2: LBK28 | F2: LBK28 10.565% 150528 | G2: 712800 | H2: 723195.45 | I2: 669940.9 | J2: 32805.11 | K2: 0 | L2: 702746.01 | M2: 11.88 | N2: 0.00159882 | O2: 44697 | P2: 46888 | Q2: 10.565 | R2: 4.73 | S2: 4.4668326 | T2: FI | U2: FI | V2: VB | W2: ZAR | AA2: AA+ | AC2: 12.232836 | AD2: 11.596214 | AE2: 12.23 | AF2: 11.596214 | AG2: 2.41 | AH2: 702746.01 | AI2: 0 | AJ2: 44673 | AK2: PLPRNA | AL2: 11.88 | AM2: 10.56 | AN2: 4.47 | AO2: LANDBANK | AP2: ZAG000151275 | AQ2: LBK28
A3: 27four Life - Pos Ret | B3: BONDS | C3: Bonds (3 - 7 Years) | D3: RSA 10.50% R186 211226 | E3: R186 | F3: RSA 10.50% R186 211226 | G3: 5700000 | H3: 6355488.9 | I3: 6192648.2 | J3: 201686.3 | K3: 0 | L3: 6394334.5 | M3: 8.225 | N3: 0.0145478 | O3: 44733 | P3: 46377 | Q3: 10.5 | R3: 3.72 | S3: 3.572673 | T3: FI | U3: FI | V3: VB | W3: ZAR | X3: GOVI | AA3: AAA | AC3: 8.3941266 | AD3: 8.0875032 | AE3: 8.39 | AF3: 8.0875032 | AG3: 21.96 | AH3: 6394334.5 | AI3: 0.01 | AJ3: 44673 | AK3: PLPRNA | AL3: 8.23 | AM3: 10.5 | AN3: 3.57 | AO3: REP OF SOUTH AFRICA | AP3: ZAG000016320 | AQ3: R186
A4: 27four Life - Pos Ret | B4: BONDS | C4: Bonds (7 - 12 Years) | D4: Transnet 10.50% TN30 091030 | E4: TN30 | F4: Transnet 10.50% TN30 091030 | G4: 250000 | H4: 249155.29 | I4: 239047.7 | J4: 863.01 | K4: 0 | L4: 239910.71 | M4: 11.316 | N4: 0.00054582 | O4: 44844 | P4: 47765 | Q4: 10.5 | R4: 5.71 | S4: 5.4077134 | T4: FI | U4: FI | V4: VB | W4: ZAR | AA4: AA+ | AC4: 11.63613 | AD4: 11.058095 | AE4: 11.64 | AF4: 11.058095 | AG4: 0.82 | AH4: 239910.71 | AI4: 0 | AJ4: 44673 | AK4: PLPRNA | AL4: 11.32 | AM4: 10.5 | AN4: 5.41 | AO4: TRANSNET SOC LTD | AP4: ZAG000120312 | AQ4: TN30
A5: 27four Life - Pos Ret | B5: BONDS | C5: Bonds (Greater than 12 Years) | D5: R2048 8.75% 280248 | E5: R2048 | F5: R2048 8.75% 280248 | G5: 800000 | H5: 643705.51 | I5: 657589.12 | J5: 10571.92 | K5: 0 | L5: 668161.04 | M5: 10.805 | N5: 0.00152014 | O5: 44804 | P5: 54116 | Q5: 8.75 | R5: 9.22 | S5: 8.7507642 | T5: FI | U5: FI | V5: VB | W5: ZAR | X5: GOVI | AA5: AAA | AC5: 11.09687 | AD5: 10.56951 | AE5: 11.1 | AF5: 10.56951 | AG5: 2.29 | AH5: 668161.04 | AI5: 0 | AJ5: 44673 | AK5: PLPRNA | AL5: 10.8 | AM5: 8.75 | AN5: 8.75 | AO5: REP OF SOUTH AFRICA | AP5: ZAG000096173 | AQ5: R2048
A6: 27four Life - Pos Ret | B6: BONDS | C6: Bonds (Greater than 12 Years) | D6: RSA 8.50% R2037 310137 | E6: R2037 | F6: RSA 8.50% R2037 310137 | G6: 770000 | H6: 643445.5 | I6: 643822.03 | J6: 14494.25 | K6: 0 | L6: 658316.28 | M6: 10.735 | N6: 0.00149774 | O6: 44774 | P6: 50071 | Q6: 8.5 | R6: 7.91 | S6: 7.5106017 | T6: FI | U6: FI | V6: VB | W6: ZAR | X6: GOVI | AA6: AAA | AC6: 11.023101 | AD6: 10.502504 | AE6: 11.02 | AF6: 10.502504 | AG6: 2.26 | AH6: 658316.28 | AI6: 0 | AJ6: 44673 | AK6: PLPRNA | AL6: 10.73 | AM6: 8.5 | AN6: 7.51 | AO6: REP OF SOUTH AFRICA | AP6: ZAG000107012 | AQ6: R2037
A7: 27four Life - Pos Ret | B7: BONDS | C7: Bonds (Greater than 12 Years) | D7: Transnet 10.75% TN40 091040 | E7: TN40 | F7: Transnet 10.75% TN40 091040 | G7: 750000 | H7: 689768.42 | I7: 678319.58 | J7: 3092.47 | K7: 0 | L7: 681412.05 | M7: 12.05 | N7: 0.00155029 | O7: 44844 | P7: 51418 | Q7: 10.75 | R7: 7.89 | S7: 7.4432484 | T7: FI | U7: FI | V7: VB | W7: ZAR | X7: CR | AA7: AA+ | AC7: 12.413006 | AD7: 11.758178 | AE7: 12.41 | AF7: 11.758178 | AG7: 2.34 | AH7: 681412.05 | AI7: 0 | AJ7: 44673 | AK7: PLPRNA | AL7: 12.05 | AM7: 10.75 | AN7: 7.44 | AO7: TRANSNET SOC LTD | AP7: ZAG000120320 | AQ7: TN40
A8: 27four Life - Pos Ret | B8: BONDS | C8: Inflation Linked Bonds | D8: I2038 2.25% 310138 | E8: I2038 | F8: I2038 2.25% 310138 | G8: 560000 | H8: 721108.82 | I8: 724140.52 | J8: 4535.56 | K8: 0 | L8: 728676.08 | M8: 3.9 | N8: 0.00165782 | O8: 44774 | P8: 50436 | Q8: 2.25 | R8: 12.94 | S8: 12.689805 | T8: FI | U8: FI | V8: ILB | W8: ZAR | X8: GOVI | AA8: AAA | AC8: 3.938025 | AD8: 3.868685 | AE8: 3.94 | AF8: 3.868685 | AG8: 2.5 | AH8: 728676.08 | AI8: 0 | AJ8: 44673 | AK8: PLPRNA | AL8: 3.9 | AM8: 2.25 | AN8: 12.69 | AO8: REP OF SOUTH AFRICA | AP8: ZAG000096595 | AQ8: I2038
A9: 27four Life - Pos Ret | B9: BONDS | C9: Inflation Linked Bonds | D9: I2046 2.50% 310346 | E9: I2046 | F9: I2046 2.50% 310346 | G9: 610000 | H9: 717046.87 | I9: 721712.48 | J9: 1451.21 | K9: 0 | L9: 723163.69 | M9: 3.9 | N9: 0.00164528 | O9: 44834 | P9: 53417 | Q9: 2.5 | R9: 17.22 | S9: 16.886632 | T9: FI | U9: FI | V9: ILB | W9: ZAR | X9: GOVI | AA9: AAA | AC9: 3.938025 | AD9: 3.868685 | AE9: 3.94 | AF9: 3.868685 | AG9: 2.48 | AH9: 723163.69 | AI9: 0 | AJ9: 44673 | AK9: PLPRNA | AL9: 3.9 | AM9: 2.5 | AN9: 16.89 | AO9: REP OF SOUTH AFRICA | AP9: ZAG000106980 | AQ9: I2046
A10: 27four Life - Pos Ret | B10: BONDS | C10: Inflation Linked Bonds | D10: I2050 2.25% 2050 | E10: I2050 | F10: I2050 2.25% 2050 | G10: 670000 | H10: 799864.37 | I10: 814726.49 | J10: 8301.19 | K10: 0 | L10: 823027.68 | M10: 3.9 | N10: 0.00187248 | O10: 44742 | P10: 55153 | Q10: 2.5 | R10: 19.05 | S10: 18.689624 | T10: FI | U10: FI | V10: ILB | W10: ZAR | X10: GOVI | AA10: AAA | AC10: 3.938025 | AD10: 3.868685 | AE10: 3.94 | AF10: 3.868685 | AG10: 2.83 | AH10: 823027.68 | AI10: 0 | AJ10: 44673 | AK10: PLPRNA | AL10: 3.9 | AM10: 2.5 | AN10: 18.69 | AO10: REP OF SOUTH AFRICA | AP10: ZAG000096603 | AQ10: I2050
A11: 27four Life - Pos Ret | B11: BONDS | C11: Inflation Linked Bonds | D11: RSA 1.875% I2033 280233 | E11: I2033 | F11: RSA 1.875% I2033 280233 | G11: 630000 | H11: 714819.35 | I11: 712992.51 | J11: 2387.12 | K11: 0 | L11: 715379.63 | M11: 3.82 | N11: 0.00162757 | O11: 44804 | P11: 48638 | Q11: 1.875 | R11: 9.71 | S11: 9.5277219 | T11: FI | U11: FI | V11: ILB | W11: ZAR | X11: GOVI | AA11: AAA | AC11: 3.856481 | AD11: 3.7899493 | AE11: 3.86 | AF11: 3.7899493 | AG11: 2.46 | AH11: 715379.63 | AI11: 0 | AJ11: 44673 | AK11: PLPRNA | AL11: 3.82 | AM11: 1.88 | AN11: 9.53 | AO11: REP OF SOUTH AFRICA | AP11: ZAG000125998 | AQ11: I2033
A12: 27four Life - Pos Ret | B12: CASH | C12: Cash on Call | D12: Prescient Money Market Fund B3 | E12: PRMFB3 | F12: Prescient Money Market Fund B3 | G12: 641852.67 | H12: 641852.68 | I12: 641852.68 | J12: 2058.36 | K12: 0 | L12: 643911.04 | N12: 0.00146497 | O12: 40756 | P12: 73020 | Q12: 0 | T12: FI | U12: CIS | V12: CSH | W12: ZAR | AE12: 0 | AF12: 0 | AG12: 2.21 | AH12: 643911.04 | AI12: 0 | AJ12: 44673 | AK12: PLPRNA | AL12: 0 | AM12: 0 | AN12: 0 | AP12: ZAE000140885 | AQ12: PRMFB3
A13: 27four Life - Pos Ret | B13: CASH | C13: Safex Margin Deposits | D13: SAFEX Margin | E13: SAFEX | F13: Margin Account | G13: 922517 | H13: 922517 | I13: 922517 | J13: 3253.23 | K13: 0 | L13: 925770.23 | M13: 6.88 | N13: 0.00210623 | P13: 55153 | Q13: 6.88 | R13: 0.08 | S13: 0.002600675 | T13: ST | U13: CSH | V13: MARGIN | W13: ZAR | AE13: 0 | AF13: 0 | AG13: 3.18 | AH13: 925770.23 | AI13: 0 | AJ13: 44673 | AK13: PLPRNA | AL13: 0 | AM13: 6.88 | AN13: 0 | AO13: SAFEX | AQ13: SAFEX
A14: 27four Life - Pos Ret | B14: CASH | C14: Traded Cash | D14: Interest on Cash ZAR | E14: INTRZAR | F14: Interest on Cash | G14: 0 | H14: 0 | I14: 0 | J14: 0 | K14: 0 | L14: 312.49 | N14: 7.1e-07 | R14: 0.08 | T14: CASH | U14: CSH | W14: ZAR | AC14: 5.116339 | AD14: 5.0001425 | AE14: 5.12 | AF14: 5.0001425 | AG14: 0 | AH14: 312.49 | AI14: 0 | AJ14: 44673 | AK14: PLPRNA | AL14: 5.05 | AM14: 0 | AN14: 0
A15: 27four Life - Pos Ret | B15: CASH | C15: Traded Cash | D15: South African Rand | E15: CASHZAR | F15: South African Rand | G15: 311922.04 | H15: 311921.48 | I15: 311922.04 | J15: 0 | K15: 0 | L15: 311922.04 | N15: 0.00070966 | R15: 0.08 | T15: CASH | U15: CRNY | W15: ZAR | AC15: 5.116339 | AD15: 5.0001425 | AE15: 5.12 | AF15: 5.0001425 | AG15: 1.07 | AH15: 311922.04 | AI15: 0 | AJ15: 44673 | AK15: PLPRNA | AL15: 5.05 | AM15: 0 | AN15: 0 | AQ15: ZAR
A16: 27four Life - Pos Ret | B16: CASH | C16: Unsettled Cash | D16: Audit Fee | E16: AUDITFEE | F16: Audit Fee | G16: -12118.12 | H16: -12118.12 | I16: -12118.12 | J16: 0 | L16: -12118.12 | N16: -2.757e-05 | P16: 73051 | Q16: 0 | R16: 0.08 | T16: CASH | U16: EXP | W16: ZAR | AC16: 5.116339 | AD16: 5.0001425 | AE16: 5.12 | AF16: 5.0001425 | AG16: -0.04 | AH16: -12118.12 | AI16: 0 | AJ16: 44673 | AK16: PLPRNA | AL16: 5.05 | AM16: 0 | AN16: 0
A17: 27four Life - Pos Ret | B17: CASH | C17: Unsettled Cash | D17: Management Fee | E17: MGMTFEE | G17: -2499.98 | H17: -2499.98 | I17: -2499.98 | J17: 0 | L17: -2499.98 | N17: -5.69e-06 | P17: 73051 | Q17: 0 | R17: 0.08 | T17: CASH | W17: ZAR | AC17: 5.116339 | AD17: 5.0001425 | AE17: 5.12 | AF17: 5.0001425 | AG17: -0.01 | AH17: -2499.98 | AI17: 0 | AJ17: 44673 | AK17: PLPRNA | AL17: 5.05 | AM17: 0 | AN17: 0
A18: 27four Life - Pos Ret | B18: CASH | C18: Unsettled Cash | D18: Other Fee | E18: OTHFEE | G18: -3039.6 | H18: -3039.6 | I18: -3039.6 | J18: 0 | L18: -3039.6 | N18: -6.92e-06 | P18: 73051 | Q18: 0 | R18: 0.08 | T18: CASH | W18: ZAR | AC18: 5.116339 | AD18: 5.0001425 | AE18: 5.12 | AF18: 5.0001425 | AG18: -0.01 | AH18: -3039.6 | AI18: 0 | AJ18: 44673 | AK18: PLPRNA | AL18: 5.05 | AM18: 0 | AN18: 0
A19: 27four Life - Pos Ret | B19: CASH | C19: Unsettled Cash | D19: Variation Margin | E19: VARMARG | G19: -270103.1 | H19: -270103.1 | I19: -270103.1 | J19: 0 | L19: -270103.1 | N19: -0.00061451 | P19: 73051 | Q19: 0 | R19: 0.08 | T19: CASH | W19: ZAR | AC19: 5.116339 | AD19: 5.0001425 | AE19: 5.12 | AF19: 5.0001425 | AG19: -0.93 | AH19: -270103.1 | AI19: 0 | AJ19: 44673 | AK19: PLPRNA | AL19: 5.05 | AM19: 0 | AN19: 0
A20: 27four Life - Pos Ret | B20: COLLECTIVE INVESTMENT SCHEMES | C20: Domestic | D20: Prescient Flexible Fixed Interest Fund B3 | E20: PFFB3 | F20: Prescient Flexible Fixed Interest Fund B3 | G20: 4898432.2 | H20: 5152718.6 | I20: 5088001.5 | J20: 0 | K20: 0 | L20: 5088001.5 | M20: 1.0387 | N20: 0.01157575 | T20: EQ | U20: CIS | V20: CIS | W20: ZAR | AE20: 0 | AF20: 0 | AG20: 17.48 | AH20: 5088001.5 | AI20: 0.01 | AJ20: 44673 | AK20: PLPRNA | AL20: 0 | AM20: 0 | AN20: 0 | AP20: ZAE000222469 | AQ20: PFFB3
A21: 27four Life - Pos Ret | B21: COLLECTIVE INVESTMENT SCHEMES | C21: Domestic | D21: Prescient Income Plus Fund B3 | E21: PLUSB3 | F21: Prescient Income Plus Fund B3 | G21: 2968566.7 | H21: 2974464.9 | I21: 2985190.7 | J21: 0 | K21: 0 | L21: 2985190.7 | M21: 1.0056 | N21: 0.00679163 | T21: EQ | U21: CIS | V21: CIS | W21: ZAR | AE21: 0 | AF21: 0 | AG21: 10.25 | AH21: 2985190.7 | AI21: 0.01 | AJ21: 44673 | AK21: PLPRNA | AL21: 0 | AM21: 0 | AN21: 0 | AP21: ZAE000284303 | AQ21: PLUSB3
A22: 27four Life - Pos Ret | B22: COLLECTIVE INVESTMENT SCHEMES | C22: Domestic | D22: Prescient Property Equity Fund B3 | E22: PPEB3 | F22: Prescient Property Equity Fund B3 | G22: 2338538.6 | H22: 1974323.8 | I22: 2347892.7 | J22: 0 | K22: 0 | L22: 2347892.7 | M22: 1.004 | N22: 0.00534171 | T22: EQ | U22: CIS | V22: CIS | W22: ZAR | AE22: 0 | AF22: 0 | AG22: 8.06 | AH22: 2347892.7 | AI22: 0.01 | AJ22: 44673 | AK22: PLPRNA | AL22: 0 | AM22: 0 | AN22: 0 | AP22: ZAE000140117 | AQ22: PPEB3
A23: 27four Life - Pos Ret | B23: DERIVATIVES | C23: Equity Derivatives | D23: 15DEC22 ALSI | E23: 15DEC22 ALSI | F23: 15DEC22 ALSI | G23: -12 | H23: 0 | I23: 0 | J23: 0 | K23: 0 | L23: 0 | M23: 65943 | N23: 0 | P23: 44910 | T23: FT | U23: DER | V23: IDXFT | W23: ZAR | AE23: 0 | AF23: 0 | AG23: 0 | AH23: -7913160 | AI23: -0.02 | AJ23: 44673 | AK23: PLPRNA | AL23: 0 | AM23: 0 | AN23: 0 | AP23: ZAD000277689 | AQ23: 15DEC22 ALSI
A24: 27four Life - Pos Ret | B24: DERIVATIVES | C24: Equity Derivatives | D24: 15DEC22 ALSI 70000C | E24: 15DEC22 ALSI 70000C | F24: 15DEC22 ALSI 70000C | G24: 21 | H24: 0 | I24: 0 | J24: 0 | K24: 0 | L24: 0 | M24: 23175 | N24: 0 | P24: 44910 | T24: OP | U24: DER | V24: IDXOP | W24: ZAR | AE24: 0 | AF24: 0 | AG24: 0 | AH24: 5146819.8 | AI24: 0.01 | AJ24: 44673 | AK24: PLPRNA | AL24: 0 | AM24: 0 | AN24: 0 | AP24: ZADA00256149 | AQ24: 15DEC22 ALSI 70000C
A25: 27four Life - Pos Ret | B25: DERIVATIVES | C25: Equity Derivatives | D25: 15JUN22 ALSI | E25: 15JUN22 ALSI | F25: 15JUN22 ALSI | G25: 15 | H25: 0 | I25: 0 | J25: 0 | K25: 0 | L25: 0 | M25: 65704 | N25: 0 | P25: 44727 | T25: FT | U25: DER | V25: IDXFT | W25: ZAR | AE25: 0 | AF25: 0 | AG25: 0 | AH25: 9855600 | AI25: 0.02 | AJ25: 44673 | AK25: PLPRNA | AL25: 0 | AM25: 0 | AN25: 0 | AP25: ZAD000277663 | AQ25: 15JUN22 ALSI
A26: 27four Life - Pos Ret | B26: DERIVATIVES | C26: Equity Derivatives | D26: 15JUN22 ALSI 63000P | E26: 15JUN22 ALSI 63000P | F26: 15JUN22 ALSI 63000P | G26: -4 | H26: 0 | I26: 0 | J26: 0 | K26: 0 | L26: 0 | M26: 11809 | N26: 0 | P26: 44727 | T26: OP | U26: DER | V26: IDXOP | W26: ZAR | AE26: 0 | AF26: 0 | AG26: 0 | AH26: 795312.24 | AI26: 0 | AJ26: 44673 | AK26: PLPRNA | AL26: 0 | AM26: 0 | AN26: 0 | AP26: ZADA00255067 | AQ26: 15JUN22 ALSI 63000P
A27: 27four Life - Pos Ret | B27: DERIVATIVES | C27: Equity Derivatives | D27: 15JUN22 ALSI 74000C | E27: 15JUN22 ALSI 74000C | F27: 15JUN22 ALSI 74000C | G27: -10 | H27: 0 | I27: 0 | J27: 0 | K27: 0 | L27: 0 | M27: 615 | N27: 0 | P27: 44727 | T27: OP | U27: DER | V27: IDXOP | W27: ZAR | AE27: 0 | AF27: 0 | AG27: 0 | AH27: -241880.94 | AI27: 0 | AJ27: 44673 | AK27: PLPRNA | AL27: 0 | AM27: 0 | AN27: 0 | AP27: ZADA00254565 | AQ27: 15JUN22 ALSI 74000C
A28: 27four Life - Pos Ret | B28: DERIVATIVES | C28: Equity Derivatives | D28: 15SEP22 ALSI | E28: 15SEP22 ALSI | F28: 15SEP22 ALSI | G28: -4 | H28: 0 | I28: 0 | J28: 0 | K28: 0 | L28: 0 | M28: 65741 | N28: 0 | P28: 44819 | T28: FT | U28: DER | V28: IDXFT | W28: ZAR | AE28: 0 | AF28: 0 | AG28: 0 | AH28: -2629640 | AI28: -0.01 | AJ28: 44673 | AK28: PLPRNA | AL28: 0 | AM28: 0 | AN28: 0 | AP28: ZAD000277671 | AQ28: 15SEP22 ALSI
A29: 27four Life - Pos Ret | B29: DERIVATIVES | C29: Equity Derivatives | D29: 15SEP22 ALSI 69000C | E29: 15SEP22 ALSI 69000C | F29: 15SEP22 ALSI 69000C | G29: 11 | H29: 0 | I29: 0 | J29: 0 | K29: 0 | L29: 0 | M29: 17668 | N29: 0 | P29: 44819 | T29: OP | U29: DER | V29: IDXOP | W29: ZAR | AE29: 0 | AF29: 0 | AG29: 0 | AH29: 2607657.7 | AI29: 0.01 | AJ29: 44673 | AK29: PLPRNA | AL29: 0 | AM29: 0 | AN29: 0 | AP29: ZADA00259275 | AQ29: 15SEP22 ALSI 69000C
A30: 27four Life - Pos Ret | B30: DERIVATIVES | C30: Equity Derivatives | D30: 15SEP22 ALSI 70000C | E30: 15SEP22 ALSI 70000C | F30: 15SEP22 ALSI 70000C | G30: 12 | H30: 0 | I30: 0 | J30: 0 | K30: 0 | L30: 0 | M30: 14076 | N30: 0 | P30: 44819 | T30: OP | U30: DER | V30: IDXOP | W30: ZAR | AE30: 0 | AF30: 0 | AG30: 0 | AH30: 2449487 | AI30: 0.01 | AJ30: 44673 | AK30: PLPRNA | AL30: 0 | AM30: 0 | AN30: 0 | AP30: ZADA00256511 | AQ30: 15SEP22 ALSI 70000C
A31: 27four Life - Pos Ret | B31: DERIVATIVES | C31: Equity Derivatives | D31: 15SEP22 ALSI 74000C | E31: 15SEP22 ALSI 74000C | F31: 15SEP22 ALSI 74000C | G31: -11 | H31: 0 | I31: 0 | J31: 0 | K31: 0 | L31: 0 | M31: 5097 | N31: 0 | P31: 44819 | T31: OP | U31: DER | V31: IDXOP | W31: ZAR | AE31: 0 | AF31: 0 | AG31: 0 | AH31: -1062695.8 | AI31: 0 | AJ31: 44673 | AK31: PLPRNA | AL31: 0 | AM31: 0 | AN31: 0 | AP31: ZADA00260075 | AQ31: 15SEP22 ALSI 74000C
A32: 27four Life - Pos Ret | B32: DERIVATIVES | C32: Equity Derivatives | D32: 15SEP22 ALSI 77000C | E32: 15SEP22 ALSI 77000C | F32: 15SEP22 ALSI 77000C | G32: -11 | H32: 0 | I32: 0 | J32: 0 | K32: 0 | L32: 0 | M32: 2268 | N32: 0 | P32: 44819 | T32: OP | U32: DER | V32: IDXOP | W32: ZAR | AE32: 0 | AF32: 0 | AG32: 0 | AH32: -546227.36 | AI32: 0 | AJ32: 44673 | AK32: PLPRNA | AL32: 0 | AM32: 0 | AN32: 0 | AP32: ZADA00259283 | AQ32: 15SEP22 ALSI 77000C
A33: 27four Life - Pos Ret | B33: PREFERENCE SHARES | C33: Preference Shares | D33: Absa Bank Ltd Preference Shares | E33: ABSP | F33: Absa Bank Ltd Preference Shares | G33: 1444 | H33: 953083.22 | I33: 1299600 | J33: 0 | K33: 36014.94 | L33: 1335614.9 | M33: 90000 | N33: 0.00303867 | T33: EQ | U33: EQ | V33: PREF | W33: ZAR | AA33: AA+ | AE33: 0 | AF33: 0 | AG33: 4.59 | AH33: 1335614.9 | AI33: 0 | AJ33: 44673 | AK33: PLPRNA | AL33: 0 | AM33: 0 | AN33: 0 | AO33: ABSA BANK LTD | AP33: ZAE000079810 | AQ33: ABSP
A34: 27four Life - Pos Ret | B34: PREFERENCE SHARES | C34: Preference Shares | D34: Discovery B Preference Shares | E34: DSBP | F34: Discovery B Preference Shares | G34: 9852 | H34: 878996.99 | I34: 952195.8 | J34: 0 | K34: 0 | L34: 952195.8 | M34: 9665 | N34: 0.00216635 | T34: EQ | U34: EQ | V34: PREF | W34: ZAR | X34: PREF | AE34: 0 | AF34: 0 | AG34: 3.27 | AH34: 952195.8 | AI34: 0 | AJ34: 44673 | AK34: PLPRNA | AL34: 0 | AM34: 0 | AN34: 0 | AP34: ZAE000158564 | AQ34: DSBP
A35: 27four Life - Pos Ret | B35: PREFERENCE SHARES | C35: Preference Shares | D35: Investec Ltd Preference Share | E35: INPR | F35: Investec Ltd Preference Share | G35: 7038 | H35: 516804.31 | I35: 678040.92 | J35: 0 | K35: 0 | L35: 678040.92 | M35: 9634 | N35: 0.00154262 | T35: EQ | U35: EQ | V35: PREF | W35: ZAR | AE35: 0 | AF35: 0 | AG35: 2.33 | AH35: 678040.92 | AI35: 0 | AJ35: 44673 | AK35: PLPRNA | AL35: 0 | AM35: 0 | AN35: 0 | AP35: ZAE000063814 | AQ35: INPR
A36: 27four Life - Pos Ret | B36: PREFERENCE SHARES | C36: Preference Shares | D36: Netcare Preference Share Ltd | E36: NTCP | F36: Netcare Preference Share Ltd | G36: 2312 | H36: 179077.7 | I36: 198832 | J36: 0 | K36: 0 | L36: 198832 | M36: 8600 | N36: 0.00045236 | T36: EQ | U36: EQ | V36: PREF | W36: ZAR | AE36: 0 | AF36: 0 | AG36: 0.68 | AH36: 198832 | AI36: 0 | AJ36: 44673 | AK36: PLPRNA | AL36: 0 | AM36: 0 | AN36: 0 | AP36: ZAE000081121 | AQ36: NTCP
A37: 27four Life - Pos Ret | B37: PREFERENCE SHARES | C37: Preference Shares | D37: Standard Bank Group Ltd Preference Shares | E37: SBPP | F37: Standard Bank Group Ltd Pref | G37: 5006 | H37: 378277.66 | I37: 462504.34 | J37: 0 | K37: 0 | L37: 462504.34 | M37: 9239 | N37: 0.00105225 | T37: EQ | U37: EQ | V37: PREF | W37: ZAR | AA37: AA+ | AE37: 0 | AF37: 0 | AG37: 1.59 | AH37: 462504.34 | AI37: 0 | AJ37: 44673 | AK37: PLPRNA | AL37: 0 | AM37: 0 | AN37: 0 | AO37: STANDARD BANK LTD | AP37: ZAE000056339 | AQ37: SBPP
A38: 27four Life - Pos Ret | B38: PRIVATE COMPANY | C38: Private Company | D38: Prescient Clean Energy and Infrastructure Debt Fund Trust | E38: PIMEVOA | F38: Prescient Clean Energy and Infrastructure Debt Fund Trust | G38: 1457675 | H38: 1465981.4 | I38: 1459569.9 | J38: 0 | K38: 0 | L38: 1459569.9 | M38: 1.0013 | N38: 0.00332068 | T38: EQ | U38: PRIVATE COMP | V38: OTHER | W38: ZAR | AE38: 0 | AF38: 0 | AG38: 5.01 | AH38: 1459569.9 | AI38: 0 | AJ38: 44673 | AK38: PLPRNA | AL38: 0 | AM38: 0 | AN38: 0 | AQ38: PIMEVOA
A39: 27four Life - Pos Ret | B39: UNKNOWN | C39: UNKNOWN | D39: Synthetic Cash_15DEC22 ALSI | E39: 15DEC22 ALSI | F39: Synthetic Cash_15DEC22 ALSI | G39: -12 | I39: 0 | L39: 0 | N39: 0 | T39: SYTH | U39: SYNCASHFUT | V39: CASH | W39: ZAR | AE39: 0 | AF39: 0 | AG39: 0 | AH39: 7913160 | AI39: 0.02 | AJ39: 44673 | AK39: PLPRNA | AL39: 0 | AM39: 0 | AN39: 0 | AQ39: SYNZAR
A40: 27four Life - Pos Ret | B40: UNKNOWN | C40: UNKNOWN | D40: Synthetic Cash_15DEC22 ALSI 70000C | E40: 15DEC22 ALSI 70000C | F40: Synthetic Cash_15DEC22 ALSI 70000C | G40: 21 | I40: 0 | L40: 0 | N40: 0 | T40: SYTH | U40: SYNCASHOPT | V40: CASH | W40: ZAR | AE40: 0 | AF40: 0 | AG40: 0 | AH40: -5146819.8 | AI40: -0.01 | AJ40: 44673 | AK40: PLPRNA | AL40: 0 | AM40: 0 | AN40: 0 | AQ40: SYNZAR
A41: 27four Life - Pos Ret | B41: UNKNOWN | C41: UNKNOWN | D41: Synthetic Cash_15JUN22 ALSI | E41: 15JUN22 ALSI | F41: Synthetic Cash_15JUN22 ALSI | G41: 15 | I41: 0 | L41: 0 | N41: 0 | T41: SYTH | U41: SYNCASHFUT | V41: CASH | W41: ZAR | AE41: 0 | AF41: 0 | AG41: 0 | AH41: -9855600 | AI41: -0.02 | AJ41: 44673 | AK41: PLPRNA | AL41: 0 | AM41: 0 | AN41: 0 | AQ41: SYNZAR
A42: 27four Life - Pos Ret | B42: UNKNOWN | C42: UNKNOWN | D42: Synthetic Cash_15JUN22 ALSI 63000P | E42: 15JUN22 ALSI 63000P | F42: Synthetic Cash_15JUN22 ALSI 63000P | G42: -4 | I42: 0 | L42: 0 | N42: 0 | T42: SYTH | U42: SYNCASHOPT | V42: CASH | W42: ZAR | AE42: 0 | AF42: 0 | AG42: 0 | AH42: -795312.24 | AI42: 0 | AJ42: 44673 | AK42: PLPRNA | AL42: 0 | AM42: 0 | AN42: 0 | AQ42: SYNZAR
A43: 27four Life - Pos Ret | B43: UNKNOWN | C43: UNKNOWN | D43: Synthetic Cash_15JUN22 ALSI 74000C | E43: 15JUN22 ALSI 74000C | F43: Synthetic Cash_15JUN22 ALSI 74000C | G43: -10 | I43: 0 | L43: 0 | N43: 0 | T43: SYTH | U43: SYNCASHOPT | V43: CASH | W43: ZAR | AE43: 0 | AF43: 0 | AG43: 0 | AH43: 241880.94 | AI43: 0 | AJ43: 44673 | AK43: PLPRNA | AL43: 0 | AM43: 0 | AN43: 0 | AQ43: SYNZAR
A44: 27four Life - Pos Ret | B44: UNKNOWN | C44: UNKNOWN | D44: Synthetic Cash_15SEP22 ALSI | E44: 15SEP22 ALSI | F44: Synthetic Cash_15SEP22 ALSI | G44: -4 | I44: 0 | L44: 0 | N44: 0 | T44: SYTH | U44: SYNCASHFUT | V44: CASH | W44: ZAR | AE44: 0 | AF44: 0 | AG44: 0 | AH44: 2629640 | AI44: 0.01 | AJ44: 44673 | AK44: PLPRNA | AL44: 0 | AM44: 0 | AN44: 0 | AQ44: SYNZAR
A45: 27four Life - Pos Ret | B45: UNKNOWN | C45: UNKNOWN | D45: Synthetic Cash_15SEP22 ALSI 69000C | E45: 15SEP22 ALSI 69000C | F45: Synthetic Cash_15SEP22 ALSI 69000C | G45: 11 | I45: 0 | L45: 0 | N45: 0 | T45: SYTH | U45: SYNCASHOPT | V45: CASH | W45: ZAR | AE45: 0 | AF45: 0 | AG45: 0 | AH45: -2607657.7 | AI45: -0.01 | AJ45: 44673 | AK45: PLPRNA | AL45: 0 | AM45: 0 | AN45: 0 | AQ45: SYNZAR
A46: 27four Life - Pos Ret | B46: UNKNOWN | C46: UNKNOWN | D46: Synthetic Cash_15SEP22 ALSI 70000C | E46: 15SEP22 ALSI 70000C | F46: Synthetic Cash_15SEP22 ALSI 70000C | G46: 12 | I46: 0 | L46: 0 | N46: 0 | T46: SYTH | U46: SYNCASHOPT | V46: CASH | W46: ZAR | AE46: 0 | AF46: 0 | AG46: 0 | AH46: -2449487 | AI46: -0.01 | AJ46: 44673 | AK46: PLPRNA | AL46: 0 | AM46: 0 | AN46: 0 | AQ46: SYNZAR
A47: 27four Life - Pos Ret | B47: UNKNOWN | C47: UNKNOWN | D47: Synthetic Cash_15SEP22 ALSI 74000C | E47: 15SEP22 ALSI 74000C | F47: Synthetic Cash_15SEP22 ALSI 74000C | G47: -11 | I47: 0 | L47: 0 | N47: 0 | T47: SYTH | U47: SYNCASHOPT | V47: CASH | W47: ZAR | AE47: 0 | AF47: 0 | AG47: 0 | AH47: 1062695.8 | AI47: 0 | AJ47: 44673 | AK47: PLPRNA | AL47: 0 | AM47: 0 | AN47: 0 | AQ47: SYNZAR
A48: 27four Life - Pos Ret | B48: UNKNOWN | C48: UNKNOWN | D48: Synthetic Cash_15SEP22 ALSI 77000C | E48: 15SEP22 ALSI 77000C | F48: Synthetic Cash_15SEP22 ALSI 77000C | G48: -11 | I48: 0 | L48: 0 | N48: 0 | T48: SYTH | U48: SYNCASHOPT | V48: CASH | W48: ZAR | AE48: 0 | AF48: 0 | AG48: 0 | AH48: 546227.36 | AI48: 0 | AJ48: 44673 | AK48: PLPRNA | AL48: 0 | AM48: 0 | AN48: 0 | AQ48: SYNZAR
A49: 27four Life - Pos Ret Med | B49: BONDS | C49: Bonds (1 - 3 Years) | D49: Nedbank Group Ltd FRN NGT104 150125 JB3+450 | E49: NGT104 | F49: Nedbank Group Ltd FRN NGT104 150125 JB3+450 | G49: 5200000 | H49: 5308605.6 | I49: 5406405.2 | J49: 5062.09 | K49: 0 | L49: 5411467.2 | M49: 7.16388 | N49: 0.01231167 | O49: 44757 | P49: 45672 | Q49: 8.883 | R49: 0.22 | S49: 0.20744315 | T49: FI | U49: FI | V49: FRN | W49: ZAR | X49: BANKS | AA49: AA | AC49: 7.2921834 | AD49: 7.0592439 | AE49: 7.29 | AF49: 7.0592439 | AG49: 5.04 | AH49: 5411467.2 | AI49: 0.01 | AJ49: 44673 | AK49: PLMED | AL49: 7.16 | AM49: 8.88 | AN49: 0.21 | AO49: NEDBANK LTD | AP49: ZAG000160441 | AQ49: NGT104
A50: 27four Life - Pos Ret Med | B50: BONDS | C50: Bonds (3 - 7 Years) | D50: LBK28 10.565% 150528 | E50: LBK28 | F50: LBK28 10.565% 150528 | G50: 3207600 | H50: 3254953.3 | I50: 3014734.1 | J50: 147622.98 | K50: 0 | L50: 3162357 | M50: 11.88 | N50: 0.0071947 | O50: 44697 | P50: 46888 | Q50: 10.565 | R50: 4.73 | S50: 4.4668326 | T50: FI | U50: FI | V50: VB | W50: ZAR | AA50: AA+ | AC50: 12.232836 | AD50: 11.596214 | AE50: 12.23 | AF50: 11.596214 | AG50: 2.94 | AH50: 3162357 | AI50: 0.01 | AJ50: 44673 | AK50: PLMED | AL50: 11.88 | AM50: 10.56 | AN50: 4.47 | AO50: LANDBANK | AP50: ZAG000151275 | AQ50: LBK28
A51: 27four Life - Pos Ret Med | B51: BONDS | C51: Bonds (3 - 7 Years) | D51: RSA 10.50% R186 211226 | E51: R186 | F51: RSA 10.50% R186 211226 | G51: 19200000 | H51: 21438549 | I51: 20859446 | J51: 679364.38 | K51: 0 | L51: 21538811 | M51: 8.225 | N51: 0.04900311 | O51: 44733 | P51: 46377 | Q51: 10.5 | R51: 3.72 | S51: 3.572673 | T51: FI | U51: FI | V51: VB | W51: ZAR | X51: GOVI | AA51: AAA | AC51: 8.3941266 | AD51: 8.0875032 | AE51: 8.39 | AF51: 8.0875032 | AG51: 20.05 | AH51: 21538811 | AI51: 0.05 | AJ51: 44673 | AK51: PLMED | AL51: 8.23 | AM51: 10.5 | AN51: 3.57 | AO51: REP OF SOUTH AFRICA | AP51: ZAG000016320 | AQ51: R186
A52: 27four Life - Pos Ret Med | B52: BONDS | C52: Bonds (3 - 7 Years) | D52: Standard Bank Group Ltd SBT107 Jb3+379 080427 | E52: SBT107 | F52: Standard Bank Group Ltd SBT107 Jb3+379 080427 | G52: 2260000 | H52: 2260000 | I52: 2262567.1 | J52: 8081.02 | K52: 0 | L52: 2270648.1 | M52: 8.040975 | N52: 0.00516597 | O52: 44750 | P52: 46485 | Q52: 8.157 | R52: 0.2 | S52: 0.094975698 | T52: FI | U52: FI | V52: FRN | W52: ZAR | X52: BANKS | AA52: AA | AC52: 8.2026183 | AD52: 7.9094906 | AE52: 8.2 | AF52: 7.9094906 | AG52: 2.11 | AH52: 2270648.1 | AI52: 0.01 | AJ52: 44673 | AK52: PLMED | AL52: 8.04 | AM52: 8.16 | AN52: 0.09 | AO52: STANDARD BANK GROUP | AP52: ZAG000184896 | AQ52: SBT107
A53: 27four Life - Pos Ret Med | B53: BONDS | C53: Bonds (7 - 12 Years) | D53: Transnet 10.50% TN30 091030 | E53: TN30 | F53: Transnet 10.50% TN30 091030 | G53: 2700000 | H53: 2698288.1 | I53: 2581715.2 | J53: 9320.55 | K53: 0 | L53: 2591035.7 | M53: 11.316 | N53: 0.00589489 | O53: 44844 | P53: 47765 | Q53: 10.5 | R53: 5.71 | S53: 5.4077134 | T53: FI | U53: FI | V53: VB | W53: ZAR | AA53: AA+ | AC53: 11.63613 | AD53: 11.058095 | AE53: 11.64 | AF53: 11.058095 | AG53: 2.41 | AH53: 2591035.7 | AI53: 0.01 | AJ53: 44673 | AK53: PLMED | AL53: 11.32 | AM53: 10.5 | AN53: 5.41 | AO53: TRANSNET SOC LTD | AP53: ZAG000120312 | AQ53: TN30
A54: 27four Life - Pos Ret Med | B54: BONDS | C54: Bonds (Greater than 12 Years) | D54: R2048 8.75% 280248 | E54: R2048 | F54: R2048 8.75% 280248 | G54: 3100000 | H54: 2494267.3 | I54: 2548157.8 | J54: 40993.17 | K54: 0 | L54: 2589151 | M54: 10.805 | N54: 0.0058906 | O54: 44804 | P54: 54116 | Q54: 8.75 | R54: 9.22 | S54: 8.7507642 | T54: FI | U54: FI | V54: VB | W54: ZAR | X54: GOVI | AA54: AAA | AC54: 11.09687 | AD54: 10.56951 | AE54: 11.1 | AF54: 10.56951 | AG54: 2.41 | AH54: 2589151 | AI54: 0.01 | AJ54: 44673 | AK54: PLMED | AL54: 10.8 | AM54: 8.75 | AN54: 8.75 | AO54: REP OF SOUTH AFRICA | AP54: ZAG000096173 | AQ54: R2048
A55: 27four Life - Pos Ret Med | B55: BONDS | C55: Bonds (Greater than 12 Years) | D55: RSA 8.50% R2037 310137 | E55: R2037 | F55: RSA 8.50% R2037 310137 | G55: 2800000 | H55: 2334932.8 | I55: 2341171 | J55: 52630.16 | K55: 0 | L55: 2393801.2 | M55: 10.735 | N55: 0.00544616 | O55: 44774 | P55: 50071 | Q55: 8.5 | R55: 7.91 | S55: 7.5106017 | T55: FI | U55: FI | V55: VB | W55: ZAR | X55: GOVI | AA55: AAA | AC55: 11.023101 | AD55: 10.502504 | AE55: 11.02 | AF55: 10.502504 | AG55: 2.23 | AH55: 2393801.2 | AI55: 0.01 | AJ55: 44673 | AK55: PLMED | AL55: 10.73 | AM55: 8.5 | AN55: 7.51 | AO55: REP OF SOUTH AFRICA | AP55: ZAG000107012 | AQ55: R2037
A56: 27four Life - Pos Ret Med | B56: BONDS | C56: Inflation Linked Bonds | D56: I2038 2.25% 310138 | E56: I2038 | F56: I2038 2.25% 310138 | G56: 2050000 | H56: 2639906.9 | I56: 2650871.5 | J56: 16603.38 | K56: 0 | L56: 2667474.9 | M56: 3.9 | N56: 0.00606879 | O56: 44774 | P56: 50436 | Q56: 2.25 | R56: 12.94 | S56: 12.689805 | T56: FI | U56: FI | V56: ILB | W56: ZAR | X56: GOVI | AA56: AAA | AC56: 3.938025 | AD56: 3.868685 | AE56: 3.94 | AF56: 3.868685 | AG56: 2.48 | AH56: 2667474.9 | AI56: 0.01 | AJ56: 44673 | AK56: PLMED | AL56: 3.9 | AM56: 2.25 | AN56: 12.69 | AO56: REP OF SOUTH AFRICA | AP56: ZAG000096595 | AQ56: I2038
A57: 27four Life - Pos Ret Med | B57: BONDS | C57: Inflation Linked Bonds | D57: I2046 2.50% 310346 | E57: I2046 | F57: I2046 2.50% 310346 | G57: 2230000 | H57: 2621833.8 | I57: 2638391.5 | J57: 5305.26 | K57: 0 | L57: 2643696.8 | M57: 3.9 | N57: 0.00601469 | O57: 44834 | P57: 53417 | Q57: 2.5 | R57: 17.22 | S57: 16.886632 | T57: FI | U57: FI | V57: ILB | W57: ZAR | X57: GOVI | AA57: AAA | AC57: 3.938025 | AD57: 3.868685 | AE57: 3.94 | AF57: 3.868685 | AG57: 2.46 | AH57: 2643696.8 | AI57: 0.01 | AJ57: 44673 | AK57: PLMED | AL57: 3.9 | AM57: 2.5 | AN57: 16.89 | AO57: REP OF SOUTH AFRICA | AP57: ZAG000106980 | AQ57: I2046
A58: 27four Life - Pos Ret Med | B58: BONDS | C58: Inflation Linked Bonds | D58: I2050 2.25% 2050 | E58: I2050 | F58: I2050 2.25% 2050 | G58: 2460000 | H58: 2990480.5 | I58: 2991383.9 | J58: 30478.98 | K58: 0 | L58: 3021862.8 | M58: 3.9 | N58: 0.00687506 | O58: 44742 | P58: 55153 | Q58: 2.5 | R58: 19.05 | S58: 18.689624 | T58: FI | U58: FI | V58: ILB | W58: ZAR | X58: GOVI | AA58: AAA | AC58: 3.938025 | AD58: 3.868685 | AE58: 3.94 | AF58: 3.868685 | AG58: 2.81 | AH58: 3021862.8 | AI58: 0.01 | AJ58: 44673 | AK58: PLMED | AL58: 3.9 | AM58: 2.5 | AN58: 18.69 | AO58: REP OF SOUTH AFRICA | AP58: ZAG000096603 | AQ58: I2050
A59: 27four Life - Pos Ret Med | B59: BONDS | C59: Inflation Linked Bonds | D59: RSA 1.875% I2033 280233 | E59: I2033 | F59: RSA 1.875% I2033 280233 | G59: 2340000 | H59: 2656052.5 | I59: 2648257.9 | J59: 8866.44 | K59: 0 | L59: 2657124.3 | M59: 3.82 | N59: 0.00604524 | O59: 44804 | P59: 48638 | Q59: 1.875 | R59: 9.71 | S59: 9.5277219 | T59: FI | U59: FI | V59: ILB | W59: ZAR | X59: GOVI | AA59: AAA | AC59: 3.856481 | AD59: 3.7899493 | AE59: 3.86 | AF59: 3.7899493 | AG59: 2.47 | AH59: 2657124.3 | AI59: 0.01 | AJ59: 44673 | AK59: PLMED | AL59: 3.82 | AM59: 1.88 | AN59: 9.53 | AO59: REP OF SOUTH AFRICA | AP59: ZAG000125998 | AQ59: I2033
A60: 27four Life - Pos Ret Med | B60: CASH | C60: Cash on Call | D60: Prescient Corporate Money market B3 | E60: PCMMB3 | F60: Prescient Corporate Money market B3 | G60: 0 | H60: 0 | I60: 0 | J60: 0 | K60: 0 | L60: 0.03 | N60: 0 | O60: 44378 | P60: 55153 | Q60: 0 | T60: FI | U60: CIS | V60: CSH | W60: ZAR | AE60: 0 | AF60: 0 | AG60: 0 | AH60: 0.03 | AI60: 0 | AJ60: 44673 | AK60: PLMED | AL60: 0 | AM60: 0 | AN60: 0 | AP60: ZAE000280848 | AQ60: PCMMB3
A61: 27four Life - Pos Ret Med | B61: CASH | C61: Cash on Call | D61: Prescient Money Market Fund B3 | E61: PRMFB3 | F61: Prescient Money Market Fund B3 | G61: 3930133.2 | H61: 3930133.2 | I61: 3930133.2 | J61: 14851.47 | K61: 0 | L61: 3944984.7 | N61: 0.00897526 | O61: 40756 | P61: 73020 | Q61: 0 | T61: FI | U61: CIS | V61: CSH | W61: ZAR | AE61: 0 | AF61: 0 | AG61: 3.67 | AH61: 3944984.7 | AI61: 0.01 | AJ61: 44673 | AK61: PLMED | AL61: 0 | AM61: 0 | AN61: 0 | AP61: ZAE000140885 | AQ61: PRMFB3
A62: 27four Life - Pos Ret Med | B62: CASH | C62: Safex Margin Deposits | D62: SAFEX Margin | E62: SAFEX | F62: Margin Account | G62: 1413566 | H62: 1413566 | I62: 1413566 | J62: 4988.92 | K62: 0 | L62: 1418554.9 | M62: 6.88 | N62: 0.00322737 | P62: 55153 | Q62: 6.88 | R62: 0.08 | S62: 0.002600675 | T62: ST | U62: CSH | V62: MARGIN | W62: ZAR | AE62: 0 | AF62: 0 | AG62: 1.32 | AH62: 1418554.9 | AI62: 0 | AJ62: 44673 | AK62: PLMED | AL62: 0 | AM62: 6.88 | AN62: 0 | AO62: SAFEX | AQ62: SAFEX
A63: 27four Life - Pos Ret Med | B63: CASH | C63: Traded Cash | D63: Interest on Cash ZAR | E63: INTRZAR | F63: Interest on Cash | G63: 0 | H63: 0 | I63: 0 | J63: 0 | K63: 0 | L63: 738.27 | N63: 1.68e-06 | R63: 0.08 | T63: CASH | U63: CSH | W63: ZAR | AC63: 5.116339 | AD63: 5.0001425 | AE63: 5.12 | AF63: 5.0001425 | AG63: 0 | AH63: 738.27 | AI63: 0 | AJ63: 44673 | AK63: PLMED | AL63: 5.05 | AM63: 0 | AN63: 0
A64: 27four Life - Pos Ret Med | B64: CASH | C64: Traded Cash | D64: South African Rand | E64: CASHZAR | F64: South African Rand | G64: 587348.87 | H64: 587348.08 | I64: 587348.87 | J64: 0 | K64: 0 | L64: 587348.87 | N64: 0.00133628 | R64: 0.08 | T64: CASH | U64: CRNY | W64: ZAR | AC64: 5.116339 | AD64: 5.0001425 | AE64: 5.12 | AF64: 5.0001425 | AG64: 0.55 | AH64: 587348.87 | AI64: 0 | AJ64: 44673 | AK64: PLMED | AL64: 5.05 | AM64: 0 | AN64: 0 | AQ64: ZAR
A65: 27four Life - Pos Ret Med | B65: CASH | C65: Unsettled Cash | D65: Management Fee | E65: MGMTFEE | G65: -24355.13 | H65: -24355.13 | I65: -24355.13 | J65: 0 | L65: -24355.13 | N65: -5.541e-05 | P65: 73051 | Q65: 0 | R65: 0.08 | T65: CASH | W65: ZAR | AC65: 5.116339 | AD65: 5.0001425 | AE65: 5.12 | AF65: 5.0001425 | AG65: -0.02 | AH65: -24355.13 | AI65: 0 | AJ65: 44673 | AK65: PLMED | AL65: 5.05 | AM65: 0 | AN65: 0
A66: 27four Life - Pos Ret Med | B66: CASH | C66: Unsettled Cash | D66: Other Fee | E66: OTHFEE | G66: -11154.51 | H66: -11154.51 | I66: -11154.51 | J66: 0 | L66: -11154.51 | N66: -2.538e-05 | P66: 73051 | Q66: 0 | R66: 0.08 | T66: CASH | W66: ZAR | AC66: 5.116339 | AD66: 5.0001425 | AE66: 5.12 | AF66: 5.0001425 | AG66: -0.01 | AH66: -11154.51 | AI66: 0 | AJ66: 44673 | AK66: PLMED | AL66: 5.05 | AM66: 0 | AN66: 0
A67: 27four Life - Pos Ret Med | B67: CASH | C67: Unsettled Cash | D67: Variation Margin | E67: VARMARG | G67: -393235 | H67: -393235 | I67: -393235 | J67: 0 | L67: -393235 | N67: -0.00089465 | P67: 73051 | Q67: 0 | R67: 0.08 | T67: CASH | W67: ZAR | AC67: 5.116339 | AD67: 5.0001425 | AE67: 5.12 | AF67: 5.0001425 | AG67: -0.37 | AH67: -393235 | AI67: 0 | AJ67: 44673 | AK67: PLMED | AL67: 5.05 | AM67: 0 | AN67: 0
A68: 27four Life - Pos Ret Med | B68: DERIVATIVES | C68: Equity Derivatives | D68: 15JUN22 ALSI | E68: 15JUN22 ALSI | F68: 15JUN22 ALSI | G68: 24 | H68: 0 | I68: 0 | J68: 0 | K68: 0 | L68: 0 | M68: 65704 | N68: 0 | P68: 44727 | T68: FT | U68: DER | V68: IDXFT | W68: ZAR | AE68: 0 | AF68: 0 | AG68: 0 | AH68: 15768960 | AI68: 0.04 | AJ68: 44673 | AK68: PLMED | AL68: 0 | AM68: 0 | AN68: 0 | AP68: ZAD000277663 | AQ68: 15JUN22 ALSI
A69: 27four Life - Pos Ret Med | B69: DERIVATIVES | C69: Equity Derivatives | D69: 15SEP22 ALSI | E69: 15SEP22 ALSI | F69: 15SEP22 ALSI | G69: -18 | H69: 0 | I69: 0 | J69: 0 | K69: 0 | L69: 0 | M69: 65741 | N69: 0 | P69: 44819 | T69: FT | U69: DER | V69: IDXFT | W69: ZAR | AE69: 0 | AF69: 0 | AG69: 0 | AH69: -11833380 | AI69: -0.03 | AJ69: 44673 | AK69: PLMED | AL69: 0 | AM69: 0 | AN69: 0 | AP69: ZAD000277671 | AQ69: 15SEP22 ALSI
A70: 27four Life - Pos Ret Med | B70: DERIVATIVES | C70: Equity Derivatives | D70: 15SEP22 ALSI 69000C | E70: 15SEP22 ALSI 69000C | F70: 15SEP22 ALSI 69000C | G70: 35 | H70: 0 | I70: 0 | J70: 0 | K70: 0 | L70: 0 | M70: 17668 | N70: 0 | P70: 44819 | T70: OP | U70: DER | V70: IDXOP | W70: ZAR | AE70: 0 | AF70: 0 | AG70: 0 | AH70: 8297092.8 | AI70: 0.02 | AJ70: 44673 | AK70: PLMED | AL70: 0 | AM70: 0 | AN70: 0 | AP70: ZADA00259275 | AQ70: 15SEP22 ALSI 69000C
A71: 27four Life - Pos Ret Med | B71: DERIVATIVES | C71: Equity Derivatives | D71: 15SEP22 ALSI 70000C | E71: 15SEP22 ALSI 70000C | F71: 15SEP22 ALSI 70000C | G71: 36 | H71: 0 | I71: 0 | J71: 0 | K71: 0 | L71: 0 | M71: 14076 | N71: 0 | P71: 44819 | T71: OP | U71: DER | V71: IDXOP | W71: ZAR | AE71: 0 | AF71: 0 | AG71: 0 | AH71: 7348461 | AI71: 0.02 | AJ71: 44673 | AK71: PLMED | AL71: 0 | AM71: 0 | AN71: 0 | AP71: ZADA00256511 | AQ71: 15SEP22 ALSI 70000C
A72: 27four Life - Pos Ret Med | B72: DERIVATIVES | C72: Equity Derivatives | D72: 15SEP22 ALSI 74000C | E72: 15SEP22 ALSI 74000C | F72: 15SEP22 ALSI 74000C | G72: -35 | H72: 0 | I72: 0 | J72: 0 | K72: 0 | L72: 0 | M72: 5097 | N72: 0 | P72: 44819 | T72: OP | U72: DER | V72: IDXOP | W72: ZAR | AE72: 0 | AF72: 0 | AG72: 0 | AH72: -3381304.8 | AI72: -0.01 | AJ72: 44673 | AK72: PLMED | AL72: 0 | AM72: 0 | AN72: 0 | AP72: ZADA00260075 | AQ72: 15SEP22 ALSI 74000C
A73: 27four Life - Pos Ret Med | B73: EQUITIES | C73: FINANCIALS | D73: Equites Property Fund Limited | E73: EQU | F73: Equites Property Fund Limited | G73: 26629 | H73: 528747.45 | I73: 574653.82 | J73: 0 | K73: 0 | L73: 574653.82 | M73: 2158 | N73: 0.0013074 | T73: EQ | U73: EQ | V73: EQ | W73: ZAR | X73: REAL ESTATE | Y73: FINANCIAL SERVICES | Z73: FINANCIALS | AE73: 0 | AF73: 0 | AG73: 0.53 | AH73: 574653.82 | AI73: 0 | AJ73: 44673 | AK73: PLMED | AL73: 0 | AM73: 0 | AN73: 0 | AP73: ZAE000188843 | AQ73: EQU
A74: 27four Life - Pos Ret Med | B74: EQUITIES | C74: FINANCIALS | D74: Fortress Reit Limited A | E74: FFA | F74: Fortress Reit Limited A | G74: 46426 | H74: 646759.91 | I74: 578932.22 | J74: 0 | K74: 0 | L74: 578932.22 | M74: 1247 | N74: 0.00131713 | T74: EQ | U74: EQ | V74: EQ | W74: ZAR | X74: REAL ESTATE | Y74: FINANCIAL SERVICES | Z74: FINANCIALS | AE74: 0 | AF74: 0 | AG74: 0.54 | AH74: 578932.22 | AI74: 0 | AJ74: 44673 | AK74: PLMED | AL74: 0 | AM74: 0 | AN74: 0 | AP74: ZAE000248498 | AQ74: FFA
A75: 27four Life - Pos Ret Med | B75: EQUITIES | C75: FINANCIALS | D75: Growthpoint Properties Ltd | E75: GRT | F75: Growthpoint Properties Ltd | G75: 132480 | H75: 1925365.3 | I75: 1854720 | J75: 0 | K75: 0 | L75: 1854720 | M75: 1400 | N75: 0.00421969 | T75: EQ | U75: EQ | V75: EQ | W75: ZAR | X75: REAL ESTATE | Y75: FINANCIAL SERVICES | Z75: FINANCIALS | AE75: 0 | AF75: 0 | AG75: 1.73 | AH75: 1854720 | AI75: 0 | AJ75: 44673 | AK75: PLMED | AL75: 0 | AM75: 0 | AN75: 0 | AP75: ZAE000179420 | AQ75: GRT
A76: 27four Life - Pos Ret Med | B76: EQUITIES | C76: FINANCIALS | D76: Hyprop Investments Ltd | E76: HYP | F76: Hyprop Investments Ltd | G76: 13420 | H76: 395089.72 | I76: 484193.6 | J76: 0 | K76: 0 | L76: 484193.6 | M76: 3608 | N76: 0.00110159 | T76: EQ | U76: EQ | V76: EQ | W76: ZAR | X76: REAL ESTATE | Y76: FINANCIAL SERVICES | Z76: FINANCIALS | AE76: 0 | AF76: 0 | AG76: 0.45 | AH76: 484193.6 | AI76: 0 | AJ76: 44673 | AK76: PLMED | AL76: 0 | AM76: 0 | AN76: 0 | AP76: ZAE000190724 | AQ76: HYP
A77: 27four Life - Pos Ret Med | B77: EQUITIES | C77: FINANCIALS | D77: MAS PLC | E77: MSP | F77: MAS PLC | G77: 16755 | H77: 311413.71 | I77: 366599.4 | J77: 0 | K77: 0 | L77: 366599.4 | M77: 2188 | N77: 0.00083405 | T77: EQ | U77: EQ | V77: EQ | W77: ZAR | X77: REAL ESTATE | Y77: FINANCIAL SERVICES | Z77: FINANCIALS | AE77: 0 | AF77: 0 | AG77: 0.34 | AH77: 366599.4 | AI77: 0 | AJ77: 44673 | AK77: PLMED | AL77: 0 | AM77: 0 | AN77: 0 | AP77: VGG5884M1041 | AQ77: MSP
A78: 27four Life - Pos Ret Med | B78: EQUITIES | C78: FINANCIALS | D78: Nepi Rockcastle PLC | E78: NRP | F78: Nepi Rockcastle PLC | G78: 17768 | H78: 1726534.1 | I78: 1711058.4 | J78: 0 | K78: 0 | L78: 1711058.4 | M78: 9630 | N78: 0.00389284 | T78: EQ | U78: EQ | V78: EQ | W78: ZAR | X78: REAL ESTATE | Y78: FINANCIAL SERVICES | Z78: FINANCIALS | AE78: 0 | AF78: 0 | AG78: 1.59 | AH78: 1711058.4 | AI78: 0 | AJ78: 44673 | AK78: PLMED | AL78: 0 | AM78: 0 | AN78: 0 | AP78: IM00BDD7WV31 | AQ78: NRP
A79: 27four Life - Pos Ret Med | B79: EQUITIES | C79: FINANCIALS | D79: Redefine Properties Limited | E79: RDF | F79: Redefine Properties Limited | G79: 264712 | H79: 1170003 | I79: 1172674.2 | J79: 0 | K79: 0 | L79: 1172674.2 | M79: 443 | N79: 0.00266796 | T79: EQ | U79: EQ | V79: EQ | W79: ZAR | X79: REAL ESTATE | Y79: FINANCIAL SERVICES | Z79: FINANCIALS | AE79: 0 | AF79: 0 | AG79: 1.09 | AH79: 1172674.2 | AI79: 0 | AJ79: 44673 | AK79: PLMED | AL79: 0 | AM79: 0 | AN79: 0 | AP79: ZAE000190252 | AQ79: RDF
A80: 27four Life - Pos Ret Med | B80: EQUITIES | C80: FINANCIALS | D80: Resilient REIT Limited | E80: RES | F80: Resilient Property Income Fund Ltd | G80: 12721 | H80: 701874.93 | I80: 744178.5 | J80: 0 | K80: 0 | L80: 744178.5 | M80: 5850 | N80: 0.00169309 | T80: EQ | U80: EQ | V80: REIT | W80: ZAR | X80: REAL ESTATE | Y80: FINANCIAL SERVICES | Z80: FINANCIALS | AE80: 0 | AF80: 0 | AG80: 0.69 | AH80: 744178.5 | AI80: 0 | AJ80: 44673 | AK80: PLMED | AL80: 0 | AM80: 0 | AN80: 0 | AP80: ZAE000209557 | AQ80: RES
A81: 27four Life - Pos Ret Med | B81: EQUITIES | C81: FINANCIALS | D81: Sirius Real Estate Ltd | E81: SRE | F81: Sirius Real Estate Ltd | G81: 11674 | H81: 241977.23 | I81: 277841.2 | J81: 0 | K81: 0 | L81: 277841.2 | M81: 2380 | N81: 0.00063212 | T81: EQ | U81: EQ | V81: EQ | W81: ZAR | X81: REAL ESTATE | Y81: FINANCIAL SERVICES | Z81: FINANCIALS | AE81: 0 | AF81: 0 | AG81: 0.26 | AH81: 277841.2 | AI81: 0 | AJ81: 44673 | AK81: PLMED | AL81: 0 | AM81: 0 | AN81: 0 | AP81: GG00B1W3VF54 | AQ81: SRE
A82: 27four Life - Pos Ret Med | B82: EQUITIES | C82: FINANCIALS | D82: Vukile Property Fund Ltd | E82: VKE | F82: Vukile Property Fund Ltd | G82: 34824 | H82: 419546.28 | I82: 466641.6 | J82: 0 | K82: 0 | L82: 466641.6 | M82: 1340 | N82: 0.00106166 | T82: EQ | U82: EQ | V82: EQ | W82: ZAR | X82: REAL ESTATE | Y82: FINANCIAL SERVICES | Z82: FINANCIALS | AE82: 0 | AF82: 0 | AG82: 0.43 | AH82: 466641.6 | AI82: 0 | AJ82: 44673 | AK82: PLMED | AL82: 0 | AM82: 0 | AN82: 0 | AP82: ZAE000180865 | AQ82: VKE
A83: 27four Life - Pos Ret Med | B83: MONEY MARKET | C83: Money Market : Maturity (6-12) Months | D83: ABSA NCD 5.95% 220223 | E83: ABSAN220223A | F83: ABSA NCD 5.95% 220223 | G83: 7000000 | H83: 7000000 | I83: 6991828.1 | J83: 68465.75 | K83: 0 | L83: 7060293.8 | M83: 6.036665 | N83: 0.01606293 | O83: 44979 | P83: 44979 | Q83: 5.95 | R83: 0.83 | S83: 0.79052189 | T83: FI | U83: MM | V83: NCD | W83: ZAR | X83: BANKS | AA83: AA+ | AC83: 6.0672129 | AD83: 5.9047592 | AE83: 6.07 | AF83: 5.9047592 | AG83: 6.57 | AH83: 7060293.8 | AI83: 0.02 | AJ83: 44673 | AK83: PLMED | AL83: 5.98 | AM83: 5.95 | AN83: 0.79 | AO83: ABSA BANK LTD | AP83: ZAM000566470 | AQ83: ABSAN220223A
A84: 27four Life - Pos Ret Med | B84: MONEY MARKET | C84: Money Market : Maturity (6-12) Months | D84: Nedbank NCD 5.95% 140223 | E84: NEDN140223 | F84: Nedbank NCD 5.95% 140223 | G84: 7000000 | H84: 7000000 | I84: 6995076.4 | J84: 77594.52 | K84: 0 | L84: 7072670.9 | M84: 5.97307 | N84: 0.01609109 | O84: 44971 | P84: 44971 | Q84: 5.95 | R84: 0.81 | S84: 0.77099882 | T84: FI | U84: MM | V84: NCD | W84: ZAR | X84: BANKS | AA84: AA | AC84: 6.0068706 | AD84: 5.8475737 | AE84: 6.01 | AF84: 5.8475737 | AG84: 6.58 | AH84: 7072670.9 | AI84: 0.02 | AJ84: 44673 | AK84: PLMED | AL84: 5.92 | AM84: 5.95 | AN84: 0.77 | AO84: NEDBANK LTD | AP84: ZAM000565282 | AQ84: NEDN140223
A85: 27four Life - Pos Ret Med | B85: MONEY MARKET | C85: Money Market : Maturity (6-12) Months | D85: Standard Bank NCD 5.325% 141222 | E85: STDN141222 | F85: Standard Bank NCD 5.325% 141222 | G85: 3000000 | H85: 3000000 | I85: 2994024.9 | J85: 56897.26 | K85: 0 | L85: 3050922.2 | M85: 5.541328 | N85: 0.00694118 | O85: 44909 | P85: 44909 | Q85: 5.325 | R85: 0.64 | S85: 0.6165468 | T85: FI | U85: MM | V85: NCD | W85: ZAR | X85: BANKS | AA85: AA+ | AC85: 5.5965718 | AD85: 5.4579467 | AE85: 5.6 | AF85: 5.4579467 | AG85: 2.84 | AH85: 3050922.2 | AI85: 0.01 | AJ85: 44673 | AK85: PLMED | AL85: 5.52 | AM85: 5.33 | AN85: 0.62 | AO85: STANDARD BANK LTD | AP85: ZAM000559558 | AQ85: STDN141222
A86: 27four Life - Pos Ret Med | B86: MONEY MARKET | C86: Money Market : Maturity (6-12) Months | D86: Standard Bank NCD 6.35% 310323 | E86: STDN310323 | F86: Standard Bank NCD 6.35% 310323 | G86: 2000000 | H86: 2000000 | I86: 2002086.3 | J86: 8002.74 | K86: 0 | L86: 2010089.1 | M86: 6.204556 | N86: 0.00457317 | O86: 45016 | P86: 45016 | Q86: 6.35 | R86: 0.93 | S86: 0.88061116 | T86: FI | U86: MM | V86: NCD | W86: ZAR | X86: BANKS | AA86: AA+ | AC86: 6.217511 | AD86: 6.0470648 | AE86: 6.22 | AF86: 6.0470648 | AG86: 1.87 | AH86: 2010089.1 | AI86: 0 | AJ86: 44673 | AK86: PLMED | AL86: 6.12 | AM86: 6.35 | AN86: 0.88 | AO86: STANDARD BANK LTD | AP86: ZAM000571397 | AQ86: STDN310323
A87: 27four Life - Pos Ret Med | B87: MONEY MARKET | C87: Money Market : Maturity 12+ Months | D87: FirstRand NCD 6.43% 110523 | E87: FSRN110523 | F87: FirstRand NCD 6.43% 110523 | G87: 2000000 | H87: 2000000 | I87: 2000292.3 | J87: 3875.62 | K87: 0 | L87: 2004167.9 | M87: 6.400406 | N87: 0.0045597 | O87: 45057 | P87: 45057 | Q87: 6.43 | R87: 1.04 | S87: 0.97846467 | T87: FI | U87: MM | V87: NCD | W87: ZAR | X87: BANKS | AA87: AA+ | AC87: 6.3916292 | AD87: 6.2116934 | AE87: 6.39 | AF87: 6.2116934 | AG87: 1.87 | AH87: 2004167.9 | AI87: 0 | AJ87: 44673 | AK87: PLMED | AL87: 6.29 | AM87: 6.43 | AN87: 0.98 | AO87: FIRSTRAND BANK LTD | AP87: ZAM000572718 | AQ87: FSRN110523
A88: 27four Life - Pos Ret Med | B88: MONEY MARKET | C88: Money Market : Maturity 12+ Months | D88: Investec Tier1 FRN 12082024 Jb+425 | E88: INLV01 | F88: Investec Tier1 FRN 12082024 Jb+425 | G88: 3000000 | H88: 3025089.3 | I88: 3082343.5 | J88: 47042.96 | K88: 0 | L88: 3129386.5 | M88: 7.16453 | N88: 0.00711969 | O88: 44693 | P88: 45516 | Q88: 8.417 | R88: 0.05 | S88: 0.032810324 | T88: FI | U88: MM | V88: FRN | W88: ZAR | X88: BANKS | AA88: AA | AB88: A- | AC88: 7.4146104 | AD88: 7.1739614 | AE88: 7.41 | AF88: 7.1739614 | AG88: 2.91 | AH88: 3129386.5 | AI88: 0.01 | AJ88: 44673 | AK88: PLMED | AL88: 7.28 | AM88: 8.42 | AN88: 0.03 | AO88: INVESTEC LTD | AP88: ZAG000118647 | AQ88: INLV01
A89: 27four Life - Pos Ret Med | B89: MONEY MARKET | C89: Money Market : Maturity 12+ Months | D89: Standard bank NCD 6.51% 220224 | E89: STDN220224 | F89: Standard bank NCD 6.51% 220224 | G89: 6000000 | H89: 6000000 | I89: 5945939.2 | J89: 64208.22 | K89: 0 | L89: 6010147.4 | M89: 7.035848 | N89: 0.01367373 | O89: 44795 | P89: 45344 | Q89: 6.51 | R89: 1.74 | S89: 1.6779886 | T89: FI | U89: MM | V89: NCD | W89: ZAR | AA89: AA+ | AC89: 7.1596058 | AD89: 6.9348797 | AE89: 7.16 | AF89: 6.9348797 | AG89: 5.59 | AH89: 6010147.4 | AI89: 0.01 | AJ89: 44673 | AK89: PLMED | AL89: 7.04 | AM89: 6.51 | AN89: 1.68 | AO89: STANDARD BANK LTD | AP89: ZAM000566447 | AQ89: STDN220224
A90: 27four Life - Pos Ret Med | B90: PREFERENCE SHARES | C90: Preference Shares | D90: Absa Bank Ltd Preference Shares | E90: ABSP | F90: Absa Bank Ltd Preference Shares | G90: 2871 | H90: 1953165.1 | I90: 2583900 | J90: 0 | K90: 71605.89 | L90: 2655505.9 | M90: 90000 | N90: 0.00604156 | T90: EQ | U90: EQ | V90: PREF | W90: ZAR | AA90: AA+ | AE90: 0 | AF90: 0 | AG90: 2.47 | AH90: 2655505.9 | AI90: 0.01 | AJ90: 44673 | AK90: PLMED | AL90: 0 | AM90: 0 | AN90: 0 | AO90: ABSA BANK LTD | AP90: ZAE000079810 | AQ90: ABSP
A91: 27four Life - Pos Ret Med | B91: PREFERENCE SHARES | C91: Preference Shares | D91: Investec Ltd Preference Share | E91: INPR | F91: Investec Ltd Preference Share | G91: 28406 | H91: 2077537.4 | I91: 2736634 | J91: 0 | K91: 0 | L91: 2736634 | M91: 9634 | N91: 0.00622614 | T91: EQ | U91: EQ | V91: PREF | W91: ZAR | AE91: 0 | AF91: 0 | AG91: 2.55 | AH91: 2736634 | AI91: 0.01 | AJ91: 44673 | AK91: PLMED | AL91: 0 | AM91: 0 | AN91: 0 | AP91: ZAE000063814 | AQ91: INPR
A92: 27four Life - Pos Ret Med | B92: PREFERENCE SHARES | C92: Preference Shares | D92: Netcare Preference Share Ltd | E92: NTCP | F92: Netcare Preference Share Ltd | G92: 7500 | H92: 605832.37 | I92: 645000 | J92: 0 | K92: 0 | L92: 645000 | M92: 8600 | N92: 0.00146744 | T92: EQ | U92: EQ | V92: PREF | W92: ZAR | AE92: 0 | AF92: 0 | AG92: 0.6 | AH92: 645000 | AI92: 0 | AJ92: 44673 | AK92: PLMED | AL92: 0 | AM92: 0 | AN92: 0 | AP92: ZAE000081121 | AQ92: NTCP
A93: 27four Life - Pos Ret Med | B93: PREFERENCE SHARES | C93: Preference Shares | D93: Standard Bank Group Ltd Preference Shares | E93: SBPP | F93: Standard Bank Group Ltd Pref | G93: 25825 | H93: 1954420.9 | I93: 2385971.8 | J93: 0 | K93: 0 | L93: 2385971.8 | M93: 9239 | N93: 0.00542834 | T93: EQ | U93: EQ | V93: PREF | W93: ZAR | AA93: AA+ | AE93: 0 | AF93: 0 | AG93: 2.22 | AH93: 2385971.8 | AI93: 0.01 | AJ93: 44673 | AK93: PLMED | AL93: 0 | AM93: 0 | AN93: 0 | AO93: STANDARD BANK LTD | AP93: ZAE000056339 | AQ93: SBPP
A94: 27four Life - Pos Ret Med | B94: PRIVATE COMPANY | C94: Private Company | D94: Prescient Clean Energy and Infrastructure Debt Fund Trust | E94: PIMEVOA | F94: Prescient Clean Energy and Infrastructure Debt Fund Trust | G94: 5386808.4 | H94: 5422486.4 | I94: 5393811.2 | J94: 0 | K94: 0 | L94: 5393811.2 | M94: 1.0013 | N94: 0.0122715 | T94: EQ | U94: PRIVATE COMP | V94: OTHER | W94: ZAR | AE94: 0 | AF94: 0 | AG94: 5.02 | AH94: 5393811.2 | AI94: 0.01 | AJ94: 44673 | AK94: PLMED | AL94: 0 | AM94: 0 | AN94: 0 | AQ94: PIMEVOA
A95: 27four Life - Pos Ret Med | B95: UNKNOWN | C95: UNKNOWN | D95: Synthetic Cash_15JUN22 ALSI | E95: 15JUN22 ALSI | F95: Synthetic Cash_15JUN22 ALSI | G95: 24 | I95: 0 | L95: 0 | N95: 0 | T95: SYTH | U95: SYNCASHFUT | V95: CASH | W95: ZAR | AE95: 0 | AF95: 0 | AG95: 0 | AH95: -15768960 | AI95: -0.04 | AJ95: 44673 | AK95: PLMED | AL95: 0 | AM95: 0 | AN95: 0 | AQ95: SYNZAR
A96: 27four Life - Pos Ret Med | B96: UNKNOWN | C96: UNKNOWN | D96: Synthetic Cash_15SEP22 ALSI | E96: 15SEP22 ALSI | F96: Synthetic Cash_15SEP22 ALSI | G96: -18 | I96: 0 | L96: 0 | N96: 0 | T96: SYTH | U96: SYNCASHFUT | V96: CASH | W96: ZAR | AE96: 0 | AF96: 0 | AG96: 0 | AH96: 11833380 | AI96: 0.03 | AJ96: 44673 | AK96: PLMED | AL96: 0 | AM96: 0 | AN96: 0 | AQ96: SYNZAR
A97: 27four Life - Pos Ret Med | B97: UNKNOWN | C97: UNKNOWN | D97: Synthetic Cash_15SEP22 ALSI 69000C | E97: 15SEP22 ALSI 69000C | F97: Synthetic Cash_15SEP22 ALSI 69000C | G97: 35 | I97: 0 | L97: 0 | N97: 0 | T97: SYTH | U97: SYNCASHOPT | V97: CASH | W97: ZAR | AE97: 0 | AF97: 0 | AG97: 0 | AH97: -8297092.8 | AI97: -0.02 | AJ97: 44673 | AK97: PLMED | AL97: 0 | AM97: 0 | AN97: 0 | AQ97: SYNZAR
A98: 27four Life - Pos Ret Med | B98: UNKNOWN | C98: UNKNOWN | D98: Synthetic Cash_15SEP22 ALSI 70000C | E98: 15SEP22 ALSI 70000C | F98: Synthetic Cash_15SEP22 ALSI 70000C | G98: 36 | I98: 0 | L98: 0 | N98: 0 | T98: SYTH | U98: SYNCASHOPT | V98: CASH | W98: ZAR | AE98: 0 | AF98: 0 | AG98: 0 | AH98: -7348461 | AI98: -0.02 | AJ98: 44673 | AK98: PLMED | AL98: 0 | AM98: 0 | AN98: 0 | AQ98: SYNZAR
A99: 27four Life - Pos Ret Med | B99: UNKNOWN | C99: UNKNOWN | D99: Synthetic Cash_15SEP22 ALSI 74000C | E99: 15SEP22 ALSI 74000C | F99: Synthetic Cash_15SEP22 ALSI 74000C | G99: -35 | I99: 0 | L99: 0 | N99: 0 | T99: SYTH | U99: SYNCASHOPT | V99: CASH | W99: ZAR | AE99: 0 | AF99: 0 | AG99: 0 | AH99: 3381304.8 | AI99: 0.01 | AJ99: 44673 | AK99: PLMED | AL99: 0 | AM99: 0 | AN99: 0 | AQ99: SYNZAR
A100: Absa MM Abs Ret Prud Fund | B100: BONDS | C100: Bonds (3 - 7 Years) | D100: LBK28 10.565% 150528 | E100: LBK28 | F100: LBK28 10.565% 150528 | G100: 5844960 | H100: 5930661.7 | I100: 5493515.4 | J100: 269001.87 | K100: 0 | L100: 5762517.3 | M100: 11.88 | N100: 0.01311035 | O100: 44697 | P100: 46888 | Q100: 10.565 | R100: 4.73 | S100: 4.4668326 | T100: FI | U100: FI | V100: VB | W100: ZAR | AA100: AA+ | AC100: 12.232836 | AD100: 11.596214 | AE100: 12.23 | AF100: 11.596214 | AG100: 3.58 | AH100: 5762517.3 | AI100: 0.01 | AJ100: 44673 | AK100: ABMMABR | AL100: 11.88 | AM100: 10.56 | AN100: 4.47 | AO100: LANDBANK | AP100: ZAG000151275 | AQ100: LBK28
...

Sheet D
A1: Entity Name | B1: i Issue Name | C1: Primary Asset ID | D1: Nominal Holding | E1: Delta | F1: Market Value | G1: Effective Exposure
A2: 27four Life - Pos Ret | B2: 15DEC22 ALSI | C2: 15DEC22 ALSI | D2: -12 | E2: 1 | F2: 0 | G2: -7913160
A3: 27four Life - Pos Ret | B3: 15DEC22 ALSI 70000C | C3: 15DEC22 ALSI 70000C | D3: 21 | E3: 0.37166 | F3: 0 | G3: 5146819.8
A4: 27four Life - Pos Ret | B4: 15JUN22 ALSI | C4: 15JUN22 ALSI | D4: 15 | E4: 1 | F4: 0 | G4: 9855600
A5: 27four Life - Pos Ret | B5: 15JUN22 ALSI 63000P | C5: 15JUN22 ALSI 63000P | D5: -4 | E5: -0.30261 | F5: 0 | G5: 795312.24
A6: 27four Life - Pos Ret | B6: 15JUN22 ALSI 74000C | C6: 15JUN22 ALSI 74000C | D6: -10 | E6: 0.03681 | F6: 0 | G6: -241880.94
A7: 27four Life - Pos Ret | B7: 15JUN22 ALSI 75000C | C7: 15JUN22 ALSI 75000C | D7: 0 | E7: 0.04141 | F7: 0 | G7: 0
A8: 27four Life - Pos Ret | B8: 15SEP22 ALSI | C8: 15SEP22 ALSI | D8: -4 | E8: 1 | F8: 0 | G8: -2629640
A9: 27four Life - Pos Ret | B9: 15SEP22 ALSI 65000C | C9: 15SEP22 ALSI 65000C | D9: 0 | E9: 0.56031 | F9: 0 | G9: 0
A10: 27four Life - Pos Ret | B10: 15SEP22 ALSI 69000C | C10: 15SEP22 ALSI 69000C | D10: 11 | E10: 0.3606 | F10: 0 | G10: 2607657.7
A11: 27four Life - Pos Ret | B11: 15SEP22 ALSI 70000C | C11: 15SEP22 ALSI 70000C | D11: 12 | E11: 0.3105 | F11: 0 | G11: 2449487
A12: 27four Life - Pos Ret | B12: 15SEP22 ALSI 74000C | C12: 15SEP22 ALSI 74000C | D12: -11 | E12: 0.14695 | F12: 0 | G12: -1062695.8
A13: 27four Life - Pos Ret | B13: 15SEP22 ALSI 77000C | C13: 15SEP22 ALSI 77000C | D13: -11 | E13: 0.07553 | F13: 0 | G13: -546227.36
... A31: Absa MM Abs Ret Prud Fund | B31: 15SEP22 ALSI 77000C | C31: 15SEP22 ALSI 77000C | D31: -49 | E31: 0.07553 | F31: 0 | G31: -2433194.6
A32: ABSA MM Bond Fund | B32: No Data found for this Entity
A33: ABSA MULTI MAN EQ FUND PRESC | B33: 15JUN22 ALSI | C33: 15JUN22 ALSI | D33: 128 | E33: 1 | F33: 0 | G33: 84101120
A34: AFIL - Life Bond Fund | B34: No Data found for this Entity
A35: AFIL - Pensioner | B35: 15DEC22 ALSI | C35: 15DEC22 ALSI | D35: -60 | E35: 1 | F35: 0 | G35: -39565800
A36: AFIL - Pensioner | B36: 15DEC22 ALSI 70000C | C36: 15DEC22 ALSI 70000C | D36: 109 | E36: 0.37166 | F36: 0 | G36: 26714445
A37: AFIL - Pensioner | B37: 15JUN22 ALSI | C37: 15JUN22 ALSI | D37: 85 | E37: 1 | F37: 0 | G37: 55848400
A38: AFIL - Pensioner | B38: 15JUN22 ALSI 63000P | C38: 15JUN22 ALSI 63000P | D38: -26 | E38: -0.30261 | F38: 0 | G38: 5169529.5
A39: AFIL - Pensioner | B39: 15JUN22 ALSI 74000C | C39: 15JUN22 ALSI 74000C | D39: -72 | E39: 0.03681 | F39: 0 | G39: -1741542.7
A40: AFIL - Pensioner | B40: 15JUN22 ALSI 75000C | C40: 15JUN22 ALSI 75000C | D40: 0 | E40: 0.04141 | F40: 0 | G40: 0
A41: AFIL - Pensioner | B41: 15SEP22 ALSI | C41: 15SEP22 ALSI | D41: -29 | E41: 1 | F41: 0 | G41: -19064890
A42: AFIL - Pensioner | B42: 15SEP22 ALSI 65000C | C42: 15SEP22 ALSI 65000C | D42: 0 | E42: 0.56031 | F42: 0 | G42: 0
A43: AFIL - Pensioner | B43: 15SEP22 ALSI 69000C | C43: 15SEP22 ALSI 69000C | D43: 77 | E43: 0.3606 | F43: 0 | G43: 18253604
A44: AFIL - Pensioner | B44: 15SEP22 ALSI 70000C | C44: 15SEP22 ALSI 70000C | D44: 78 | E44: 0.3105 | F44: 0 | G44: 15921666
A45: AFIL - Pensioner | B45: 15SEP22 ALSI 74000C | C45: 15SEP22 ALSI 74000C | D45: -61 | E45: 0.14695 | F45: 0 | G45: -5893131.2
A46: AFIL - Pensioner | B46: 15SEP22 ALSI 77000C | C46: 15SEP22 ALSI 77000C | D46: -62 | E46: 0.07553 | F46: 0 | G46: -3078736
A47: Custodian BCI Income Plus Fund | B47: No Data found for this Entity
A48: ECIC Composite | B48: No Data found for this Entity
A49: Electric Cont Indust Pens Fund | B49: 15JUN22 DCAP | C49: 15JUN22 DCAP | D49: 96 | E49: 1 | F49: 0 | G49: 19211520
A50: Electric Cont Indust Pens Fund | B50: 15JUN22 DCAR | C50: 15JUN22 DCAR | D50: 30 | E50: 1 | F50: 0 | G50: 8720100
A51: EMBF - Positive Return Fund | B51: 15JUN22 ALSI | C51: 15JUN22 ALSI | D51: 15 | E51: 1 | F51: 0 | G51: 9855600
A52: EMBF - Positive Return Fund | B52: 15SEP22 ALSI | C52: 15SEP22 ALSI | D52: -11 | E52: 1 | F52: 0 | G52: -7231510
A53: EMBF - Positive Return Fund | B53: 15SEP22 ALSI 65000C | C53: 15SEP22 ALSI 65000C | D53: 0 | E53: 0.56031 | F53: 0 | G53: 0
A54: EMBF - Positive Return Fund | B54: 15SEP22 ALSI 69000C | C54: 15SEP22 ALSI 69000C | D54: 21 | E54: 0.3606 | F54: 0 | G54: 4978255.7
A55: EMBF - Positive Return Fund | B55: 15SEP22 ALSI 70000C | C55: 15SEP22 ALSI 70000C | D55: 22 | E55: 0.3105 | F55: 0 | G55: 4490726.2
A56: EMBF - Positive Return Fund | B56: 15SEP22 ALSI 74000C | C56: 15SEP22 ALSI 74000C | D56: -21 | E56: 0.14695 | F56: 0 | G56: -2028782.9
A57: FRB ITF GTC Wealth Preserver2 | B57: 15DEC22 ALSI | C57: 15DEC22 ALSI | D57: -82 | E57: 1 | F57: 0 | G57: -54073260
A58: FRB ITF GTC Wealth Preserver2 | B58: 15DEC22 ALSI 70000C | C58: 15DEC22 ALSI 70000C | D58: 150 | E58: 0.37166 | F58: 0 | G58: 36762998
A59: FRB ITF GTC Wealth Preserver2 | B59: 15JUN22 ALSI | C59: 15JUN22 ALSI | D59: 226 | E59: 1 | F59: 0 | G59: 148491040
A60: FRB ITF GTC Wealth Preserver2 | B60: 15JUN22 ALSI 63000P | C60: 15JUN22 ALSI 63000P | D60: -66 | E60: -0.30261 | F60: 0 | G60: 13122652
... A68: FRB ITF GTC Wealth Preserver2 | B68: 15SEP22 ALSI 77000C | C68: 15SEP22 ALSI 77000C | D68: -99 | E68: 0.07553 | F68: 0 | G68: -4916046.3
A69: FRB ITF Hollard Prime Income | B69: No Data found for this Entity
A70: FRB ITF Hollard Prime Yld Pls | B70: No Data found for this Entity
A71: FRB ITF IFM Inc Fund Pres | B71: No Data found for this Entity
A72: GA Empolyees Medical BF | B72: 15JUN22 ALSI | C72: 15JUN22 ALSI | D72: 23 | E72: 1 | F72: 0 | G72: 15111920
A73: GA Empolyees Medical BF | B73: 15SEP22 ALSI | C73: 15SEP22 ALSI | D73: -17 | E73: 1 | F73: 0 | G73: -11175970
A74: GA Empolyees Medical BF | B74: 15SEP22 ALSI 65000C | C74: 15SEP22 ALSI 65000C | D74: 0 | E74: 0.56031 | F74: 0 | G74: 0
A75: GA Empolyees Medical BF | B75: 15SEP22 ALSI 69000C | C75: 15SEP22 ALSI 69000C | D75: 34 | E75: 0.3606 | F75: 0 | G75: 8060033
A76: GA Empolyees Medical BF | B76: 15SEP22 ALSI 70000C | C76: 15SEP22 ALSI 70000C | D76: 34 | E76: 0.3105 | F76: 0 | G76: 6940213.2
A77: GA Empolyees Medical BF | B77: 15SEP22 ALSI 74000C | C77: 15SEP22 ALSI 74000C | D77: -34 | E77: 0.14695 | F77: 0 | G77: -3284696.1
A78: Germiston Mun Ret Fund 2 | B78: 15DEC22 ALSI | C78: 15DEC22 ALSI | D78: -40 | E78: 1 | F78: 0 | G78: -26377200
A79: Germiston Mun Ret Fund 2 | B79: 15DEC22 ALSI 70000C | C79: 15DEC22 ALSI 70000C | D79: 73 | E79: 0.37166 | F79: 0 | G79: 17891326
A80: Germiston Mun Ret Fund 2 | B80: 15JUN22 ALSI | C80: 15JUN22 ALSI | D80: 62 | E80: 1 | F80: 0 | G80: 40736480
A81: Germiston Mun Ret Fund 2 | B81: 15JUN22 ALSI 63000P | C81: 15JUN22 ALSI 63000P | D81: -20 | E81: -0.30261 | F81: 0 | G81: 3976561.2
A82: Germiston Mun Ret Fund 2 | B82: 15JUN22 ALSI 74000C | C82: 15JUN22 ALSI 74000C | D82: -40 | E82: 0.03681 | F82: 0 | G82: -967523.74
A83: Germiston Mun Ret Fund 2 | B83: 15JUN22 ALSI 75000C | C83: 15JUN22 ALSI 75000C | D83: 0 | E83: 0.04141 | F83: 0 | G83: 0
... A101: Germiston Municipal RF | B101: 15SEP22 ALSI 77000C | C101: 15SEP22 ALSI 77000C | D101: -61 | E101: 0.07553 | F101: 0 | G101: -3029079
A102: Graviton SCI Flexible Income | B102: No Data found for this Entity
A103: IJG Balanced Fund | B103: 13JUN22 EEMI CSH | C103: 13JUN22 EEMI CSH | D103: 889 | E103: 1 | F103: 0 | G103: 599479.37
A104: IJG Balanced Fund | B104: 13JUN22 EEMI CSH DN | C104: 13JUN22 EEMI CSH DN | D104: 5041 | E104: 1 | F104: 0 | G104: 3401364.3
A105: IJG Balanced Fund | B105: 13JUN22 IWDAI CSH | C105: 13JUN22 IWDAI CSH | D105: 591 | E105: 1 | F105: 0 | G105: 755558.04
A106: IJG Balanced Fund | B106: 13JUN22 IWDAI CSH DN | C106: 13JUN22 IWDAI CSH DN | D106: 3349 | E106: 1 | F106: 0 | G106: 4281495.6
A107: IJG Balanced Fund | B107: 15JUN22 ALSI | C107: 15JUN22 ALSI | D107: 9 | E107: 1 | F107: 0 | G107: 5913360
A108: IJG Balanced Fund | B108: 15JUN22 DCAP | C108: 15JUN22 DCAP | D108: 24 | E108: 1 | F108: 0 | G108: 4802880
A109: IJG Balanced Fund | B109: Aug22 R2037 Bond Future | C109: 2037Q2 | D109: 29 | E109: 1 | F109: 0 | G109: 2397695.9
A110: IJG Corporate Fund | B110: No Data found for this Entity
A111: IJG Income Provider Fund | B111: No Data found for this Entity
A112: Impala Workers Prov Fund | B112: No Data found for this Entity
A113: Liberty Group Ltd - TAA | B113: 13JUN22 USDZAR | C113: 13JUN22 USDZAR | D113: -62893 | E113: 1 | F113: 0 | G113: -9.8796727e+08
A114: Liberty Group Ltd - TAA | B114: 13JUN22 USDZAR 14.5P | C114: 13JUN22 USDZAR 14.5P | D114: -22090 | E114: -0.04912 | F114: 0 | G114: 17044561
A115: Liberty Group Ltd - TAA | B115: 13JUN22 USDZAR 15.5P | C115: 13JUN22 USDZAR 15.5P | D115: 22090 | E115: -0.38974 | F115: 0 | G115: -1.3524056e+08
A116: Liberty Group Ltd - TAA | B116: 13JUN22 USDZAR 18C | C116: 13JUN22 USDZAR 18C | D116: -22090 | E116: 0.02643 | F116: 0 | G116: -9171292.3
A117: Liberty Group Ltd - TAA | B117: 15JUN22 DCAP | C117: 15JUN22 DCAP | D117: 3143 | E117: 1 | F117: 0 | G117: 628977160
A118: Liberty Group Ltd - TAA | B118: 15JUN22 DCAR | C118: 15JUN22 DCAR | D118: 626 | E118: 1 | F118: 0 | G118: 181959420
A119: Medipos Medical Scheme Income | B119: No Data found for this Entity
A120: Mineworkers Prov Fund | B120: 15JUN22 ALSI | C120: 15JUN22 ALSI | D120: 152 | E120: 1 | F120: 0 | G120: 99870080
A121: Momentum Group Ltd - Pos Ret | B121: 15DEC22 ALSI | C121: 15DEC22 ALSI | D121: -169 | E121: 1 | F121: 0 | G121: -111443670
A122: Momentum Group Ltd - Pos Ret | B122: 15DEC22 ALSI 70000C | C122: 15DEC22 ALSI 70000C | D122: 309 | E122: 0.37166 | F122: 0 | G122: 75731776
A123: Momentum Group Ltd - Pos Ret | B123: 15JUN22 ALSI | C123: 15JUN22 ALSI | D123: 235 | E123: 1 | F123: 0 | G123: 154404400
A124: Momentum Group Ltd - Pos Ret | B124: 15JUN22 ALSI 63000P | C124: 15JUN22 ALSI 63000P | D124: -71 | E124: -0.30261 | F124: 0 | G124: 14116792
A125: Momentum Group Ltd - Pos Ret | B125: 15JUN22 ALSI 74000C | C125: 15JUN22 ALSI 74000C | D125: -175 | E125: 0.03681 | F125: 0 | G125: -4232916.4
A126: Momentum Group Ltd - Pos Ret | B126: 15JUN22 ALSI 75000C | C126: 15JUN22 ALSI 75000C | D126: 0 | E126: 0.04141 | F126: 0 | G126: 0
A127: Momentum Group Ltd - Pos Ret | B127: 15SEP22 ALSI | C127: 15SEP22 ALSI | D127: -67 | E127: 1 | F127: 0 | G127: -44046470
A128: Momentum Group Ltd - Pos Ret | B128: 15SEP22 ALSI 65000C | C128: 15SEP22 ALSI 65000C | D128: 0 | E128: 0.56031 | F128: 0 | G128: 0
A129: Momentum Group Ltd - Pos Ret | B129: 15SEP22 ALSI 69000C | C129: 15SEP22 ALSI 69000C | D129: 195 | E129: 0.3606 | F129: 0 | G129: 46226660
A130: Momentum Group Ltd - Pos Ret | B130: 15SEP22 ALSI 70000C | C130: 15SEP22 ALSI 70000C | D130: 196 | E130: 0.3105 | F130: 0 | G130: 40008288
A131: Momentum Group Ltd - Pos Ret | B131: 15SEP22 ALSI 74000C | C131: 15SEP22 ALSI 74000C | D131: -172 | E131: 0.14695 | F131: 0 | G131: -16616698
... A136: NFMW - Equity Fund | B136: 15JUN22 DCAR | C136: 15JUN22 DCAR | D136: 387 | E136: 1 | F136: 0 | G136: 112489290
A137: OMMM Income Fund No5 - PIM | B137: No Data found for this Entity
A138: Picbel Groepvoorsorgfonds | B138: No Data found for this Entity
A139: PIM Absolute Balanced | B139: 15JUN22 ALSI | C139: 15JUN22 ALSI | D139: 2 | E139: 1 | F139: 0 | G139: 1314080
A140: PIM Absolute Balanced | B140: 15JUN22 DCAP | C140: 15JUN22 DCAP | D140: 0 | E140: 1 | F140: 0 | G140: 0
A141: PIM Absolute Balanced | B141: June22 MSCI Emerging Markets Index Future | C141: MESM2 | D141: 20 | E141: 1 | F141: -869935.2 | G141: 16485284
A142: PIM Absolute Balanced | B142: LONG GILT FUTURE Jun22 | C142: G M2 | D142: 1 | E142: 1 | F142: -87174.35 | G142: 2365130.3
A143: PIM Absolute Balanced | B143: US 10YR NOTE (CBT)Jun22 | C143: TYM2 | D143: 3 | E143: 1 | F143: -340658.91 | G143: 5571278
A144: PIM Balanced | B144: 15JUN22 ALSI | C144: 15JUN22 ALSI | D144: 10 | E144: 1 | F144: 0 | G144: 6570400
A145: PIM Balanced | B145: 15JUN22 ATRI | C145: 15JUN22 ATRI | D145: 0 | E145: 1 | F145: 0 | G145: 0
...

Sheet S
A1: Entity ID | B1: UT? | C1: # | D1: Cash Cover | E1: Cash Cover 2 | F1: Incl CLNs & longer dated debt | G1: Incl underlying UTs | H1: SA Bond Cover | I1: MSCI Cover | J1: ALSI Cover | K1: Total Equity | L1: Total Foreign | M1: Global Exposure | N1: Net Effective Exposure | O1: ="Derivative Calculations "&TEXT(Data!$AJ$2,"ddd d mmm yyyy") -> Derivative Calculations Wed 6 Apr 2022 | P1: Mandate
A2: PPSBAL_C | B2: =[1]Summary!$G$3 -> UT | C2: =[1]Summary!$E$1 -> 10 | D2: =[1]Summary!$C$34 -> 0.23653506 | E2: =[1]Summary!$E$34/100 -> 0.23653506 | F2: =[1]Summary!$C$36 -> 0.18917393 | G2: =[1]Summary!$C$32 -> 0 | H2: =[1]Summary!$E$6/100 -> 0.021755043 | I2: =[1]Summary!$E$10/100 -> 0.019637699 | J2: =[1]Summary!$E$14/100 -> 0.19157251 | K2: =[1]Summary!$C$40 -> 0.59271599 | L2: =[1]Summary!$C$54 -> 20.109194 | M2: ='[1]Glbl Expsr'!$D$2 -> 0.095371567 | N2: ='[1]Glbl Expsr'!$D$3 -> 0.095371567 | O2: \\pim-cpt-statpro\SPC_602\Client\Profiles\PIM\Exports\PPSBAL_C Derv Calc 6Apr2022.xlsx | P2: PPSBAL_C Mandate
A3: PCAEF | B3: =[2]Summary!$G$3 -> UT | C3: =[2]Summary!$E$1 -> 10 | D3: =[2]Summary!$C$34 -> 0.50252909 | E3: =[2]Summary!$E$34/100 -> 0.50252909 | F3: =[2]Summary!$C$36 -> 0 | G3: =[2]Summary!$C$32 -> 0 | H3: =[2]Summary!$E$6/100 -> 0 | I3: =[2]Summary!$E$10/100 -> 0.017757483 | J3: =[2]Summary!$E$14/100 -> 0.12463345 | K3: =[2]Summary!$C$40 -> 0.99223767 | L3: =[2]Summary!$C$54 -> 0 | M3: ='[2]Glbl Expsr'!$D$2 -> 0.066275317 | N3: ='[2]Glbl Expsr'!$D$3 -> 0.066275317 | O3: \\pim-cpt-statpro\SPC_602\Client\Profiles\PIM\Exports\PCAEF Derv Calc 6Apr2022.xlsx | P3: PCAEF Mandate
A4: ADRRC | B4: =[3]Summary!$G$3 -> UT | C4: =[3]Summary!$E$1 -> 9 | D4: =[3]Summary!$C$34 -> 0.01560478 | E4: =[3]Summary!$E$34/100 -> 0.01560478 | F4: =[3]Summary!$C$36 -> 0.19828813 | G4: =[3]Summary!$C$32 -> 0 | H4: =[3]Summary!$E$6/100 -> 0 | I4: =[3]Summary!$E$10/100 -> 0 | J4: =[3]Summary!$E$14/100 -> 0 | K4: =[3]Summary!$C$40 -> 0.40730673 | L4: =[3]Summary!$C$54 -> 0 | M4: ='[3]Glbl Expsr'!$D$2 -> 0.94737804 | N4: ='[3]Glbl Expsr'!$D$3 -> 0.21091173 | O4: \\pim-cpt-statpro\SPC_602\Client\Profiles\PIM\Exports\ADRRC Derv Calc 6Apr2022.xlsx | P4: ADRRC Mandate
A5: PPOS | B5: =[4]Summary!$G$3 -> UT | C5: =[4]Summary!$E$1 -> 9 | D5: =[4]Summary!$C$34 -> 0.029279105 | E5: =[4]Summary!$E$34/100 -> 0.029279105 | F5: =[4]Summary!$C$36 -> 0.20279073 | G5: =[4]Summary!$C$32 -> 0 | H5: =[4]Summary!$E$6/100 -> 0 | I5: =[4]Summary!$E$10/100 -> 0 | J5: =[4]Summary!$E$14/100 -> 0 | K5: =[4]Summary!$C$40 -> 0.42110671 | L5: =[4]Summary!$C$54 -> 0 | M5: ='[4]Glbl Expsr'!$D$2 -> 1.0335819 | N5: ='[4]Glbl Expsr'!$D$3 -> 0.21834449 | O5: \\pim-cpt-statpro\SPC_602\Client\Profiles\PIM\Exports\PPOS Derv Calc 6Apr2022.xlsx | P5: PPOS Mandate
A6: ABMMABR | B6: =[5]Summary!$G$3 -> UT | C6: =[5]Summary!$E$1 -> 9 | D6: =[5]Summary!$C$34 -> 0.032542983 | E6: =[5]Summary!$E$34/100 -> 0.032542983 | F6: =[5]Summary!$C$36 -> 0.16070469 | G6: =[5]Summary!$C$32 -> 0 | H6: =[5]Summary!$E$6/100 -> 0 | I6: =[5]Summary!$E$10/100 -> 0 | J6: =[5]Summary!$E$14/100 -> 0 | K6: =[5]Summary!$C$40 -> 0.35493861 | L6: =[5]Summary!$C$54 -> 19.462523 | M6: ='[5]Glbl Expsr'!$D$2 -> 0.84041325 | N6: ='[5]Glbl Expsr'!$D$3 -> 0.18768625 | O6: \\pim-cpt-statpro\SPC_602\Client\Profiles\PIM\Exports\ABMMABR Derv Calc 6Apr2022.xlsx | P6: ABMMABR Mandate
A7: GTCWP2 | B7: =[6]Summary!$G$3 -> UT | C7: =[6]Summary!$E$1 -> 9 | D7: =[6]Summary!$C$34 -> 0.058168227 | E7: =[6]Summary!$E$34/100 -> 0.058168227 | F7: =[6]Summary!$C$36 -> 0 | G7: =[6]Summary!$C$32 -> 0 | H7: =[6]Summary!$E$6/100 -> 0 | I7: =[6]Summary!$E$10/100 -> 0 | J7: =[6]Summary!$E$14/100 -> 0 | K7: =[6]Summary!$C$40 -> 0.6895952 | L7: =[6]Summary!$C$54 -> 0 | M7: ='[6]Glbl Expsr'!$D$2 -> 1.7138448 | N7: ='[6]Glbl Expsr'!$D$3 -> 0.50317318 | O7: \\pim-cpt-statpro\SPC_602\Client\Profiles\PIM\Exports\GTCWP2 Derv Calc 6Apr2022.xlsx | P7: GTCWP2 Mandate
A8: IJGBAL | B8: =[7]Summary!$G$3 -> UT | C8: =[7]Summary!$E$1 -> 7 | D8: =[7]Summary!$C$34 -> 0.3194741 | E8: =[7]Summary!$E$34/100 -> 0.3194741 | F8: =[7]Summary!$C$36 | G8: =[7]Summary!$C$32 -> 0.19963364 | H8: =[7]Summary!$E$6/100 -> 0 | I8: =[7]Summary!$E$10/100 -> 0 | J8: =[7]Summary!$E$14/100 -> 0 | K8: =[7]Summary!$C$40 -> 2.9931069 | L8: =[7]Summary!$C$54 -> 17.269108 | M8: ='[7]Glbl Expsr'!$D$2 -> 2.81539 | N8: ='[7]Glbl Expsr'!$D$3 -> 2.81539 | O8: \\pim-cpt-statpro\SPC_602\Client\Profiles\PIM\Exports\IJGBAL Derv Calc 6Apr2022.xlsx | P8: IJGBAL Mandate
A9: PCCEF | B9: =[8]Summary!$G$3 -> UT | C9: =[8]Summary!$E$1 -> 7 | D9: =[8]Summary!$C$34 -> 0.25044271 | E9: =[8]Summary!$E$34/100 -> 0.25044271 | F9: =[8]Summary!$C$36 -> 0 | G9: =[8]Summary!$C$32 -> 0 | H9: =[8]Summary!$E$6/100 -> 0 | I9: =[8]Summary!$E$10/100 -> 0.033255527 | J9: =[8]Summary!$E$14/100 -> 0.17587447 | K9: =[8]Summary!$C$40 -> 0.99069313 | L9: =[8]Summary!$C$54 -> 0 | M9: ='[8]Glbl Expsr'!$D$2 -> 0.23999995 | N9: ='[8]Glbl Expsr'!$D$3 -> 0.23999995 | O9: \\pim-cpt-statpro\SPC_602\Client\Profiles\PIM\Exports\PCCEF Derv Calc 6Apr2022.xlsx | P9: PCCEF Mandate
A10: PCEQTF | B10: =[9]Summary!$G$3 -> UT | C10: =[9]Summary!$E$1 -> 7 | D10: =[9]Summary!$C$34 -> 0.34681845 | E10: =[9]Summary!$E$34/100 -> 0.34681845 | F10: =[9]Summary!$C$36 -> 0 | G10: =[9]Summary!$C$32 -> 0 | H10: =[9]Summary!$E$6/100 -> 0 | I10: =[9]Summary!$E$10/100 -> 0.019768545 | J10: =[9]Summary!$E$14/100 -> 0.14712865 | K10: =[9]Summary!$C$40 -> 0.93018558 | L10: =[9]Summary!$C$54 -> 0 | M10: ='[9]Glbl Expsr'!$D$2 -> 0.088422855 | N10: ='[9]Glbl Expsr'!$D$3 -> 0.088422855 | O10: \\pim-cpt-statpro\SPC_602\Client\Profiles\PIM\Exports\PCEQTF Derv Calc 6Apr2022.xlsx | P10: PCEQTF Mandate
A11: PIMBAL | B11: =[10]Summary!$G$3 -> UT | C11: =[10]Summary!$E$1 -> 6 | D11: =[10]Summary!$C$34 -> 0.0071720338 | E11: =[10]Summary!$E$34/100 -> 0.037108757 | F11: =[10]Summary!$C$36 -> 0.12636503 | G11: =[10]Summary!$C$32 -> 0 | H11: =[10]Summary!$E$6/100 -> 0 | I11: =[10]Summary!$E$10/100 -> 0 | J11: =[10]Summary!$E$14/100 -> 0 | K11: =[10]Summary!$C$40 -> 0.64844859 | L11: =[10]Summary!$C$54 -> 43.825415 | M11: ='[10]Glbl Expsr'!$D$2 -> 0.028740154 | N11: ='[10]Glbl Expsr'!$D$3 -> 0.028740154 | O11: \\pim-cpt-statpro\SPC_602\Client\Profiles\PIM\Exports\PIMBAL Derv Calc 6Apr2022.xlsx | P11: PIMBAL Mandate
A12: PEAQ | B12: =[11]Summary!$G$3 -> UT | C12: =[11]Summary!$E$1 -> 5 | D12: =[11]Summary!$C$34 -> 0.47815719 | E12: =[11]Summary!$E$34/100 -> 0.47815719 | F12: =[11]Summary!$C$36 -> 0 | G12: =[11]Summary!$C$32 -> 0 | H12: =[11]Summary!$E$6/100 -> 0 | I12: =[11]Summary!$E$10/100 -> 0.042280309 | J12: =[11]Summary!$E$14/100 -> 0.21361833 | K12: =[11]Summary!$C$40 -> 0.98260704 | L12: =[11]Summary!$C$54 -> 0 | M12: ='[11]Glbl Expsr'!$D$2 -> 0.29444411 | N12: ='[11]Glbl Expsr'!$D$3 -> 0.29444411 | O12: \\pim-cpt-statpro\SPC_602\Client\Profiles\PIM\Exports\PEAQ Derv Calc 6Apr2022.xlsx | P12: PEAQ Mandate
A13: PBAL | B13: =[12]Summary!$G$3 -> UT | C13: =[12]Summary!$E$1 -> 4 | D13: =[12]Summary!$C$34 -> 0.0077845601 | E13: =[12]Summary!$E$34/100 -> 0.052814815 | F13: =[12]Summary!$C$36 -> 0.1589352 | G13: =[12]Summary!$C$32 -> 0 | H13: =[12]Summary!$E$6/100 -> 0 | I13: =[12]Summary!$E$10/100 -> 0 | J13: =[12]Summary!$E$14/100 -> 0 | K13: =[12]Summary!$C$40 -> 0.66108884 | L13: =[12]Summary!$C$54 -> 44.692991 | M13: ='[12]Glbl Expsr'!$D$2 -> 0.02812015 | N13: ='[12]Glbl Expsr'!$D$3 -> 0.02812015 | O13: \\pim-cpt-statpro\SPC_602\Client\Profiles\PIM\Exports\PBAL Derv Calc 6Apr2022.xlsx | P13: PBAL Mandate
A14: PPEF | B14: =[13]Summary!$G$3 -> UT | C14: =[13]Summary!$E$1 -> 4 | D14: =[13]Summary!$C$34 -> 0.12496283 | E14: =[13]Summary!$E$34/100 -> 0.12496283 | F14: =[13]Summary!$C$36 -> 0 | G14: =[13]Summary!$C$32 -> 0 | H14: =[13]Summary!$E$6/100 -> 0 | I14: =[13]Summary!$E$10/100 -> 0.017163907 | J14: =[13]Summary!$E$14/100 -> 0.38376815 | K14: =[13]Summary!$C$40 -> 0.99371009 | L14: =[13]Summary!$C$54 -> 0 | M14: ='[13]Glbl Expsr'!$D$2 -> 0.30927369 | N14: ='[13]Glbl Expsr'!$D$3 -> 0.30927369 | O14: \\pim-cpt-statpro\SPC_602\Client\Profiles\PIM\Exports\PPEF Derv Calc 6Apr2022.xlsx | P14: PPEF Mandate
A15: ABMMEQU | B15: =[14]Summary!$G$3 -> UT | C15: =[14]Summary!$E$1 -> 4 | D15: =[14]Summary!$C$34 -> 0.36844942 | E15: =[14]Summary!$E$34/100 -> 0.36844942 | F15: =[14]Summary!$C$36 -> 0 | G15: =[14]Summary!$C$32 -> 0 | H15: =[14]Summary!$E$6/100 -> 0 | I15: =[14]Summary!$E$10/100 -> 0.014180764 | J15: =[14]Summary!$E$14/100 -> 0.11705303 | K15: =[14]Summary!$C$40 -> 0.99281602 | L15: =[14]Summary!$C$54 -> 0 | M15: ='[14]Glbl Expsr'!$D$2 -> 0.12444838 | N15: ='[14]Glbl Expsr'!$D$3 -> 0.12444838 | O15: \\pim-cpt-statpro\SPC_602\Client\Profiles\PIM\Exports\ABMMEQU Derv Calc 6Apr2022.xlsx | P15: ABMMEQU Mandate
A16: PEQ | B16: =[15]Summary!$G$3 -> UT | C16: =[15]Summary!$E$1 -> 4 | D16: =[15]Summary!$C$34 -> 0.46363122 | E16: =[15]Summary!$E$34/100 -> 0.46363122 | F16: =[15]Summary!$C$36 -> 0 | G16: =[15]Summary!$C$32 -> 0 | H16: =[15]Summary!$E$6/100 -> 0 | I16: =[15]Summary!$E$10/100 -> 0 | J16: =[15]Summary!$E$14/100 -> 0 | K16: =[15]Summary!$C$40 -> 0.99423061 | L16: =[15]Summary!$C$54 -> 0 | M16: ='[15]Glbl Expsr'!$D$2 -> 0.15333856 | N16: ='[15]Glbl Expsr'!$D$3 -> 0.15333856 | O16: \\pim-cpt-statpro\SPC_602\Client\Profiles\PIM\Exports\PEQ Derv Calc 6Apr2022.xlsx | P16: PEQ Mandate
A17: SAAMMAN | B17: =[16]Summary!$G$3 -> UT | C17: =[16]Summary!$E$1 -> 3 | D17: =[16]Summary!$C$34 -> 0.0064514805 | E17: =[16]Summary!$E$34/100 -> 0.0064514805 | F17: =[16]Summary!$C$36 -> 0 | G17: =[16]Summary!$C$32 -> 0 | H17: =[16]Summary!$E$6/100 -> 0 | I17: =[16]Summary!$E$10/100 -> 0 | J17: =[16]Summary!$E$14/100 -> 0 | K17: =[16]Summary!$C$40 -> 4.5373426 | L17: =[16]Summary!$C$54 -> 0 | M17: ='[16]Glbl Expsr'!$D$2 -> 4.5373426 | N17: ='[16]Glbl Expsr'!$D$3 -> 4.5373426 | O17: \\pim-cpt-statpro\SPC_602\Client\Profiles\PIM\Exports\SAAMMAN Derv Calc 6Apr2022.xlsx | P17: SAAMMAN Mandate
A18: SAAMCAU | B18: =[17]Summary!$G$3 -> UT | C18: =[17]Summary!$E$1 -> 3 | D18: =[17]Summary!$C$34 -> 0.0087109861 | E18: =[17]Summary!$E$34/100 -> 0.0087109861 | F18: =[17]Summary!$C$36 -> 0 | G18: =[17]Summary!$C$32 -> 0 | H18: =[17]Summary!$E$6/100 -> 0 | I18: =[17]Summary!$E$10/100 -> 0 | J18: =[17]Summary!$E$14/100 -> 0 | K18: =[17]Summary!$C$40 -> 4.8874986 | L18: =[17]Summary!$C$54 -> 0 | M18: ='[17]Glbl Expsr'!$D$2 -> 4.8874986 | N18: ='[17]Glbl Expsr'!$D$3 -> 4.8874986 | O18: \\pim-cpt-statpro\SPC_602\Client\Profiles\PIM\Exports\SAAMCAU Derv Calc 6Apr2022.xlsx | P18: SAAMCAU Mandate
A19: PABS | B19: =[18]Summary!$G$3 -> UT | C19: =[18]Summary!$E$1 -> 3 | D19: =[18]Summary!$C$34 -> 0.010002733 | E19: =[18]Summary!$E$34/100 -> 0.10720719 | F19: =[18]Summary!$C$36 -> 0.29925094 | G19: =[18]Summary!$C$32 -> 0 | H19: =[18]Summary!$E$6/100 -> 0 | I19: =[18]Summary!$E$10/100 -> 0 | J19: =[18]Summary!$E$14/100 -> 0 | K19: =[18]Summary!$C$40 -> 0.31714404 | L19: =[18]Summary!$C$54 -> 43.613811 | M19: ='[18]Glbl Expsr'!$D$2 -> 0.0092307135 | N19: ='[18]Glbl Expsr'!$D$3 -> 0.0092307135 | O19: \\pim-cpt-statpro\SPC_602\Client\Profiles\PIM\Exports\PABS Derv Calc 6Apr2022.xlsx | P19: PABS Mandate
A20: SAAMMOD | B20: =[19]Summary!$G$3 -> UT | C20: =[19]Summary!$E$1 -> 3 | D20: =[19]Summary!$C$34 -> 0.011947854 | E20: =[19]Summary!$E$34/100 -> 0.011947854 | F20: =[19]Summary!$C$36 -> 0 | G20: =[19]Summary!$C$32 -> 0 | H20: =[19]Summary!$E$6/100 -> 0 | I20: =[19]Summary!$E$10/100 -> 0 | J20: =[19]Summary!$E$14/100 -> 0 | K20: =[19]Summary!$C$40 -> 4.5371611 | L20: =[19]Summary!$C$54 -> 0 | M20: ='[19]Glbl Expsr'!$D$2 -> 4.5371611 | N20: ='[19]Glbl Expsr'!$D$3 -> 4.5371611 | O20: \\pim-cpt-statpro\SPC_602\Client\Profiles\PIM\Exports\SAAMMOD Derv Calc 6Apr2022.xlsx | P20: SAAMMOD Mandate
A21: SMMRRF | B21: =[20]Summary!$G$3 -> UT | C21: =[20]Summary!$E$1 -> 2 | D21: =[20]Summary!$C$34 -> 0.0037491671 | E21: =[20]Summary!$E$34/100 -> 0.0037491671 | F21: =[20]Summary!$C$36 -> 0.0099448086 | G21: =[20]Summary!$C$32 -> 0 | H21: =[20]Summary!$E$6/100 -> 0 | I21: =[20]Summary!$E$10/100 -> 0 | J21: =[20]Summary!$E$14/100 -> 0 | K21: =[20]Summary!$C$40 -> 0.35472694 | L21: =[20]Summary!$C$54 -> 0 | M21: ='[20]Glbl Expsr'!$D$2 -> 0.26707297 | N21: ='[20]Glbl Expsr'!$D$3 -> 0.26707297 | O21: \\pim-cpt-statpro\SPC_602\Client\Profiles\PIM\Exports\SMMRRF Derv Calc 6Apr2022.xlsx | P21: SMMRRF Mandate
A22: HOLDINC | B22: =[21]Summary!$G$3 -> UT | C22: =[21]Summary!$E$1 -> 2 | D22: =[21]Summary!$C$34 -> 0.16480126 | E22: =[21]Summary!$E$34/100 -> 0.16480126 | F22: =[21]Summary!$C$36 -> 0.67706999 | G22: =[21]Summary!$C$32 -> 0 | H22: =[21]Summary!$E$6/100 -> 0.13037834 | I22: =[21]Summary!$E$10/100 -> 0 | J22: =[21]Summary!$E$14/100 -> 0.0020140446 | K22: =[21]Summary!$C$40 -> 0.047540833 | L22: =[21]Summary!$C$54 -> 5.1072566 | M22: ='[21]Glbl Expsr'!$D$2 -> 0.00019583205 | N22: ='[21]Glbl Expsr'!$D$3 -> 0.00019413205 | O22: \\pim-cpt-statpro\SPC_602\Client\Profiles\PIM\Exports\HOLDINC Derv Calc 6Apr2022.xlsx | P22: HOLDINC Mandate
A23: CAPGIP | B23: =[22]Summary!$G$3 -> UT | C23: =[22]Summary!$E$1 -> 2 | D23: =[22]Summary!$C$34 -> 0.1873959 | E23: =[22]Summary!$E$34/100 -> 0.1873959 | F23: =[22]Summary!$C$36 -> 0.45405665 | G23: =[22]Summary!$C$32 -> 0 | H23: =[22]Summary!$E$6/100 -> 0.057555138 | I23: =[22]Summary!$E$10/100 -> 0 | J23: =[22]Summary!$E$14/100 -> 0 | K23: =[22]Summary!$C$40 -> 0.057927489 | L23: =[22]Summary!$C$54 -> 8.4597345 | M23: ='[22]Glbl Expsr'!$D$2 -> 0.00017937063 | N23: ='[22]Glbl Expsr'!$D$3 -> 0.00017781353 | O23: \\pim-cpt-statpro\SPC_602\Client\Profiles\PIM\Exports\CAPGIP Derv Calc 6Apr2022.xlsx | P23: CAPGIP Mandate
A24: MOMBBF | B24: =[23]Summary!$G$3 -> UT | C24: =[23]Summary!$E$1 -> 2 | D24: =[23]Summary!$C$34 -> 0.18812216 | E24: =[23]Summary!$E$34/100 -> 0.18812216 | F24: =[23]Summary!$C$36 -> 0.66968045 | G24: =[23]Summary!$C$32 -> 0 | H24: =[23]Summary!$E$6/100 -> 0.11040074 | I24: =[23]Summary!$E$10/100 -> 0 | J24: =[23]Summary!$E$14/100 -> 0 | K24: =[23]Summary!$C$40 -> 0.056875318 | L24: =[23]Summary!$C$54 -> 5.6319494 | M24: ='[23]Glbl Expsr'!$D$2 -> 0.00023108087 | N24: ='[23]Glbl Expsr'!$D$3 -> 0.00022907488 | O24: \\pim-cpt-statpro\SPC_602\Client\Profiles\PIM\Exports\MOMBBF Derv Calc 6Apr2022.xlsx | P24: MOMBBF Mandate
A25: PPSFLEX | B25: =[24]Summary!$G$3 -> UT | C25: =[24]Summary!$E$1 -> 2 | D25: =[24]Summary!$C$34 -> 0.19016158 | E25: =[24]Summary!$E$34/100 -> 0.19016158 | F25: =[24]Summary!$C$36 -> 0.63298718 | G25: =[24]Summary!$C$32 -> 0 | H25: =[24]Summary!$E$6/100 -> 0.10877986 | I25: =[24]Summary!$E$10/100 -> 0 | J25: =[24]Summary!$E$14/100 -> 0 | K25: =[24]Summary!$C$40 -> 0.057519799 | L25: =[24]Summary!$C$54 -> 7.8233252 | M25: ='[24]Glbl Expsr'!$D$2 -> 0.00028324351 | N25: ='[24]Glbl Expsr'!$D$3 -> 0.0002807847 | O25: \\pim-cpt-statpro\SPC_602\Client\Profiles\PIM\Exports\PPSFLEX Derv Calc 6Apr2022.xlsx | P25: PPSFLEX Mandate
A26: HOLYPF | B26: =[25]Summary!$G$3 -> UT | C26: =[25]Summary!$E$1 -> 2 | D26: =[25]Summary!$C$34 -> 0.22456624 | E26: =[25]Summary!$E$34/100 -> 0.22456624 | F26: =[25]Summary!$C$36 -> 0.77463768 | G26: =[25]Summary!$C$32 -> 0 | H26: =[25]Summary!$E$6/100 -> 0.12072134 | I26: =[25]Summary!$E$10/100 -> 0 | J26: =[25]Summary!$E$14/100 -> 0 | K26: =[25]Summary!$C$40 -> 0.00013893527 | L26: =[25]Summary!$C$54 -> -1.4970156 | M26: ='[25]Glbl Expsr'!$D$2 -> 0.00014015192 | N26: ='[25]Glbl Expsr'!$D$3 -> 0.00013893527 | O26: \\pim-cpt-statpro\SPC_602\Client\Profiles\PIM\Exports\HOLYPF Derv Calc 6Apr2022.xlsx | P26: HOLYPF Mandate
A27: SMMAIF | B27: =[26]Summary!$G$3 -> UT | C27: =[26]Summary!$E$1 -> 2 | D27: =[26]Summary!$C$34 -> 0.22633957 | E27: =[26]Summary!$E$34/100 -> 0.22633957 | F27: =[26]Summary!$C$36 -> 0.57166136 | G27: =[26]Summary!$C$32 -> 0 | H27: =[26]Summary!$E$6/100 -> 0.042692009 | I27: =[26]Summary!$E$10/100 -> 0 | J27: =[26]Summary!$E$14/100 -> 0 | K27: =[26]Summary!$C$40 -> 0.036006721 | L27: =[26]Summary!$C$54 -> 4.7421055 | M27: ='[26]Glbl Expsr'!$D$2 -> 0.0001621699 | N27: ='[26]Glbl Expsr'!$D$3 -> 0.00016076212 | O27: \\pim-cpt-statpro\SPC_602\Client\Profiles\PIM\Exports\SMMAIF Derv Calc 6Apr2022.xlsx | P27: SMMAIF Mandate
A28: GRFINV | B28: =[27]Summary!$G$3 -> UT | C28: =[27]Summary!$E$1 -> 2 | D28: =[27]Summary!$C$34 -> 0.29621998 | E28: =[27]Summary!$E$34/100 -> 0.29621998 | F28: =[27]Summary!$C$36 -> 0.39682893 | G28: =[27]Summary!$C$32 -> 0 | H28: =[27]Summary!$E$6/100 -> 0.046830667 | I28: =[27]Summary!$E$10/100 -> 0 | J28: =[27]Summary!$E$14/100 -> 0 | K28: =[27]Summary!$C$40 -> 0.043889842 | L28: =[27]Summary!$C$54 -> 2.0980708 | M28: ='[27]Glbl Expsr'!$D$2 -> 0.00039647873 | N28: ='[27]Glbl Expsr'!$D$3 -> 0.00039303693 | O28: \\pim-cpt-statpro\SPC_602\Client\Profiles\PIM\Exports\GRFINV Derv Calc 6Apr2022.xlsx | P28: GRFINV Mandate
A29: ASHFLX | B29: =[28]Summary!$G$3 -> UT | C29: =[28]Summary!$E$1 -> 2 | D29: =[28]Summary!$C$34 -> 0.36241963 | E29: =[28]Summary!$E$34/100 -> 0.36241963 | F29: =[28]Summary!$C$36 -> 0.55031471 | G29: =[28]Summary!$C$32 -> 0 | H29: =[28]Summary!$E$6/100 -> 0.1143555 | I29: =[28]Summary!$E$10/100 -> 0 | J29: =[28]Summary!$E$14/100 -> 0 | K29: =[28]Summary!$C$40 -> 0.038489007 | L29: =[28]Summary!$C$54 -> 1.9755032 | M29: ='[28]Glbl Expsr'!$D$2 -> 0.00026332107 | N29: ='[28]Glbl Expsr'!$D$3 -> 0.0002610352 | O29: \\pim-cpt-statpro\SPC_602\Client\Profiles\PIM\Exports\ASHFLX Derv Calc 6Apr2022.xlsx | P29: ASHFLX Mandate
A30: MOMFLX | B30: =[29]Summary!$G$3 -> UT | C30: =[29]Summary!$E$1 -> 0 | D30: =[29]Summary!$C$34 -> 0.002056792 | E30: =[29]Summary!$E$34/100 -> 0.002056792 | F30: =[29]Summary!$C$36 -> 0.99794321 | G30: =[29]Summary!$C$32 -> 0 | H30: =[29]Summary!$E$6/100 -> 0 | I30: =[29]Summary!$E$10/100 -> 0 | J30: =[29]Summary!$E$14/100 -> 0 | K30: =[29]Summary!$C$40 -> 0 | L30: =[29]Summary!$C$54 -> 0 | M30: ='[29]Glbl Expsr'!$D$2 -> 0 | N30: ='[29]Glbl Expsr'!$D$3 -> 0 | O30: \\pim-cpt-statpro\SPC_602\Client\Profiles\PIM\Exports\MOMFLX Derv Calc 6Apr2022.xlsx | P30: MOMFLX Mandate
A31: SMMIBF | B31: =[30]Summary!$G$3 -> UT | C31: =[30]Summary!$E$1 -> 0 | D31: =[30]Summary!$C$34 -> 0.0024365093 | E31: =[30]Summary!$E$34/100 -> 0.0024365093 | F31: =[30]Summary!$C$36 -> 0.99756349 | G31: =[30]Summary!$C$32 -> 0 | H31: =[30]Summary!$E$6/100 -> 0.023064705 | I31: =[30]Summary!$E$10/100 -> 0 | J31: =[30]Summary!$E$14/100 -> 0 | K31: =[30]Summary!$C$40 -> 0 | L31: =[30]Summary!$C$54 -> 0 | M31: ='[30]Glbl Expsr'!$D$2 -> 0 | N31: ='[30]Glbl Expsr'!$D$3 -> 0 | O31: \\pim-cpt-statpro\SPC_602\Client\Profiles\PIM\Exports\SMMIBF Derv Calc 6Apr2022.xlsx | P31: SMMIBF Mandate
A32: PBNDQ | B32: =[31]Summary!$G$3 -> UT | C32: =[31]Summary!$E$1 -> 0 | D32: =[31]Summary!$C$34 -> 0.0030173301 | E32: =[31]Summary!$E$34/100 -> 0.0030173301 | F32: =[31]Summary!$C$36 -> 0.99698267 | G32: =[31]Summary!$C$32 -> 0 | H32: =[31]Summary!$E$6/100 -> 0 | I32: =[31]Summary!$E$10/100 -> 0 | J32: =[31]Summary!$E$14/100 -> 0 | K32: =[31]Summary!$C$40 -> 0 | L32: =[31]Summary!$C$54 -> 0 | M32: ='[31]Glbl Expsr'!$D$2 -> 0 | N32: ='[31]Glbl Expsr'!$D$3 -> 0 | O32: \\pim-cpt-statpro\SPC_602\Client\Profiles\PIM\Exports\PBNDQ Derv Calc 6Apr2022.xlsx | P32: PBNDQ Mandate
A33: OMFLXI5 | B33: =[32]Summary!$G$3 -> UT | C33: =[32]Summary!$E$1 -> 0 | D33: =[32]Summary!$C$34 -> 0.0032614639 | E33: =[32]Summary!$E$34/100 -> 0.0032614639 | F33: =[32]Summary!$C$36 -> 0.99673854 | G33: =[32]Summary!$C$32 -> 0 | H33: =[32]Summary!$E$6/100 -> 0 | I33: =[32]Summary!$E$10/100 -> 0 | J33: =[32]Summary!$E$14/100 -> 0 | K33: =[32]Summary!$C$40 -> 0 | L33: =[32]Summary!$C$54 -> 0 | M33: ='[32]Glbl Expsr'!$D$2 -> 0 | N33: ='[32]Glbl Expsr'!$D$3 -> 0 | O33: \\pim-cpt-statpro\SPC_602\Client\Profiles\PIM\Exports\OMFLXI5 Derv Calc 6Apr2022.xlsx | P33: OMFLXI5 Mandate
A34: SMMBPR | B34: =[33]Summary!$G$3 -> UT | C34: =[33]Summary!$E$1 -> 0 | D34: =[33]Summary!$C$34 -> 0.0035404715 | E34: =[33]Summary!$E$34/100 -> 0.0035404715 | F34: =[33]Summary!$C$36 -> 0.99645953 | G34: =[33]Summary!$C$32 -> 0 | H34: =[33]Summary!$E$6/100 -> 0.0064483781 | I34: =[33]Summary!$E$10/100 -> 0 | J34: =[33]Summary!$E$14/100 -> 0 | K34: =[33]Summary!$C$40 -> 0 | L34: =[33]Summary!$C$54 -> 0 | M34: ='[33]Glbl Expsr'!$D$2 -> 0 | N34: ='[33]Glbl Expsr'!$D$3 -> 0 | O34: \\pim-cpt-statpro\SPC_602\Client\Profiles\PIM\Exports\SMMBPR Derv Calc 6Apr2022.xlsx | P34: SMMBPR Mandate
A35: STSBND | B35: =[34]Summary!$G$3 -> UT | C35: =[34]Summary!$E$1 -> 0 | D35: =[34]Summary!$C$34 -> 0.0037745671 | E35: =[34]Summary!$E$34/100 -> 0.0037745671 | F35: =[34]Summary!$C$36 -> 0.99622543 | G35: =[34]Summary!$C$32 -> 0 | H35: =[34]Summary!$E$6/100 -> 0.01509834 | I35: =[34]Summary!$E$10/100 -> 0 | J35: =[34]Summary!$E$14/100 -> 0 | K35: =[34]Summary!$C$40 -> 0 | L35: =[34]Summary!$C$54 -> 0 | M35: ='[34]Glbl Expsr'!$D$2 -> 0 | N35: ='[34]Glbl Expsr'!$D$3 -> 0 | O35: \\pim-cpt-statpro\SPC_602\Client\Profiles\PIM\Exports\STSBND Derv Calc 6Apr2022.xlsx | P35: STSBND Mandate
A36: ASHGFB | B36: =[35]Summary!$G$3 -> UT | C36: =[35]Summary!$E$1 -> 0 | D36: =[35]Summary!$C$34 -> 0.0042467954 | E36: =[35]Summary!$E$34/100 -> 0.0042467954 | F36: =[35]Summary!$C$36 -> 0.9957532 | G36: =[35]Summary!$C$32 -> 0 | H36: =[35]Summary!$E$6/100 -> 0 | I36: =[35]Summary!$E$10/100 -> 0 | J36: =[35]Summary!$E$14/100 -> 0 | K36: =[35]Summary!$C$40 -> 0 | L36: =[35]Summary!$C$54 -> 0 | M36: ='[35]Glbl Expsr'!$D$2 -> 0 | N36: ='[35]Glbl Expsr'!$D$3 -> 0 | O36: \\pim-cpt-statpro\SPC_602\Client\Profiles\PIM\Exports\ASHGFB Derv Calc 6Apr2022.xlsx | P36: ASHGFB Mandate
A37: ABMMBND | B37: =[36]Summary!$G$3 -> UT | C37: =[36]Summary!$E$1 -> 0 | D37: =[36]Summary!$C$34 -> 0.0056691116 | E37: =[36]Summary!$E$34/100 -> 0.0056691116 | F37: =[36]Summary!$C$36 -> 0.99433089 | G37: =[36]Summary!$C$32 -> 0 | H37: =[36]Summary!$E$6/100 -> 0 | I37: =[36]Summary!$E$10/100 -> 0 | J37: =[36]Summary!$E$14/100 -> 0 | K37: =[36]Summary!$C$40 -> 0 | L37: =[36]Summary!$C$54 -> 0 | M37: ='[36]Glbl Expsr'!$D$2 -> 0 | N37: ='[36]Glbl Expsr'!$D$3 -> 0 | O37: \\pim-cpt-statpro\SPC_602\Client\Profiles\PIM\Exports\ABMMBND Derv Calc 6Apr2022.xlsx | P37: ABMMBND Mandate
A38: PCGEF | B38: =[37]Summary!$G$3 -> UT | C38: =[37]Summary!$E$1 -> 0 | D38: =[37]Summary!$C$34 -> 0.0094445606 | E38: =[37]Summary!$E$34/100 -> 0.0094445606 | F38: =[37]Summary!$C$36 -> 0 | G38: =[37]Summary!$C$32 -> 0 | H38: =[37]Summary!$E$6/100 -> 0 | I38: =[37]Summary!$E$10/100 -> 0 | J38: =[37]Summary!$E$14/100 -> 0 | K38: =[37]Summary!$C$40 -> 0.99055544 | L38: =[37]Summary!$C$54 -> 99.055544 | M38: ='[37]Glbl Expsr'!$D$2 -> 0 | N38: ='[37]Glbl Expsr'!$D$3 -> 0 | O38: \\pim-cpt-statpro\SPC_602\Client\Profiles\PIM\Exports\PCGEF Derv Calc 6Apr2022.xlsx | P38: PCGEF Mandate
A39: PGGF | B39: =[38]Summary!$G$3 -> UT | C39: =[38]Summary!$E$1 -> 0 | D39: =[38]Summary!$C$34 -> 0.010070441 | E39: =[38]Summary!$E$34/100 -> 0.010070441 | F39: =[38]Summary!$C$36 -> 0 | G39: =[38]Summary!$C$32 -> 0 | H39: =[38]Summary!$E$6/100 -> 0 | I39: =[38]Summary!$E$10/100 -> 0 | J39: =[38]Summary!$E$14/100 -> 0 | K39: =[38]Summary!$C$40 -> 0.98992956 | L39: =[38]Summary!$C$54 -> 98.992956 | M39: ='[38]Glbl Expsr'!$D$2 -> 0 | N39: ='[38]Glbl Expsr'!$D$3 -> 0 | O39: \\pim-cpt-statpro\SPC_602\Client\Profiles\PIM\Exports\PGGF Derv Calc 6Apr2022.xlsx | P39: PGGF Mandate
A40: IJGCOR | B40: =[39]Summary!$G$3 -> UT | C40: =[39]Summary!$E$1 -> 0 | D40: =[39]Summary!$C$34 -> 0.035793677 | E40: =[39]Summary!$E$34/100 -> 0.035793677 | F40: =[39]Summary!$C$36 -> 0 | G40: =[39]Summary!$C$32 -> 0 | H40: =[39]Summary!$E$6/100 -> 0 | I40: =[39]Summary!$E$10/100 -> 0 | J40: =[39]Summary!$E$14/100 -> 0 | K40: =[39]Summary!$C$40 -> 0 | L40: =[39]Summary!$C$54 -> 96.420632 | M40: ='[39]Glbl Expsr'!$D$2 -> 0 | N40: ='[39]Glbl Expsr'!$D$3 -> 0 | O40: \\pim-cpt-statpro\SPC_602\Client\Profiles\PIM\Exports\IJGCOR Derv Calc 6Apr2022.xlsx | P40: IJGCOR Mandate
A41: PGIF | B41: =[40]Summary!$G$3 -> UT | C41: =[40]Summary!$E$1 -> 0 | D41: =[40]Summary!$C$34 -> 0.039919152 | E41: =[40]Summary!$E$34/100 -> 0.039919152 | F41: =[40]Summary!$C$36 -> 0 | G41: =[40]Summary!$C$32 -> 0 | H41: =[40]Summary!$E$6/100 -> 0 | I41: =[40]Summary!$E$10/100 -> 0 | J41: =[40]Summary!$E$14/100 -> 0 | K41: =[40]Summary!$C$40 -> 0 | L41: =[40]Summary!$C$54 -> 96.008085 | M41: ='[40]Glbl Expsr'!$D$2 -> 0 | N41: ='[40]Glbl Expsr'!$D$3 -> 0 | O41: \\pim-cpt-statpro\SPC_602\Client\Profiles\PIM\Exports\PGIF Derv Calc 6Apr2022.xlsx | P41: PGIF Mandate
A42: PFFIF | B42: =[41]Summary!$G$3 -> UT | C42: =[41]Summary!$E$1 -> 0 | D42: =[41]Summary!$C$34 -> 0.11338492 | E42: =[41]Summary!$E$34/100 -> 0.11338492 | F42: =[41]Summary!$C$36 -> 0.68511499 | G42: =[41]Summary!$C$32 -> 0 | H42: =[41]Summary!$E$6/100 -> 0.060509617 | I42: =[41]Summary!$E$10/100 -> 0 | J42: =[41]Summary!$E$14/100 -> 0 | K42: =[41]Summary!$C$40 -> 0.022371381 | L42: =[41]Summary!$C$54 -> 0 | M42: ='[41]Glbl Expsr'!$D$2 -> 0 | N42: ='[41]Glbl Expsr'!$D$3 -> 0 | O42: \\pim-cpt-statpro\SPC_602\Client\Profiles\PIM\Exports\PFFIF Derv Calc 6Apr2022.xlsx | P42: PFFIF Mandate
A43: PSTIF | B43: =[42]Summary!$G$3 -> UT | C43: =[42]Summary!$E$1 -> 0 | D43: =[42]Summary!$C$34 -> 0.14451327 | E43: =[42]Summary!$E$34/100 -> 0.14451327 | F43: =[42]Summary!$C$36 -> 0.74948062 | G43: =[42]Summary!$C$32 -> 0 | H43: =[42]Summary!$E$6/100 -> 0.15792863 | I43: =[42]Summary!$E$10/100 -> 0 | J43: =[42]Summary!$E$14/100 -> 0 | K43: =[42]Summary!$C$40 -> 0.040134911 | L43: =[42]Summary!$C$54 -> 0 | M43: ='[42]Glbl Expsr'!$D$2 -> 0 | N43: ='[42]Glbl Expsr'!$D$3 -> 0 | O43: \\pim-cpt-statpro\SPC_602\Client\Profiles\PIM\Exports\PSTIF Derv Calc 6Apr2022.xlsx | P43: PSTIF Mandate
A44: POIF_C | B44: =[43]Summary!$G$3 -> UT | C44: =[43]Summary!$E$1 -> 0 | D44: =[43]Summary!$C$34 -> 0.15540484 | E44: =[43]Summary!$E$34/100 -> 0.15540484 | F44: =[43]Summary!$C$36 -> 0 | G44: =[43]Summary!$C$32 -> 0 | H44: =[43]Summary!$E$6/100 -> 0 | I44: =[43]Summary!$E$10/100 -> 0.046931227 | J44: =[43]Summary!$E$14/100 -> 0.8045002 | K44: =[43]Summary!$C$40 -> 0.84459516 | L44: =[43]Summary!$C$54 -> 0 | M44: ='[43]Glbl Expsr'!$D$2 -> 0 | N44: ='[43]Glbl Expsr'!$D$3 -> 0 | O44: \\pim-cpt-statpro\SPC_602\Client\Profiles\PIM\Exports\POIF_C Derv Calc 6Apr2022.xlsx | P44: POIF_C Mandate
A45: IJGIPF | B45: =[44]Summary!$G$3 -> UT | C45: =[44]Summary!$E$1 -> 0 | D45: =[44]Summary!$C$34 -> 0.19236636 | E45: =[44]Summary!$E$34/100 -> 0.19236636 | F45: =[44]Summary!$C$36 -> 0.45836587 | G45: =[44]Summary!$C$32 -> 0 | H45: =[44]Summary!$E$6/100 -> 0.054097085 | I45: =[44]Summary!$E$10/100 -> 0 | J45: =[44]Summary!$E$14/100 -> 0 | K45: =[44]Summary!$C$40 -> 0.070857989 | L45: =[44]Summary!$C$54 -> 22.561907 | M45: ='[44]Glbl Expsr'!$D$2 -> 0 | N45: ='[44]Glbl Expsr'!$D$3 -> 0 | O45: \\pim-cpt-statpro\SPC_602\Client\Profiles\PIM\Exports\IJGIPF Derv Calc 6Apr2022.xlsx | P45: IJGIPF Mandate
A46: PSIF | B46: =[45]Summary!$G$3 -> UT | C46: =[45]Summary!$E$1 -> 0 | D46: =[45]Summary!$C$34 -> 0.27139439 | E46: =[45]Summary!$E$34/100 -> 0.27139439 | F46: =[45]Summary!$C$36 -> 0.67762721 | G46: =[45]Summary!$C$32 -> 0 | H46: =[45]Summary!$E$6/100 -> 0.087436615 | I46: =[45]Summary!$E$10/100 -> 0 | J46: =[45]Summary!$E$14/100 -> 0.00080769415 | K46: =[45]Summary!$C$40 -> 0.05086244 | L46: =[45]Summary!$C$54 -> 0 | M46: ='[45]Glbl Expsr'!$D$2 -> 0 | N46: ='[45]Glbl Expsr'!$D$3 -> 0 | O46: \\pim-cpt-statpro\SPC_602\Client\Profiles\PIM\Exports\PSIF Derv Calc 6Apr2022.xlsx | P46: PSIF Mandate
A47: PCSHQ | B47: =[46]Summary!$G$3 -> UT | C47: =[46]Summary!$E$1 -> 0 | D47: =[46]Summary!$C$34 -> 0.41742217 | E47: =[46]Summary!$E$34/100 -> 0.41742217 | F47: =[46]Summary!$C$36 -> 0.58250212 | G47: =[46]Summary!$C$32 -> 0 | H47: =[46]Summary!$E$6/100 -> 0 | I47: =[46]Summary!$E$10/100 -> 0 | J47: =[46]Summary!$E$14/100 -> 0 | K47: =[46]Summary!$C$40 -> 0 | L47: =[46]Summary!$C$54 -> 0 | M47: ='[46]Glbl Expsr'!$D$2 -> 0 | N47: ='[46]Glbl Expsr'!$D$3 -> 0 | O47: \\pim-cpt-statpro\SPC_602\Client\Profiles\PIM\Exports\PCSHQ Derv Calc 6Apr2022.xlsx | P47: PCSHQ Mandate
A48: SMMEYP | B48: =[47]Summary!$G$3 -> UT | C48: =[47]Summary!$E$1 -> 0 | D48: =[47]Summary!$C$34 -> 0.42282884 | E48: =[47]Summary!$E$34/100 -> 0.42282884 | F48: =[47]Summary!$C$36 -> 0.57700254 | G48: =[47]Summary!$C$32 -> 0 | H48: =[47]Summary!$E$6/100 -> 0 | I48: =[47]Summary!$E$10/100 -> 0 | J48: =[47]Summary!$E$14/100 -> 0 | K48: =[47]Summary!$C$40 -> 0 | L48: =[47]Summary!$C$54 -> 0 | M48: ='[47]Glbl Expsr'!$D$2 -> 0 | N48: ='[47]Glbl Expsr'!$D$3 -> 0 | O48: \\pim-cpt-statpro\SPC_602\Client\Profiles\PIM\Exports\SMMEYP Derv Calc 6Apr2022.xlsx | P48: SMMEYP Mandate
A49: EMHPBQ | B49: =[48]Summary!$G$3 -> UT | C49: =[48]Summary!$E$1 -> 0 | D49: =[48]Summary!$C$34 -> 1 | E49: =[48]Summary!$E$34/100 -> 1 | F49: =[48]Summary!$C$36 -> 0 | G49: =[48]Summary!$C$32 -> 0 | H49: =[48]Summary!$E$6/100 -> 0 | I49: =[48]Summary!$E$10/100 -> 0 | J49: =[48]Summary!$E$14/100 -> 0 | K49: =[48]Summary!$C$40 -> 0 | L49: =[48]Summary!$C$54 -> 0 | M49: ='[48]Glbl Expsr'!$D$2 -> 0 | N49: ='[48]Glbl Expsr'!$D$3 -> 0 | O49: \\pim-cpt-statpro\SPC_602\Client\Profiles\PIM\Exports\EMHPBQ Derv Calc 6Apr2022.xlsx | P49: EMHPBQ Mandate
A50: SWGSWX | B50: =[49]Summary!$G$3 -> ≠ UT | C50: =[49]Summary!$E$1 -> 10 | D50: =[49]Summary!$C$34 -> 0.69521514 | E50: =[49]Summary!$E$34/100 -> 0.69521514 | F50: =[49]Summary!$C$36 | G50: =[49]Summary!$C$32 -> 0.70086344 | H50: =[49]Summary!$E$6/100 -> 0 | I50: =[49]Summary!$E$10/100 -> 0.020171587 | J50: =[49]Summary!$E$14/100 -> 0.15776626 | K50: =[49]Summary!$C$40 -> 0.99496796 | L50: =[49]Summary!$C$54 -> 0 | M50: ='[49]Glbl Expsr'!$D$2 -> 0.13254017 | N50: ='[49]Glbl Expsr'!$D$3 -> 0.13254017 | O50: \\pim-cpt-statpro\SPC_602\Client\Profiles\PIM\Exports\SWGSWX Derv Calc 6Apr2022.xlsx | P50: SWGSWX Mandate
A51: ASBTOS | B51: =[50]Summary!$G$3 -> ≠ UT | C51: =[50]Summary!$E$1 -> 9 | D51: =[50]Summary!$C$34 -> 0.48600155 | E51: =[50]Summary!$E$34/100 -> 0.48600155 | F51: =[50]Summary!$C$36 | G51: =[50]Summary!$C$32 -> 0.25839679 | H51: =[50]Summary!$E$6/100 -> 0.19864304 | I51: =[50]Summary!$E$10/100 -> 0 | J51: =[50]Summary!$E$14/100 -> 0 | K51: =[50]Summary!$C$40 -> 0.42661143 | L51: =[50]Summary!$C$54 -> 0 | M51: ='[50]Glbl Expsr'!$D$2 -> 1.0003738 | N51: ='[50]Glbl Expsr'!$D$3 -> 0.22442118 | O51: \\pim-cpt-statpro\SPC_602\Client\Profiles\PIM\Exports\ASBTOS Derv Calc 6Apr2022.xlsx | P51: ASBTOS Mandate
A52: MOMPRET | B52: =[51]Summary!$G$3 -> ≠ UT | C52: =[51]Summary!$E$1 -> 9 | D52: =[51]Summary!$C$34 -> 0.48881222 | E52: =[51]Summary!$E$34/100 -> 0.48881222 | F52: =[51]Summary!$C$36 | G52: =[51]Summary!$C$32 -> 0.36585764 | H52: =[51]Summary!$E$6/100 -> 0.19841458 | I52: =[51]Summary!$E$10/100 -> 0 | J52: =[51]Summary!$E$14/100 -> 0 | K52: =[51]Summary!$C$40 -> 0.42530382 | L52: =[51]Summary!$C$54 -> 0 | M52: ='[51]Glbl Expsr'!$D$2 -> 1.0281698 | N52: ='[51]Glbl Expsr'!$D$3 -> 0.22646763 | O52: \\pim-cpt-statpro\SPC_602\Client\Profiles\PIM\Exports\MOMPRET Derv Calc 6Apr2022.xlsx | P52: MOMPRET Mandate
A53: PSPAM | B53: =[52]Summary!$G$3 -> ≠ UT | C53: =[52]Summary!$E$1 -> 9 | D53: =[52]Summary!$C$34 -> 0.49519552 | E53: =[52]Summary!$E$34/100 -> 0.49519552 | F53: =[52]Summary!$C$36 | G53: =[52]Summary!$C$32 -> 0.25850493 | H53: =[52]Summary!$E$6/100 -> 0.19412024 | I53: =[52]Summary!$E$10/100 -> 0 | J53: =[52]Summary!$E$14/100 -> 0 | K53: =[52]Summary!$C$40 -> 0.41247377 | L53: =[52]Summary!$C$54 -> 0 | M53: ='[52]Glbl Expsr'!$D$2 -> 1.0412002 | N53: ='[52]Glbl Expsr'!$D$3 -> 0.2166133 | O53: \\pim-cpt-statpro\SPC_602\Client\Profiles\PIM\Exports\PSPAM Derv Calc 6Apr2022.xlsx | P53: PSPAM Mandate
A54: PLPRNA | B54: =[53]Summary!$G$3 -> ≠ UT | C54: =[53]Summary!$E$1 -> 9 | D54: =[53]Summary!$C$34 -> 0.49592282 | E54: =[53]Summary!$E$34/100 -> 0.49592282 | F54: =[53]Summary!$C$36 | G54: =[53]Summary!$C$32 -> 0.3511329 | H54: =[53]Summary!$E$6/100 -> 0.21370953 | I54: =[53]Summary!$E$10/100 -> 0 | J54: =[53]Summary!$E$14/100 -> 0 | K54: =[53]Summary!$C$40 -> 0.41970656 | L54: =[53]Summary!$C$54 -> 0 | M54: ='[53]Glbl Expsr'!$D$2 -> 1.058431 | N54: ='[53]Glbl Expsr'!$D$3 -> 0.22022183 | O54: \\pim-cpt-statpro\SPC_602\Client\Profiles\PIM\Exports\PLPRNA Derv Calc 6Apr2022.xlsx | P54: PLPRNA Mandate
A55: PORFGPR | B55: =[54]Summary!$G$3 -> ≠ UT | C55: =[54]Summary!$E$1 -> 9 | D55: =[54]Summary!$C$34 -> 0.52590718 | E55: =[54]Summary!$E$34/100 -> 0.52590718 | F55: =[54]Summary!$C$36 | G55: =[54]Summary!$C$32 -> 0.43251845 | H55: =[54]Summary!$E$6/100 -> 0.15955254 | I55: =[54]Summary!$E$10/100 -> 0 | J55: =[54]Summary!$E$14/100 -> 0 | K55: =[54]Summary!$C$40 -> 0.36624659 | L55: =[54]Summary!$C$54 -> 19.625628 | M55: ='[54]Glbl Expsr'!$D$2 -> 0.93497344 | N55: ='[54]Glbl Expsr'!$D$3 -> 0.18306944 | O55: \\pim-cpt-statpro\SPC_602\Client\Profiles\PIM\Exports\PORFGPR Derv Calc 6Apr2022.xlsx | P55: PORFGPR Mandate
A56: GMRETF | B56: =[55]Summary!$G$3 -> ≠ UT | C56: =[55]Summary!$E$1 -> 9 | D56: =[55]Summary!$C$34 -> 0.54325361 | E56: =[55]Summary!$E$34/100 -> 0.54325361 | F56: =[55]Summary!$C$36 | G56: =[55]Summary!$C$32 -> 0.44788333 | H56: =[55]Summary!$E$6/100 -> 0.16722989 | I56: =[55]Summary!$E$10/100 -> 0 | J56: =[55]Summary!$E$14/100 -> 0 | K56: =[55]Summary!$C$40 -> 0.37438532 | L56: =[55]Summary!$C$54 -> 19.668501 | M56: ='[55]Glbl Expsr'!$D$2 -> 0.86223606 | N56: ='[55]Glbl Expsr'!$D$3 -> 0.20501827 | O56: \\pim-cpt-statpro\SPC_602\Client\Profiles\PIM\Exports\GMRETF Derv Calc 6Apr2022.xlsx | P56: GMRETF Mandate
A57: GMRETF2 | B57: =[56]Summary!$G$3 -> ≠ UT | C57: =[56]Summary!$E$1 -> 9 | D57: =[56]Summary!$C$34 -> 0.54757375 | E57: =[56]Summary!$E$34/100 -> 0.54757375 | F57: =[56]Summary!$C$36 | G57: =[56]Summary!$C$32 -> 0.45606054 | H57: =[56]Summary!$E$6/100 -> 0.16554408 | I57: =[56]Summary!$E$10/100 -> 0 | J57: =[56]Summary!$E$14/100 -> 0 | K57: =[56]Summary!$C$40 -> 0.38361174 | L57: =[56]Summary!$C$54 -> 18.873765 | M57: ='[56]Glbl Expsr'!$D$2 -> 0.88747081 | N57: ='[56]Glbl Expsr'!$D$3 -> 0.22052143 | O57: \\pim-cpt-statpro\SPC_602\Client\Profiles\PIM\Exports\GMRETF2 Derv Calc 6Apr2022.xlsx | P57: GMRETF2 Mandate
A58: ELCIPF | B58: =[57]Summary!$G$3 -> ≠ UT | C58: =[57]Summary!$E$1 -> 8 | D58: =[57]Summary!$C$34 -> 0.020179498 | E58: =[57]Summary!$E$34/100 -> 0.020179498 | F58: =[57]Summary!$C$36 -> 0 | G58: =[57]Summary!$C$32 -> 0 | H58: =[57]Summary!$E$6/100 -> 0 | I58: =[57]Summary!$E$10/100 -> 0.033811283 | J58: =[57]Summary!$E$14/100 -> 0.18559155 | K58: =[57]Summary!$C$40 -> 0.99149454 | L58: =[57]Summary!$C$54 -> 0 | M58: ='[57]Glbl Expsr'!$D$2 -> 0.15218442 | N58: ='[57]Glbl Expsr'!$D$3 -> 0.15218442 | O58: \\pim-cpt-statpro\SPC_602\Client\Profiles\PIM\Exports\ELCIPF Derv Calc 6Apr2022.xlsx | P58: ELCIPF Mandate
A59: TSHMPF | B59: =[58]Summary!$G$3 -> ≠ UT | C59: =[58]Summary!$E$1 -> 8 | D59: =[58]Summary!$C$34 -> 0.036012353 | E59: =[58]Summary!$E$34/100 -> 0.036012353 | F59: =[58]Summary!$C$36 -> 0 | G59: =[58]Summary!$C$32 -> 0 | H59: =[58]Summary!$E$6/100 -> 0 | I59: =[58]Summary!$E$10/100 -> 0.038791986 | J59: =[58]Summary!$E$14/100 -> 0.19918968 | K59: =[58]Summary!$C$40 -> 0.99065849 | L59: =[58]Summary!$C$54 -> 0 | M59: ='[58]Glbl Expsr'!$D$2 -> 0.13466471 | N59: ='[58]Glbl Expsr'!$D$3 -> 0.13466471 | O59: \\pim-cpt-statpro\SPC_602\Client\Profiles\PIM\Exports\TSHMPF Derv Calc 6Apr2022.xlsx | P59: TSHMPF Mandate
A60: NFMWEQU | B60: =[59]Summary!$G$3 -> ≠ UT | C60: =[59]Summary!$E$1 -> 8 | D60: =[59]Summary!$C$34 -> 0.082315026 | E60: =[59]Summary!$E$34/100 -> 0.082315026 | F60: =[59]Summary!$C$36 -> 0 | G60: =[59]Summary!$C$32 -> 0 | H60: =[59]Summary!$E$6/100 -> 0 | I60: =[59]Summary!$E$10/100 -> 0.041456634 | J60: =[59]Summary!$E$14/100 -> 0.20559187 | K60: =[59]Summary!$C$40 -> 0.9929748 | L60: =[59]Summary!$C$54 -> 0 | M60: ='[59]Glbl Expsr'!$D$2 -> 0.12791244 | N60: ='[59]Glbl Expsr'!$D$3 -> 0.12791244 | O60: \\pim-cpt-statpro\SPC_602\Client\Profiles\PIM\Exports\NFMWEQU Derv Calc 6Apr2022.xlsx | P60: NFMWEQU Mandate
A61: MWPFEQU | B61: =[60]Summary!$G$3 -> ≠ UT | C61: =[60]Summary!$E$1 -> 7 | D61: =[60]Summary!$C$34 -> 0.092714644 | E61: =[60]Summary!$E$34/100 -> 0.092714644 | F61: =[60]Summary!$C$36 -> 0 | G61: =[60]Summary!$C$32 -> 0 | H61: =[60]Summary!$E$6/100 -> 0 | I61: =[60]Summary!$E$10/100 -> 0 | J61: =[60]Summary!$E$14/100 -> 0 | K61: =[60]Summary!$C$40 -> 0.99600668 | L61: =[60]Summary!$C$54 -> 0 | M61: ='[60]Glbl Expsr'!$D$2 -> 0.15441125 | N61: ='[60]Glbl Expsr'!$D$3 -> 0.15441125 | O61: \\pim-cpt-statpro\SPC_602\Client\Profiles\PIM\Exports\MWPFEQU Derv Calc 6Apr2022.xlsx | P61: MWPFEQU Mandate
A62: PPWEQU | B62: =[61]Summary!$G$3 -> ≠ UT | C62: =[61]Summary!$E$1 -> 7 | D62: =[61]Summary!$C$34 -> 0.10865402 | E62: =[61]Summary!$E$34/100 -> 0.10865402 | F62: =[61]Summary!$C$36 -> 0 | G62: =[61]Summary!$C$32 -> 0 | H62: =[61]Summary!$E$6/100 -> 0 | I62: =[61]Summary!$E$10/100 -> 0.038332914 | J62: =[61]Summary!$E$14/100 -> 0.19039019 | K62: =[61]Summary!$C$40 -> 0.99150557 | L62: =[61]Summary!$C$54 -> 0 | M62: ='[61]Glbl Expsr'!$D$2 -> 0.060655969 | N62: ='[61]Glbl Expsr'!$D$3 -> 0.060655969 | O62: \\pim-cpt-statpro\SPC_602\Client\Profiles\PIM\Exports\PPWEQU Derv Calc 6Apr2022.xlsx | P62: PPWEQU Mandate
A63: TOYCEF | B63: =[62]Summary!$G$3 -> ≠ UT | C63: =[62]Summary!$E$1 -> 7 | D63: =[62]Summary!$C$34 -> 0.18388094 | E63: =[62]Summary!$E$34/100 -> 0.18388094 | F63: =[62]Summary!$C$36 -> 0 | G63: =[62]Summary!$C$32 -> 0 | H63: =[62]Summary!$E$6/100 -> 0 | I63: =[62]Summary!$E$10/100 -> 0.018937928 | J63: =[62]Summary!$E$14/100 -> 0.15724512 | K63: =[62]Summary!$C$40 -> 0.99324049 | L63: =[62]Summary!$C$54 -> 0 | M63: ='[62]Glbl Expsr'!$D$2 -> 0.049272184 | N63: ='[62]Glbl Expsr'!$D$3 -> 0.049272184 | O63: \\pim-cpt-statpro\SPC_602\Client\Profiles\PIM\Exports\TOYCEF Derv Calc 6Apr2022.xlsx | P63: TOYCEF Mandate
A64: LIBTAA | B64: =[63]Summary!$G$3 -> ≠ UT | C64: =[63]Summary!$E$1 -> 6 | D64: =[63]Summary!$C$34 -> -9.8724884 | E64: =[63]Summary!$E$34/100 -> -9.8724884 | F64: =[63]Summary!$C$36 | G64: =[63]Summary!$C$32 -> 0 | H64: =[63]Summary!$E$6/100 -> 0 | I64: =[63]Summary!$E$10/100 -> 0 | J64: =[63]Summary!$E$14/100 -> 0 | K64: =[63]Summary!$C$40 -> 4.8229683 | L64: =[63]Summary!$C$54 -> 0 | M64: ='[63]Glbl Expsr'!$D$2 -> 4.8229683 | N64: ='[63]Glbl Expsr'!$D$3 -> 4.8229683 | O64: \\pim-cpt-statpro\SPC_602\Client\Profiles\PIM\Exports\LIBTAA Derv Calc 6Apr2022.xlsx | P64: LIBTAA Mandate
A65: NESEQU | B65: =[64]Summary!$G$3 -> ≠ UT | C65: =[64]Summary!$E$1 -> 5 | D65: =[64]Summary!$C$34 -> 0.32332707 | E65: =[64]Summary!$E$34/100 -> 0.32332707 | F65: =[64]Summary!$C$36 | G65: =[64]Summary!$C$32 -> 0.61037529 | H65: =[64]Summary!$E$6/100 -> 0 | I65: =[64]Summary!$E$10/100 -> 0.038329992 | J65: =[64]Summary!$E$14/100 -> 0.198451 | K65: =[64]Summary!$C$40 -> 0.99265782 | L65: =[64]Summary!$C$54 -> 0 | M65: ='[64]Glbl Expsr'!$D$2 -> 0.46525073 | N65: ='[64]Glbl Expsr'!$D$3 -> 0.46525073 | O65: \\pim-cpt-statpro\SPC_602\Client\Profiles\PIM\Exports\NESEQU Derv Calc 6Apr2022.xlsx | P65: NESEQU Mandate
A66: PPSNAM | B66: =[65]Summary!$G$3 -> ≠ UT | C66: =[65]Summary!$E$1 -> 5 | D66: =[65]Summary!$C$34 -> 0.34005022 | E66: =[65]Summary!$E$34/100 -> 0.34005022 | F66: =[65]Summary!$C$36 -> 0.14896869 | G66: =[65]Summary!$C$32 -> 0 | H66: =[65]Summary!$E$6/100 -> 0 | I66: =[65]Summary!$E$10/100 -> 0 | J66: =[65]Summary!$E$14/100 -> 0 | K66: =[65]Summary!$C$40 -> 2.2573325 | L66: =[65]Summary!$C$54 -> 20.716682 | M66: ='[65]Glbl Expsr'!$D$2 -> 2.2193856 | N66: ='[65]Glbl Expsr'!$D$3 -> 2.2193856 | O66: \\pim-cpt-statpro\SPC_602\Client\Profiles\PIM\Exports\PPSNAM Derv Calc 6Apr2022.xlsx | P66: PPSNAM Mandate
A67: ENGENMBF | B67: =[66]Summary!$G$3 -> ≠ UT | C67: =[66]Summary!$E$1 -> 4 | D67: =[66]Summary!$C$34 -> 0.026913899 | E67: =[66]Summary!$E$34/100 -> 0.026913899 | F67: =[66]Summary!$C$36 -> 0.53939459 | G67: =[66]Summary!$C$32 -> 0 | H67: =[66]Summary!$E$6/100 -> 0.18080561 | I67: =[66]Summary!$E$10/100 -> 0.0024552069 | J67: =[66]Summary!$E$14/100 -> 0.077266517 | K67: =[66]Summary!$C$40 -> 0.26617114 | L67: =[66]Summary!$C$54 -> 0 | M67: ='[66]Glbl Expsr'!$D$2 -> 0.40592791 | N67: ='[66]Glbl Expsr'!$D$3 -> 0.095009306 | O67: \\pim-cpt-statpro\SPC_602\Client\Profiles\PIM\Exports\ENGENMBF Derv Calc 6Apr2022.xlsx | P67: ENGENMBF Mandate
A68: PLMED | B68: =[67]Summary!$G$3 -> ≠ UT | C68: =[67]Summary!$E$1 -> 4 | D68: =[67]Summary!$C$34 -> 0.052054816 | E68: =[67]Summary!$E$34/100 -> 0.052054816 | F68: =[67]Summary!$C$36 -> 0.54928121 | G68: =[67]Summary!$C$32 -> 0 | H68: =[67]Summary!$E$6/100 -> 0.19617424 | I68: =[67]Summary!$E$10/100 -> 0.0024544533 | J68: =[67]Summary!$E$14/100 -> 0.0774701 | K68: =[67]Summary!$C$40 -> 0.23280053 | L68: =[67]Summary!$C$54 -> 0 | M68: ='[67]Glbl Expsr'!$D$2 -> 0.38805549 | N68: ='[67]Glbl Expsr'!$D$3 -> 0.077649449 | O68: \\pim-cpt-statpro\SPC_602\Client\Profiles\PIM\Exports\PLMED Derv Calc 6Apr2022.xlsx | P68: PLMED Mandate
A69: GAEMBF | B69: =[68]Summary!$G$3 -> ≠ UT | C69: =[68]Summary!$E$1 -> 4 | D69: =[68]Summary!$C$34 -> 0.066435256 | E69: =[68]Summary!$E$34/100 -> 0.066435256 | F69: =[68]Summary!$C$36 -> 0.53472296 | G69: =[68]Summary!$C$32 -> 0 | H69: =[68]Summary!$E$6/100 -> 0.18872322 | I69: =[68]Summary!$E$10/100 -> 0.0024727652 | J69: =[68]Summary!$E$14/100 -> 0.077776726 | K69: =[68]Summary!$C$40 -> 0.2334199 | L69: =[68]Summary!$C$54 -> 0 | M69: ='[68]Glbl Expsr'!$D$2 -> 0.38630358 | N69: ='[68]Glbl Expsr'!$D$3 -> 0.07708471 | O69: \\pim-cpt-statpro\SPC_602\Client\Profiles\PIM\Exports\GAEMBF Derv Calc 6Apr2022.xlsx | P69: GAEMBF Mandate
A70: PICPROV | B70: =[69]Summary!$G$3 -> ≠ UT | C70: =[69]Summary!$E$1 -> 0 | D70: =[69]Summary!$C$34 -> 0.00022616534 | E70: =[69]Summary!$E$34/100 -> 0.00022616534 | F70: =[69]Summary!$C$36 -> 0 | G70: =[69]Summary!$C$32 -> 0 | H70: =[69]Summary!$E$6/100 -> 0 | I70: =[69]Summary!$E$10/100 -> 0 | J70: =[69]Summary!$E$14/100 -> 0 | K70: =[69]Summary!$C$40 -> 0 | L70: =[69]Summary!$C$54 -> 0 | M70: ='[69]Glbl Expsr'!$D$2 -> 0 | N70: ='[69]Glbl Expsr'!$D$3 -> 0 | O70: \\pim-cpt-statpro\SPC_602\Client\Profiles\PIM\Exports\PICPROV Derv Calc 6Apr2022.xlsx | P70: PICPROV Mandate
A71: ECICBALC | B71: =[70]Summary!$G$3 -> ≠ UT | C71: =[70]Summary!$E$1 -> 0 | D71: =[70]Summary!$C$34 -> 0.0013665616 | E71: =[70]Summary!$E$34/100 -> 0.0013665616 | F71: =[70]Summary!$C$36 -> 0.20375182 | G71: =[70]Summary!$C$32 -> 0 | H71: =[70]Summary!$E$6/100 -> 0 | I71: =[70]Summary!$E$10/100 -> 0.17560309 | J71: =[70]Summary!$E$14/100 -> 0.41816658 | K71: =[70]Summary!$C$40 -> 0.79488162 | L71: =[70]Summary!$C$54 -> 28.54072 | M71: ='[70]Glbl Expsr'!$D$2 -> 0 | N71: ='[70]Glbl Expsr'!$D$3 -> 0 | O71: \\pim-cpt-statpro\SPC_602\Client\Profiles\PIM\Exports\ECICBALC Derv Calc 6Apr2022.xlsx | P71: ECICBALC Mandate
A72: SISLP | B72: =[71]Summary!$G$3 -> ≠ UT | C72: =[71]Summary!$E$1 -> 0 | D72: =[71]Summary!$C$34 -> 0.0033739815 | E72: =[71]Summary!$E$34/100 -> 0.0033739815 | F72: =[71]Summary!$C$36 -> 0.94846202 | G72: =[71]Summary!$C$32 -> 0 | H72: =[71]Summary!$E$6/100 -> 0 | I72: =[71]Summary!$E$10/100 -> 0 | J72: =[71]Summary!$E$14/100 -> 0 | K72: =[71]Summary!$C$40 -> 0 | L72: =[71]Summary!$C$54 -> 0 | M72: ='[71]Glbl Expsr'!$D$2 -> 0 | N72: ='[71]Glbl Expsr'!$D$3 -> 0 | O72: \\pim-cpt-statpro\SPC_602\Client\Profiles\PIM\Exports\SISLP Derv Calc 6Apr2022.xlsx | P72: SISLP Mandate
A73: SILEQF | B73: =[72]Summary!$G$3 -> ≠ UT | C73: =[72]Summary!$E$1 -> 0 | D73: =[72]Summary!$C$34 -> 0.0037735423 | E73: =[72]Summary!$E$34/100 -> 0.0037735423 | F73: =[72]Summary!$C$36 -> 0 | G73: =[72]Summary!$C$32 -> 0 | H73: =[72]Summary!$E$6/100 -> 0 | I73: =[72]Summary!$E$10/100 -> 0.40608401 | J73: =[72]Summary!$E$14/100 -> 0.91193662 | K73: =[72]Summary!$C$40 -> 0.99622646 | L73: =[72]Summary!$C$54 -> 0 | M73: ='[72]Glbl Expsr'!$D$2 -> 0 | N73: ='[72]Glbl Expsr'!$D$3 -> 0 | O73: \\pim-cpt-statpro\SPC_602\Client\Profiles\PIM\Exports\SILEQF Derv Calc 6Apr2022.xlsx | P73: SILEQF Mandate
A74: SHNIPF | B74: =[73]Summary!$G$3 -> ≠ UT | C74: =[73]Summary!$E$1 -> 0 | D74: =[73]Summary!$C$34 -> 0.24908775 | E74: =[73]Summary!$E$34/100 -> 0.24908775 | F74: =[73]Summary!$C$36 -> 0.69915416 | G74: =[73]Summary!$C$32 -> 0 | H74: =[73]Summary!$E$6/100 -> 0.084928238 | I74: =[73]Summary!$E$10/100 -> 0 | J74: =[73]Summary!$E$14/100 -> 0 | K74: =[73]Summary!$C$40 -> 0.051706024 | L74: =[73]Summary!$C$54 -> 0 | M74: ='[73]Glbl Expsr'!$D$2 -> 0 | N74: ='[73]Glbl Expsr'!$D$3 -> 0 | O74: \\pim-cpt-statpro\SPC_602\Client\Profiles\PIM\Exports\SHNIPF Derv Calc 6Apr2022.xlsx | P74: SHNIPF Mandate
A75: NGKINC | B75: =[74]Summary!$G$3 -> ≠ UT | C75: =[74]Summary!$E$1 -> 0 | D75: =[74]Summary!$C$34 -> 0.35447371 | E75: =[74]Summary!$E$34/100 -> 0.35447371 | F75: =[74]Summary!$C$36 -> 0.59734229 | G75: =[74]Summary!$C$32 -> 0 | H75: =[74]Summary!$E$6/100 -> 0.086169346 | I75: =[74]Summary!$E$10/100 -> 0 | J75: =[74]Summary!$E$14/100 -> 0 | K75: =[74]Summary!$C$40 -> 0.048135573 | L75: =[74]Summary!$C$54 -> 0 | M75: ='[74]Glbl Expsr'!$D$2 -> 0 | N75: ='[74]Glbl Expsr'!$D$3 -> 0 | O75: \\pim-cpt-statpro\SPC_602\Client\Profiles\PIM\Exports\NGKINC Derv Calc 6Apr2022.xlsx | P75: NGKINC Mandate
A76: AMMIPF | B76: =[75]Summary!$G$3 -> ≠ UT | C76: =[75]Summary!$E$1 -> 0 | D76: =[75]Summary!$C$34 -> 0.44461666 | E76: =[75]Summary!$E$34/100 -> 0.44461666 | F76: =[75]Summary!$C$36 -> 0.55538334 | G76: =[75]Summary!$C$32 -> 0 | H76: =[75]Summary!$E$6/100 -> 0.25836517 | I76: =[75]Summary!$E$10/100 -> 0 | J76: =[75]Summary!$E$14/100 -> 0 | K76: =[75]Summary!$C$40 -> 0 | L76: =[75]Summary!$C$54 -> 0 | M76: ='[75]Glbl Expsr'!$D$2 -> 0 | N76: ='[75]Glbl Expsr'!$D$3 -> 0 | O76: \\pim-cpt-statpro\SPC_602\Client\Profiles\PIM\Exports\AMMIPF Derv Calc 6Apr2022.xlsx | P76: AMMIPF Mandate
A77: MEDINC | B77: =[76]Summary!$G$3 -> ≠ UT | C77: =[76]Summary!$E$1 -> 0 | D77: =[76]Summary!$C$34 -> 0.53402459 | E77: =[76]Summary!$E$34/100 -> 0.53402459 | F77: =[76]Summary!$C$36 -> 0.32152803 | G77: =[76]Summary!$C$32 -> 0 | H77: =[76]Summary!$E$6/100 -> 0.11023489 | I77: =[76]Summary!$E$10/100 -> 0 | J77: =[76]Summary!$E$14/100 -> 0 | K77: =[76]Summary!$C$40 -> 0.094706446 | L77: =[76]Summary!$C$54 -> 0 | M77: ='[76]Glbl Expsr'!$D$2 -> 0 | N77: ='[76]Glbl Expsr'!$D$3 -> 0 | O77: \\pim-cpt-statpro\SPC_602\Client\Profiles\PIM\Exports\MEDINC Derv Calc 6Apr2022.xlsx | P77: MEDINC Mandate

Sheet k
A1: =HYPERLINK("https://pimportalprod2015.eagleaccess.com/Default.aspx","Derivative Cover "&TEXT(H!$AJ$2,"dddd d mmmm yyyy")&" from Eagle") -> Derivative Cover Friday 22 April 2022 from Eagle | C1: Entity Name | D1: HoldingsStartRow | E1: DeltasStartRow
A2: Process: | C2: 27four Life - Pos Ret | D2: =MATCH(C2,H!A:A,0) -> 2 | E2: =MATCH(C2,D!A:A,0) -> 2
A3: =HYPERLINK("https://pimportalprod2015.eagleaccess.com/Reports/Reports.aspx","1) Get holdings from Eagle") -> 1) Get holdings from Eagle | C3: 27four Life - Pos Ret Med | D3: =MATCH(C3,H!A:A,0) -> 49 | E3: =MATCH(C3,D!A:A,0) -> 14
A4: i) Get the funds' derivative deltas from Eagle | C4: Absa MM Abs Ret Prud Fund | D4: =MATCH(C4,H!A:A,0) -> 100 | E4: =MATCH(C4,D!A:A,0) -> 20
A5: a) Queries -> Portfolios -> Derivative Exposure -> Edit Criteria | C5: ABSA MM Bond Fund | D5: =MATCH(C5,H!A:A,0) -> 148 | E5: =MATCH(C5,D!A:A,0) -> 32
A6: b) Locate "Entity ID", click on down arrow and select "Favorite" | C6: ABSA MULTI MAN EQ FUND PRESC | D6: =MATCH(C6,H!A:A,0) -> 158 | E6: =MATCH(C6,D!A:A,0) -> 33
A7: c) click on ellipses (…) and then on Entity ID to select all favourites | C7: AFIL - Life Bond Fund | D7: =MATCH(C7,H!A:A,0) -> 240 | E7: =MATCH(C7,D!A:A,0) -> 34
A8: d) Enter prior working day's date in the calendar at bottom left of the screen | C8: AFIL - Pensioner | D8: =MATCH(C8,H!A:A,0) -> 246 | E8: =MATCH(C8,D!A:A,0) -> 35
A9: e) Submit | C9: Custodian BCI Income Plus Fund | D9: =MATCH(C9,H!A:A,0) -> 292 | E9: =MATCH(C9,D!A:A,0) -> 47
A10: f) Hover over "Export" and then left click on "XLS Analysis Mode" | C10: ECIC Composite | D10: =MATCH(C10,H!A:A,0) -> 382 | E10: =MATCH(C10,D!A:A,0) -> 48
A11: g) When it's done downloading, click on "Download Complete" | C11: Electric Cont Indust Pens Fund | D11: =MATCH(C11,H!A:A,0) -> 484 | E11: =MATCH(C11,D!A:A,0) -> 49
A12: h) Copy columns "A" through "G" from the "Derivative Exposure.xls" sheet | C12: EMBF - Positive Return Fund | D12: =MATCH(C12,H!A:A,0) -> 563 | E12: =MATCH(C12,D!A:A,0) -> 51
A13: i) Paste into cell "A1" of sheet "D" in this file | C13: FRB ITF GTC Wealth Preserver2 | D13: =MATCH(C13,H!A:A,0) -> 614 | E13: =MATCH(C13,D!A:A,0) -> 57
A14: ii) Get the funds' holdings from Eagle | C14: FRB ITF Hollard Prime Income | D14: =MATCH(C14,H!A:A,0) -> 649 | E14: =MATCH(C14,D!A:A,0) -> 69
A15: a) Queries -> Portfolios -> Portfolio Analytics Report - New -> Edit Criteria | C15: FRB ITF Hollard Prime Yld Pls | D15: =MATCH(C15,H!A:A,0) -> 736 | E15: =MATCH(C15,D!A:A,0) -> 70
... A24: 2) | C24: IJG Income Provider Fund | D24: =MATCH(C24,H!A:A,0) -> 1072 | E24: =MATCH(C24,D!A:A,0) -> 111
A25: =HYPERLINK("\\pim-cpt-statpro\SPC_602\Client\Profiles\PIM\Exports","3) Get the results in the derivative check folder") -> 3) Get the results in the derivative check folder | C25: Liberty Group Ltd - TAA | D25: =MATCH(C25,H!A:A,0) -> 1190 | E25: =MATCH(C25,D!A:A,0) -> 113
C26: Medipos Medical Scheme Income | D26: =MATCH(C26,H!A:A,0) -> 1210 | E26: =MATCH(C26,D!A:A,0) -> 119
C27: Mineworkers Prov Fund | D27: =MATCH(C27,H!A:A,0) -> 1247 | E27: =MATCH(C27,D!A:A,0) -> 120
C28: Momentum Group Ltd - Pos Ret | D28: =MATCH(C28,H!A:A,0) -> 1267 | E28: =MATCH(C28,D!A:A,0) -> 121
C29: Nestle Provident Fund - PIM | D29: =MATCH(C29,H!A:A,0) -> 1311 | E29: =MATCH(C29,D!A:A,0) -> 133
C30: NFMW - Equity Fund | D30: =MATCH(C30,H!A:A,0) -> 1392 | E30: =MATCH(C30,D!A:A,0) -> 135
C31: OMMM Income Fund No5 - PIM | D31: =MATCH(C31,H!A:A,0) -> 1469 | E31: =MATCH(C31,D!A:A,0) -> 137
C32: Picbel Groepvoorsorgfonds | D32: =MATCH(C32,H!A:A,0) -> 1484 | E32: =MATCH(C32,D!A:A,0) -> 138
C33: PIM Absolute Balanced | D33: =MATCH(C33,H!A:A,0) -> 1487 | E33: =MATCH(C33,D!A:A,0) -> 139
C34: PIM Balanced | D34: =MATCH(C34,H!A:A,0) -> 1528 | E34: =MATCH(C34,D!A:A,0) -> 144
C35: PIM Core All Share Equity | D35: =MATCH(C35,H!A:A,0) -> 1577 | E35: =MATCH(C35,D!A:A,0) -> 152
C36: PIM Core Capped Equity | D36: =MATCH(C36,H!A:A,0) -> 1677 | E36: =MATCH(C36,D!A:A,0) -> 153
C37: PIM Core Equity | D37: =MATCH(C37,H!A:A,0) -> 1779 | E37: =MATCH(C37,D!A:A,0) -> 155
... C77: Tshwane Municipal Prov Fund | D77: =MATCH(C77,H!A:A,0) -> 3869 | E77: =MATCH(C77,D!A:A,0) -> 259
D78: 3724 | E78: 361

Sheet Static
A1: 44181 | B1: Day of Reconciliation | D1: Back to links
A2: 44190 | B2: Christmas Day
A3: 44191 | B3: Boxing Day
A4: 44197 | B4: New Year's Day
A5: 44277 | B5: Human Rights Day
A6: 44288 | B6: Good Friday
A7: 44291 | B7: Family Day
A8: 44313 | B8: Freedom Day
A9: 44317 | B9: International Workers' Day
A10: 44363 | B10: Youth Day (in South Africa)
A11: 44417 | B11: National Women's Day
A12: 44463 | B12: Heritage Day
A13: 44501 | B13: Election Day
... A29: 44921 | B29: Day of Goodwill

Sheet Summary
A1: =Data!$A$2&" ("&Data!$AK$2&")" -> Tshwane Municipal Prov Fund (TSHMPF) | B1: Current Exposure | C1: Market Value | E1: =COUNTIF(Data!$B:$B,"Derivatives")+COUNTIF(Data!$B:$B,"Forwards")+COUNTIF(Data!$B:$B,"Swaps") -> 8 | F1: ="derivative"&IF(E1=1,"","s") -> derivatives | G1: =HYPERLINK("J:\PProfile Operations\Legal\Legal and Compliance Framework\Hilton\Client Mandates\"&SUBSTITUTE(Data!$AK$2,"_C","")&" Rules.docx","Mandate") -> Mandate | H1: {="SA equity indices ("&SUMPRODUCT((Data!$C:$C="Equity Derivatives")*(Data!$W:$W="ZAR"))&")"} -> SA equity indices (2) | I1: {=IF(ISNA(MATCH(1,("Equity derivatives"=Data!C:C)*("ZAR"=Data!W:W),0)),"",INDEX(Data!D:D,MATCH(1,("Equity derivatives"=Data!C:C)*("ZAR"=Data!W:W),0)))} -> 15JUN22 DCAP | J1: {=IF(COUNTA($I$1:I$1)<COUNTIFS(Data!$C:$C,"Equity derivatives",Data!$W:$W,"ZAR"),INDEX(Data!$D:$D,MATCH(I$1,Data!$D:$D,0)+1),"")} -> 15JUN22 DCAR | K1: {=IF(COUNTA($I$1:J$1)<COUNTIFS(Data!$C:$C,"Equity derivatives",Data!$W:$W,"ZAR"),INDEX(Data!$D:$D,MATCH(J$1,Data!$D:$D,0)+1),"")} | L1: {=IF(COUNTA($I$1:K$1)<COUNTIFS(Data!$C:$C,"Equity derivatives",Data!$W:$W,"ZAR"),INDEX(Data!$D:$D,MATCH(K$1,Data!$D:$D,0)+1),"")} | M1: {=IF(COUNTA($I$1:L$1)<COUNTIFS(Data!$C:$C,"Equity derivatives",Data!$W:$W,"ZAR"),INDEX(Data!$D:$D,MATCH(L$1,Data!$D:$D,0)+1),"")} | N1: {=IF(COUNTA($I$1:M$1)<COUNTIFS(Data!$C:$C,"Equity derivatives",Data!$W:$W,"ZAR"),INDEX(Data!$D:$D,MATCH(M$1,Data!$D:$D,0)+1),"")} | O1: {=IF(COUNTA($I$1:N$1)<COUNTIFS(Data!$C:$C,"Equity derivatives",Data!$W:$W,"ZAR"),INDEX(Data!$D:$D,MATCH(N$1,Data!$D:$D,0)+1),"")} | P1: {=IF(COUNTA($I$1:O$1)<COUNTIFS(Data!$C:$C,"Equity derivatives",Data!$W:$W,"ZAR"),INDEX(Data!$D:$D,MATCH(O$1,Data!$D:$D,0)+1),"")} | Q1: {=IF(COUNTA($I$1:P$1)<COUNTIFS(Data!$C:$C,"Equity derivatives",Data!$W:$W,"ZAR"),INDEX(Data!$D:$D,MATCH(P$1,Data!$D:$D,0)+1),"")} | ... BH1: {=IF(COUNTA($I$1:BG$1)<COUNTIFS(Data!$C:$C,"Equity derivatives",Data!$W:$W,"ZAR"),INDEX(Data!$D:$D,MATCH(BG$1,Data!$D:$D,0)+1),"")}
A2: =HYPERLINK("https://pimportalprod2015.eagleaccess.com/Default.aspx","Derivative Cover "&TEXT(Data!$AJ$2,"dddd d mmmm yyyy")) -> Derivative Cover Wednesday 6 April 2022 | B2: R | C2: % | F2: ASSET COVER CHECK | G2: {=CELL("filename")} -> \\pim-cpt-fs\profile$\PProfile Operations\Legal\Legal and Compliance Framework\Hilton\W\[Derv.xlsm]k | H2: =IF(ISNA(SUM(I2:BH2)),0,SUM(I2:BH2)) -> 0.13466471 | I2: =IF(I$1="","",INDEX(Data!$AH:$AH,MATCH(I$1,Data!$D:$D,0))/$B$4) -> 0.074538129 | J2: =IF(J$1="","",INDEX(Data!$AH:$AH,MATCH(J$1,Data!$D:$D,0))/$B$4) -> 0.060126578 | K2: =IF(K$1="","",INDEX(Data!$AH:$AH,MATCH(K$1,Data!$D:$D,0))/$B$4) | L2: =IF(L$1="","",INDEX(Data!$AH:$AH,MATCH(L$1,Data!$D:$D,0))/$B$4) | M2: =IF(M$1="","",INDEX(Data!$AH:$AH,MATCH(M$1,Data!$D:$D,0))/$B$4) | N2: =IF(N$1="","",INDEX(Data!$AH:$AH,MATCH(N$1,Data!$D:$D,0))/$B$4) | O2: =IF(O$1="","",INDEX(Data!$AH:$AH,MATCH(O$1,Data!$D:$D,0))/$B$4) | P2: =IF(P$1="","",INDEX(Data!$AH:$AH,MATCH(P$1,Data!$D:$D,0))/$B$4) | ... BH2: =IF(BH$1="","",INDEX(Data!$AH:$AH,MATCH(BH$1,Data!$D:$D,0))/$B$4)
A3: UT | E3: 0 | F3: Total direct SA bonds available to cover short exposures | G3: =_xlfn.XLOOKUP(Data!AK$2,[77]Funds!$A:$A,[77]Funds!$E:$E) -> ≠ UT
A4: Fund NAV | B4: =SUM(Data!$L:$L) -> 1.7548146e+08 | C4: =SUM(Data!$N:$N)/100 -> 1 | E4: =IF(ISNA(MATCH($G4,Data!$E:$E,0)),0,_xlfn.XLOOKUP($G4,Data!$E:$E,Data!$AI:$AI))+IF(ISNA(MATCH(186,Data!$E:$E,0)),0,_xlfn.XLOOKUP(186,Data!$E:$E,Data!$AI:$AI)) -> 0 | F4: Total same or similar bonds available to cover short exposures | G4: R186 | H4: {="World equity indices ("&SUMPRODUCT((Data!$C:$C="Equity Derivatives")*(Data!$W:$W<>"ZAR"))&")"} -> World equity indices (0) | I4: {=IF(ISNA(MATCH(1,("Equity derivatives"=Data!C:C)*("ZAR"<>Data!W:W),0)),"",INDEX(Data!D:D,MATCH(1,("Equity derivatives"=Data!C:C)*("ZAR"<>Data!W:W),0)))} | J4: {=IF(COUNTA($I$4:I$4)<COUNTIFS(Data!$C:$C,"Equity derivatives",Data!$W:$W,"<>ZAR"),INDEX(Data!$D:$D,MATCH(I$4,Data!$D:$D,0)+1),"")} | K4: {=IF(COUNTA($I$4:J$4)<COUNTIFS(Data!$C:$C,"Equity derivatives",Data!$W:$W,"<>ZAR"),INDEX(Data!$D:$D,MATCH(J$4,Data!$D:$D,0)+1),"")} | L4: {=IF(COUNTA($I$4:K$4)<COUNTIFS(Data!$C:$C,"Equity derivatives",Data!$W:$W,"<>ZAR"),INDEX(Data!$D:$D,MATCH(K$4,Data!$D:$D,0)+1),"")} | M4: {=IF(COUNTA($I$4:L$4)<COUNTIFS(Data!$C:$C,"Equity derivatives",Data!$W:$W,"<>ZAR"),INDEX(Data!$D:$D,MATCH(L$4,Data!$D:$D,0)+1),"")} | N4: {=IF(COUNTA($I$4:M$4)<COUNTIFS(Data!$C:$C,"Equity derivatives",Data!$W:$W,"<>ZAR"),INDEX(Data!$D:$D,MATCH(M$4,Data!$D:$D,0)+1),"")} | O4: {=IF(COUNTA($I$4:N$4)<COUNTIFS(Data!$C:$C,"Equity derivatives",Data!$W:$W,"<>ZAR"),INDEX(Data!$D:$D,MATCH(N$4,Data!$D:$D,0)+1),"")} | P4: {=IF(COUNTA($I$4:O$4)<COUNTIFS(Data!$C:$C,"Equity derivatives",Data!$W:$W,"<>ZAR"),INDEX(Data!$D:$D,MATCH(O$4,Data!$D:$D,0)+1),"")} | Q4: {=IF(COUNTA($I$4:P$4)<COUNTIFS(Data!$C:$C,"Equity derivatives",Data!$W:$W,"<>ZAR"),INDEX(Data!$D:$D,MATCH(P$4,Data!$D:$D,0)+1),"")} | ... BH4: {=IF(COUNTA($I$4:BG$4)<COUNTIFS(Data!$C:$C,"Equity derivatives",Data!$W:$W,"<>ZAR"),INDEX(Data!$D:$D,MATCH(BG$4,Data!$D:$D,0)+1),"")}
E5: =MIN(0,$H$8*100) -> 0 | F5: Net short derivative exposure | H5: =IF(ISNA(SUM(I5:BH5)),0,SUM(I5:BH5)) -> 0 | I5: =IF(I$4="","",INDEX(Data!$AH:$AH,MATCH(I$4,Data!$D:$D,0))/$B$4) | J5: =IF(J$4="","",INDEX(Data!$AH:$AH,MATCH(J$4,Data!$D:$D,0))/$B$4) | K5: =IF(K$4="","",INDEX(Data!$AH:$AH,MATCH(K$4,Data!$D:$D,0))/$B$4) | L5: =IF(L$4="","",INDEX(Data!$AH:$AH,MATCH(L$4,Data!$D:$D,0))/$B$4) | M5: =IF(M$4="","",INDEX(Data!$AH:$AH,MATCH(M$4,Data!$D:$D,0))/$B$4) | N5: =IF(N$4="","",INDEX(Data!$AH:$AH,MATCH(N$4,Data!$D:$D,0))/$B$4) | O5: =IF(O$4="","",INDEX(Data!$AH:$AH,MATCH(O$4,Data!$D:$D,0))/$B$4) | P5: =IF(P$4="","",INDEX(Data!$AH:$AH,MATCH(P$4,Data!$D:$D,0))/$B$4) | ... BH5: =IF(BH$4="","",INDEX(Data!$AH:$AH,MATCH(BH$4,Data!$D:$D,0))/$B$4)
A6: Assets in liquid form | B6: =SUM(B7:B11) -> 31237968 | C6: =SUM(C7:C11) -> 0.17801292 | E6: =SUM(E3:E5) -> 0 | F6: =IF($E6>=0,"Adequate","INADEQUATE")&" short SA bond bond derivative cover [BN90 16(1)(a) & (b)]" -> Adequate short SA bond bond derivative cover [BN90 16(1)(a) & (b)]
A7: Cash (incl MMFs, excl margin) | B7: =SUMIF(Data!$B:$B,"CASH",Data!$AH:$AH)-SUMIF(Data!$E:$E,"SAFEX",Data!$AH:$AH)-SUMIF(Data!$E:$E,"VARMARG",Data!$AH:$AH) -> 28839688 | C7: =$B7/$B$4 -> 0.16434606 | H7: {="SA bond indices ("&SUMPRODUCT((Data!$C:$C="Bond Derivatives")*(Data!$W:$W="ZAR"))&")"} -> SA bond indices (0) | I7: {=IF(ISNA(MATCH(1,("Bond derivatives"=Data!C:C)*("ZAR"=Data!W:W),0)),"",INDEX(Data!D:D,MATCH(1,("Bond derivatives"=Data!C:C)*("ZAR"=Data!W:W),0)))} | J7: {=IF(I7<>"",IF(COUNTA($I$7:I$7)<COUNTIF(Data!$C:$C,"Bond Derivatives"),INDEX(Data!$D:$D,MATCH(I$7,Data!$D:$D,0)+1),""),"")} | K7: {=IF(COUNTA($I$7:J$7)<COUNTIF(Data!$C:$C,"Bond derivatives"),INDEX(Data!$D:$D,MATCH(J$7,Data!$D:$D,0)+1),"")} | L7: {=IF(COUNTA($I$7:K$7)<COUNTIF(Data!$C:$C,"Bond derivatives"),INDEX(Data!$D:$D,MATCH(K$7,Data!$D:$D,0)+1),"")} | M7: {=IF(COUNTA($I$7:L$7)<COUNTIF(Data!$C:$C,"Bond derivatives"),INDEX(Data!$D:$D,MATCH(L$7,Data!$D:$D,0)+1),"")} | N7: {=IF(COUNTA($I$7:M$7)<COUNTIF(Data!$C:$C,"Bond derivatives"),INDEX(Data!$D:$D,MATCH(M$7,Data!$D:$D,0)+1),"")} | O7: {=IF(COUNTA($I$7:N$7)<COUNTIF(Data!$C:$C,"Bond derivatives"),INDEX(Data!$D:$D,MATCH(N$7,Data!$D:$D,0)+1),"")} | P7: {=IF(COUNTA($I$7:O$7)<COUNTIF(Data!$C:$C,"Bond derivatives"),INDEX(Data!$D:$D,MATCH(O$7,Data!$D:$D,0)+1),"")} | Q7: {=IF(COUNTA($I$7:P$7)<COUNTIF(Data!$C:$C,"Bond derivatives"),INDEX(Data!$D:$D,MATCH(P$7,Data!$D:$D,0)+1),"")} | R7: {=IF(COUNTA($I$7:Q$7)<COUNTIF(Data!$C:$C,"Bond derivatives"),INDEX(Data!$D:$D,MATCH(Q$7,Data!$D:$D,0)+1),"")} | ... BH7: {=IF(COUNTA($I$7:BG$7)<COUNTIF(Data!$C:$C,"Bond derivatives"),INDEX(Data!$D:$D,MATCH(BG$7,Data!$D:$D,0)+1),"")}
A8: ="Money market instruments"&IF($A3="UT"," (excl CLNs and > 13 month bonds)","") -> Money market instruments (excl CLNs and > 13 month bonds) | B8: {=IF($A3="UT",SUMPRODUCT((Data!$B:$B="MONEY MARKET")*((Data!$P:$P<Data!$AJ$2+397)*(Data!$V:$V<>"CLN")),(Data!$AH:$AH)),SUMIF(Data!$B:$B,"MONEY MARKET",Data!$AH:$AH))} -> 0 | C8: =$B8/$B$4 -> 0 | E8: =SUM(BM!$V:$V) -> 3.8791986 | F8: Total direct MSCI ACWI assets available to cover short exposures | H8: =SUM(I8:BH8) -> 0 | I8: =IF(I$7="","",INDEX(Data!$AH:$AH,MATCH(I$7,Data!$D:$D,0))/$B$4) | J8: =IF(J$7="","",INDEX(Data!$AH:$AH,MATCH(J$7,Data!$D:$D,0))/$B$4) | K8: =IF(K$7="","",INDEX(Data!$AH:$AH,MATCH(K$7,Data!$D:$D,0))/$B$4) | L8: =IF(L$7="","",INDEX(Data!$AH:$AH,MATCH(L$7,Data!$D:$D,0))/$B$4) | M8: =IF(M$7="","",INDEX(Data!$AH:$AH,MATCH(M$7,Data!$D:$D,0))/$B$4) | N8: =IF(N$7="","",INDEX(Data!$AH:$AH,MATCH(N$7,Data!$D:$D,0))/$B$4) | O8: =IF(O$7="","",INDEX(Data!$AH:$AH,MATCH(O$7,Data!$D:$D,0))/$B$4) | P8: =IF(P$7="","",INDEX(Data!$AH:$AH,MATCH(P$7,Data!$D:$D,0))/$B$4) | ... BH8: =IF(BH$7="","",INDEX(Data!$AH:$AH,MATCH(BH$7,Data!$D:$D,0))/$B$4)
A9: Bonds (excl > 13 month bonds) | B9: {=IF($A3="UT",SUMPRODUCT((Data!$B:$B="BONDS")*((Data!$P:$P<Data!$AJ$2+397)*(Data!$V:$V<>"CLN")),(Data!$AH:$AH)),SUMIF(Data!$B:$B,"BONDS",Data!$AH:$AH))} -> 0 | C9: =$B9/$B$4 -> 0 | E9: =MIN(0,$H$5*100) -> 0 | F9: Net short derivative exposure
A10: SAFEX [BN90 19(2)] | B10: =SUMIF(Data!$E:$E,"SAFEX",Data!$AH:$AH) -> 2496840.5 | C10: =$B10/$B$4 -> 0.014228514 | E10: =SUM(E8:E9) -> 3.8791986 | F10: =IF($E10>=0,"Adequate","INADEQUATE")&" short MSCI derivative cover [BN90 16(1)(a) & (b)]" -> Adequate short MSCI derivative cover [BN90 16(1)(a) & (b)] | H10: {="World bond indices ("&SUMPRODUCT((Data!$C:$C="Bond Derivatives")*(Data!$W:$W<>"ZAR"))&")"} -> World bond indices (0) | I10: {=IF(ISNA(MATCH(1,("bond derivatives"=Data!C:C)*("ZAR"<>Data!W:W),0)),"",INDEX(Data!D:D,MATCH(1,("bond derivatives"=Data!C:C)*("ZAR"<>Data!W:W),0)))} | J10: {=IF(I10<>"",IF(COUNTA($I$10:I$10)<COUNTIF(Data!$C:$C,"Bond Derivatives"),INDEX(Data!$D:$D,MATCH(I$10,Data!$D:$D,0)+1),""),"")} | K10: {=IF(COUNTA($I$10:J$10)<COUNTIF(Data!$C:$C,"Bond Derivatives"),INDEX(Data!$D:$D,MATCH(J$10,Data!$D:$D,0)+1),"")} | L10: {=IF(COUNTA($I$10:K$10)<COUNTIF(Data!$C:$C,"Bond Derivatives"),INDEX(Data!$D:$D,MATCH(K$10,Data!$D:$D,0)+1),"")} | M10: {=IF(COUNTA($I$10:L$10)<COUNTIF(Data!$C:$C,"Bond Derivatives"),INDEX(Data!$D:$D,MATCH(L$10,Data!$D:$D,0)+1),"")} | N10: {=IF(COUNTA($I$10:M$10)<COUNTIF(Data!$C:$C,"Bond Derivatives"),INDEX(Data!$D:$D,MATCH(M$10,Data!$D:$D,0)+1),"")} | O10: {=IF(COUNTA($I$10:N$10)<COUNTIF(Data!$C:$C,"Bond Derivatives"),INDEX(Data!$D:$D,MATCH(N$10,Data!$D:$D,0)+1),"")} | P10: {=IF(COUNTA($I$10:O$10)<COUNTIF(Data!$C:$C,"Bond Derivatives"),INDEX(Data!$D:$D,MATCH(O$10,Data!$D:$D,0)+1),"")} | Q10: {=IF(COUNTA($I$10:P$10)<COUNTIF(Data!$C:$C,"Bond Derivatives"),INDEX(Data!$D:$D,MATCH(P$10,Data!$D:$D,0)+1),"")} | R10: {=IF(COUNTA($I$10:Q$10)<COUNTIF(Data!$C:$C,"Bond Derivatives"),INDEX(Data!$D:$D,MATCH(Q$10,Data!$D:$D,0)+1),"")} | ... BH10: {=IF(COUNTA($I$10:BG$10)<COUNTIF(Data!$C:$C,"Bond Derivatives"),INDEX(Data!$D:$D,MATCH(BG$10,Data!$D:$D,0)+1),"")}
A11: Variation Margin [BN90 19(2)] | B11: =SUMIF(Data!$E:$E,"VARMARG",Data!$AH:$AH) -> -98560 | C11: =$B11/$B$4 -> -0.00056165476 | H11: =SUM(I11:BH11) -> 0 | I11: =IF(I$10="","",INDEX(Data!$AH:$AH,MATCH(I$10,Data!$D:$D,0))/$B$4) | J11: =IF(J$10="","",INDEX(Data!$AH:$AH,MATCH(J$10,Data!$D:$D,0))/$B$4) | K11: =IF(K$10="","",INDEX(Data!$AH:$AH,MATCH(K$10,Data!$D:$D,0))/$B$4) | L11: =IF(L$10="","",INDEX(Data!$AH:$AH,MATCH(L$10,Data!$D:$D,0))/$B$4) | M11: =IF(M$10="","",INDEX(Data!$AH:$AH,MATCH(M$10,Data!$D:$D,0))/$B$4) | N11: =IF(N$10="","",INDEX(Data!$AH:$AH,MATCH(N$10,Data!$D:$D,0))/$B$4) | O11: =IF(O$10="","",INDEX(Data!$AH:$AH,MATCH(O$10,Data!$D:$D,0))/$B$4) | P11: =IF(P$10="","",INDEX(Data!$AH:$AH,MATCH(P$10,Data!$D:$D,0))/$B$4) | ... BH11: =IF(BH$10="","",INDEX(Data!$AH:$AH,MATCH(BH$10,Data!$D:$D,0))/$B$4)
E12: =SUMIF(BM!$A:$A,"J203",BM!$E:$E) -> 19.918968 | F12: Total direct ALSI assets available to cover short exposures
A13: less Sold currency futures to be covered by cash [BN90 16(1)(i)] | B13: =SUM(B14:B14) -> 0 | C13: =SUM(C14:C14) -> 0 | E13: =MIN(0, $H$2*100) -> 0 | F13: Net short derivative exposure | H13: ="Currency futures ("&COUNTIF(Data!$C:$C,"Currency Derivatives")&")" -> Currency futures (0) | I13: =IF(ISNA(IF(ISNA(MATCH("Currency Derivatives",Data!$C:$C,0)),"",INDEX(Data!$D:$D,MATCH("Currency Derivatives",Data!$C:$C,0)))),"",IF(ISNA(MATCH("Currency Derivatives",Data!$C:$C,0)),"",INDEX(Data!$D:$D,MATCH("Currency Derivatives",Data!$C:$C,0)))) | J13: {=IF(COUNTA($I$13:I$13)<COUNTIF(Data!$C:$C,"Currency derivatives"),INDEX(Data!$D:$D,MATCH(I$13,Data!$D:$D,0)+1),"")} | K13: {=IF(COUNTA($I$13:J$13)<COUNTIF(Data!$C:$C,"Currency derivatives"),INDEX(Data!$D:$D,MATCH(J$13,Data!$D:$D,0)+1),"")} | L13: {=IF(COUNTA($I$13:K$13)<COUNTIF(Data!$C:$C,"Currency derivatives"),INDEX(Data!$D:$D,MATCH(K$13,Data!$D:$D,0)+1),"")} | M13: {=IF(COUNTA($I$13:L$13)<COUNTIF(Data!$C:$C,"Currency derivatives"),INDEX(Data!$D:$D,MATCH(L$13,Data!$D:$D,0)+1),"")} | N13: {=IF(COUNTA($I$13:M$13)<COUNTIF(Data!$C:$C,"Currency derivatives"),INDEX(Data!$D:$D,MATCH(M$13,Data!$D:$D,0)+1),"")} | O13: {=IF(COUNTA($I$13:N$13)<COUNTIF(Data!$C:$C,"Currency derivatives"),INDEX(Data!$D:$D,MATCH(N$13,Data!$D:$D,0)+1),"")} | P13: {=IF(COUNTA($I$13:O$13)<COUNTIF(Data!$C:$C,"Currency derivatives"),INDEX(Data!$D:$D,MATCH(O$13,Data!$D:$D,0)+1),"")} | Q13: {=IF(COUNTA($I$13:P$13)<COUNTIF(Data!$C:$C,"Currency derivatives"),INDEX(Data!$D:$D,MATCH(P$13,Data!$D:$D,0)+1),"")} | ... BH13: {=IF(COUNTA($I$13:BG$13)<COUNTIF(Data!$C:$C,"Currency derivatives"),INDEX(Data!$D:$D,MATCH(BG$13,Data!$D:$D,0)+1),"")}
A14: Currency Derivatives | B14: =IF(SUMIF(Data!$C:$C,$A14,Data!$AH:$AH)<0,SUMIF(Data!$C:$C,$A14,Data!$AH:$AH),0) -> 0 | C14: =$B14/$B$4 -> 0 | E14: =SUM(E12:E13) -> 19.918968 | F14: =IF($E14>=0,"Adequate","INADEQUATE")&" short ALSI derivative cover [BN90 16(1)(a) & (b)]" -> Adequate short ALSI derivative cover [BN90 16(1)(a) & (b)] | H14: =SUM(I14:BH14) -> 0 | I14: =IF(I$13="","",INDEX(Data!$AH:$AH,MATCH(I$13,Data!$D:$D,0))/$B$4) | J14: =IF(J$13="","",INDEX(Data!$AH:$AH,MATCH(J$13,Data!$D:$D,0))/$B$4) | K14: =IF(K$13="","",INDEX(Data!$AH:$AH,MATCH(K$13,Data!$D:$D,0))/$B$4) | L14: =IF(L$13="","",INDEX(Data!$AH:$AH,MATCH(L$13,Data!$D:$D,0))/$B$4) | M14: =IF(M$13="","",INDEX(Data!$AH:$AH,MATCH(M$13,Data!$D:$D,0))/$B$4) | N14: =IF(N$13="","",INDEX(Data!$AH:$AH,MATCH(N$13,Data!$D:$D,0))/$B$4) | O14: =IF(O$13="","",INDEX(Data!$AH:$AH,MATCH(O$13,Data!$D:$D,0))/$B$4) | P14: =IF(P$13="","",INDEX(Data!$AH:$AH,MATCH(P$13,Data!$D:$D,0))/$B$4) | ... BH14: =IF(BH$13="","",INDEX(Data!$AH:$AH,MATCH(BH$13,Data!$D:$D,0))/$B$4)
A16: less Net negative MtM OTC derivative exposure [BN90 17(1)(a)] | B16: =SUM(B17:B19) -> 0 | C16: =SUM(C17:C19) -> 0 | E16: ='Glbl Expsr'!$D$3 -> 0.13466471 | F16: Leverage (net effective exposure ÷ NAV) | H16: ="Currency forwards ("&COUNTIF(Data!$C:$C,"Forwards")&")" -> Currency forwards (0) | I16: =IF(ISNA(IF(ISNA(MATCH("Forwards",Data!$C:$C,0)),"",INDEX(Data!$D:$D,MATCH("Forwards",Data!$C:$C,0)))),"",IF(ISNA(MATCH("Forwards",Data!$C:$C,0)),"",INDEX(Data!$D:$D,MATCH("Forwards",Data!$C:$C,0)))) | J16: {=IF(COUNTA($I$16:I$16)<COUNTIF(Data!$C:$C,"Forwards"),INDEX(Data!$D:$D,MATCH(I$16,Data!$D:$D,0)+1),"")} | K16: {=IF(COUNTA($I$16:J$16)<COUNTIF(Data!$C:$C,"Forwards"),INDEX(Data!$D:$D,MATCH(J$16,Data!$D:$D,0)+1),"")} | L16: {=IF(COUNTA($I$16:K$16)<COUNTIF(Data!$C:$C,"Forwards"),INDEX(Data!$D:$D,MATCH(K$16,Data!$D:$D,0)+1),"")} | M16: {=IF(COUNTA($I$16:L$16)<COUNTIF(Data!$C:$C,"Forwards"),INDEX(Data!$D:$D,MATCH(L$16,Data!$D:$D,0)+1),"")} | N16: {=IF(COUNTA($I$16:M$16)<COUNTIF(Data!$C:$C,"Forwards"),INDEX(Data!$D:$D,MATCH(M$16,Data!$D:$D,0)+1),"")} | O16: {=IF(COUNTA($I$16:N$16)<COUNTIF(Data!$C:$C,"Forwards"),INDEX(Data!$D:$D,MATCH(N$16,Data!$D:$D,0)+1),"")} | P16: {=IF(COUNTA($I$16:O$16)<COUNTIF(Data!$C:$C,"Forwards"),INDEX(Data!$D:$D,MATCH(O$16,Data!$D:$D,0)+1),"")} | Q16: {=IF(COUNTA($I$16:P$16)<COUNTIF(Data!$C:$C,"Forwards"),INDEX(Data!$D:$D,MATCH(P$16,Data!$D:$D,0)+1),"")} | ... BH16: {=IF(COUNTA($I$16:BG$16)<COUNTIF(Data!$C:$C,"Forwards"),INDEX(Data!$D:$D,MATCH(BG$16,Data!$D:$D,0)+1),"")} | BI16: {=IF(COUNTA($I$1:BH$1)<COUNTIF(Data!$C:$C,"Swaps"),INDEX(Data!$D:$D,MATCH(BH$1,Data!$D:$D,0)+1),"")} | BJ16: {=IF(COUNTA($I$1:BI$1)<COUNTIF(Data!$C:$C,"Swaps"),INDEX(Data!$D:$D,MATCH(BI$1,Data!$D:$D,0)+1),"")} | BK16: {=IF(COUNTA($I$1:BJ$1)<COUNTIF(Data!$C:$C,"Swaps"),INDEX(Data!$D:$D,MATCH(BJ$1,Data!$D:$D,0)+1),"")} | BL16: {=IF(COUNTA($I$1:BK$1)<COUNTIF(Data!$C:$C,"Swaps"),INDEX(Data!$D:$D,MATCH(BK$1,Data!$D:$D,0)+1),"")} | BM16: {=IF(COUNTA($I$1:BL$1)<COUNTIF(Data!$C:$C,"Swaps"),INDEX(Data!$D:$D,MATCH(BL$1,Data!$D:$D,0)+1),"")} | BN16: {=IF(COUNTA($I$1:BM$1)<COUNTIF(Data!$C:$C,"Swaps"),INDEX(Data!$D:$D,MATCH(BM$1,Data!$D:$D,0)+1),"")} | BO16: {=IF(COUNTA($I$1:BN$1)<COUNTIF(Data!$C:$C,"Swaps"),INDEX(Data!$D:$D,MATCH(BN$1,Data!$D:$D,0)+1),"")} | BP16: {=IF(COUNTA($I$1:BO$1)<COUNTIF(Data!$C:$C,"Swaps"),INDEX(Data!$D:$D,MATCH(BO$1,Data!$D:$D,0)+1),"")} | ... DO16: {=IF(COUNTA($I$1:DN$1)<COUNTIF(Data!$C:$C,"Swaps"),INDEX(Data!$D:$D,MATCH(DN$1,Data!$D:$D,0)+1),"")}
A17: Forwards | B17: =MIN(0,SUMIF(Data!$C:$C,$A17,Data!$AH:$AH)) -> 0 | C17: =$B17/$B$4 -> 0 | H17: =SUM(I17:BH17) -> 0 | I17: =IF(I$16="","",INDEX(Data!$AH:$AH,MATCH(I$16,Data!$D:$D,0))/$B$4) | J17: =IF(J$16="","",INDEX(Data!$AH:$AH,MATCH(J$16,Data!$D:$D,0))/$B$4) | K17: =IF(K$16="","",INDEX(Data!$AH:$AH,MATCH(K$16,Data!$D:$D,0))/$B$4) | L17: =IF(L$16="","",INDEX(Data!$AH:$AH,MATCH(L$16,Data!$D:$D,0))/$B$4) | M17: =IF(M$16="","",INDEX(Data!$AH:$AH,MATCH(M$16,Data!$D:$D,0))/$B$4) | N17: =IF(N$16="","",INDEX(Data!$AH:$AH,MATCH(N$16,Data!$D:$D,0))/$B$4) | O17: =IF(O$16="","",INDEX(Data!$AH:$AH,MATCH(O$16,Data!$D:$D,0))/$B$4) | P17: =IF(P$16="","",INDEX(Data!$AH:$AH,MATCH(P$16,Data!$D:$D,0))/$B$4) | ... BH17: =IF(BH$16="","",INDEX(Data!$AH:$AH,MATCH(BH$16,Data!$D:$D,0))/$B$4)
A18: Swaps | B18: {=MIN(0,SUMPRODUCT((Data!$B$2:$B$1000="SWAPS")*((Data!$G$2:$G$1000)*(Data!$M$2:$M$1000))))/100} -> 0 | C18: =$B18/$B$4 -> 0
A19: FRAs | B19: {=MIN(0,SUMPRODUCT((Data!$B$2:$B$1000="FORWARD RATE AGREEMENT")*((Data!$G$2:$G$1000)*(Data!$M$2:$M$1000))))/100} -> 0 | C19: =$B19/$B$4 -> 0 | F19: CASH COVER CHECK | H19: ="Swaps ("&COUNTIF(Data!$C:$C,"SWAPS")&")" -> Swaps (6) | I19: =IF(ISNA(IF(ISNA(MATCH("Swaps",Data!$C:$C,0)),"",INDEX(Data!$D:$D,MATCH("Swaps",Data!$C:$C,0)))),"",IF(ISNA(MATCH("Swaps",Data!$C:$C,0)),"",INDEX(Data!$D:$D,MATCH("Swaps",Data!$C:$C,0)))) -> ABSA TRS 040822 A | J19: {=IF(COUNTA($I$19:I$19)<COUNTIF(Data!$C:$C,"Swaps"),INDEX(Data!$D:$D,MATCH(I$19,Data!$D:$D,0)+1),"")} -> ABSA TRS 040822 A_P | K19: {=IF(COUNTA($I$19:J$19)<COUNTIF(Data!$C:$C,"Swaps"),INDEX(Data!$D:$D,MATCH(J$19,Data!$D:$D,0)+1),"")} -> ABSA TRS 040822 A_R | L19: {=IF(COUNTA($I$19:K$19)<COUNTIF(Data!$C:$C,"Swaps"),INDEX(Data!$D:$D,MATCH(K$19,Data!$D:$D,0)+1),"")} -> INVESTEC TRS 030822 B | M19: {=IF(COUNTA($I$19:L$19)<COUNTIF(Data!$C:$C,"Swaps"),INDEX(Data!$D:$D,MATCH(L$19,Data!$D:$D,0)+1),"")} -> INVESTEC TRS 030822 B_P | N19: {=IF(COUNTA($I$19:M$19)<COUNTIF(Data!$C:$C,"Swaps"),INDEX(Data!$D:$D,MATCH(M$19,Data!$D:$D,0)+1),"")} -> INVESTEC TRS 030822 B_R | O19: {=IF(COUNTA($I$19:N$19)<COUNTIF(Data!$C:$C,"Swaps"),INDEX(Data!$D:$D,MATCH(N$19,Data!$D:$D,0)+1),"")} | P19: {=IF(COUNTA($I$19:O$19)<COUNTIF(Data!$C:$C,"Swaps"),INDEX(Data!$D:$D,MATCH(O$19,Data!$D:$D,0)+1),"")} | Q19: {=IF(COUNTA($I$19:P$19)<COUNTIF(Data!$C:$C,"Swaps"),INDEX(Data!$D:$D,MATCH(P$19,Data!$D:$D,0)+1),"")} | ... BH19: {=IF(COUNTA($I$19:BG$19)<COUNTIF(Data!$C:$C,"Swaps"),INDEX(Data!$D:$D,MATCH(BG$19,Data!$D:$D,0)+1),"")} | BI19: {=IF(COUNTA($I$1:BH$1)<COUNTIF(Data!$C:$C,"Forward Rate Agreement"),INDEX(Data!$D:$D,MATCH(BH$1,Data!$D:$D,0)+1),"")} | BJ19: {=IF(COUNTA($I$1:BI$1)<COUNTIF(Data!$C:$C,"Forward Rate Agreements"),INDEX(Data!$D:$D,MATCH(BI$1,Data!$D:$D,0)+1),"")} | BK19: {=IF(COUNTA($I$1:BJ$1)<COUNTIF(Data!$C:$C,"Forward Rate Agreements"),INDEX(Data!$D:$D,MATCH(BJ$1,Data!$D:$D,0)+1),"")} | BL19: {=IF(COUNTA($I$1:BK$1)<COUNTIF(Data!$C:$C,"Forward Rate Agreements"),INDEX(Data!$D:$D,MATCH(BK$1,Data!$D:$D,0)+1),"")} | BM19: {=IF(COUNTA($I$1:BL$1)<COUNTIF(Data!$C:$C,"Forward Rate Agreements"),INDEX(Data!$D:$D,MATCH(BL$1,Data!$D:$D,0)+1),"")} | BN19: {=IF(COUNTA($I$1:BM$1)<COUNTIF(Data!$C:$C,"Forward Rate Agreements"),INDEX(Data!$D:$D,MATCH(BM$1,Data!$D:$D,0)+1),"")} | BO19: {=IF(COUNTA($I$1:BN$1)<COUNTIF(Data!$C:$C,"Forward Rate Agreements"),INDEX(Data!$D:$D,MATCH(BN$1,Data!$D:$D,0)+1),"")} | BP19: {=IF(COUNTA($I$1:BO$1)<COUNTIF(Data!$C:$C,"Forward Rate Agreements"),INDEX(Data!$D:$D,MATCH(BO$1,Data!$D:$D,0)+1),"")} | BQ19: {=IF(COUNTA($I$1:BP$1)<COUNTIF(Data!$C:$C,"Swaps"),INDEX(Data!$D:$D,MATCH(BP$1,Data!$D:$D,0)+1),"")} | BR19: {=IF(COUNTA($I$1:BQ$1)<COUNTIF(Data!$C:$C,"Swaps"),INDEX(Data!$D:$D,MATCH(BQ$1,Data!$D:$D,0)+1),"")} | BS19: {=IF(COUNTA($I$1:BR$1)<COUNTIF(Data!$C:$C,"Swaps"),INDEX(Data!$D:$D,MATCH(BR$1,Data!$D:$D,0)+1),"")} | BT19: {=IF(COUNTA($I$1:BS$1)<COUNTIF(Data!$C:$C,"Swaps"),INDEX(Data!$D:$D,MATCH(BS$1,Data!$D:$D,0)+1),"")} | BU19: {=IF(COUNTA($I$1:BT$1)<COUNTIF(Data!$C:$C,"Swaps"),INDEX(Data!$D:$D,MATCH(BT$1,Data!$D:$D,0)+1),"")} | BV19: {=IF(COUNTA($I$1:BU$1)<COUNTIF(Data!$C:$C,"Swaps"),INDEX(Data!$D:$D,MATCH(BU$1,Data!$D:$D,0)+1),"")} | BW19: {=IF(COUNTA($I$1:BV$1)<COUNTIF(Data!$C:$C,"Swaps"),INDEX(Data!$D:$D,MATCH(BV$1,Data!$D:$D,0)+1),"")}
E20: =$C6*100 -> 17.801292 | F20: ="Cash, including cash value of options, available for long cover"&IF($A3="UT","",", and including underlying UT cash") -> Cash, including cash value of options, available for long cover | H20: =SUM(I20:BH20) -> -0.0073358632 | I20: =IF(I$19="","",INDEX(Data!$AH:$AH,MATCH(I$19,Data!$D:$D,0))/$B$4) -> 0 | J20: =IF(J$19="","",INDEX(Data!$AH:$AH,MATCH(J$19,Data!$D:$D,0))/$B$4) -> -0.37883172 | K20: =IF(K$19="","",INDEX(Data!$AH:$AH,MATCH(K$19,Data!$D:$D,0))/$B$4) -> 0.37456466 | L20: =IF(L$19="","",INDEX(Data!$AH:$AH,MATCH(L$19,Data!$D:$D,0))/$B$4) -> 0 | M20: =IF(M$19="","",INDEX(Data!$AH:$AH,MATCH(M$19,Data!$D:$D,0))/$B$4) -> -0.272516 | N20: =IF(N$19="","",INDEX(Data!$AH:$AH,MATCH(N$19,Data!$D:$D,0))/$B$4) -> 0.26944719 | O20: =IF(O$19="","",INDEX(Data!$AH:$AH,MATCH(O$19,Data!$D:$D,0))/$B$4) | P20: =IF(P$19="","",INDEX(Data!$AH:$AH,MATCH(P$19,Data!$D:$D,0))/$B$4) | ... BH20: =IF(BH$19="","",INDEX(Data!$AH:$AH,MATCH(BH$19,Data!$D:$D,0))/$B$4)
E21: =MIN(0,$H$11*100) -> 0 | F21: ="Net "&IF(E21<0,"short","long")&" currency derivatives, so "&IF(E21<0,"adequate","no")&" cash cover required" -> Net long currency derivatives, so no cash cover required
A22: =IF(B22>=0,"A","Ina")&"dequate cash cover for currency derivatives" -> Adequate cash cover for currency derivatives | B22: =B6+B13+B16 -> 31237968 | C22: =C6+C13+C16 -> 0.17801292 | E22: =SUM(E20:E21) -> 17.801292 | F22: =IF($E22>=0,"Adequate","INADEQUATE")&" currency future cover [BN90 16(1)(i)]" -> Adequate currency future cover [BN90 16(1)(i)] | H22: ="FRAs ("&COUNTIF(Data!$C:$C,"Forward Rate Agreement")&")" -> FRAs (0) | I22: =IF(ISNA(IF(ISNA(MATCH("Forward Rate Agreement",Data!$C:$C,0)),"",INDEX(Data!$D:$D,MATCH("Forward Rate Agreement",Data!$C:$C,0)))),"",IF(ISNA(MATCH("Forward Rate Agreement",Data!$C:$C,0)),"",INDEX(Data!$D:$D,MATCH("Forward Rate Agreement",Data!$C:$C,0)))) | J22: {=IF(COUNTA($I$22:I$22)<COUNTIF(Data!$C:$C,"Forward Rate Agreement"),INDEX(Data!$D:$D,MATCH(I$22,Data!$D:$D,0)+1),"")} | K22: {=IF(COUNTA($I$22:J$22)<COUNTIF(Data!$C:$C,"Forward Rate Agreement"),INDEX(Data!$D:$D,MATCH(J$22,Data!$D:$D,0)+1),"")} | L22: {=IF(COUNTA($I$22:K$22)<COUNTIF(Data!$C:$C,"Forward Rate Agreement"),INDEX(Data!$D:$D,MATCH(K$22,Data!$D:$D,0)+1),"")} | M22: {=IF(COUNTA($I$22:L$22)<COUNTIF(Data!$C:$C,"Forward Rate Agreement"),INDEX(Data!$D:$D,MATCH(L$22,Data!$D:$D,0)+1),"")} | N22: {=IF(COUNTA($I$22:M$22)<COUNTIF(Data!$C:$C,"Forward Rate Agreement"),INDEX(Data!$D:$D,MATCH(M$22,Data!$D:$D,0)+1),"")} | O22: {=IF(COUNTA($I$22:N$22)<COUNTIF(Data!$C:$C,"Forward Rate Agreement"),INDEX(Data!$D:$D,MATCH(N$22,Data!$D:$D,0)+1),"")} | P22: {=IF(COUNTA($I$22:O$22)<COUNTIF(Data!$C:$C,"Forward Rate Agreement"),INDEX(Data!$D:$D,MATCH(O$22,Data!$D:$D,0)+1),"")} | Q22: {=IF(COUNTA($I$22:P$22)<COUNTIF(Data!$C:$C,"Forward Rate Agreement"),INDEX(Data!$D:$D,MATCH(P$22,Data!$D:$D,0)+1),"")} | ... BH22: {=IF(COUNTA($I$22:BG$22)<COUNTIF(Data!$C:$C,"Forward Rate Agreement"),INDEX(Data!$D:$D,MATCH(BG$22,Data!$D:$D,0)+1),"")}
E23: =MIN(0,$H$14*100) -> 0 | F23: ="Net "&IF($E23>0,"positive","negative")&" MtM OTC forwards, so "&IF($E23>0,"no ","")&"cash cover required" -> Net negative MtM OTC forwards, so cash cover required | H23: =SUM(I23:BH23) -> 0 | I23: =IF(I$22="","",INDEX(Data!$AH:$AH,MATCH(I$22,Data!$D:$D,0))/$B$4) | J23: =IF(J$22="","",INDEX(Data!$AH:$AH,MATCH(J$22,Data!$D:$D,0))/$B$4) | K23: =IF(K$22="","",INDEX(Data!$AH:$AH,MATCH(K$22,Data!$D:$D,0))/$B$4) | L23: =IF(L$22="","",INDEX(Data!$AH:$AH,MATCH(L$22,Data!$D:$D,0))/$B$4) | M23: =IF(M$22="","",INDEX(Data!$AH:$AH,MATCH(M$22,Data!$D:$D,0))/$B$4) | N23: =IF(N$22="","",INDEX(Data!$AH:$AH,MATCH(N$22,Data!$D:$D,0))/$B$4) | O23: =IF(O$22="","",INDEX(Data!$AH:$AH,MATCH(O$22,Data!$D:$D,0))/$B$4) | P23: =IF(P$22="","",INDEX(Data!$AH:$AH,MATCH(P$22,Data!$D:$D,0))/$B$4) | ... BH23: =IF(BH$22="","",INDEX(Data!$AH:$AH,MATCH(BH$22,Data!$D:$D,0))/$B$4)
A24: less Bought futures or calls & sold puts to be covered by cash [BN90 16(1)(c)] | B24: =SUM(B25:B30) -> 24918468 | C24: =SUM(C25:C30) -> 0.14200057 | E24: =MIN(0,B18/B$4)*100 -> 0 | F24: ="Net "&IF($E24>0,"positive","negative")&" MtM OTC swaps, so "&IF($E24>0,"no ","")&"cash cover required" -> Net negative MtM OTC swaps, so cash cover required
A25: Equity Derivatives | B25: =IF(SUMIF(Data!$C:$C,"Equity Derivatives",Data!$AH:$AH)>=0,SUMIF(Data!$C:$C,"Equity Derivatives",Data!$AH:$AH),0) -> 23631160 | C25: =$B25/$B$4 -> 0.13466471 | E25: =MIN(0,B19/B$4)*100 -> 0 | F25: ="Net "&IF($E25>0,"positive","negative")&" MtM OTC FRAs, so "&IF($E25>0,"no ","")&"cash cover required" -> Net negative MtM OTC FRAs, so cash cover required
A26: excl MtM P&L on internationally listed derivatives | B26: =IF($H$5=0,0,-SUMIF(Data!$B:$B,"DERIVATIVES",Data!$AH:$AH)-SUMIF(Data!$B:$B,"UNKNOWN",Data!$AH:$AH)) -> 0 | C26: =$B26/$B$4 -> 0 | E26: =SUM(E22:E24) -> 17.801292 | F26: =IF($E26>=0,"Adequate","INADEQUATE")&" OTC currency forward and swap cover [BN90 17(1)(a)]" -> Adequate OTC currency forward and swap cover [BN90 17(1)(a)]
A27: Effective equity exposure from swaps | B27: {=SUMPRODUCT((Data!$C$2:$C$1000="SWAPS")*((Data!$G$2:$G$1000)*(Data!$M$2:$M$1000))>0)} -> 0 | C27: =$B27/$B$4 -> 0 | E27: =MAX(0,($H$2+$H$5+C26)*100) -> 13.466471 | F27: ="Net "&IF(E27>=0,"long","short")&" equity index, so adequate "&IF(E27>=0,"cash","similar asset")&" cover required" -> Net long equity index, so adequate cash cover required
A28: excl MtM P&L on OTC swaps | B28: {=-SUMPRODUCT((Data!$C$2:$C$1000="SWAPS")*((Data!$AH$2:$AH$1000)))} -> 1287308 | C28: =$B28/$B$4 -> 0.0073358632 | E28: =MAX(0,$H$8*100) -> 0 | F28: ="Net "&IF(E28>=0,"long","short")&" bond index, so adequate "&IF(E28>=0,"cash","similar asset")&" cover required" -> Net long bond index, so adequate cash cover required
A29: Currency Derivatives | B29: =IF(SUMIF(Data!$C:$C,$A29,Data!$AH:$AH)>=0,SUMIF(Data!$C:$C,$A29,Data!$AH:$AH),0) -> 0 | C29: =$B29/$B$4 -> 0
A30: Bond Derivatives | B30: =IF(SUMIF(Data!$C:$C,$A30,Data!$AH:$AH)>=0,SUMIF(Data!$C:$C,$A30,Data!$AH:$AH),0) -> 0 | C30: =$B30/$B$4 -> 0 | E30: =SUM(C27:C28)*100 -> 0.73358632 | F30: Effective equity exposure from swaps, after MtM
A32: =IF($A3="UT","","Cash from the "&COUNTIF(Data!$B:$B,"COLLECTIVE INVESTMENT SCHEMES")&" underlying UT"&IF(COUNTIF(Data!$B:$B,"COLLECTIVE INVESTMENT SCHEMES")=1,"","s")) | B32: =IF($A$3="UT",0,SUMIF(Data!$B:$B,"COLLECTIVE INVESTMENT SCHEMES",Data!$AH:$AH)) -> 0 | C32: =IF($A3="UT",0,$B32/$B$4) -> 0 | E32: =C32*100 -> 0
A34: =IF(B34>=0,"A","Ina")&"dequate cash cover for derivatives" -> Adequate cash cover for derivatives | B34: =B22-B24+B32 -> 6319500.4 | C34: =C22-C24+C32 -> 0.036012353 | E34: =E26-E27-E28-E29-E30+E32 -> 3.6012353 | F34: =IF($E34>=0,"Adequate","INADEQUATE")&" long derivative cash cover [BN90 16(1)(c)]" -> Adequate long derivative cash cover [BN90 16(1)(c)]
A36: =IF($A3="UT","The numbers above exclude these assets which don't qualify as AiLF for UTs: *","") -> The numbers above exclude these assets which don't qualify as AiLF for UTs: * | B36: =IF($A3="UT",SUM(B37:B38),"") -> 0 | C36: =IF($A3="UT",SUM(C37:C38),"") -> 0
A37: =IF($A3="UT","Money Market","") -> Money Market | B37: {=IF($A3="UT",SUMIF(Data!$B:$B,"MONEY MARKET",Data!$AH:$AH)-SUMPRODUCT((Data!$B:$B="MONEY MARKET")*((Data!$P:$P<Data!$AJ$2+397)*(Data!$V:$V<>"CLN")),(Data!$AH:$AH)),"")} -> 0 | C37: =IF($A3="UT",B37/$B$4,"") -> 0
A38: =IF($A3="UT","Bonds","") -> Bonds | B38: {=IF($A3="UT",SUMIF(Data!$B:$B,"BONDS",Data!$AH:$AH)-SUMPRODUCT((Data!$B:$B="BONDS")*((Data!$P:$P<Data!$AJ$2+397)*(Data!$V:$V<>"CLN")),(Data!$AH:$AH)),"")} -> 0 | C38: =IF($A3="UT",B38/$B$4,"") -> 0
A40: Total equity, incl property equity | B40: =B42+B50 -> 1.738422e+08 | C40: =C42+C50 -> 0.99065849
A42: Total non-property equity | B42: =SUM(B43:B48) -> 1.6973705e+08 | C42: =SUM(C43:C48) -> 0.96726481
A43: Equity futures and options | B43: {=SUMPRODUCT(('Glbl Expsr'!$H$2:$H$68)*('Glbl Expsr'!$I$2:$I$68)*('Glbl Expsr'!$J$2:$J$68)*('Glbl Expsr'!$L$2:$L$68)*('Glbl Expsr'!$O$2:$O$68))+$B$26} -> 23631160 | C43: {=SUMPRODUCT(('Glbl Expsr'!$H$2:$H$68)*('Glbl Expsr'!$I$2:$I$68)*('Glbl Expsr'!$J$2:$J$68)*('Glbl Expsr'!$L$2:$L$68)*('Glbl Expsr'!$O$2:$O$68))/SUM(Data!$L:$L)+$C$26} -> 0.13466471
A44: Equity linked notes | B44: {=SUMPRODUCT(--(Data!$C$2:$C$1000="EQUITY LINKED NOTES"), (Data!$AH$2:$AH$1000))} -> 0 | C44: {=SUMPRODUCT(--(Data!$C$2:$C$1000="EQUITY LINKED NOTES"),(Data!$AI2:$AI1000))/100} -> 0
A45: Equity TRSs | B45: {=SUMPRODUCT((Data!$C$2:$C$1000="SWAPS")*((Data!$G$2:$G$1000)*(Data!$M$2:$M$1000)))} -> 1.1301214e+08 | C45: {=SUMPRODUCT((Data!$C$2:$C$1000="SWAPS")*((Data!$G$2:$G$1000)*(Data!$M$2:$M$1000)))/SUM(Data!$L:$L)} -> 0.64401186
A46: Direct equities, excl direct property equity | B46: {=SUMPRODUCT((Data!$B:$B="EQUITIES")*(Data!$X:$X<>"REAL ESTATE")*(Data!$V:$V<>"EQUITY - ELN"),(Data!$AH:$AH))} -> 33093741 | C46: {=SUMPRODUCT((Data!$B:$B="EQUITIES")*(Data!$X:$X<>"REAL ESTATE")*(Data!$V:$V<>"EQUITY - ELN"),(Data!$AI:$AI))/100} -> 0.18858824
A47: Direct preference shares | B47: =SUMIF(Data!$B:$B,"PREFERENCE SHARES",Data!$AH:$AH) -> 0 | C47: =SUMIF(Data!$B:$B,"PREFERENCE SHARES",Data!$AI:$AI)/100 -> 0
A48: Equity unit trusts | B48: {=SUMPRODUCT(--((Data!$B:$B="COLLECTIVE INVESTMENT SCHEMES")*(ISNUMBER(SEARCH("equity",Data!$D:$D))-ISNUMBER(SEARCH("property equity",Data!$D:$D))+ISNUMBER(SEARCH("balanced",Data!$D:$D)))>0),(Data!$AH:$AH))} -> 0 | C48: {=SUMPRODUCT(--((Data!$B:$B="COLLECTIVE INVESTMENT SCHEMES")*(ISNUMBER(SEARCH("equity",Data!$D:$D))-ISNUMBER(SEARCH("property equity",Data!$D:$D))+ISNUMBER(SEARCH("balanced",Data!$D:$D)))>0),(Data!$AI:$AI))/100} -> 0
A50: Total property equity | B50: =SUM(B51:B52) -> 4105156.4 | C50: =SUM(C51:C52) -> 0.023393675
A51: Direct property equity | B51: {=SUMPRODUCT((Data!$B:$B="EQUITIES")*(Data!$X:$X="REAL ESTATE"),(Data!$AH:$AH))} -> 4105156.4 | C51: {=SUMPRODUCT((Data!$B:$B="EQUITIES")*(Data!$X:$X="REAL ESTATE"),(Data!$AI:$AI))/100} -> 0.023393675
A52: Property equity unit trusts | B52: {=SUMPRODUCT(--((Data!$B:$B="COLLECTIVE INVESTMENT SCHEMES")*(ISNUMBER(SEARCH("property equity",Data!$D:$D)))>0),(Data!$AH:$AH))} -> 0 | C52: {=SUMPRODUCT(--((Data!$B:$B="COLLECTIVE INVESTMENT SCHEMES")*(ISNUMBER(SEARCH("property equity",Data!$D:$D)))>0),(Data!$AI:$AI))/100} -> 0
A54: Total foreign | B54: =SUM(B56,B63,B69,B73) -> 0 | C54: =SUM(C56,C63,C69) -> 0 | D54: < 45%
A56: Direct foreign exposure excl foreign derivatives | B56: =SUM(B57:B61) -> 0 | C56: =SUM(C57:C61) -> 0
A57: Direct foreign assets excl derivatives, cash, MMIs, 'SYNCASH', CISes | B57: {=SUMPRODUCT((Data!$B:$B<>"CASH")*(Data!$B:$B<>"MONEY MARKET")*(Data!$B:$B<>"DERIVATIVES")*(Data!$B:$B<>"COLLECTIVE INVESTMENT SCHEMES")*(Data!$W:$W<>"ZAR")*(Data!$T:$T<>"SYTH"),Data!$AH:$AH)} -> 0 | C57: {=SUMPRODUCT((Data!$B:$B<>"CASH")*(Data!$B:$B<>"MONEY MARKET")*(Data!$B:$B<>"DERIVATIVES")*(Data!$B:$B<>"COLLECTIVE INVESTMENT SCHEMES")*(Data!$W:$W<>"ZAR")*(Data!$T:$T<>"SYTH"),Data!$AI:$AI)} -> 0
A58: {="Direct foreign cash excl 'SYNCASH' ("&SUMPRODUCT((Data!$B:$B="CASH")*(Data!$W:$W<>"ZAR")*(Data!$T:$T<>"SYTH"))&")"} -> Direct foreign cash excl 'SYNCASH' (0) | B58: {=SUMPRODUCT((Data!$B:$B="CASH")*(Data!$W:$W<>"ZAR")*(Data!$T:$T<>"SYTH"),Data!$AH:$AH)} -> 0 | C58: {=SUMPRODUCT((Data!$B:$B="CASH")*(Data!$W:$W<>"ZAR")*(Data!$T:$T<>"SYTH"),Data!$AI:$AI)} -> 0
A59: {="Direct foreign MMIs excl 'SYNCASH' ("&SUMPRODUCT((Data!$B:$B="MONEY MARKET")*(Data!$W:$W<>"ZAR")*(Data!$T:$T<>"SYTH"))&")"} -> Direct foreign MMIs excl 'SYNCASH' (0) | B59: {=SUMPRODUCT((Data!$B:$B="MONEY MARKET")*(Data!$W:$W<>"ZAR")*(Data!$T:$T<>"SYTH"),Data!$AH:$AH)} -> 0 | C59: {=SUMPRODUCT((Data!$B:$B="MONEY MARKET")*(Data!$W:$W<>"ZAR")*(Data!$T:$T<>"SYTH"),Data!$AI:$AI)} -> 0
A60: {="Global funds denominated as non-ZAR ("&SUMPRODUCT((Data!$B:$B="COLLECTIVE INVESTMENT SCHEMES")*(Data!$W:$W<>"ZAR")*(Data!$T:$T<>"SYTH"))&")"} -> Global funds denominated as non-ZAR (0) | B60: {=SUMPRODUCT((Data!$B:$B="COLLECTIVE INVESTMENT SCHEMES")*(Data!$W:$W<>"ZAR")*(Data!$T:$T<>"SYTH"),Data!$AH:$AH)} -> 0 | C60: {=SUMPRODUCT((Data!$B:$B="COLLECTIVE INVESTMENT SCHEMES")*(Data!$W:$W<>"ZAR")*(Data!$T:$T<>"SYTH"),Data!$AI:$AI)} -> 0
A61: {="Global funds denominated as ZAR ("&SUMPRODUCT((ISNUMBER(SEARCH("global",Data!$D:$D)))*(Data!$B:$B="COLLECTIVE INVESTMENT SCHEMES")*(Data!$W:$W="ZAR")*(Data!$T:$T<>"SYTH"))&")"} -> Global funds denominated as ZAR (0) | B61: {=SUMPRODUCT(Data!$AH:$AH,(ISNUMBER(SEARCH("global",Data!$D:$D)))*(Data!$B:$B="COLLECTIVE INVESTMENT SCHEMES")*(Data!$W:$W="ZAR")*(Data!$T:$T<>"SYTH"))} -> 0 | C61: {=SUMPRODUCT(Data!$AI:$AI,(ISNUMBER(SEARCH("global",Data!$D:$D)))*(Data!$B:$B="COLLECTIVE INVESTMENT SCHEMES")*(Data!$W:$W="ZAR")*(Data!$T:$T<>"SYTH"))} -> 0
A63: Indirect foreign exposure from derivatives | B63: =SUM(B64:B67) -> 0 | C63: =SUM(C64:C67) -> 0
A64: {="Foreign equity derivatives ("&SUMPRODUCT(--(Data!$C:$C="Equity Derivatives")*(Data!$W:$W<>"ZAR"))&")"} -> Foreign equity derivatives (0) | B64: {=SUMPRODUCT((Data!$C:$C="Equity derivatives")*(Data!$W:$W<>"ZAR"),Data!$AH:$AH)} -> 0 | C64: {=SUMPRODUCT((Data!$C:$C="Equity derivatives")*(Data!$W:$W<>"ZAR"),Data!$AI:$AI)} -> 0
A65: {="Foreign bond derivatives ("&SUMPRODUCT(--(Data!$C:$C="Bond Derivatives")*(Data!$W:$W<>"ZAR"))&")"} -> Foreign bond derivatives (0) | B65: {=SUMPRODUCT((Data!$C:$C="Bond derivatives")*(Data!$W:$W<>"ZAR"),Data!$AH:$AH)} -> 0 | C65: {=SUMPRODUCT((Data!$C:$C="Bond derivatives")*(Data!$W:$W<>"ZAR"),Data!$AI:$AI)} -> 0
A66: {="Foreign currency derivatives ("&SUMPRODUCT(--(Data!$C:$C="Currency Derivatives")*(Data!$W:$W<>"ZAR"))&")"} -> Foreign currency derivatives (0) | B66: {=SUMPRODUCT((Data!$C:$C="Currency derivatives")*(Data!$W:$W<>"ZAR"),Data!$AH:$AH)} -> 0 | C66: {=SUMPRODUCT((Data!$C:$C="Currency derivatives")*(Data!$W:$W<>"ZAR"),Data!$AI:$AI)} -> 0
A67: {="Foreign currency forwards ("&SUMPRODUCT(--(Data!$C:$C="Forwards")*(Data!$W:$W<>"ZAR"))&")"} -> Foreign currency forwards (0) | B67: {=SUMPRODUCT((Data!$C:$C="Forwards")*(Data!$W:$W<>"ZAR"),Data!$AH:$AH)} -> 0 | C67: {=SUMPRODUCT((Data!$C:$C="Forwards")*(Data!$W:$W<>"ZAR"),Data!$AI:$AI)} -> 0
A69: less Foreign cash | B69: =-SUM(B58:B59) -> 0 | C69: =-SUM(C58:C59) -> 0
A70: {="Direct foreign cash excl 'SYNCASH' ("&SUMPRODUCT((Data!$B:$B="CASH")*(Data!$W:$W<>"ZAR")*(Data!$T:$T<>"SYTH"))&")"} -> Direct foreign cash excl 'SYNCASH' (0) | B70: {=SUMPRODUCT((Data!$B:$B="CASH")*(Data!$W:$W<>"ZAR")*(Data!$T:$T<>"SYTH"),Data!$AH:$AH)} -> 0 | C70: {=SUMPRODUCT((Data!$B:$B="CASH")*(Data!$W:$W<>"ZAR")*(Data!$T:$T<>"SYTH"),Data!$AI:$AI)} -> 0
A71: {="Direct foreign MMIs excl 'SYNCASH' ("&SUMPRODUCT((Data!$B:$B="MONEY MARKET")*(Data!$W:$W<>"ZAR")*(Data!$T:$T<>"SYTH"))&")"} -> Direct foreign MMIs excl 'SYNCASH' (0) | B71: {=SUMPRODUCT((Data!$B:$B="MONEY MARKET")*(Data!$W:$W<>"ZAR")*(Data!$T:$T<>"SYTH"),Data!$AH:$AH)} -> 0 | C71: {=SUMPRODUCT((Data!$B:$B="MONEY MARKET")*(Data!$W:$W<>"ZAR")*(Data!$T:$T<>"SYTH"),Data!$AI:$AI)} -> 0
A73: "Additional foreign added by derivative" | B73: =B63+B69 -> 0 | C73: =C63+C69 -> 0
A76: Synthetic cash | B76: =SUM(B77:B78) -> -23631160 | C76: =SUM(C77:C78) -> -13.466471
A77: {="ZAR 'SYNCASH' ("&SUMPRODUCT((Data!$W:$W="ZAR")*(Data!$T:$T="SYTH"))&")"} -> ZAR 'SYNCASH' (2) | B77: {=SUMPRODUCT((Data!$W:$W="ZAR")*(Data!$T:$T="SYTH"),(Data!$AH:$AH))} -> -23631160 | C77: {=SUMPRODUCT((Data!$W:$W="ZAR")*(Data!$T:$T="SYTH"),(Data!$AI:$AI))} -> -13.466471
A78: {="Non-ZAR 'SYNCASH' ("&SUMPRODUCT((Data!$W:$W<>"ZAR")*(Data!$T:$T="SYTH"))&")"} -> Non-ZAR 'SYNCASH' (0) | B78: {=SUMPRODUCT((Data!$W:$W<>"ZAR")*(Data!$T:$T="SYTH"),(Data!$AH:$AH))} -> 0 | C78: {=SUMPRODUCT((Data!$W:$W<>"ZAR")*(Data!$T:$T="SYTH"),(Data!$AI:$AI))} -> 0

Sheet Glbl Expsr
A1: =Data!$A$2&" ("&Data!$AK$2&") Exposures "&TEXT(Data!$AJ$2,"d mmm yy") -> Tshwane Municipal Prov Fund (TSHMPF) Exposures 6 Apr 22 | C1: ZAR | D1: % NAV | F1: =_xlfn.XLOOKUP(Data!$AK$2,[77]Funds!$A:$A,[77]Funds!$E:$E) -> ≠ UT | G1: {="SA Equity Derivatives ("&SUMPRODUCT((Data!$C:$C="Equity Derivatives")*(Data!$W:$W="ZAR"))&")"} -> SA Equity Derivatives (2) | H1: Contracts Held | I1: Multiplier | J1: Market Price | K1: Nominal Exposure | L1: Delta | M1: Effective Exposure | N1: Gross Effective Exposure (%) | O1: Forex rate
A2: Global exposure (sum of the absolute effective exposures) | B2: a | C2: {=SUMPRODUCT(ABS(($H$2:$H$68))*($I$2:$I$68)*ABS(($J$2:$J$68))*ABS(($L$2:$L$68))*(O2:O68))+Summary!$B$26} -> 23631160 | D2: {=SUMPRODUCT(ABS(($H$2:$H$68))*($I$2:$I$68)*ABS(($J$2:$J$68))*ABS(($L$2:$L$68))*(O2:O68))/SUM(Data!$L:$L)+Summary!$C$26} -> 0.13466471 | G2: =Summary!I$1 -> 15JUN22 DCAP | H2: =IF($G2<>"",INDEX(Data!$G:$G,MATCH($G2,Data!$D:$D,0)),0) -> 63 | I2: =IF($G2<>"",10,0) -> 10 | J2: =IF($G2<>"",INDEX(Data!$M:$M,MATCH($G2,Data!$D:$D,0)),0) -> 20762 | K2: =PRODUCT($H2:$J2)*$O$53 -> 2.0378733e+08 | L2: =IF($G2<>"",INDEX(Deltas!$E:$E,MATCH($G2,Deltas!$B:$B,0)),0) -> 1 | M2: =PRODUCT($H2:$J2,$L2) -> 13080060 | N2: =ABS(PRODUCT($H2:$J2,$L2))/Summary!$B$4*$O$53 -> 1.161304 | O2: 1
A3: Net effective exposure (sum of the net effective exposures) | B3: b | C3: {=SUMPRODUCT(($H$2:$H$68)*($I$2:$I$68)*($J$2:$J$68)*($L$2:$L$68)*($O$2:$O$68))+Summary!$B$26} -> 23631160 | D3: {=SUMPRODUCT(($H$2:$H$68)*($I$2:$I$68)*($J$2:$J$68)*($L$2:$L$68)*($O$2:$O$68))/SUM(Data!$L:$L)+Summary!$C$26} -> 0.13466471 | G3: =Summary!J$1 -> 15JUN22 DCAR | H3: =IF($G3<>"",INDEX(Data!$G:$G,MATCH($G3,Data!$D:$D,0)),0) -> 35 | I3: =IF($G3<>"",10,0) -> 10 | J3: =IF($G3<>"",INDEX(Data!$M:$M,MATCH($G3,Data!$D:$D,0)),0) -> 30146 | K3: =PRODUCT($H3:$J3)*$O$53 -> 164386138 | L3: =IF($G3<>"",INDEX(Deltas!$E:$E,MATCH($G3,Deltas!$B:$B,0)),0) -> 1 | M3: =PRODUCT($H3:$J3,$L3) -> 10551100 | N3: =ABS(PRODUCT($H3:$J3,$L3))/Summary!$B$4*$O$53 -> 0.93677209 | O3: 1
A4: Liquid assets | B4: c | C4: =Summary!$B6 -> 31237968 | D4: =Summary!$B6/SUM(Data!$L:$L) -> 0.17801292 | G4: =Summary!K$1 | H4: =IF($G4<>"",INDEX(Data!$G:$G,MATCH($G4,Data!$D:$D,0)),0) -> 0 | I4: =IF($G4<>"",10,0) -> 0 | J4: =IF($G4<>"",INDEX(Data!$M:$M,MATCH($G4,Data!$D:$D,0)),0) -> 0 | K4: =PRODUCT($H4:$J4)*$O$53 -> 0 | L4: =IF($G4<>"",INDEX(Deltas!$E:$E,MATCH($G4,Deltas!$B:$B,0)),0) -> 0 | M4: =PRODUCT($H4:$J4,$L4) -> 0 | N4: =ABS(PRODUCT($H4:$J4,$L4))/Summary!$B$4*$O$53 -> 0 | O4: 1
A5: Liquid assets and collective investment schemes | B5: d | C5: =Summary!$B6+SUMIF(Data!$B:$B,"COLLECTIVE INVESTMENT SCHEMES",Data!$AH:$AH) -> 1.3956988e+08 | D5: =(Summary!$B6+SUMIF(Data!$B:$B,"COLLECTIVE INVESTMENT SCHEMES",Data!$AH:$AH))/SUM(Data!$L:$L) -> 0.79535395 | G5: =Summary!L$1 | H5: =IF($G5<>"",INDEX(Data!$G:$G,MATCH($G5,Data!$D:$D,0)),0) -> 0 | I5: =IF($G5<>"",10,0) -> 0 | J5: =IF($G5<>"",INDEX(Data!$M:$M,MATCH($G5,Data!$D:$D,0)),0) -> 0 | K5: =PRODUCT($H5:$J5)*$O$53 -> 0 | L5: =IF($G5<>"",INDEX(Deltas!$E:$E,MATCH($G5,Deltas!$B:$B,0)),0) -> 0 | M5: =PRODUCT($H5:$J5,$L5) -> 0 | N5: =ABS(PRODUCT($H5:$J5,$L5))/Summary!$B$4*$O$53 -> 0 | O5: 1
G6: =Summary!M$1 | H6: =IF($G6<>"",INDEX(Data!$G:$G,MATCH($G6,Data!$D:$D,0)),0) -> 0 | I6: =IF($G6<>"",10,0) -> 0 | J6: =IF($G6<>"",INDEX(Data!$M:$M,MATCH($G6,Data!$D:$D,0)),0) -> 0 | K6: =PRODUCT($H6:$J6)*$O$53 -> 0 | L6: =IF($G6<>"",INDEX(Deltas!$E:$E,MATCH($G6,Deltas!$B:$B,0)),0) -> 0 | M6: =PRODUCT($H6:$J6,$L6) -> 0 | N6: =ABS(PRODUCT($H6:$J6,$L6))/Summary!$B$4*$O$53 -> 0 | O6: 1
A7: Liquid asset cover over global exposure (must be > 100%) | B7: c ÷ a | C7: =IF(C2=0,1,C4/C2) -> 1.3218974 | D7: =D4-D2 -> 0.043348216 | E7: c - a | G7: =Summary!N$1 | H7: =IF($G7<>"",INDEX(Data!$G:$G,MATCH($G7,Data!$D:$D,0)),0) -> 0 | I7: =IF($G7<>"",10,0) -> 0 | J7: =IF($G7<>"",INDEX(Data!$M:$M,MATCH($G7,Data!$D:$D,0)),0) -> 0 | K7: =PRODUCT($H7:$J7)*$O$53 -> 0 | L7: =IF($G7<>"",INDEX(Deltas!$E:$E,MATCH($G7,Deltas!$B:$B,0)),0) -> 0 | M7: =PRODUCT($H7:$J7,$L7) -> 0 | N7: =ABS(PRODUCT($H7:$J7,$L7))/Summary!$B$4*$O$53 -> 0 | O7: 1
A8: Liquid asset cover over net effective exposure (must be > 100%) | B8: c ÷ b | C8: =IF(C3=0,1,C4/C3) -> 1.3218974 | D8: =D4-D3 -> 0.043348216 | E8: c - b | G8: =Summary!O$1 | H8: =IF($G8<>"",INDEX(Data!$G:$G,MATCH($G8,Data!$D:$D,0)),0) -> 0 | I8: =IF($G8<>"",10,0) -> 0 | J8: =IF($G8<>"",INDEX(Data!$M:$M,MATCH($G8,Data!$D:$D,0)),0) -> 0 | K8: =PRODUCT($H8:$J8)*$O$53 -> 0 | L8: =IF($G8<>"",INDEX(Deltas!$E:$E,MATCH($G8,Deltas!$B:$B,0)),0) -> 0 | M8: =PRODUCT($H8:$J8,$L8) -> 0 | N8: =ABS(PRODUCT($H8:$J8,$L8))/Summary!$B$4*$O$53 -> 0 | O8: 1
G9: =Summary!P$1 | H9: =IF($G9<>"",INDEX(Data!$G:$G,MATCH($G9,Data!$D:$D,0)),0) -> 0 | I9: =IF($G9<>"",10,0) -> 0 | J9: =IF($G9<>"",INDEX(Data!$M:$M,MATCH($G9,Data!$D:$D,0)),0) -> 0 | K9: =PRODUCT($H9:$J9)*$O$53 -> 0 | L9: =IF($G9<>"",INDEX(Deltas!$E:$E,MATCH($G9,Deltas!$B:$B,0)),0) -> 0 | M9: =PRODUCT($H9:$J9,$L9) -> 0 | N9: =ABS(PRODUCT($H9:$J9,$L9))/Summary!$B$4*$O$53 -> 0 | O9: 1
A10: Liquid asset cover, incl CISes, over net effective exposure (must be > 100%) | B10: d ÷ a | C10: =IF(C2=0,1,C5/C2) -> 5.9061796 | D10: =D5-D2 -> 0.66068924 | E10: d - a | G10: =Summary!Q$1 | H10: =IF($G10<>"",INDEX(Data!$G:$G,MATCH($G10,Data!$D:$D,0)),0) -> 0 | I10: =IF($G10<>"",10,0) -> 0 | J10: =IF($G10<>"",INDEX(Data!$M:$M,MATCH($G10,Data!$D:$D,0)),0) -> 0 | K10: =PRODUCT($H10:$J10)*$O$53 -> 0 | L10: =IF($G10<>"",INDEX(Deltas!$E:$E,MATCH($G10,Deltas!$B:$B,0)),0) -> 0 | M10: =PRODUCT($H10:$J10,$L10) -> 0 | N10: =ABS(PRODUCT($H10:$J10,$L10))/Summary!$B$4*$O$53 -> 0 | O10: 1
A11: Liquid asset cover, incl CISes, over net effective exposure (must be > 100%) | B11: d ÷ b | C11: =IF(C3=0,1,C5/C3) -> 5.9061796 | D11: =D5-D3 -> 0.66068924 | E11: d - b | G11: =Summary!R$1 | H11: =IF($G11<>"",INDEX(Data!$G:$G,MATCH($G11,Data!$D:$D,0)),0) -> 0 | I11: =IF($G11<>"",10,0) -> 0 | J11: =IF($G11<>"",INDEX(Data!$M:$M,MATCH($G11,Data!$D:$D,0)),0) -> 0 | K11: =PRODUCT($H11:$J11)*$O$53 -> 0 | L11: =IF($G11<>"",INDEX(Deltas!$E:$E,MATCH($G11,Deltas!$B:$B,0)),0) -> 0 | M11: =PRODUCT($H11:$J11,$L11) -> 0 | N11: =ABS(PRODUCT($H11:$J11,$L11))/Summary!$B$4*$O$53 -> 0 | O11: 1
G12: =Summary!S$1 | H12: =IF($G12<>"",INDEX(Data!$G:$G,MATCH($G12,Data!$D:$D,0)),0) -> 0 | I12: =IF($G12<>"",10,0) -> 0 | J12: =IF($G12<>"",INDEX(Data!$M:$M,MATCH($G12,Data!$D:$D,0)),0) -> 0 | K12: =PRODUCT($H12:$J12)*$O$53 -> 0 | L12: =IF($G12<>"",INDEX(Deltas!$E:$E,MATCH($G12,Deltas!$B:$B,0)),0) -> 0 | M12: =PRODUCT($H12:$J12,$L12) -> 0 | N12: =ABS(PRODUCT($H12:$J12,$L12))/Summary!$B$4*$O$53 -> 0 | O12: 1
G13: =Summary!T$1 | H13: =IF($G13<>"",INDEX(Data!$G:$G,MATCH($G13,Data!$D:$D,0)),0) -> 0 | I13: =IF($G13<>"",10,0) -> 0 | J13: =IF($G13<>"",INDEX(Data!$M:$M,MATCH($G13,Data!$D:$D,0)),0) -> 0 | K13: =PRODUCT($H13:$J13)*$O$53 -> 0 | L13: =IF($G13<>"",INDEX(Deltas!$E:$E,MATCH($G13,Deltas!$B:$B,0)),0) -> 0 | M13: =PRODUCT($H13:$J13,$L13) -> 0 | N13: =ABS(PRODUCT($H13:$J13,$L13))/Summary!$B$4*$O$53 -> 0 | O13: 1
G14: =Summary!U$1 | H14: =IF($G14<>"",INDEX(Data!$G:$G,MATCH($G14,Data!$D:$D,0)),0) -> 0 | I14: =IF($G14<>"",10,0) -> 0 | J14: =IF($G14<>"",INDEX(Data!$M:$M,MATCH($G14,Data!$D:$D,0)),0) -> 0 | K14: =PRODUCT($H14:$J14)*$O$53 -> 0 | L14: =IF($G14<>"",INDEX(Deltas!$E:$E,MATCH($G14,Deltas!$B:$B,0)),0) -> 0 | M14: =PRODUCT($H14:$J14,$L14) -> 0 | N14: =ABS(PRODUCT($H14:$J14,$L14))/Summary!$B$4*$O$53 -> 0 | O14: 1
G15: =Summary!V$1 | H15: =IF($G15<>"",INDEX(Data!$G:$G,MATCH($G15,Data!$D:$D,0)),0) -> 0 | I15: =IF($G15<>"",10,0) -> 0 | J15: =IF($G15<>"",INDEX(Data!$M:$M,MATCH($G15,Data!$D:$D,0)),0) -> 0 | K15: =PRODUCT($H15:$J15)*$O$53 -> 0 | L15: =IF($G15<>"",INDEX(Deltas!$E:$E,MATCH($G15,Deltas!$B:$B,0)),0) -> 0 | M15: =PRODUCT($H15:$J15,$L15) -> 0 | N15: =ABS(PRODUCT($H15:$J15,$L15))/Summary!$B$4*$O$53 -> 0 | O15: 1
G16: =Summary!W$1 | H16: =IF($G16<>"",INDEX(Data!$G:$G,MATCH($G16,Data!$D:$D,0)),0) -> 0 | I16: =IF($G16<>"",10,0) -> 0 | J16: =IF($G16<>"",INDEX(Data!$M:$M,MATCH($G16,Data!$D:$D,0)),0) -> 0 | K16: =PRODUCT($H16:$J16)*$O$53 -> 0 | L16: =IF($G16<>"",INDEX(Deltas!$E:$E,MATCH($G16,Deltas!$B:$B,0)),0) -> 0 | M16: =PRODUCT($H16:$J16,$L16) -> 0 | N16: =ABS(PRODUCT($H16:$J16,$L16))/Summary!$B$4*$O$53 -> 0 | O16: 1
G17: =Summary!X$1 | H17: =IF($G17<>"",INDEX(Data!$G:$G,MATCH($G17,Data!$D:$D,0)),0) -> 0 | I17: =IF($G17<>"",10,0) -> 0 | J17: =IF($G17<>"",INDEX(Data!$M:$M,MATCH($G17,Data!$D:$D,0)),0) -> 0 | K17: =PRODUCT($H17:$J17)*$O$53 -> 0 | L17: =IF($G17<>"",INDEX(Deltas!$E:$E,MATCH($G17,Deltas!$B:$B,0)),0) -> 0 | M17: =PRODUCT($H17:$J17,$L17) -> 0 | N17: =ABS(PRODUCT($H17:$J17,$L17))/Summary!$B$4*$O$53 -> 0 | O17: 1
G18: ="Swaps ("&COUNTIF(Data!$C:$C,"Swaps")&")" -> Swaps (6)
G19: =Summary!I$16 | H19: =IF($G19<>"",INDEX(Data!$G:$G,MATCH($G19,Data!$D:$D,0)),0) -> 0 | I19: =IF($G19<>"",1,0) -> 0 | J19: =IF($G19<>"",INDEX(Data!$M:$M,MATCH($G19,Data!$D:$D,0)),0)/100 -> 0 | K19: =PRODUCT($H19,$J19)*$O$53 -> 0 | L19: =IF($G19<>"",1,0) -> 0 | M19: =PRODUCT($H19,$J19,$L19) -> 0 | N19: =ABS(PRODUCT($H19:$J19,$L19))/Summary!$B$4*$O$53 -> 0 | O19: 1
G20: =Summary!J$16 | H20: =IF($G20<>"",INDEX(Data!$G:$G,MATCH($G20,Data!$D:$D,0)),0) -> 0 | I20: =IF($G20<>"",1,0) -> 0 | J20: =IF($G20<>"",INDEX(Data!$M:$M,MATCH($G20,Data!$D:$D,0)),0)/100 -> 0 | K20: =PRODUCT($H20,$J20)*$O$53 -> 0 | L20: =IF($G20<>"",1,0) -> 0 | M20: =PRODUCT($H20,$J20,$L20) -> 0 | N20: =ABS(PRODUCT($H20:$J20,$L20))/Summary!$B$4*$O$53 -> 0 | O20: 1
G21: =Summary!K$16 | H21: =IF($G21<>"",INDEX(Data!$G:$G,MATCH($G21,Data!$D:$D,0)),0) -> 0 | I21: =IF($G21<>"",1,0) -> 0 | J21: =IF($G21<>"",INDEX(Data!$M:$M,MATCH($G21,Data!$D:$D,0)),0)/100 -> 0 | K21: =PRODUCT($H21,$J21)*$O$53 -> 0 | L21: =IF($G21<>"",1,0) -> 0 | M21: =PRODUCT($H21,$J21,$L21) -> 0 | N21: =ABS(PRODUCT($H21:$J21,$L21))/Summary!$B$4*$O$53 -> 0 | O21: 1
G22: =Summary!L$16 | H22: =IF($G22<>"",INDEX(Data!$G:$G,MATCH($G22,Data!$D:$D,0)),0) -> 0 | I22: =IF($G22<>"",1,0) -> 0 | J22: =IF($G22<>"",INDEX(Data!$M:$M,MATCH($G22,Data!$D:$D,0)),0)/100 -> 0 | K22: =PRODUCT($H22,$J22)*$O$53 -> 0 | L22: =IF($G22<>"",1,0) -> 0 | M22: =PRODUCT($H22:$J22,$L22) -> 0 | N22: =ABS(PRODUCT($H22:$J22,$L22))/Summary!$B$4*$O$53 -> 0 | O22: 1
G23: =Summary!M$16 | H23: =IF($G23<>"",INDEX(Data!$G:$G,MATCH($G23,Data!$D:$D,0)),0) -> 0 | I23: =IF($G23<>"",1,0) -> 0 | J23: =IF($G23<>"",INDEX(Data!$M:$M,MATCH($G23,Data!$D:$D,0)),0)/100 -> 0 | K23: =PRODUCT($H23,$J23)*$O$53 -> 0 | L23: =IF($G23<>"",1,0) -> 0 | M23: =PRODUCT($H23:$J23,$L23) -> 0 | N23: =ABS(PRODUCT($H23:$J23,$L23))/Summary!$B$4*$O$53 -> 0 | O23: 1
G24: =Summary!N$16 | H24: =IF($G24<>"",INDEX(Data!$G:$G,MATCH($G24,Data!$D:$D,0)),0) -> 0 | I24: =IF($G24<>"",1,0) -> 0 | J24: =IF($G24<>"",INDEX(Data!$M:$M,MATCH($G24,Data!$D:$D,0)),0)/100 -> 0 | K24: =PRODUCT($H24,$J24)*$O$53 -> 0 | L24: =IF($G24<>"",1,0) -> 0 | M24: =PRODUCT($H24:$J24,$L24) -> 0 | N24: =ABS(PRODUCT($H24:$J24,$L24))/Summary!$B$4*$O$53 -> 0 | O24: 1
G25: =Summary!O$16 | H25: =IF($G25<>"",INDEX(Data!$G:$G,MATCH($G25,Data!$D:$D,0)),0) -> 0 | I25: =IF($G25<>"",1,0) -> 0 | J25: =IF($G25<>"",INDEX(Data!$M:$M,MATCH($G25,Data!$D:$D,0)),0)/100 -> 0 | K25: =PRODUCT($H25,$J25)*$O$53 -> 0 | L25: =IF($G25<>"",1,0) -> 0 | M25: =PRODUCT($H25:$J25,$L25) -> 0 | N25: =ABS(PRODUCT($H25:$J25,$L25))/Summary!$B$4*$O$53 -> 0 | O25: 1
G26: =Summary!P$16 | H26: =IF($G26<>"",INDEX(Data!$G:$G,MATCH($G26,Data!$D:$D,0)),0) -> 0 | I26: =IF($G26<>"",1,0) -> 0 | J26: =IF($G26<>"",INDEX(Data!$M:$M,MATCH($G26,Data!$D:$D,0)),0)/100 -> 0 | K26: =PRODUCT($H26,$J26)*$O$53 -> 0 | L26: =IF($G26<>"",1,0) -> 0 | M26: =PRODUCT($H26:$J26,$L26) -> 0 | N26: =ABS(PRODUCT($H26:$J26,$L26))/Summary!$B$4*$O$53 -> 0 | O26: 1
G27: =Summary!Q$16 | H27: =IF($G27<>"",INDEX(Data!$G:$G,MATCH($G27,Data!$D:$D,0)),0) -> 0 | I27: =IF($G27<>"",1,0) -> 0 | J27: =IF($G27<>"",INDEX(Data!$M:$M,MATCH($G27,Data!$D:$D,0)),0)/100 -> 0 | K27: =PRODUCT($H27,$J27)*$O$53 -> 0 | L27: =IF($G27<>"",1,0) -> 0 | M27: =PRODUCT($H27:$J27,$L27) -> 0 | N27: =ABS(PRODUCT($H27:$J27,$L27))/Summary!$B$4*$O$53 -> 0 | O27: 1
G28: =Summary!R$16 | H28: =IF($G28<>"",INDEX(Data!$G:$G,MATCH($G28,Data!$D:$D,0)),0) -> 0 | I28: =IF($G28<>"",1,0) -> 0 | J28: =IF($G28<>"",INDEX(Data!$M:$M,MATCH($G28,Data!$D:$D,0)),0)/100 -> 0 | K28: =PRODUCT($H28,$J28)*$O$53 -> 0 | L28: =IF($G28<>"",1,0) -> 0 | M28: =PRODUCT($H28:$J28,$L28) -> 0 | N28: =ABS(PRODUCT($H28:$J28,$L28))/Summary!$B$4*$O$53 -> 0 | O28: 1
G29: =Summary!S$16 | H29: =IF($G29<>"",INDEX(Data!$G:$G,MATCH($G29,Data!$D:$D,0)),0) -> 0 | I29: =IF($G29<>"",1,0) -> 0 | J29: =IF($G29<>"",INDEX(Data!$M:$M,MATCH($G29,Data!$D:$D,0)),0)/100 -> 0 | K29: =PRODUCT($H29,$J29)*$O$53 -> 0 | L29: =IF($G29<>"",1,0) -> 0 | M29: =PRODUCT($H29:$J29,$L29) -> 0 | N29: =ABS(PRODUCT($H29:$J29,$L29))/Summary!$B$4*$O$53 -> 0 | O29: 1
G30: =Summary!T$16 | H30: =IF($G30<>"",INDEX(Data!$G:$G,MATCH($G30,Data!$D:$D,0)),0) -> 0 | I30: =IF($G30<>"",1,0) -> 0 | J30: =IF($G30<>"",INDEX(Data!$M:$M,MATCH($G30,Data!$D:$D,0)),0)/100 -> 0 | K30: =PRODUCT($H30,$J30)*$O$53 -> 0 | L30: =IF($G30<>"",1,0) -> 0 | M30: =PRODUCT($H30:$J30,$L30) -> 0 | N30: =ABS(PRODUCT($H30:$J30,$L30))/Summary!$B$4*$O$53 -> 0 | O30: 1
G31: =Summary!U$16 | H31: =IF($G31<>"",INDEX(Data!$G:$G,MATCH($G31,Data!$D:$D,0)),0) -> 0 | I31: =IF($G31<>"",1,0) -> 0 | J31: =IF($G31<>"",INDEX(Data!$M:$M,MATCH($G31,Data!$D:$D,0)),0)/100 -> 0 | K31: =PRODUCT($H31,$J31)*$O$53 -> 0 | L31: =IF($G31<>"",1,0) -> 0 | M31: =PRODUCT($H31:$J31,$L31) -> 0 | N31: =ABS(PRODUCT($H31:$J31,$L31))/Summary!$B$4*$O$53 -> 0 | O31: 1
G32: =Summary!V$16 | H32: =IF($G32<>"",INDEX(Data!$G:$G,MATCH($G32,Data!$D:$D,0)),0) -> 0 | I32: =IF($G32<>"",1,0) -> 0 | J32: =IF($G32<>"",INDEX(Data!$M:$M,MATCH($G32,Data!$D:$D,0)),0)/100 -> 0 | K32: =PRODUCT($H32,$J32)*$O$53 -> 0 | L32: =IF($G32<>"",1,0) -> 0 | M32: =PRODUCT($H32:$J32,$L32) -> 0 | N32: =ABS(PRODUCT($H32:$J32,$L32))/Summary!$B$4*$O$53 -> 0 | O32: 1
G33: =Summary!W$16 | H33: =IF($G33<>"",INDEX(Data!$G:$G,MATCH($G33,Data!$D:$D,0)),0) -> 0 | I33: =IF($G33<>"",1,0) -> 0 | J33: =IF($G33<>"",INDEX(Data!$M:$M,MATCH($G33,Data!$D:$D,0)),0)/100 -> 0 | K33: =PRODUCT($H33,$J33)*$O$53 -> 0 | L33: =IF($G33<>"",1,0) -> 0 | M33: =PRODUCT($H33:$J33,$L33) -> 0 | N33: =ABS(PRODUCT($H33:$J33,$L33))/Summary!$B$4*$O$53 -> 0 | O33: 1
G34: =Summary!X$16 | H34: =IF($G34<>"",INDEX(Data!$G:$G,MATCH($G34,Data!$D:$D,0)),0) -> 0 | I34: =IF($G34<>"",1,0) -> 0 | J34: =IF($G34<>"",INDEX(Data!$M:$M,MATCH($G34,Data!$D:$D,0)),0)/100 -> 0 | K34: =PRODUCT($H34,$J34)*$O$53 -> 0 | L34: =IF($G34<>"",1,0) -> 0 | M34: =PRODUCT($H34:$J34,$L34) -> 0 | N34: =ABS(PRODUCT($H34:$J34,$L34))/Summary!$B$4*$O$53 -> 0 | O34: 1
G35: ="Bond Derivatives ("&COUNTIF(Data!$C:$C,"Bond Derivatives")&")" -> Bond Derivatives (0)
G36: =Summary!I$7 | H36: =IF($G36<>"",INDEX(Data!$G:$G,MATCH($G36,Data!$D:$D,0)),0) -> 0 | I36: =IF($G36<>"",10,0) -> 0 | J36: =IF($G36<>"",INDEX(Data!$M:$M,MATCH($G36,Data!$D:$D,0)),0) -> 0 | K36: =PRODUCT($H36:$J36)*$O$53 -> 0 | L36: =IF($G36<>"",INDEX(Deltas!$E:$E,MATCH($G36,Deltas!$B:$B,0)),0) -> 0 | M36: =PRODUCT($H36:$J36,$L36)*$O$53 -> 0 | N36: =ABS(PRODUCT($H36:$J36,$L36))/Summary!$B$4*$O$53 -> 0 | O36: 1
G37: =Summary!J$7 | H37: =IF($G37<>"",INDEX(Data!$G:$G,MATCH($G37,Data!$D:$D,0)),0) -> 0 | I37: =IF($G37<>"",10,0) -> 0 | J37: =IF($G37<>"",INDEX(Data!$M:$M,MATCH($G37,Data!$D:$D,0)),0) -> 0 | K37: =PRODUCT($H37:$J37)*$O$53 -> 0 | L37: =IF($G37<>"",INDEX(Deltas!$E:$E,MATCH($G37,Deltas!$B:$B,0)),0) -> 0 | M37: =PRODUCT($H37:$J37,$L37)*$O$53 -> 0 | N37: =ABS(PRODUCT($H37:$J37,$L37))/Summary!$B$4*$O$53 -> 0 | O37: 1
G38: =Summary!K$7 | H38: =IF($G38<>"",INDEX(Data!$G:$G,MATCH($G38,Data!$D:$D,0)),0) -> 0 | I38: =IF($G38<>"",10,0) -> 0 | J38: =IF($G38<>"",INDEX(Data!$M:$M,MATCH($G38,Data!$D:$D,0)),0) -> 0 | K38: =PRODUCT($H38:$J38)*$O$53 -> 0 | L38: =IF($G38<>"",INDEX(Deltas!$E:$E,MATCH($G38,Deltas!$B:$B,0)),0) -> 0 | M38: =PRODUCT($H38:$J38,$L38)*$O$53 -> 0 | N38: =ABS(PRODUCT($H38:$J38,$L38))/Summary!$B$4*$O$53 -> 0 | O38: 1
G39: =Summary!L$7 | H39: =IF($G39<>"",INDEX(Data!$G:$G,MATCH($G39,Data!$D:$D,0)),0) -> 0 | I39: =IF($G39<>"",10,0) -> 0 | J39: =IF($G39<>"",INDEX(Data!$M:$M,MATCH($G39,Data!$D:$D,0)),0) -> 0 | K39: =PRODUCT($H39:$J39)*$O$53 -> 0 | L39: =IF($G39<>"",INDEX(Deltas!$E:$E,MATCH($G39,Deltas!$B:$B,0)),0) -> 0 | M39: =PRODUCT($H39:$J39,$L39)*$O$53 -> 0 | N39: =ABS(PRODUCT($H39:$J39,$L39))/Summary!$B$4*$O$53 -> 0 | O39: 1
G40: =Summary!M$7 | H40: =IF($G40<>"",INDEX(Data!$G:$G,MATCH($G40,Data!$D:$D,0)),0) -> 0 | I40: =IF($G40<>"",10,0) -> 0 | J40: =IF($G40<>"",INDEX(Data!$M:$M,MATCH($G40,Data!$D:$D,0)),0) -> 0 | K40: =PRODUCT($H40:$J40)*$O$53 -> 0 | L40: =IF($G40<>"",INDEX(Deltas!$E:$E,MATCH($G40,Deltas!$B:$B,0)),0) -> 0 | M40: =PRODUCT($H40:$J40,$L40)*$O$53 -> 0 | N40: =ABS(PRODUCT($H40:$J40,$L40))/Summary!$B$4*$O$53 -> 0 | O40: 1
G41: =Summary!N$7 | H41: =IF($G41<>"",INDEX(Data!$G:$G,MATCH($G41,Data!$D:$D,0)),0) -> 0 | I41: =IF($G41<>"",10,0) -> 0 | J41: =IF($G41<>"",INDEX(Data!$M:$M,MATCH($G41,Data!$D:$D,0)),0) -> 0 | K41: =PRODUCT($H41:$J41)*$O$53 -> 0 | L41: =IF($G41<>"",INDEX(Deltas!$E:$E,MATCH($G41,Deltas!$B:$B,0)),0) -> 0 | M41: =PRODUCT($H41:$J41,$L41)*$O$53 -> 0 | N41: =ABS(PRODUCT($H41:$J41,$L41))/Summary!$B$4*$O$53 -> 0 | O41: 1
G42: =Summary!O$7 | H42: =IF($G42<>"",INDEX(Data!$G:$G,MATCH($G42,Data!$D:$D,0)),0) -> 0 | I42: =IF($G42<>"",10,0) -> 0 | J42: =IF($G42<>"",INDEX(Data!$M:$M,MATCH($G42,Data!$D:$D,0)),0) -> 0 | K42: =PRODUCT($H42:$J42)*$O$53 -> 0 | L42: =IF($G42<>"",INDEX(Deltas!$E:$E,MATCH($G42,Deltas!$B:$B,0)),0) -> 0 | M42: =PRODUCT($H42:$J42,$L42)*$O$53 -> 0 | N42: =ABS(PRODUCT($H42:$J42,$L42))/Summary!$B$4*$O$53 -> 0 | O42: 1
G43: =Summary!P$7 | H43: =IF($G43<>"",INDEX(Data!$G:$G,MATCH($G43,Data!$D:$D,0)),0) -> 0 | I43: =IF($G43<>"",10,0) -> 0 | J43: =IF($G43<>"",INDEX(Data!$M:$M,MATCH($G43,Data!$D:$D,0)),0) -> 0 | K43: =PRODUCT($H43:$J43)*$O$53 -> 0 | L43: =IF($G43<>"",INDEX(Deltas!$E:$E,MATCH($G43,Deltas!$B:$B,0)),0) -> 0 | M43: =PRODUCT($H43:$J43,$L43)*$O$53 -> 0 | N43: =ABS(PRODUCT($H43:$J43,$L43))/Summary!$B$4*$O$53 -> 0 | O43: 1
G44: =Summary!Q$7 | H44: =IF($G44<>"",INDEX(Data!$G:$G,MATCH($G44,Data!$D:$D,0)),0) -> 0 | I44: =IF($G44<>"",10,0) -> 0 | J44: =IF($G44<>"",INDEX(Data!$M:$M,MATCH($G44,Data!$D:$D,0)),0) -> 0 | K44: =PRODUCT($H44:$J44)*$O$53 -> 0 | L44: =IF($G44<>"",INDEX(Deltas!$E:$E,MATCH($G44,Deltas!$B:$B,0)),0) -> 0 | M44: =PRODUCT($H44:$J44,$L44)*$O$53 -> 0 | N44: =ABS(PRODUCT($H44:$J44,$L44))/Summary!$B$4*$O$53 -> 0 | O44: 1
G45: =Summary!R$7 | H45: =IF($G45<>"",INDEX(Data!$G:$G,MATCH($G45,Data!$D:$D,0)),0) -> 0 | I45: =IF($G45<>"",10,0) -> 0 | J45: =IF($G45<>"",INDEX(Data!$M:$M,MATCH($G45,Data!$D:$D,0)),0) -> 0 | K45: =PRODUCT($H45:$J45)*$O$53 -> 0 | L45: =IF($G45<>"",INDEX(Deltas!$E:$E,MATCH($G45,Deltas!$B:$B,0)),0) -> 0 | M45: =PRODUCT($H45:$J45,$L45)*$O$53 -> 0 | N45: =ABS(PRODUCT($H45:$J45,$L45))/Summary!$B$4*$O$53 -> 0 | O45: 1
G46: =Summary!S$7 | H46: =IF($G46<>"",INDEX(Data!$G:$G,MATCH($G46,Data!$D:$D,0)),0) -> 0 | I46: =IF($G46<>"",10,0) -> 0 | J46: =IF($G46<>"",INDEX(Data!$M:$M,MATCH($G46,Data!$D:$D,0)),0) -> 0 | K46: =PRODUCT($H46:$J46)*$O$53 -> 0 | L46: =IF($G46<>"",INDEX(Deltas!$E:$E,MATCH($G46,Deltas!$B:$B,0)),0) -> 0 | M46: =PRODUCT($H46:$J46,$L46)*$O$53 -> 0 | N46: =ABS(PRODUCT($H46:$J46,$L46))/Summary!$B$4*$O$53 -> 0 | O46: 1
G47: =Summary!T$7 | H47: =IF($G47<>"",INDEX(Data!$G:$G,MATCH($G47,Data!$D:$D,0)),0) -> 0 | I47: =IF($G47<>"",10,0) -> 0 | J47: =IF($G47<>"",INDEX(Data!$M:$M,MATCH($G47,Data!$D:$D,0)),0) -> 0 | K47: =PRODUCT($H47:$J47)*$O$53 -> 0 | L47: =IF($G47<>"",INDEX(Deltas!$E:$E,MATCH($G47,Deltas!$B:$B,0)),0) -> 0 | M47: =PRODUCT($H47:$J47,$L47)*$O$53 -> 0 | N47: =ABS(PRODUCT($H47:$J47,$L47))/Summary!$B$4*$O$53 -> 0 | O47: 1
G48: =Summary!U$7 | H48: =IF($G48<>"",INDEX(Data!$G:$G,MATCH($G48,Data!$D:$D,0)),0) -> 0 | I48: =IF($G48<>"",10,0) -> 0 | J48: =IF($G48<>"",INDEX(Data!$M:$M,MATCH($G48,Data!$D:$D,0)),0) -> 0 | K48: =PRODUCT($H48:$J48)*$O$53 -> 0 | L48: =IF($G48<>"",INDEX(Deltas!$E:$E,MATCH($G48,Deltas!$B:$B,0)),0) -> 0 | M48: =PRODUCT($H48:$J48,$L48)*$O$53 -> 0 | N48: =ABS(PRODUCT($H48:$J48,$L48))/Summary!$B$4*$O$53 -> 0 | O48: 1
G49: =Summary!V$7 | H49: =IF($G49<>"",INDEX(Data!$G:$G,MATCH($G49,Data!$D:$D,0)),0) -> 0 | I49: =IF($G49<>"",10,0) -> 0 | J49: =IF($G49<>"",INDEX(Data!$M:$M,MATCH($G49,Data!$D:$D,0)),0) -> 0 | K49: =PRODUCT($H49:$J49)*$O$53 -> 0 | L49: =IF($G49<>"",INDEX(Deltas!$E:$E,MATCH($G49,Deltas!$B:$B,0)),0) -> 0 | M49: =PRODUCT($H49:$J49,$L49)*$O$53 -> 0 | N49: =ABS(PRODUCT($H49:$J49,$L49))/Summary!$B$4*$O$53 -> 0 | O49: 1
G50: =Summary!W$7 | H50: =IF($G50<>"",INDEX(Data!$G:$G,MATCH($G50,Data!$D:$D,0)),0) -> 0 | I50: =IF($G50<>"",10,0) -> 0 | J50: =IF($G50<>"",INDEX(Data!$M:$M,MATCH($G50,Data!$D:$D,0)),0) -> 0 | K50: =PRODUCT($H50:$J50)*$O$53 -> 0 | L50: =IF($G50<>"",INDEX(Deltas!$E:$E,MATCH($G50,Deltas!$B:$B,0)),0) -> 0 | M50: =PRODUCT($H50:$J50,$L50)*$O$53 -> 0 | N50: =ABS(PRODUCT($H50:$J50,$L50))/Summary!$B$4*$O$53 -> 0 | O50: 1
G51: =Summary!X$7 | H51: =IF($G51<>"",INDEX(Data!$G:$G,MATCH($G51,Data!$D:$D,0)),0) -> 0 | I51: =IF($G51<>"",10,0) -> 0 | J51: =IF($G51<>"",INDEX(Data!$M:$M,MATCH($G51,Data!$D:$D,0)),0) -> 0 | K51: =PRODUCT($H51:$J51)*$O$53 -> 0 | L51: =IF($G51<>"",INDEX(Deltas!$E:$E,MATCH($G51,Deltas!$B:$B,0)),0) -> 0 | M51: =PRODUCT($H51:$J51,$L51)*$O$53 -> 0 | N51: =ABS(PRODUCT($H51:$J51,$L51))/Summary!$B$4*$O$53 -> 0 | O51: 1
G52: {="Foreign Equity Derivatives ("&SUMPRODUCT((Data!$C:$C="Equity Derivatives")*(Data!$W:$W<>"ZAR"))&")"} -> Foreign Equity Derivatives (0)
G53: =Summary!I$4 | H53: =IF($G53<>"",INDEX(Data!$G:$G,MATCH($G53,Data!$D:$D,0)),0) -> 0 | I53: =IF($G53<>"",10,0) -> 0 | J53: =IF($G53<>"",INDEX(Data!$M:$M,MATCH($G53,Data!$D:$D,0)),0) -> 0 | K53: =PRODUCT($H53:$J53)*$O$53 -> 0 | L53: =IF($G53<>"",INDEX(Deltas!$E:$E,MATCH($G53,Deltas!$B:$B,0)),0) -> 0 | M53: =PRODUCT($H53:$J53,$L53) -> 0 | N53: =ABS(PRODUCT($H53:$J53,$L53))/Summary!$B$4*$O$53 -> 0 | O53: 15.58
G54: =Summary!J$4 | H54: =IF($G54<>"",INDEX(Data!$G:$G,MATCH($G54,Data!$D:$D,0)),0) -> 0 | I54: =IF($G54<>"",10,0) -> 0 | J54: =IF($G54<>"",INDEX(Data!$M:$M,MATCH($G54,Data!$D:$D,0)),0) -> 0 | K54: =PRODUCT($H54:$J54)*$O$53 -> 0 | L54: =IF($G54<>"",INDEX(Deltas!$E:$E,MATCH($G54,Deltas!$B:$B,0)),0) -> 0 | M54: =PRODUCT($H54:$J54,$L54) -> 0 | N54: =ABS(PRODUCT($H54:$J54,$L54))/Summary!$B$4*$O$53 -> 0 | O54: 15.58
G55: =Summary!K$4 | H55: =IF($G55<>"",INDEX(Data!$G:$G,MATCH($G55,Data!$D:$D,0)),0) -> 0 | I55: =IF($G55<>"",10,0) -> 0 | J55: =IF($G55<>"",INDEX(Data!$M:$M,MATCH($G55,Data!$D:$D,0)),0) -> 0 | K55: =PRODUCT($H55:$J55)*$O$53 -> 0 | L55: =IF($G55<>"",INDEX(Deltas!$E:$E,MATCH($G55,Deltas!$B:$B,0)),0) -> 0 | M55: =PRODUCT($H55:$J55,$L55) -> 0 | N55: =ABS(PRODUCT($H55:$J55,$L55))/Summary!$B$4*$O$53 -> 0 | O55: 15.58
G56: =Summary!L$4 | H56: =IF($G56<>"",INDEX(Data!$G:$G,MATCH($G56,Data!$D:$D,0)),0) -> 0 | I56: =IF($G56<>"",10,0) -> 0 | J56: =IF($G56<>"",INDEX(Data!$M:$M,MATCH($G56,Data!$D:$D,0)),0) -> 0 | K56: =PRODUCT($H56:$J56)*$O$53 -> 0 | L56: =IF($G56<>"",INDEX(Deltas!$E:$E,MATCH($G56,Deltas!$B:$B,0)),0) -> 0 | M56: =PRODUCT($H56:$J56,$L56) -> 0 | N56: =ABS(PRODUCT($H56:$J56,$L56))/Summary!$B$4*$O$53 -> 0 | O56: 15.58
G57: =Summary!M$4 | H57: =IF($G57<>"",INDEX(Data!$G:$G,MATCH($G57,Data!$D:$D,0)),0) -> 0 | I57: =IF($G57<>"",10,0) -> 0 | J57: =IF($G57<>"",INDEX(Data!$M:$M,MATCH($G57,Data!$D:$D,0)),0) -> 0 | K57: =PRODUCT($H57:$J57)*$O$53 -> 0 | L57: =IF($G57<>"",INDEX(Deltas!$E:$E,MATCH($G57,Deltas!$B:$B,0)),0) -> 0 | M57: =PRODUCT($H57:$J57,$L57) -> 0 | N57: =ABS(PRODUCT($H57:$J57,$L57))/Summary!$B$4*$O$53 -> 0 | O57: 15.58
G58: =Summary!N$4 | H58: =IF($G58<>"",INDEX(Data!$G:$G,MATCH($G58,Data!$D:$D,0)),0) -> 0 | I58: =IF($G58<>"",10,0) -> 0 | J58: =IF($G58<>"",INDEX(Data!$M:$M,MATCH($G58,Data!$D:$D,0)),0) -> 0 | K58: =PRODUCT($H58:$J58)*$O$53 -> 0 | L58: =IF($G58<>"",INDEX(Deltas!$E:$E,MATCH($G58,Deltas!$B:$B,0)),0) -> 0 | M58: =PRODUCT($H58:$J58,$L58) -> 0 | N58: =ABS(PRODUCT($H58:$J58,$L58))/Summary!$B$4*$O$53 -> 0 | O58: 15.58
G59: =Summary!O$4 | H59: =IF($G59<>"",INDEX(Data!$G:$G,MATCH($G59,Data!$D:$D,0)),0) -> 0 | I59: =IF($G59<>"",10,0) -> 0 | J59: =IF($G59<>"",INDEX(Data!$M:$M,MATCH($G59,Data!$D:$D,0)),0) -> 0 | K59: =PRODUCT($H59:$J59)*$O$53 -> 0 | L59: =IF($G59<>"",INDEX(Deltas!$E:$E,MATCH($G59,Deltas!$B:$B,0)),0) -> 0 | M59: =PRODUCT($H59:$J59,$L59) -> 0 | N59: =ABS(PRODUCT($H59:$J59,$L59))/Summary!$B$4*$O$53 -> 0 | O59: 15.58
G60: =Summary!P$4 | H60: =IF($G60<>"",INDEX(Data!$G:$G,MATCH($G60,Data!$D:$D,0)),0) -> 0 | I60: =IF($G60<>"",10,0) -> 0 | J60: =IF($G60<>"",INDEX(Data!$M:$M,MATCH($G60,Data!$D:$D,0)),0) -> 0 | K60: =PRODUCT($H60:$J60)*$O$53 -> 0 | L60: =IF($G60<>"",INDEX(Deltas!$E:$E,MATCH($G60,Deltas!$B:$B,0)),0) -> 0 | M60: =PRODUCT($H60:$J60,$L60) -> 0 | N60: =ABS(PRODUCT($H60:$J60,$L60))/Summary!$B$4*$O$53 -> 0 | O60: 15.58
G61: =Summary!Q$4 | H61: =IF($G61<>"",INDEX(Data!$G:$G,MATCH($G61,Data!$D:$D,0)),0) -> 0 | I61: =IF($G61<>"",10,0) -> 0 | J61: =IF($G61<>"",INDEX(Data!$M:$M,MATCH($G61,Data!$D:$D,0)),0) -> 0 | K61: =PRODUCT($H61:$J61)*$O$53 -> 0 | L61: =IF($G61<>"",INDEX(Deltas!$E:$E,MATCH($G61,Deltas!$B:$B,0)),0) -> 0 | M61: =PRODUCT($H61:$J61,$L61) -> 0 | N61: =ABS(PRODUCT($H61:$J61,$L61))/Summary!$B$4*$O$53 -> 0 | O61: 15.58
G62: =Summary!R$4 | H62: =IF($G62<>"",INDEX(Data!$G:$G,MATCH($G62,Data!$D:$D,0)),0) -> 0 | I62: =IF($G62<>"",10,0) -> 0 | J62: =IF($G62<>"",INDEX(Data!$M:$M,MATCH($G62,Data!$D:$D,0)),0) -> 0 | K62: =PRODUCT($H62:$J62)*$O$53 -> 0 | L62: =IF($G62<>"",INDEX(Deltas!$E:$E,MATCH($G62,Deltas!$B:$B,0)),0) -> 0 | M62: =PRODUCT($H62:$J62,$L62) -> 0 | N62: =ABS(PRODUCT($H62:$J62,$L62))/Summary!$B$4*$O$53 -> 0 | O62: 15.58
G63: =Summary!S$4 | H63: =IF($G63<>"",INDEX(Data!$G:$G,MATCH($G63,Data!$D:$D,0)),0) -> 0 | I63: =IF($G63<>"",10,0) -> 0 | J63: =IF($G63<>"",INDEX(Data!$M:$M,MATCH($G63,Data!$D:$D,0)),0) -> 0 | K63: =PRODUCT($H63:$J63)*$O$53 -> 0 | L63: =IF($G63<>"",INDEX(Deltas!$E:$E,MATCH($G63,Deltas!$B:$B,0)),0) -> 0 | M63: =PRODUCT($H63:$J63,$L63) -> 0 | N63: =ABS(PRODUCT($H63:$J63,$L63))/Summary!$B$4*$O$53 -> 0 | O63: 15.58
G64: =Summary!T$4 | H64: =IF($G64<>"",INDEX(Data!$G:$G,MATCH($G64,Data!$D:$D,0)),0) -> 0 | I64: =IF($G64<>"",10,0) -> 0 | J64: =IF($G64<>"",INDEX(Data!$M:$M,MATCH($G64,Data!$D:$D,0)),0) -> 0 | K64: =PRODUCT($H64:$J64)*$O$53 -> 0 | L64: =IF($G64<>"",INDEX(Deltas!$E:$E,MATCH($G64,Deltas!$B:$B,0)),0) -> 0 | M64: =PRODUCT($H64:$J64,$L64) -> 0 | N64: =ABS(PRODUCT($H64:$J64,$L64))/Summary!$B$4*$O$53 -> 0 | O64: 15.58
G65: =Summary!U$4 | H65: =IF($G65<>"",INDEX(Data!$G:$G,MATCH($G65,Data!$D:$D,0)),0) -> 0 | I65: =IF($G65<>"",10,0) -> 0 | J65: =IF($G65<>"",INDEX(Data!$M:$M,MATCH($G65,Data!$D:$D,0)),0) -> 0 | K65: =PRODUCT($H65:$J65)*$O$53 -> 0 | L65: =IF($G65<>"",INDEX(Deltas!$E:$E,MATCH($G65,Deltas!$B:$B,0)),0) -> 0 | M65: =PRODUCT($H65:$J65,$L65) -> 0 | N65: =ABS(PRODUCT($H65:$J65,$L65))/Summary!$B$4*$O$53 -> 0 | O65: 15.58
G66: =Summary!V$4 | H66: =IF($G66<>"",INDEX(Data!$G:$G,MATCH($G66,Data!$D:$D,0)),0) -> 0 | I66: =IF($G66<>"",10,0) -> 0 | J66: =IF($G66<>"",INDEX(Data!$M:$M,MATCH($G66,Data!$D:$D,0)),0) -> 0 | K66: =PRODUCT($H66:$J66)*$O$53 -> 0 | L66: =IF($G66<>"",INDEX(Deltas!$E:$E,MATCH($G66,Deltas!$B:$B,0)),0) -> 0 | M66: =PRODUCT($H66:$J66,$L66) -> 0 | N66: =ABS(PRODUCT($H66:$J66,$L66))/Summary!$B$4*$O$53 -> 0 | O66: 15.58
G67: =Summary!W$4 | H67: =IF($G67<>"",INDEX(Data!$G:$G,MATCH($G67,Data!$D:$D,0)),0) -> 0 | I67: =IF($G67<>"",10,0) -> 0 | J67: =IF($G67<>"",INDEX(Data!$M:$M,MATCH($G67,Data!$D:$D,0)),0) -> 0 | K67: =PRODUCT($H67:$J67)*$O$53 -> 0 | L67: =IF($G67<>"",INDEX(Deltas!$E:$E,MATCH($G67,Deltas!$B:$B,0)),0) -> 0 | M67: =PRODUCT($H67:$J67,$L67) -> 0 | N67: =ABS(PRODUCT($H67:$J67,$L67))/Summary!$B$4*$O$53 -> 0 | O67: 15.58
G68: =Summary!X$4 | H68: =IF($G68<>"",INDEX(Data!$G:$G,MATCH($G68,Data!$D:$D,0)),0) -> 0 | I68: =IF($G68<>"",10,0) -> 0 | J68: =IF($G68<>"",INDEX(Data!$M:$M,MATCH($G68,Data!$D:$D,0)),0) -> 0 | K68: =PRODUCT($H68:$J68)*$O$53 -> 0 | L68: =IF($G68<>"",INDEX(Deltas!$E:$E,MATCH($G68,Deltas!$B:$B,0)),0) -> 0 | M68: =PRODUCT($H68:$J68,$L68) -> 0 | N68: =ABS(PRODUCT($H68:$J68,$L68))/Summary!$B$4*$O$53 -> 0 | O68: 15.58

Sheet Data
A1: Entity Name | B1: Valuation First Level | C1: Valuation Second Level | D1: i Issue Name | E1: PrimaryAssetID | F1: Issue Description | G1: Original Nominal | H1: Clean Book Value | I1: Clean Market Value | J1: Accrued Income | K1: Dividend Receivable | L1: Sum of Market Value Income | M1: Market Price /Yield | N1: % of Total Market Value | O1: Next Coupon Date | P1: Maturity Date | Q1: Coupon | R1: Duration | S1: Modified Duration | T1: Investment Type | U1: Security Type | V1: Sub Security Type | W1: CCY | X1: Sector | Y1: Supersector | Z1: Industry | AA1: Issuer Rating | AB1: Security Rating | AC1: NACA Yield | AD1: NACM Yield | AE1: Weighted Avg NACA Yield | AF1: Weighted Avg NACM Yield | AG1: Market Value % | AH1: Current Exposure | AI1: Current Exposure % | AJ1: i Position Effective Date | AK1: Entity ID | AL1: Weighted Average NACS Yield | AM1: Weighted Average Coupon | AN1: Weighted Modified Duration | AO1: Issuer | AP1: ISIN Code | AQ1: Ticker | AS1: =SUMPRODUCT((B:B = "DERIVATIVES")*(C:C = "UNKNOWN")) -> 0
A2: Tshwane Municipal Prov Fund | B2: CASH | C2: Cash on Call | D2: Investec TRS Initial Margin Account JB3+95 | E2: INVESTECINIMARG | F2: Investec TRS Initial Margin Account JB3+95 | G2: 3314771.1 | H2: 3314771.1 | I2: 3314771.1 | J2: 2898.65 | K2: 0 | L2: 3317669.8 | M2: 4.617 | N2: 1.8906098 | P2: 47848 | Q2: 4.617 | R2: 0.08 | T2: ST | U2: CSH | V2: CD | W2: ZAR | AC2: 4.7160922 | AD2: 4.6171215 | AE2: 4.72 | AF2: 4.6171215 | AG2: 1.89 | AH2: 3317669.8 | AI2: 1.8906098 | AJ2: 44657 | AK2: TSHMPF | AL2: 4.66 | AM2: 4.62 | AN2: 0 | AQ2: INVESTECINIMARG
A3: Tshwane Municipal Prov Fund | B3: CASH | C3: Cash on Call | D3: Investec TRS Variation Margin Account JB3+95 | E3: INVESTECVARMARG | F3: Investec TRS Variation Margin Account JB3+95 | G3: 3150000 | H3: 3150000 | I3: 3150000 | J3: 2754.57 | K3: 0 | L3: 3152754.6 | M3: 4.617 | N3: 1.7966311 | P3: 47848 | Q3: 4.617 | R3: 0.08 | T3: ST | U3: CSH | V3: CD | W3: ZAR | AC3: 4.7160922 | AD3: 4.6171215 | AE3: 4.72 | AF3: 4.6171215 | AG3: 1.8 | AH3: 3152754.6 | AI3: 1.7966311 | AJ3: 44657 | AK3: TSHMPF | AL3: 4.66 | AM3: 4.62 | AN3: 0 | AQ3: INVESTECVARMARG
A4: Tshwane Municipal Prov Fund | B4: CASH | C4: Cash on Call | D4: Prescient Money Market Fund B3 | E4: PRMFB3 | F4: Prescient Money Market Fund B3 | G4: 21909704 | H4: 21909704 | I4: 21909704 | J4: 18345.36 | K4: 0 | L4: 21928049 | N4: 12.495935 | O4: 40756 | P4: 73020 | Q4: 0 | T4: FI | U4: CIS | V4: CSH | W4: ZAR | AE4: 0 | AF4: 0 | AG4: 12.5 | AH4: 21928049 | AI4: 12.495935 | AJ4: 44657 | AK4: TSHMPF | AL4: 0 | AM4: 0 | AN4: 0 | AP4: ZAE000140885 | AQ4: PRMFB3
A5: Tshwane Municipal Prov Fund | B5: CASH | C5: Safex Margin Deposits | D5: SAFEX Margin | E5: SAFEX | F5: Margin Account | G5: 2495066 | H5: 2495066 | I5: 2495066 | J5: 1774.48 | K5: 0 | L5: 2496840.5 | M5: 6.88 | N5: 1.4228514 | P5: 55153 | Q5: 6.88 | R5: 0.08 | S5: 0.002600675 | T5: ST | U5: CSH | V5: MARGIN | W5: ZAR | AE5: 0 | AF5: 0 | AG5: 1.42 | AH5: 2496840.5 | AI5: 1.4228514 | AJ5: 44657 | AK5: TSHMPF | AL5: 0 | AM5: 6.88 | AN5: 0 | AO5: SAFEX | AQ5: SAFEX
A6: Tshwane Municipal Prov Fund | B6: CASH | C6: Traded Cash | D6: Interest on Cash ZAR | E6: INTRZAR | F6: Interest on Cash | G6: 0 | H6: 0 | I6: 0 | J6: 0 | K6: 0 | L6: 2128.93 | N6: 0.0012131937 | R6: 0.08 | T6: CASH | U6: CSH | W6: ZAR | AC6: 5.116339 | AD6: 5.0001425 | AE6: 5.12 | AF6: 5.0001425 | AG6: 0 | AH6: 2128.93 | AI6: 0.0012131937 | AJ6: 44657 | AK6: TSHMPF | AL6: 5.05 | AM6: 0 | AN6: 0
A7: Tshwane Municipal Prov Fund | B7: CASH | C7: Traded Cash | D7: South African Rand | E7: CASHZAR | F7: South African Rand | G7: 439085.69 | H7: 439085.69 | I7: 439085.69 | J7: 0 | K7: 0 | L7: 439085.69 | N7: 0.2502177 | R7: 0.08 | T7: CASH | U7: CRNY | W7: ZAR | AC7: 5.116339 | AD7: 5.0001425 | AE7: 5.12 | AF7: 5.0001425 | AG7: 0.25 | AH7: 439085.69 | AI7: 0.2502177 | AJ7: 44657 | AK7: TSHMPF | AL7: 5.05 | AM7: 0 | AN7: 0 | AQ7: ZAR
A8: Tshwane Municipal Prov Fund | B8: CASH | C8: Unsettled Cash | D8: Variation Margin | E8: VARMARG | G8: -98560 | H8: -98560 | I8: -98560 | J8: 0 | L8: -98560 | N8: -0.056165476 | P8: 73051 | Q8: 0 | R8: 0.08 | T8: CASH | W8: ZAR | AC8: 5.116339 | AD8: 5.0001425 | AE8: 5.12 | AF8: 5.0001425 | AG8: -0.06 | AH8: -98560 | AI8: -0.056165476 | AJ8: 44657 | AK8: TSHMPF | AL8: 5.05 | AM8: 0 | AN8: 0
A9: Tshwane Municipal Prov Fund | B9: COLLECTIVE INVESTMENT SCHEMES | C9: Domestic | D9: Prescient Income Fund B3 | E9: PRIFB3 | F9: Prescient Income Fund B3 | G9: 1.0941512e+08 | H9: 1.1268794e+08 | I9: 1.0833191e+08 | J9: 0 | K9: 0 | L9: 1.0833191e+08 | M9: 0.9901 | N9: 61.734102 | T9: EQ | U9: CIS | V9: CIS | W9: ZAR | AE9: 0 | AF9: 0 | AG9: 61.77 | AH9: 1.0833191e+08 | AI9: 61.734102 | AJ9: 44657 | AK9: TSHMPF | AL9: 0 | AM9: 0 | AN9: 0 | AP9: ZAE000273819 | AQ9: PRIFB3
A10: Tshwane Municipal Prov Fund | B10: DERIVATIVES | C10: Equity Derivatives | D10: 15JUN22 DCAP | E10: 15JUN22 DCAP | F10: 15JUN22 DCAP | G10: 63 | H10: 0 | I10: 0 | J10: 0 | K10: 0 | L10: 0 | M10: 20762 | N10: 0 | P10: 44727 | T10: FT | U10: DER | V10: IDXFT | W10: ZAR | AE10: 0 | AF10: 0 | AG10: 0 | AH10: 13080060 | AI10: 7.4538129 | AJ10: 44657 | AK10: TSHMPF | AL10: 0 | AM10: 0 | AN10: 0 | AP10: ZAD000419547 | AQ10: 15JUN22 DCAP
A11: Tshwane Municipal Prov Fund | B11: DERIVATIVES | C11: Equity Derivatives | D11: 15JUN22 DCAR | E11: 15JUN22 DCAR | F11: 15JUN22 DCAR | G11: 35 | H11: 0 | I11: 0 | J11: 0 | K11: 0 | L11: 0 | M11: 30146 | N11: 0 | P11: 44727 | T11: FT | U11: DER | V11: IDXFT | W11: ZAR | AE11: 0 | AF11: 0 | AG11: 0 | AH11: 10551100 | AI11: 6.0126578 | AJ11: 44657 | AK11: TSHMPF | AL11: 0 | AM11: 0 | AN11: 0 | AP11: ZAD000420156 | AQ11: 15JUN22 DCAR
A12: Tshwane Municipal Prov Fund | B12: EQUITIES | C12: BASIC MATERIALS | D12: AECI Ltd | E12: AFE | F12: AECI Ltd | G12: 2549 | H12: 255533.54 | I12: 281562.54 | J12: 0 | K12: 12872.45 | L12: 294434.99 | M12: 11046 | N12: 0.16778695 | T12: EQ | U12: EQ | V12: EQ | W12: ZAR | X12: CHEMICALS | Y12: CHEMICALS | Z12: BASIC MATERIALS | AE12: 0 | AF12: 0 | AG12: 0.17 | AH12: 294434.99 | AI12: 0.16778695 | AJ12: 44657 | AK12: TSHMPF | AL12: 0 | AM12: 0 | AN12: 0 | AP12: ZAE000000220 | AQ12: AFE
A13: Tshwane Municipal Prov Fund | B13: EQUITIES | C13: BASIC MATERIALS | D13: African Rainbow Minerals Ltd | E13: ARI | F13: African Rainbow Minerals Ltd | G13: 3217 | H13: 561695.59 | I13: 881876.21 | J13: 0 | K13: 0 | L13: 881876.21 | M13: 27413 | N13: 0.50254664 | T13: EQ | U13: EQ | V13: EQ | W13: ZAR | X13: MINING | Y13: BASIC RESOURCES | Z13: BASIC MATERIALS | AE13: 0 | AF13: 0 | AG13: 0.5 | AH13: 881876.21 | AI13: 0.50254664 | AJ13: 44657 | AK13: TSHMPF | AL13: 0 | AM13: 0 | AN13: 0 | AP13: ZAE000054045 | AQ13: ARI
A14: Tshwane Municipal Prov Fund | B14: EQUITIES | C14: BASIC MATERIALS | D14: Anglo American Plc | E14: AGL | F14: Anglo American Plc | G14: 1854 | H14: 1191312.6 | I14: 1432215 | J14: 0 | K14: 18997.88 | L14: 1451212.9 | M14: 77250 | N14: 0.82698927 | T14: EQ | U14: EQ | V14: EQ | W14: ZAR | X14: MINING | Y14: BASIC RESOURCES | Z14: BASIC MATERIALS | AE14: 0 | AF14: 0 | AG14: 0.83 | AH14: 1451212.9 | AI14: 0.82698927 | AJ14: 44657 | AK14: TSHMPF | AL14: 0 | AM14: 0 | AN14: 0 | AP14: GB00B1XZS820 | AQ14: AGL
A15: Tshwane Municipal Prov Fund | B15: EQUITIES | C15: BASIC MATERIALS | D15: DRD Gold Ltd | E15: DRD | F15: DRD Gold Ltd | G15: 12000 | H15: 262633.12 | I15: 153960 | J15: 0 | K15: 0 | L15: 153960 | M15: 1283 | N15: 0.087735762 | T15: EQ | U15: EQ | V15: EQ | W15: ZAR | X15: MINING | Y15: BASIC RESOURCES | Z15: BASIC MATERIALS | AE15: 0 | AF15: 0 | AG15: 0.09 | AH15: 153960 | AI15: 0.087735762 | AJ15: 44657 | AK15: TSHMPF | AL15: 0 | AM15: 0 | AN15: 0 | AP15: ZAE000058723 | AQ15: DRD
A16: Tshwane Municipal Prov Fund | B16: EQUITIES | C16: BASIC MATERIALS | D16: Harmony Gold Mining Company Ltd | E16: HAR | F16: Harmony Gold Mining Company Ltd | G16: 8965 | H16: 506585.13 | I16: 616074.8 | J16: 0 | K16: 3586 | L16: 619660.8 | M16: 6872 | N16: 0.35312037 | T16: EQ | U16: EQ | V16: EQ | W16: ZAR | X16: MINING | Y16: BASIC RESOURCES | Z16: BASIC MATERIALS | AE16: 0 | AF16: 0 | AG16: 0.35 | AH16: 619660.8 | AI16: 0.35312037 | AJ16: 44657 | AK16: TSHMPF | AL16: 0 | AM16: 0 | AN16: 0 | AP16: ZAE000015228 | AQ16: HAR
A17: Tshwane Municipal Prov Fund | B17: EQUITIES | C17: BASIC MATERIALS | D17: Kumba Iron Ore Ltd | E17: KIO | F17: Kumba Iron Ore Ltd | G17: 1988 | H17: 1025864.6 | I17: 1358122.1 | J17: 0 | K17: 0 | L17: 1358122.1 | M17: 68316 | N17: 0.77394048 | T17: EQ | U17: EQ | V17: EQ | W17: ZAR | X17: INDUSTRIAL METALS | Y17: BASIC RESOURCES | Z17: BASIC MATERIALS | AE17: 0 | AF17: 0 | AG17: 0.77 | AH17: 1358122.1 | AI17: 0.77394048 | AJ17: 44657 | AK17: TSHMPF | AL17: 0 | AM17: 0 | AN17: 0 | AP17: ZAE000085346 | AQ17: KIO
A18: Tshwane Municipal Prov Fund | B18: EQUITIES | C18: BASIC MATERIALS | D18: Omnia Holdings Limited | E18: OMN | F18: Omnia Holdings Limited | G18: 5500 | H18: 306314.99 | I18: 418055 | J18: 0 | K18: 0 | L18: 418055 | M18: 7601 | N18: 0.23823314 | T18: EQ | U18: EQ | V18: EQ | W18: ZAR | X18: CHEMICALS | Y18: CHEMICALS | Z18: BASIC MATERIALS | AE18: 0 | AF18: 0 | AG18: 0.24 | AH18: 418055 | AI18: 0.23823314 | AJ18: 44657 | AK18: TSHMPF | AL18: 0 | AM18: 0 | AN18: 0 | AP18: ZAE000005153 | AQ18: OMN
A19: Tshwane Municipal Prov Fund | B19: EQUITIES | C19: BASIC MATERIALS | D19: Pan African Resource | E19: PAN | F19: Pan African Resource | G19: 30000 | H19: 172288.66 | I19: 132000 | J19: 0 | K19: 0 | L19: 132000 | M19: 440 | N19: 0.07522162 | T19: EQ | U19: EQ | V19: EQ | W19: ZAR | X19: MINING | Y19: BASIC RESOURCES | Z19: BASIC MATERIALS | AE19: 0 | AF19: 0 | AG19: 0.08 | AH19: 132000 | AI19: 0.07522162 | AJ19: 44657 | AK19: TSHMPF | AL19: 0 | AM19: 0 | AN19: 0 | AP19: GB0004300496 | AQ19: PAN
A20: Tshwane Municipal Prov Fund | B20: EQUITIES | C20: BASIC MATERIALS | D20: Royal Bafokeng Platinum Ltd | E20: RBP | F20: Royal Bafokeng Platinum Ltd | G20: 2900 | H20: 186567.66 | I20: 463536 | J20: 0 | K20: 0 | L20: 463536 | M20: 15984 | N20: 0.26415098 | T20: EQ | U20: EQ | V20: EQ | W20: ZAR | X20: MINING | Y20: BASIC RESOURCES | Z20: BASIC MATERIALS | AE20: 0 | AF20: 0 | AG20: 0.26 | AH20: 463536 | AI20: 0.26415098 | AJ20: 44657 | AK20: TSHMPF | AL20: 0 | AM20: 0 | AN20: 0 | AP20: ZAE000149936 | AQ20: RBP
A21: Tshwane Municipal Prov Fund | B21: EQUITIES | C21: BASIC MATERIALS | D21: Sappi Ltd | E21: SAP | F21: Sappi Ltd | G21: 13213 | H21: 501193.93 | I21: 746402.37 | J21: 0 | K21: 0 | L21: 746402.37 | M21: 5649 | N21: 0.42534542 | T21: EQ | U21: EQ | V21: EQ | W21: ZAR | X21: FORESTRY & PAPER | Y21: BASIC RESOURCES | Z21: BASIC MATERIALS | AE21: 0 | AF21: 0 | AG21: 0.43 | AH21: 746402.37 | AI21: 0.42534542 | AJ21: 44657 | AK21: TSHMPF | AL21: 0 | AM21: 0 | AN21: 0 | AP21: ZAE000006284 | AQ21: SAP
A22: Tshwane Municipal Prov Fund | B22: EQUITIES | C22: BASIC MATERIALS | D22: Thungela Resources Ltd | E22: TGA | F22: THUNGELA RESOURC | G22: 800 | H22: 127732.2 | I22: 189368 | J22: 0 | K22: 0 | L22: 189368 | M22: 23671 | N22: 0.10791339 | T22: EQ | U22: EQ | V22: EQ | W22: ZAR | X22: MINING | Y22: BASIC RESOURCES | Z22: BASIC MATERIALS | AE22: 0 | AF22: 0 | AG22: 0.11 | AH22: 189368 | AI22: 0.10791339 | AJ22: 44657 | AK22: TSHMPF | AL22: 0 | AM22: 0 | AN22: 0 | AP22: ZAE000296554 | AQ22: TGA
A23: Tshwane Municipal Prov Fund | B23: EQUITIES | C23: CONSUMER GOODS | D23: Astral Foods Ltd | E23: ARL | F23: Astral Foods Ltd | G23: 1500 | H23: 322451.1 | I23: 229065 | J23: 0 | K23: 0 | L23: 229065 | M23: 15271 | N23: 0.13053515 | T23: EQ | U23: EQ | V23: EQ | W23: ZAR | X23: FOOD PRODUCERS | Y23: FOOD & BEVERAGE | Z23: CONSUMER GOODS | AE23: 0 | AF23: 0 | AG23: 0.13 | AH23: 229065 | AI23: 0.13053515 | AJ23: 44657 | AK23: TSHMPF | AL23: 0 | AM23: 0 | AN23: 0 | AP23: ZAE000029757 | AQ23: ARL
... A71: Tshwane Municipal Prov Fund | B71: EQUITIES | C71: UTILITIES | D71: Montauk Renewables Inc | E71: MKR | F71: MONTAUK RENEWABL | G71: 1000 | H71: 160558.22 | I71: 158520 | J71: 0 | K71: 0 | L71: 158520 | M71: 15852 | N71: 0.090334327 | T71: EQ | U71: EQ | V71: EQ | W71: ZAR | X71: GAS WATR & MULTIUTIL | Y71: UTILITIES | Z71: UTILITIES | AE71: 0 | AF71: 0 | AG71: 0.09 | AH71: 158520 | AI71: 0.090334327 | AJ71: 44657 | AK71: TSHMPF | AL71: 0 | AM71: 0 | AN71: 0 | AP71: US61218C1036 | AQ71: MKR
A72: Tshwane Municipal Prov Fund | B72: SWAPS | C72: SWAPS | D72: ABSA TRS 040822 A | E72: ABSATRS040822A | F72: ABSA TRS 040822 A CONTRACT SWCOTR | G72: 2198.5525 | H72: 0 | I72: 0 | J72: 0 | K72: 0 | L72: 0 | N72: 0 | P72: 44777 | Q72: 0 | T72: DERV | U72: SWP | V72: TRS | W72: ZAR | AA72: AA+ | AE72: 0 | AF72: 0 | AG72: 0 | AH72: 0 | AI72: 0 | AJ72: 44657 | AK72: TSHMPF | AL72: 0 | AM72: 0 | AN72: 0 | AO72: ABSA BANK LTD
A73: Tshwane Municipal Prov Fund | B73: SWAPS | C73: SWAPS | D73: ABSA TRS 040822 A_P | E73: ABSATRS040822A | F73: ABSA TRS 040822 A_P PAY LEG X 0.000000 ACT/365 MONTHLY 20220804 | G73: -66458372 | H73: 0 | I73: 0 | J73: -19573.36 | K73: 0 | L73: -19573.36 | N73: -0.01115409 | P73: 44777 | Q73: 0 | T73: DERV | U73: SWP | V73: TRS | W73: ZAR | AA73: AA+ | AE73: 0 | AF73: 0 | AG73: -0.01 | AH73: -66477945 | AI73: -37.883172 | AJ73: 44657 | AK73: TSHMPF | AL73: 0 | AM73: 0 | AN73: 0 | AO73: ABSA BANK LTD
A74: Tshwane Municipal Prov Fund | B74: SWAPS | C74: SWAPS | D74: ABSA TRS 040822 A_R | E74: ABSATRS040822A | F74: ABSA TRS 040822 A_R RECEIVE LEG F MONTHLY | G74: 2198.5525 | H74: 0 | I74: -729215.89 | J74: 0 | K74: 0 | L74: -729215.89 | M74: 29896.56 | N74: -0.41555152 | P74: 44777 | Q74: 0 | T74: DERV | U74: SWP | V74: TRS | W74: ZAR | AA74: AA+ | AE74: 0 | AF74: 0 | AG74: -0.42 | AH74: 65729156 | AI74: 37.456466 | AJ74: 44657 | AK74: TSHMPF | AL74: 0 | AM74: 0 | AN74: 0 | AO74: ABSA BANK LTD
A75: Tshwane Municipal Prov Fund | B75: SWAPS | C75: SWAPS | D75: INVESTEC TRS 030822 B | E75: INVTRS030822B | F75: INVESTEC TRS 030822 B CONTRACT SWCOTR | G75: 1581.5528 | H75: 0 | I75: 0 | J75: 0 | K75: 0 | L75: 0 | N75: 0 | P75: 44809 | Q75: 0 | T75: DERV | U75: SWP | V75: TRS | W75: ZAR | AA75: AA | AE75: 0 | AF75: 0 | AG75: 0 | AH75: 0 | AI75: 0 | AJ75: 44657 | AK75: TSHMPF | AL75: 0 | AM75: 0 | AN75: 0 | AO75: INVESTEC BANK LTD
A76: Tshwane Municipal Prov Fund | B76: SWAPS | C76: SWAPS | D76: INVESTEC TRS 030822 B_P | E76: INVTRS030822B | F76: INVESTEC TRS 030822 B_P PAY LEG X 0.000000 ACT/365 MONTHLY 20220905 | G76: -47807558 | H76: 0 | I76: 0 | J76: -13949.33 | K76: 0 | L76: -13949.33 | N76: -0.0079491757 | P76: 44809 | Q76: 0 | T76: DERV | U76: SWP | V76: TRS | W76: ZAR | AA76: AA | AE76: 0 | AF76: 0 | AG76: -0.01 | AH76: -47821507 | AI76: -27.2516 | AJ76: 44657 | AK76: TSHMPF | AL76: 0 | AM76: 0 | AN76: 0 | AO76: INVESTEC BANK LTD
A77: Tshwane Municipal Prov Fund | B77: SWAPS | C77: SWAPS | D77: INVESTEC TRS 030822 B_R | E77: INVTRS030822B | F77: INVESTEC TRS 030822 B_R RECEIVE LEG F MONTHLY | G77: 1581.5528 | H77: 0 | I77: -524569.43 | J77: 0 | K77: 0 | L77: -524569.43 | M77: 29896.56 | N77: -0.29893153 | P77: 44809 | Q77: 0 | T77: DERV | U77: SWP | V77: TRS | W77: ZAR | AA77: AA | AE77: 0 | AF77: 0 | AG77: -0.3 | AH77: 47282988 | AI77: 26.944719 | AJ77: 44657 | AK77: TSHMPF | AL77: 0 | AM77: 0 | AN77: 0 | AO77: INVESTEC BANK LTD
A78: Tshwane Municipal Prov Fund | B78: UNKNOWN | C78: UNKNOWN | D78: Synthetic Cash_15JUN22 DCAP | E78: 15JUN22 DCAP | F78: Synthetic Cash_15JUN22 DCAP | G78: 63 | I78: 0 | L78: 0 | N78: 0 | T78: SYTH | U78: SYNCASHFUT | V78: CASH | W78: ZAR | AE78: 0 | AF78: 0 | AG78: 0 | AH78: -13080060 | AI78: -7.4538129 | AJ78: 44657 | AK78: TSHMPF | AL78: 0 | AM78: 0 | AN78: 0 | AQ78: SYNZAR
A79: Tshwane Municipal Prov Fund | B79: UNKNOWN | C79: UNKNOWN | D79: Synthetic Cash_15JUN22 DCAR | E79: 15JUN22 DCAR | F79: Synthetic Cash_15JUN22 DCAR | G79: 35 | I79: 0 | L79: 0 | N79: 0 | T79: SYTH | U79: SYNCASHFUT | V79: CASH | W79: ZAR | AE79: 0 | AF79: 0 | AG79: 0 | AH79: -10551100 | AI79: -6.0126578 | AJ79: 44657 | AK79: TSHMPF | AL79: 0 | AM79: 0 | AN79: 0 | AQ79: SYNZAR

Sheet Deltas
A1: Entity Name | B1: i Issue Name | C1: Primary Asset ID | D1: Nominal Holding | E1: Delta | F1: Market Value | G1: Effective Exposure
A2: Tshwane Municipal Prov Fund | B2: 15JUN22 DCAP | C2: 15JUN22 DCAP | D2: 63 | E2: 1 | F2: 0 | G2: 13080060
A3: Tshwane Municipal Prov Fund | B3: 15JUN22 DCAR | C3: 15JUN22 DCAR | D3: 35 | E3: 1 | F3: 0 | G3: 10551100
A4: Tshwane Municipal Prov Fund | B4: 17MAR22 DCAP | C4: 17MAR22 DCAP | D4: 0 | E4: 1 | F4: 0 | G4: 0
A5: Tshwane Municipal Prov Fund | B5: 17MAR22 DCAR | C5: 17MAR22 DCAR | D5: 0 | E5: 1 | F5: 0 | G5: 0

Sheet BM
A1: BenchMark | B1: Type | C1: Constituent | D1: Weighting | I1: Fondsposition per | J1: 10.Jan.2020 | U1: =HYPERLINK("https://www.ishares.com/de/privatanleger/de/produkte/251882/ishares-msci-world-ucits-etf-acc-fund/1478358465952.ajax?fileType=csv&fileName=EUNL_holdings&dataType=fund","MSCI ACWI source data") -> MSCI ACWI source data
A2: ALBI | B2: Instrument | C2: 186 | D2: 16.4894 | E2: =SUMIF(Data!$E:$E,$C2,Data!$AI:$AI) -> 0
A3: ALBI | B3: Instrument | C3: 207 | D3: 3.4932 | E3: =SUMIF(Data!$E:$E,$C3,Data!$AI:$AI) -> 0 | I3: Emittententicker | J3: Name | K3: Anlageklasse | L3: Gewichtung (%) | M3: Kurs | N3: Nominale | O3: Marktwert | P3: Nominalwert | Q3: Sektor | R3: ISIN | S3: Börse | T3: Standort | U3: Marktwährung
A4: ALBI | B4: Instrument | C4: 209 | D4: 5.278 | E4: =SUMIF(Data!$E:$E,$C4,Data!$AI:$AI) -> 0 | I4: AAPL | J4: APPLE INC | K4: Aktien | L4: 3,09 | M4: 310,33 | N4: 2.424.947 | O4: 752.533.803 | P4: 752.533.802,51 | Q4: IT | R4: US0378331005 | S4: NASDAQ | T4: Vereinigte Staaten | U4: USD | V4: =SUMIF(Data!$E:$E,$I4,Data!$AI:$AI) -> 0
A5: ALBI | B5: Instrument | C5: 208 | D5: 3.7744 | E5: =SUMIF(Data!$E:$E,$C5,Data!$AI:$AI) -> 0 | I5: MSFT | J5: MICROSOFT CORP | K5: Aktien | L5: 2,59 | M5: 161,34 | N5: 3.902.293 | O5: 629.595.953 | P5: 629.595.952,62 | Q5: IT | R5: US5949181045 | S5: NASDAQ | T5: Vereinigte Staaten | U5: USD | V5: =SUMIF(Data!$E:$E,$I5,Data!$AI:$AI) -> 0
A6: ALBI | B6: Instrument | C6: DV22 | D6: 0.6599 | E6: =SUMIF(Data!$E:$E,$C6,Data!$AI:$AI) -> 0 | I6: AMZN | J6: AMAZON COM INC | K6: Aktien | L6: 1,74 | M6: 1.883,16 | N6: 225.342 | O6: 424.355.041 | P6: 424.355.040,72 | Q6: Zyklische Konsumgüter | R6: US0231351067 | S6: NASDAQ | T6: Vereinigte Staaten | U6: USD | V6: =SUMIF(Data!$E:$E,$I6,Data!$AI:$AI) -> 0
A7: ALBI | B7: Instrument | C7: DV23 | D7: 0.6891 | E7: =SUMIF(Data!$E:$E,$C7,Data!$AI:$AI) -> 0 | I7: FB | J7: FACEBOOK CLASS A INC | K7: Aktien | L7: 1,15 | M7: 218,06 | N7: 1.288.590 | O7: 280.989.935 | P7: 280.989.935,40 | Q7: Kommunikation | R7: US30303M1027 | S7: NASDAQ | T7: Vereinigte Staaten | U7: USD | V7: =SUMIF(Data!$E:$E,$I7,Data!$AI:$AI) -> 0
A8: ALBI | B8: Instrument | C8: ES33 | D8: 1.5447 | E8: =SUMIF(Data!$E:$E,$C8,Data!$AI:$AI) -> 0 | I8: GOOG | J8: ALPHABET INC CLASS C | K8: Aktien | L8: 0,99 | M8: 1.429,73 | N8: 168.382 | O8: 240.740.797 | P8: 240.740.796,86 | Q8: Kommunikation | R8: US02079K1079 | S8: NASDAQ | T8: Vereinigte Staaten | U8: USD | V8: =SUMIF(Data!$E:$E,$I8,Data!$AI:$AI) -> 0
A9: ALBI | B9: Instrument | C9: ES26 | D9: 1.6881 | E9: =SUMIF(Data!$E:$E,$C9,Data!$AI:$AI) -> 0 | I9: JPM | J9: JPMORGAN CHASE & CO | K9: Aktien | L9: 0,96 | M9: 136,07 | N9: 1.722.589 | O9: 234.392.685 | P9: 234.392.685,23 | Q9: Financials | R9: US46625H1005 | S9: New York Stock Exchange Inc. | T9: Vereinigte Staaten | U9: USD | V9: =SUMIF(Data!$E:$E,$I9,Data!$AI:$AI) -> 0
A10: ALBI | B10: Instrument | C10: ES23 | D10: 1.2486 | E10: =SUMIF(Data!$E:$E,$C10,Data!$AI:$AI) -> 0 | I10: GOOGL | J10: ALPHABET INC CLASS A | K10: Aktien | L10: 0,94 | M10: 1.428,96 | N10: 160.289 | O10: 229.046.569 | P10: 229.046.569,44 | Q10: Kommunikation | R10: US02079K3059 | S10: NASDAQ | T10: Vereinigte Staaten | U10: USD | V10: =SUMIF(Data!$E:$E,$I10,Data!$AI:$AI) -> 0
A11: ALBI | B11: Instrument | C11: 213 | D11: 6.4352 | E11: =SUMIF(Data!$E:$E,$C11,Data!$AI:$AI) -> 0 | I11: JNJ | J11: JOHNSON & JOHNSON | K11: Aktien | L11: 0,85 | M11: 145,06 | N11: 1.424.692 | O11: 206.665.822 | P11: 206.665.821,52 | Q11: Gesundheitsversorgung | R11: US4781601046 | S11: New York Stock Exchange Inc. | T11: Vereinigte Staaten | U11: USD | V11: =SUMIF(Data!$E:$E,$I11,Data!$AI:$AI) -> 0
A12: ALBI | B12: Instrument | C12: 214 | D12: 4.6957 | E12: =SUMIF(Data!$E:$E,$C12,Data!$AI:$AI) -> 0 | I12: V | J12: VISA INC CLASS A | K12: Aktien | L12: 0,74 | M12: 193,77 | N12: 935.117 | O12: 181.197.621 | P12: 181.197.621,09 | Q12: IT | R12: US92826C8394 | S12: New York Stock Exchange Inc. | T12: Vereinigte Staaten | U12: USD | V12: =SUMIF(Data!$E:$E,$I12,Data!$AI:$AI) -> 0
