Workbook
Name Hols: Static!$A$1:$A$29

Sheet S
A1: Entity ID | B1: UT? | C1: # | D1: Cash Cover | E1: Cash Cover 2 | F1: Incl CLNs & longer dated debt | G1: Incl underlying UTs | H1: SA Bond Cover | I1: MSCI Cover | J1: ALSI Cover | K1: Total Equity | L1: Total Foreign | M1: Global Exposure | N1: Net Effective Exposure | O1: ="Derivative Calculations "&TEXT(Data!$AJ$2,"ddd d mmm yyyy") -> Derivative Calculations Sat 0 Jan 1900 | P1: Mandate
A2: PPSBAL_C | B2: =[1]Summary!$G$3 -> UT | C2: =[1]Summary!$E$1 -> 10 | D2: =[1]Summary!$C$34 -> 0.23653506 | E2: =[1]Summary!$E$34/100 -> 0.23653506 | F2: =[1]Summary!$C$36 -> 0.18917393 | G2: =[1]Summary!$C$32 -> 0 | H2: =[1]Summary!$E$6/100 -> 0.021755043 | I2: =[1]Summary!$E$10/100 -> 0.019637699 | J2: =[1]Summary!$E$14/100 -> 0.19157251 | K2: =[1]Summary!$C$40 -> 0.59271599 | L2: =[1]Summary!$C$54 -> 20.109194 | M2: ='[1]Glbl Expsr'!$D$2 -> 0.095371567 | N2: ='[1]Glbl Expsr'!$D$3 -> 0.095371567 | O2: \\pim-cpt-statpro\SPC_602\Client\Profiles\PIM\Exports\PPSBAL_C Derv Calc 6Apr2022.xlsx | P2: PPSBAL_C Mandate
A3: PCAEF | B3: =[2]Summary!$G$3 -> UT | C3: =[2]Summary!$E$1 -> 10 | D3: =[2]Summary!$C$34 -> 0.50252909 | E3: =[2]Summary!$E$34/100 -> 0.50252909 | F3: =[2]Summary!$C$36 -> 0 | G3: =[2]Summary!$C$32 -> 0 | H3: =[2]Summary!$E$6/100 -> 0 | I3: =[2]Summary!$E$10/100 -> 0.017757483 | J3: =[2]Summary!$E$14/100 -> 0.12463345 | K3: =[2]Summary!$C$40 -> 0.99223767 | L3: =[2]Summary!$C$54 -> 0 | M3: ='[2]Glbl Expsr'!$D$2 -> 0.066275317 | N3: ='[2]Glbl Expsr'!$D$3 -> 0.066275317 | O3: \\pim-cpt-statpro\SPC_602\Client\Profiles\PIM\Exports\PCAEF Derv Calc 6Apr2022.xlsx | P3: PCAEF Mandate
A4: ADRRC | B4: =[3]Summary!$G$3 -> UT | C4: =[3]Summary!$E$1 -> 9 | D4: =[3]Summary!$C$34 -> 0.01560478 | E4: =[3]Summary!$E$34/100 -> 0.01560478 | F4: =[3]Summary!$C$36 -> 0.19828813 | G4: =[3]Summary!$C$32 -> 0 | H4: =[3]Summary!$E$6/100 -> 0 | I4: =[3]Summary!$E$10/100 -> 0 | J4: =[3]Summary!$E$14/100 -> 0 | K4: =[3]Summary!$C$40 -> 0.40730673 | L4: =[3]Summary!$C$54 -> 0 | M4: ='[3]Glbl Expsr'!$D$2 -> 0.94737804 | N4: ='[3]Glbl Expsr'!$D$3 -> 0.21091173 | O4: \\pim-cpt-statpro\SPC_602\Client\Profiles\PIM\Exports\ADRRC Derv Calc 6Apr2022.xlsx | P4: ADRRC Mandate
A5: PPOS | B5: =[4]Summary!$G$3 -> UT | C5: =[4]Summary!$E$1 -> 9 | D5: =[4]Summary!$C$34 -> 0.029279105 | E5: =[4]Summary!$E$34/100 -> 0.029279105 | F5: =[4]Summary!$C$36 -> 0.20279073 | G5: =[4]Summary!$C$32 -> 0 | H5: =[4]Summary!$E$6/100 -> 0 | I5: =[4]Summary!$E$10/100 -> 0 | J5: =[4]Summary!$E$14/100 -> 0 | K5: =[4]Summary!$C$40 -> 0.42110671 | L5: =[4]Summary!$C$54 -> 0 | M5: ='[4]Glbl Expsr'!$D$2 -> 1.0335819 | N5: ='[4]Glbl Expsr'!$D$3 -> 0.21834449 | O5: \\pim-cpt-statpro\SPC_602\Client\Profiles\PIM\Exports\PPOS Derv Calc 6Apr2022.xlsx | P5: PPOS Mandate
A6: ABMMABR | B6: =[5]Summary!$G$3 -> UT | C6: =[5]Summary!$E$1 -> 9 | D6: =[5]Summary!$C$34 -> 0.032542983 | E6: =[5]Summary!$E$34/100 -> 0.032542983 | F6: =[5]Summary!$C$36 -> 0.16070469 | G6: =[5]Summary!$C$32 -> 0 | H6: =[5]Summary!$E$6/100 -> 0 | I6: =[5]Summary!$E$10/100 -> 0 | J6: =[5]Summary!$E$14/100 -> 0 | K6: =[5]Summary!$C$40 -> 0.35493861 | L6: =[5]Summary!$C$54 -> 19.462523 | M6: ='[5]Glbl Expsr'!$D$2 -> 0.84041325 | N6: ='[5]Glbl Expsr'!$D$3 -> 0.18768625 | O6: \\pim-cpt-statpro\SPC_602\Client\Profiles\PIM\Exports\ABMMABR Derv Calc 6Apr2022.xlsx | P6: ABMMABR Mandate
A7: GTCWP2 | B7: =[6]Summary!$G$3 -> UT | C7: =[6]Summary!$E$1 -> 9 | D7: =[6]Summary!$C$34 -> 0.058168227 | E7: =[6]Summary!$E$34/100 -> 0.058168227 | F7: =[6]Summary!$C$36 -> 0 | G7: =[6]Summary!$C$32 -> 0 | H7: =[6]Summary!$E$6/100 -> 0 | I7: =[6]Summary!$E$10/100 -> 0 | J7: =[6]Summary!$E$14/100 -> 0 | K7: =[6]Summary!$C$40 -> 0.6895952 | L7: =[6]Summary!$C$54 -> 0 | M7: ='[6]Glbl Expsr'!$D$2 -> 1.7138448 | N7: ='[6]Glbl Expsr'!$D$3 -> 0.50317318 | O7: \\pim-cpt-statpro\SPC_602\Client\Profiles\PIM\Exports\GTCWP2 Derv Calc 6Apr2022.xlsx | P7: GTCWP2 Mandate
A8: IJGBAL | B8: =[7]Summary!$G$3 -> UT | C8: =[7]Summary!$E$1 -> 7 | D8: =[7]Summary!$C$34 -> 0.3194741 | E8: =[7]Summary!$E$34/100 -> 0.3194741 | F8: =[7]Summary!$C$36 | G8: =[7]Summary!$C$32 -> 0.19963364 | H8: =[7]Summary!$E$6/100 -> 0 | I8: =[7]Summary!$E$10/100 -> 0 | J8: =[7]Summary!$E$14/100 -> 0 | K8: =[7]Summary!$C$40 -> 2.9931069 | L8: =[7]Summary!$C$54 -> 17.269108 | M8: ='[7]Glbl Expsr'!$D$2 -> 2.81539 | N8: ='[7]Glbl Expsr'!$D$3 -> 2.81539 | O8: \\pim-cpt-statpro\SPC_602\Client\Profiles\PIM\Exports\IJGBAL Derv Calc 6Apr2022.xlsx | P8: IJGBAL Mandate
A9: PCCEF | B9: =[8]Summary!$G$3 -> UT | C9: =[8]Summary!$E$1 -> 7 | D9: =[8]Summary!$C$34 -> 0.25044271 | E9: =[8]Summary!$E$34/100 -> 0.25044271 | F9: =[8]Summary!$C$36 -> 0 | G9: =[8]Summary!$C$32 -> 0 | H9: =[8]Summary!$E$6/100 -> 0 | I9: =[8]Summary!$E$10/100 -> 0.033255527 | J9: =[8]Summary!$E$14/100 -> 0.17587447 | K9: =[8]Summary!$C$40 -> 0.99069313 | L9: =[8]Summary!$C$54 -> 0 | M9: ='[8]Glbl Expsr'!$D$2 -> 0.23999995 | N9: ='[8]Glbl Expsr'!$D$3 -> 0.23999995 | O9: \\pim-cpt-statpro\SPC_602\Client\Profiles\PIM\Exports\PCCEF Derv Calc 6Apr2022.xlsx | P9: PCCEF Mandate
A10: PCEQTF | B10: =[9]Summary!$G$3 -> UT | C10: =[9]Summary!$E$1 -> 7 | D10: =[9]Summary!$C$34 -> 0.34681845 | E10: =[9]Summary!$E$34/100 -> 0.34681845 | F10: =[9]Summary!$C$36 -> 0 | G10: =[9]Summary!$C$32 -> 0 | H10: =[9]Summary!$E$6/100 -> 0 | I10: =[9]Summary!$E$10/100 -> 0.019768545 | J10: =[9]Summary!$E$14/100 -> 0.14712865 | K10: =[9]Summary!$C$40 -> 0.93018558 | L10: =[9]Summary!$C$54 -> 0 | M10: ='[9]Glbl Expsr'!$D$2 -> 0.088422855 | N10: ='[9]Glbl Expsr'!$D$3 -> 0.088422855 | O10: \\pim-cpt-statpro\SPC_602\Client\Profiles\PIM\Exports\PCEQTF Derv Calc 6Apr2022.xlsx | P10: PCEQTF Mandate
A11: PIMBAL | B11: =[10]Summary!$G$3 -> UT | C11: =[10]Summary!$E$1 -> 6 | D11: =[10]Summary!$C$34 -> 0.0071720338 | E11: =[10]Summary!$E$34/100 -> 0.037108757 | F11: =[10]Summary!$C$36 -> 0.12636503 | G11: =[10]Summary!$C$32 -> 0 | H11: =[10]Summary!$E$6/100 -> 0 | I11: =[10]Summary!$E$10/100 -> 0 | J11: =[10]Summary!$E$14/100 -> 0 | K11: =[10]Summary!$C$40 -> 0.64844859 | L11: =[10]Summary!$C$54 -> 43.825415 | M11: ='[10]Glbl Expsr'!$D$2 -> 0.028740154 | N11: ='[10]Glbl Expsr'!$D$3 -> 0.028740154 | O11: \\pim-cpt-statpro\SPC_602\Client\Profiles\PIM\Exports\PIMBAL Derv Calc 6Apr2022.xlsx | P11: PIMBAL Mandate
A12: PEAQ | B12: =[11]Summary!$G$3 -> UT | C12: =[11]Summary!$E$1 -> 5 | D12: =[11]Summary!$C$34 -> 0.47815719 | E12: =[11]Summary!$E$34/100 -> 0.47815719 | F12: =[11]Summary!$C$36 -> 0 | G12: =[11]Summary!$C$32 -> 0 | H12: =[11]Summary!$E$6/100 -> 0 | I12: =[11]Summary!$E$10/100 -> 0.042280309 | J12: =[11]Summary!$E$14/100 -> 0.21361833 | K12: =[11]Summary!$C$40 -> 0.98260704 | L12: =[11]Summary!$C$54 -> 0 | M12: ='[11]Glbl Expsr'!$D$2 -> 0.29444411 | N12: ='[11]Glbl Expsr'!$D$3 -> 0.29444411 | O12: \\pim-cpt-statpro\SPC_602\Client\Profiles\PIM\Exports\PEAQ Derv Calc 6Apr2022.xlsx | P12: PEAQ Mandate
A13: PBAL | B13: =[12]Summary!$G$3 -> UT | C13: =[12]Summary!$E$1 -> 4 | D13: =[12]Summary!$C$34 -> 0.0077845601 | E13: =[12]Summary!$E$34/100 -> 0.052814815 | F13: =[12]Summary!$C$36 -> 0.1589352 | G13: =[12]Summary!$C$32 -> 0 | H13: =[12]Summary!$E$6/100 -> 0 | I13: =[12]Summary!$E$10/100 -> 0 | J13: =[12]Summary!$E$14/100 -> 0 | K13: =[12]Summary!$C$40 -> 0.66108884 | L13: =[12]Summary!$C$54 -> 44.692991 | M13: ='[12]Glbl Expsr'!$D$2 -> 0.02812015 | N13: ='[12]Glbl Expsr'!$D$3 -> 0.02812015 | O13: \\pim-cpt-statpro\SPC_602\Client\Profiles\PIM\Exports\PBAL Derv Calc 6Apr2022.xlsx | P13: PBAL Mandate
A14: PPEF | B14: =[13]Summary!$G$3 -> UT | C14: =[13]Summary!$E$1 -> 4 | D14: =[13]Summary!$C$34 -> 0.12496283 | E14: =[13]Summary!$E$34/100 -> 0.12496283 | F14: =[13]Summary!$C$36 -> 0 | G14: =[13]Summary!$C$32 -> 0 | H14: =[13]Summary!$E$6/100 -> 0 | I14: =[13]Summary!$E$10/100 -> 0.017163907 | J14: =[13]Summary!$E$14/100 -> 0.38376815 | K14: =[13]Summary!$C$40 -> 0.99371009 | L14: =[13]Summary!$C$54 -> 0 | M14: ='[13]Glbl Expsr'!$D$2 -> 0.30927369 | N14: ='[13]Glbl Expsr'!$D$3 -> 0.30927369 | O14: \\pim-cpt-statpro\SPC_602\Client\Profiles\PIM\Exports\PPEF Derv Calc 6Apr2022.xlsx | P14: PPEF Mandate
A15: ABMMEQU | B15: =[14]Summary!$G$3 -> UT | C15: =[14]Summary!$E$1 -> 4 | D15: =[14]Summary!$C$34 -> 0.36844942 | E15: =[14]Summary!$E$34/100 -> 0.36844942 | F15: =[14]Summary!$C$36 -> 0 | G15: =[14]Summary!$C$32 -> 0 | H15: =[14]Summary!$E$6/100 -> 0 | I15: =[14]Summary!$E$10/100 -> 0.014180764 | J15: =[14]Summary!$E$14/100 -> 0.11705303 | K15: =[14]Summary!$C$40 -> 0.99281602 | L15: =[14]Summary!$C$54 -> 0 | M15: ='[14]Glbl Expsr'!$D$2 -> 0.12444838 | N15: ='[14]Glbl Expsr'!$D$3 -> 0.12444838 | O15: \\pim-cpt-statpro\SPC_602\Client\Profiles\PIM\Exports\ABMMEQU Derv Calc 6Apr2022.xlsx | P15: ABMMEQU Mandate
A16: PEQ | B16: =[15]Summary!$G$3 -> UT | C16: =[15]Summary!$E$1 -> 4 | D16: =[15]Summary!$C$34 -> 0.46363122 | E16: =[15]Summary!$E$34/100 -> 0.46363122 | F16: =[15]Summary!$C$36 -> 0 | G16: =[15]Summary!$C$32 -> 0 | H16: =[15]Summary!$E$6/100 -> 0 | I16: =[15]Summary!$E$10/100 -> 0 | J16: =[15]Summary!$E$14/100 -> 0 | K16: =[15]Summary!$C$40 -> 0.99423061 | L16: =[15]Summary!$C$54 -> 0 | M16: ='[15]Glbl Expsr'!$D$2 -> 0.15333856 | N16: ='[15]Glbl Expsr'!$D$3 -> 0.15333856 | O16: \\pim-cpt-statpro\SPC_602\Client\Profiles\PIM\Exports\PEQ Derv Calc 6Apr2022.xlsx | P16: PEQ Mandate
A17: SAAMMAN | B17: =[16]Summary!$G$3 -> UT | C17: =[16]Summary!$E$1 -> 3 | D17: =[16]Summary!$C$34 -> 0.0064514805 | E17: =[16]Summary!$E$34/100 -> 0.0064514805 | F17: =[16]Summary!$C$36 -> 0 | G17: =[16]Summary!$C$32 -> 0 | H17: =[16]Summary!$E$6/100 -> 0 | I17: =[16]Summary!$E$10/100 -> 0 | J17: =[16]Summary!$E$14/100 -> 0 | K17: =[16]Summary!$C$40 -> 4.5373426 | L17: =[16]Summary!$C$54 -> 0 | M17: ='[16]Glbl Expsr'!$D$2 -> 4.5373426 | N17: ='[16]Glbl Expsr'!$D$3 -> 4.5373426 | O17: \\pim-cpt-statpro\SPC_602\Client\Profiles\PIM\Exports\SAAMMAN Derv Calc 6Apr2022.xlsx | P17: SAAMMAN Mandate
A18: SAAMCAU | B18: =[17]Summary!$G$3 -> UT | C18: =[17]Summary!$E$1 -> 3 | D18: =[17]Summary!$C$34 -> 0.0087109861 | E18: =[17]Summary!$E$34/100 -> 0.0087109861 | F18: =[17]Summary!$C$36 -> 0 | G18: =[17]Summary!$C$32 -> 0 | H18: =[17]Summary!$E$6/100 -> 0 | I18: =[17]Summary!$E$10/100 -> 0 | J18: =[17]Summary!$E$14/100 -> 0 | K18: =[17]Summary!$C$40 -> 4.8874986 | L18: =[17]Summary!$C$54 -> 0 | M18: ='[17]Glbl Expsr'!$D$2 -> 4.8874986 | N18: ='[17]Glbl Expsr'!$D$3 -> 4.8874986 | O18: \\pim-cpt-statpro\SPC_602\Client\Profiles\PIM\Exports\SAAMCAU Derv Calc 6Apr2022.xlsx | P18: SAAMCAU Mandate
A19: PABS | B19: =[18]Summary!$G$3 -> UT | C19: =[18]Summary!$E$1 -> 3 | D19: =[18]Summary!$C$34 -> 0.010002733 | E19: =[18]Summary!$E$34/100 -> 0.10720719 | F19: =[18]Summary!$C$36 -> 0.29925094 | G19: =[18]Summary!$C$32 -> 0 | H19: =[18]Summary!$E$6/100 -> 0 | I19: =[18]Summary!$E$10/100 -> 0 | J19: =[18]Summary!$E$14/100 -> 0 | K19: =[18]Summary!$C$40 -> 0.31714404 | L19: =[18]Summary!$C$54 -> 43.613811 | M19: ='[18]Glbl Expsr'!$D$2 -> 0.0092307135 | N19: ='[18]Glbl Expsr'!$D$3 -> 0.0092307135 | O19: \\pim-cpt-statpro\SPC_602\Client\Profiles\PIM\Exports\PABS Derv Calc 6Apr2022.xlsx | P19: PABS Mandate
A20: SAAMMOD | B20: =[19]Summary!$G$3 -> UT | C20: =[19]Summary!$E$1 -> 3 | D20: =[19]Summary!$C$34 -> 0.011947854 | E20: =[19]Summary!$E$34/100 -> 0.011947854 | F20: =[19]Summary!$C$36 -> 0 | G20: =[19]Summary!$C$32 -> 0 | H20: =[19]Summary!$E$6/100 -> 0 | I20: =[19]Summary!$E$10/100 -> 0 | J20: =[19]Summary!$E$14/100 -> 0 | K20: =[19]Summary!$C$40 -> 4.5371611 | L20: =[19]Summary!$C$54 -> 0 | M20: ='[19]Glbl Expsr'!$D$2 -> 4.5371611 | N20: ='[19]Glbl Expsr'!$D$3 -> 4.5371611 | O20: \\pim-cpt-statpro\SPC_602\Client\Profiles\PIM\Exports\SAAMMOD Derv Calc 6Apr2022.xlsx | P20: SAAMMOD Mandate
A21: SMMRRF | B21: =[20]Summary!$G$3 -> UT | C21: =[20]Summary!$E$1 -> 2 | D21: =[20]Summary!$C$34 -> 0.0037491671 | E21: =[20]Summary!$E$34/100 -> 0.0037491671 | F21: =[20]Summary!$C$36 -> 0.0099448086 | G21: =[20]Summary!$C$32 -> 0 | H21: =[20]Summary!$E$6/100 -> 0 | I21: =[20]Summary!$E$10/100 -> 0 | J21: =[20]Summary!$E$14/100 -> 0 | K21: =[20]Summary!$C$40 -> 0.35472694 | L21: =[20]Summary!$C$54 -> 0 | M21: ='[20]Glbl Expsr'!$D$2 -> 0.26707297 | N21: ='[20]Glbl Expsr'!$D$3 -> 0.26707297 | O21: \\pim-cpt-statpro\SPC_602\Client\Profiles\PIM\Exports\SMMRRF Derv Calc 6Apr2022.xlsx | P21: SMMRRF Mandate
A22: HOLDINC | B22: =[21]Summary!$G$3 -> UT | C22: =[21]Summary!$E$1 -> 2 | D22: =[21]Summary!$C$34 -> 0.16480126 | E22: =[21]Summary!$E$34/100 -> 0.16480126 | F22: =[21]Summary!$C$36 -> 0.67706999 | G22: =[21]Summary!$C$32 -> 0 | H22: =[21]Summary!$E$6/100 -> 0.13037834 | I22: =[21]Summary!$E$10/100 -> 0 | J22: =[21]Summary!$E$14/100 -> 0.0020140446 | K22: =[21]Summary!$C$40 -> 0.047540833 | L22: =[21]Summary!$C$54 -> 5.1072566 | M22: ='[21]Glbl Expsr'!$D$2 -> 0.00019583205 | N22: ='[21]Glbl Expsr'!$D$3 -> 0.00019413205 | O22: \\pim-cpt-statpro\SPC_602\Client\Profiles\PIM\Exports\HOLDINC Derv Calc 6Apr2022.xlsx | P22: HOLDINC Mandate
A23: CAPGIP | B23: =[22]Summary!$G$3 -> UT | C23: =[22]Summary!$E$1 -> 2 | D23: =[22]Summary!$C$34 -> 0.1873959 | E23: =[22]Summary!$E$34/100 -> 0.1873959 | F23: =[22]Summary!$C$36 -> 0.45405665 | G23: =[22]Summary!$C$32 -> 0 | H23: =[22]Summary!$E$6/100 -> 0.057555138 | I23: =[22]Summary!$E$10/100 -> 0 | J23: =[22]Summary!$E$14/100 -> 0 | K23: =[22]Summary!$C$40 -> 0.057927489 | L23: =[22]Summary!$C$54 -> 8.4597345 | M23: ='[22]Glbl Expsr'!$D$2 -> 0.00017937063 | N23: ='[22]Glbl Expsr'!$D$3 -> 0.00017781353 | O23: \\pim-cpt-statpro\SPC_602\Client\Profiles\PIM\Exports\CAPGIP Derv Calc 6Apr2022.xlsx | P23: CAPGIP Mandate
A24: MOMBBF | B24: =[23]Summary!$G$3 -> UT | C24: =[23]Summary!$E$1 -> 2 | D24: =[23]Summary!$C$34 -> 0.18812216 | E24: =[23]Summary!$E$34/100 -> 0.18812216 | F24: =[23]Summary!$C$36 -> 0.66968045 | G24: =[23]Summary!$C$32 -> 0 | H24: =[23]Summary!$E$6/100 -> 0.11040074 | I24: =[23]Summary!$E$10/100 -> 0 | J24: =[23]Summary!$E$14/100 -> 0 | K24: =[23]Summary!$C$40 -> 0.056875318 | L24: =[23]Summary!$C$54 -> 5.6319494 | M24: ='[23]Glbl Expsr'!$D$2 -> 0.00023108087 | N24: ='[23]Glbl Expsr'!$D$3 -> 0.00022907488 | O24: \\pim-cpt-statpro\SPC_602\Client\Profiles\PIM\Exports\MOMBBF Derv Calc 6Apr2022.xlsx | P24: MOMBBF Mandate
A25: PPSFLEX | B25: =[24]Summary!$G$3 -> UT | C25: =[24]Summary!$E$1 -> 2 | D25: =[24]Summary!$C$34 -> 0.19016158 | E25: =[24]Summary!$E$34/100 -> 0.19016158 | F25: =[24]Summary!$C$36 -> 0.63298718 | G25: =[24]Summary!$C$32 -> 0 | H25: =[24]Summary!$E$6/100 -> 0.10877986 | I25: =[24]Summary!$E$10/100 -> 0 | J25: =[24]Summary!$E$14/100 -> 0 | K25: =[24]Summary!$C$40 -> 0.057519799 | L25: =[24]Summary!$C$54 -> 7.8233252 | M25: ='[24]Glbl Expsr'!$D$2 -> 0.00028324351 | N25: ='[24]Glbl Expsr'!$D$3 -> 0.0002807847 | O25: \\pim-cpt-statpro\SPC_602\Client\Profiles\PIM\Exports\PPSFLEX Derv Calc 6Apr2022.xlsx | P25: PPSFLEX Mandate
A26: HOLYPF | B26: =[25]Summary!$G$3 -> UT | C26: =[25]Summary!$E$1 -> 2 | D26: =[25]Summary!$C$34 -> 0.22456624 | E26: =[25]Summary!$E$34/100 -> 0.22456624 | F26: =[25]Summary!$C$36 -> 0.77463768 | G26: =[25]Summary!$C$32 -> 0 | H26: =[25]Summary!$E$6/100 -> 0.12072134 | I26: =[25]Summary!$E$10/100 -> 0 | J26: =[25]Summary!$E$14/100 -> 0 | K26: =[25]Summary!$C$40 -> 0.00013893527 | L26: =[25]Summary!$C$54 -> -1.4970156 | M26: ='[25]Glbl Expsr'!$D$2 -> 0.00014015192 | N26: ='[25]Glbl Expsr'!$D$3 -> 0.00013893527 | O26: \\pim-cpt-statpro\SPC_602\Client\Profiles\PIM\Exports\HOLYPF Derv Calc 6Apr2022.xlsx | P26: HOLYPF Mandate
A27: SMMAIF | B27: =[26]Summary!$G$3 -> UT | C27: =[26]Summary!$E$1 -> 2 | D27: =[26]Summary!$C$34 -> 0.22633957 | E27: =[26]Summary!$E$34/100 -> 0.22633957 | F27: =[26]Summary!$C$36 -> 0.57166136 | G27: =[26]Summary!$C$32 -> 0 | H27: =[26]Summary!$E$6/100 -> 0.042692009 | I27: =[26]Summary!$E$10/100 -> 0 | J27: =[26]Summary!$E$14/100 -> 0 | K27: =[26]Summary!$C$40 -> 0.036006721 | L27: =[26]Summary!$C$54 -> 4.7421055 | M27: ='[26]Glbl Expsr'!$D$2 -> 0.0001621699 | N27: ='[26]Glbl Expsr'!$D$3 -> 0.00016076212 | O27: \\pim-cpt-statpro\SPC_602\Client\Profiles\PIM\Exports\SMMAIF Derv Calc 6Apr2022.xlsx | P27: SMMAIF Mandate
A28: GRFINV | B28: =[27]Summary!$G$3 -> UT | C28: =[27]Summary!$E$1 -> 2 | D28: =[27]Summary!$C$34 -> 0.29621998 | E28: =[27]Summary!$E$34/100 -> 0.29621998 | F28: =[27]Summary!$C$36 -> 0.39682893 | G28: =[27]Summary!$C$32 -> 0 | H28: =[27]Summary!$E$6/100 -> 0.046830667 | I28: =[27]Summary!$E$10/100 -> 0 | J28: =[27]Summary!$E$14/100 -> 0 | K28: =[27]Summary!$C$40 -> 0.043889842 | L28: =[27]Summary!$C$54 -> 2.0980708 | M28: ='[27]Glbl Expsr'!$D$2 -> 0.00039647873 | N28: ='[27]Glbl Expsr'!$D$3 -> 0.00039303693 | O28: \\pim-cpt-statpro\SPC_602\Client\Profiles\PIM\Exports\GRFINV Derv Calc 6Apr2022.xlsx | P28: GRFINV Mandate
A29: ASHFLX | B29: =[28]Summary!$G$3 -> UT | C29: =[28]Summary!$E$1 -> 2 | D29: =[28]Summary!$C$34 -> 0.36241963 | E29: =[28]Summary!$E$34/100 -> 0.36241963 | F29: =[28]Summary!$C$36 -> 0.55031471 | G29: =[28]Summary!$C$32 -> 0 | H29: =[28]Summary!$E$6/100 -> 0.1143555 | I29: =[28]Summary!$E$10/100 -> 0 | J29: =[28]Summary!$E$14/100 -> 0 | K29: =[28]Summary!$C$40 -> 0.038489007 | L29: =[28]Summary!$C$54 -> 1.9755032 | M29: ='[28]Glbl Expsr'!$D$2 -> 0.00026332107 | N29: ='[28]Glbl Expsr'!$D$3 -> 0.0002610352 | O29: \\pim-cpt-statpro\SPC_602\Client\Profiles\PIM\Exports\ASHFLX Derv Calc 6Apr2022.xlsx | P29: ASHFLX Mandate
A30: MOMFLX | B30: =[29]Summary!$G$3 -> UT | C30: =[29]Summary!$E$1 -> 0 | D30: =[29]Summary!$C$34 -> 0.002056792 | E30: =[29]Summary!$E$34/100 -> 0.002056792 | F30: =[29]Summary!$C$36 -> 0.99794321 | G30: =[29]Summary!$C$32 -> 0 | H30: =[29]Summary!$E$6/100 -> 0 | I30: =[29]Summary!$E$10/100 -> 0 | J30: =[29]Summary!$E$14/100 -> 0 | K30: =[29]Summary!$C$40 -> 0 | L30: =[29]Summary!$C$54 -> 0 | M30: ='[29]Glbl Expsr'!$D$2 -> 0 | N30: ='[29]Glbl Expsr'!$D$3 -> 0 | O30: \\pim-cpt-statpro\SPC_602\Client\Profiles\PIM\Exports\MOMFLX Derv Calc 6Apr2022.xlsx | P30: MOMFLX Mandate
A31: SMMIBF | B31: =[30]Summary!$G$3 -> UT | C31: =[30]Summary!$E$1 -> 0 | D31: =[30]Summary!$C$34 -> 0.0024365093 | E31: =[30]Summary!$E$34/100 -> 0.0024365093 | F31: =[30]Summary!$C$36 -> 0.99756349 | G31: =[30]Summary!$C$32 -> 0 | H31: =[30]Summary!$E$6/100 -> 0.023064705 | I31: =[30]Summary!$E$10/100 -> 0 | J31: =[30]Summary!$E$14/100 -> 0 | K31: =[30]Summary!$C$40 -> 0 | L31: =[30]Summary!$C$54 -> 0 | M31: ='[30]Glbl Expsr'!$D$2 -> 0 | N31: ='[30]Glbl Expsr'!$D$3 -> 0 | O31: \\pim-cpt-statpro\SPC_602\Client\Profiles\PIM\Exports\SMMIBF Derv Calc 6Apr2022.xlsx | P31: SMMIBF Mandate
A32: PBNDQ | B32: =[31]Summary!$G$3 -> UT | C32: =[31]Summary!$E$1 -> 0 | D32: =[31]Summary!$C$34 -> 0.0030173301 | E32: =[31]Summary!$E$34/100 -> 0.0030173301 | F32: =[31]Summary!$C$36 -> 0.99698267 | G32: =[31]Summary!$C$32 -> 0 | H32: =[31]Summary!$E$6/100 -> 0 | I32: =[31]Summary!$E$10/100 -> 0 | J32: =[31]Summary!$E$14/100 -> 0 | K32: =[31]Summary!$C$40 -> 0 | L32: =[31]Summary!$C$54 -> 0 | M32: ='[31]Glbl Expsr'!$D$2 -> 0 | N32: ='[31]Glbl Expsr'!$D$3 -> 0 | O32: \\pim-cpt-statpro\SPC_602\Client\Profiles\PIM\Exports\PBNDQ Derv Calc 6Apr2022.xlsx | P32: PBNDQ Mandate
A33: OMFLXI5 | B33: =[32]Summary!$G$3 -> UT | C33: =[32]Summary!$E$1 -> 0 | D33: =[32]Summary!$C$34 -> 0.0032614639 | E33: =[32]Summary!$E$34/100 -> 0.0032614639 | F33: =[32]Summary!$C$36 -> 0.99673854 | G33: =[32]Summary!$C$32 -> 0 | H33: =[32]Summary!$E$6/100 -> 0 | I33: =[32]Summary!$E$10/100 -> 0 | J33: =[32]Summary!$E$14/100 -> 0 | K33: =[32]Summary!$C$40 -> 0 | L33: =[32]Summary!$C$54 -> 0 | M33: ='[32]Glbl Expsr'!$D$2 -> 0 | N33: ='[32]Glbl Expsr'!$D$3 -> 0 | O33: \\pim-cpt-statpro\SPC_602\Client\Profiles\PIM\Exports\OMFLXI5 Derv Calc 6Apr2022.xlsx | P33: OMFLXI5 Mandate
A34: SMMBPR | B34: =[33]Summary!$G$3 -> UT | C34: =[33]Summary!$E$1 -> 0 | D34: =[33]Summary!$C$34 -> 0.0035404715 | E34: =[33]Summary!$E$34/100 -> 0.0035404715 | F34: =[33]Summary!$C$36 -> 0.99645953 | G34: =[33]Summary!$C$32 -> 0 | H34: =[33]Summary!$E$6/100 -> 0.0064483781 | I34: =[33]Summary!$E$10/100 -> 0 | J34: =[33]Summary!$E$14/100 -> 0 | K34: =[33]Summary!$C$40 -> 0 | L34: =[33]Summary!$C$54 -> 0 | M34: ='[33]Glbl Expsr'!$D$2 -> 0 | N34: ='[33]Glbl Expsr'!$D$3 -> 0 | O34: \\pim-cpt-statpro\SPC_602\Client\Profiles\PIM\Exports\SMMBPR Derv Calc 6Apr2022.xlsx | P34: SMMBPR Mandate
A35: STSBND | B35: =[34]Summary!$G$3 -> UT | C35: =[34]Summary!$E$1 -> 0 | D35: =[34]Summary!$C$34 -> 0.0037745671 | E35: =[34]Summary!$E$34/100 -> 0.0037745671 | F35: =[34]Summary!$C$36 -> 0.99622543 | G35: =[34]Summary!$C$32 -> 0 | H35: =[34]Summary!$E$6/100 -> 0.01509834 | I35: =[34]Summary!$E$10/100 -> 0 | J35: =[34]Summary!$E$14/100 -> 0 | K35: =[34]Summary!$C$40 -> 0 | L35: =[34]Summary!$C$54 -> 0 | M35: ='[34]Glbl Expsr'!$D$2 -> 0 | N35: ='[34]Glbl Expsr'!$D$3 -> 0 | O35: \\pim-cpt-statpro\SPC_602\Client\Profiles\PIM\Exports\STSBND Derv Calc 6Apr2022.xlsx | P35: STSBND Mandate
A36: ASHGFB | B36: =[35]Summary!$G$3 -> UT | C36: =[35]Summary!$E$1 -> 0 | D36: =[35]Summary!$C$34 -> 0.0042467954 | E36: =[35]Summary!$E$34/100 -> 0.0042467954 | F36: =[35]Summary!$C$36 -> 0.9957532 | G36: =[35]Summary!$C$32 -> 0 | H36: =[35]Summary!$E$6/100 -> 0 | I36: =[35]Summary!$E$10/100 -> 0 | J36: =[35]Summary!$E$14/100 -> 0 | K36: =[35]Summary!$C$40 -> 0 | L36: =[35]Summary!$C$54 -> 0 | M36: ='[35]Glbl Expsr'!$D$2 -> 0 | N36: ='[35]Glbl Expsr'!$D$3 -> 0 | O36: \\pim-cpt-statpro\SPC_602\Client\Profiles\PIM\Exports\ASHGFB Derv Calc 6Apr2022.xlsx | P36: ASHGFB Mandate
A37: ABMMBND | B37: =[36]Summary!$G$3 -> UT | C37: =[36]Summary!$E$1 -> 0 | D37: =[36]Summary!$C$34 -> 0.0056691116 | E37: =[36]Summary!$E$34/100 -> 0.0056691116 | F37: =[36]Summary!$C$36 -> 0.99433089 | G37: =[36]Summary!$C$32 -> 0 | H37: =[36]Summary!$E$6/100 -> 0 | I37: =[36]Summary!$E$10/100 -> 0 | J37: =[36]Summary!$E$14/100 -> 0 | K37: =[36]Summary!$C$40 -> 0 | L37: =[36]Summary!$C$54 -> 0 | M37: ='[36]Glbl Expsr'!$D$2 -> 0 | N37: ='[36]Glbl Expsr'!$D$3 -> 0 | O37: \\pim-cpt-statpro\SPC_602\Client\Profiles\PIM\Exports\ABMMBND Derv Calc 6Apr2022.xlsx | P37: ABMMBND Mandate
A38: PCGEF | B38: =[37]Summary!$G$3 -> UT | C38: =[37]Summary!$E$1 -> 0 | D38: =[37]Summary!$C$34 -> 0.0094445606 | E38: =[37]Summary!$E$34/100 -> 0.0094445606 | F38: =[37]Summary!$C$36 -> 0 | G38: =[37]Summary!$C$32 -> 0 | H38: =[37]Summary!$E$6/100 -> 0 | I38: =[37]Summary!$E$10/100 -> 0 | J38: =[37]Summary!$E$14/100 -> 0 | K38: =[37]Summary!$C$40 -> 0.99055544 | L38: =[37]Summary!$C$54 -> 99.055544 | M38: ='[37]Glbl Expsr'!$D$2 -> 0 | N38: ='[37]Glbl Expsr'!$D$3 -> 0 | O38: \\pim-cpt-statpro\SPC_602\Client\Profiles\PIM\Exports\PCGEF Derv Calc 6Apr2022.xlsx | P38: PCGEF Mandate
A39: PGGF | B39: =[38]Summary!$G$3 -> UT | C39: =[38]Summary!$E$1 -> 0 | D39: =[38]Summary!$C$34 -> 0.010070441 | E39: =[38]Summary!$E$34/100 -> 0.010070441 | F39: =[38]Summary!$C$36 -> 0 | G39: =[38]Summary!$C$32 -> 0 | H39: =[38]Summary!$E$6/100 -> 0 | I39: =[38]Summary!$E$10/100 -> 0 | J39: =[38]Summary!$E$14/100 -> 0 | K39: =[38]Summary!$C$40 -> 0.98992956 | L39: =[38]Summary!$C$54 -> 98.992956 | M39: ='[38]Glbl Expsr'!$D$2 -> 0 | N39: ='[38]Glbl Expsr'!$D$3 -> 0 | O39: \\pim-cpt-statpro\SPC_602\Client\Profiles\PIM\Exports\PGGF Derv Calc 6Apr2022.xlsx | P39: PGGF Mandate
A40: IJGCOR | B40: =[39]Summary!$G$3 -> UT | C40: =[39]Summary!$E$1 -> 0 | D40: =[39]Summary!$C$34 -> 0.035793677 | E40: =[39]Summary!$E$34/100 -> 0.035793677 | F40: =[39]Summary!$C$36 -> 0 | G40: =[39]Summary!$C$32 -> 0 | H40: =[39]Summary!$E$6/100 -> 0 | I40: =[39]Summary!$E$10/100 -> 0 | J40: =[39]Summary!$E$14/100 -> 0 | K40: =[39]Summary!$C$40 -> 0 | L40: =[39]Summary!$C$54 -> 96.420632 | M40: ='[39]Glbl Expsr'!$D$2 -> 0 | N40: ='[39]Glbl Expsr'!$D$3 -> 0 | O40: \\pim-cpt-statpro\SPC_602\Client\Profiles\PIM\Exports\IJGCOR Derv Calc 6Apr2022.xlsx | P40: IJGCOR Mandate
A41: PGIF | B41: =[40]Summary!$G$3 -> UT | C41: =[40]Summary!$E$1 -> 0 | D41: =[40]Summary!$C$34 -> 0.039919152 | E41: =[40]Summary!$E$34/100 -> 0.039919152 | F41: =[40]Summary!$C$36 -> 0 | G41: =[40]Summary!$C$32 -> 0 | H41: =[40]Summary!$E$6/100 -> 0 | I41: =[40]Summary!$E$10/100 -> 0 | J41: =[40]Summary!$E$14/100 -> 0 | K41: =[40]Summary!$C$40 -> 0 | L41: =[40]Summary!$C$54 -> 96.008085 | M41: ='[40]Glbl Expsr'!$D$2 -> 0 | N41: ='[40]Glbl Expsr'!$D$3 -> 0 | O41: \\pim-cpt-statpro\SPC_602\Client\Profiles\PIM\Exports\PGIF Derv Calc 6Apr2022.xlsx | P41: PGIF Mandate
A42: PFFIF | B42: =[41]Summary!$G$3 -> UT | C42: =[41]Summary!$E$1 -> 0 | D42: =[41]Summary!$C$34 -> 0.11338492 | E42: =[41]Summary!$E$34/100 -> 0.11338492 | F42: =[41]Summary!$C$36 -> 0.68511499 | G42: =[41]Summary!$C$32 -> 0 | H42: =[41]Summary!$E$6/100 -> 0.060509617 | I42: =[41]Summary!$E$10/100 -> 0 | J42: =[41]Summary!$E$14/100 -> 0 | K42: =[41]Summary!$C$40 -> 0.022371381 | L42: =[41]Summary!$C$54 -> 0 | M42: ='[41]Glbl Expsr'!$D$2 -> 0 | N42: ='[41]Glbl Expsr'!$D$3 -> 0 | O42: \\pim-cpt-statpro\SPC_602\Client\Profiles\PIM\Exports\PFFIF Derv Calc 6Apr2022.xlsx | P42: PFFIF Mandate
A43: PSTIF | B43: =[42]Summary!$G$3 -> UT | C43: =[42]Summary!$E$1 -> 0 | D43: =[42]Summary!$C$34 -> 0.14451327 | E43: =[42]Summary!$E$34/100 -> 0.14451327 | F43: =[42]Summary!$C$36 -> 0.74948062 | G43: =[42]Summary!$C$32 -> 0 | H43: =[42]Summary!$E$6/100 -> 0.15792863 | I43: =[42]Summary!$E$10/100 -> 0 | J43: =[42]Summary!$E$14/100 -> 0 | K43: =[42]Summary!$C$40 -> 0.040134911 | L43: =[42]Summary!$C$54 -> 0 | M43: ='[42]Glbl Expsr'!$D$2 -> 0 | N43: ='[42]Glbl Expsr'!$D$3 -> 0 | O43: \\pim-cpt-statpro\SPC_602\Client\Profiles\PIM\Exports\PSTIF Derv Calc 6Apr2022.xlsx | P43: PSTIF Mandate
A44: POIF_C | B44: =[43]Summary!$G$3 -> UT | C44: =[43]Summary!$E$1 -> 0 | D44: =[43]Summary!$C$34 -> 0.15540484 | E44: =[43]Summary!$E$34/100 -> 0.15540484 | F44: =[43]Summary!$C$36 -> 0 | G44: =[43]Summary!$C$32 -> 0 | H44: =[43]Summary!$E$6/100 -> 0 | I44: =[43]Summary!$E$10/100 -> 0.046931227 | J44: =[43]Summary!$E$14/100 -> 0.8045002 | K44: =[43]Summary!$C$40 -> 0.84459516 | L44: =[43]Summary!$C$54 -> 0 | M44: ='[43]Glbl Expsr'!$D$2 -> 0 | N44: ='[43]Glbl Expsr'!$D$3 -> 0 | O44: \\pim-cpt-statpro\SPC_602\Client\Profiles\PIM\Exports\POIF_C Derv Calc 6Apr2022.xlsx | P44: POIF_C Mandate
A45: IJGIPF | B45: =[44]Summary!$G$3 -> UT | C45: =[44]Summary!$E$1 -> 0 | D45: =[44]Summary!$C$34 -> 0.19236636 | E45: =[44]Summary!$E$34/100 -> 0.19236636 | F45: =[44]Summary!$C$36 -> 0.45836587 | G45: =[44]Summary!$C$32 -> 0 | H45: =[44]Summary!$E$6/100 -> 0.054097085 | I45: =[44]Summary!$E$10/100 -> 0 | J45: =[44]Summary!$E$14/100 -> 0 | K45: =[44]Summary!$C$40 -> 0.070857989 | L45: =[44]Summary!$C$54 -> 22.561907 | M45: ='[44]Glbl Expsr'!$D$2 -> 0 | N45: ='[44]Glbl Expsr'!$D$3 -> 0 | O45: \\pim-cpt-statpro\SPC_602\Client\Profiles\PIM\Exports\IJGIPF Derv Calc 6Apr2022.xlsx | P45: IJGIPF Mandate
A46: PSIF | B46: =[45]Summary!$G$3 -> UT | C46: =[45]Summary!$E$1 -> 0 | D46: =[45]Summary!$C$34 -> 0.27139439 | E46: =[45]Summary!$E$34/100 -> 0.27139439 | F46: =[45]Summary!$C$36 -> 0.67762721 | G46: =[45]Summary!$C$32 -> 0 | H46: =[45]Summary!$E$6/100 -> 0.087436615 | I46: =[45]Summary!$E$10/100 -> 0 | J46: =[45]Summary!$E$14/100 -> 0.00080769415 | K46: =[45]Summary!$C$40 -> 0.05086244 | L46: =[45]Summary!$C$54 -> 0 | M46: ='[45]Glbl Expsr'!$D$2 -> 0 | N46: ='[45]Glbl Expsr'!$D$3 -> 0 | O46: \\pim-cpt-statpro\SPC_602\Client\Profiles\PIM\Exports\PSIF Derv Calc 6Apr2022.xlsx | P46: PSIF Mandate
A47: PCSHQ | B47: =[46]Summary!$G$3 -> UT | C47: =[46]Summary!$E$1 -> 0 | D47: =[46]Summary!$C$34 -> 0.41742217 | E47: =[46]Summary!$E$34/100 -> 0.41742217 | F47: =[46]Summary!$C$36 -> 0.58250212 | G47: =[46]Summary!$C$32 -> 0 | H47: =[46]Summary!$E$6/100 -> 0 | I47: =[46]Summary!$E$10/100 -> 0 | J47: =[46]Summary!$E$14/100 -> 0 | K47: =[46]Summary!$C$40 -> 0 | L47: =[46]Summary!$C$54 -> 0 | M47: ='[46]Glbl Expsr'!$D$2 -> 0 | N47: ='[46]Glbl Expsr'!$D$3 -> 0 | O47: \\pim-cpt-statpro\SPC_602\Client\Profiles\PIM\Exports\PCSHQ Derv Calc 6Apr2022.xlsx | P47: PCSHQ Mandate
A48: SMMEYP | B48: =[47]Summary!$G$3 -> UT | C48: =[47]Summary!$E$1 -> 0 | D48: =[47]Summary!$C$34 -> 0.42282884 | E48: =[47]Summary!$E$34/100 -> 0.42282884 | F48: =[47]Summary!$C$36 -> 0.57700254 | G48: =[47]Summary!$C$32 -> 0 | H48: =[47]Summary!$E$6/100 -> 0 | I48: =[47]Summary!$E$10/100 -> 0 | J48: =[47]Summary!$E$14/100 -> 0 | K48: =[47]Summary!$C$40 -> 0 | L48: =[47]Summary!$C$54 -> 0 | M48: ='[47]Glbl Expsr'!$D$2 -> 0 | N48: ='[47]Glbl Expsr'!$D$3 -> 0 | O48: \\pim-cpt-statpro\SPC_602\Client\Profiles\PIM\Exports\SMMEYP Derv Calc 6Apr2022.xlsx | P48: SMMEYP Mandate
A49: EMHPBQ | B49: =[48]Summary!$G$3 -> UT | C49: =[48]Summary!$E$1 -> 0 | D49: =[48]Summary!$C$34 -> 1 | E49: =[48]Summary!$E$34/100 -> 1 | F49: =[48]Summary!$C$36 -> 0 | G49: =[48]Summary!$C$32 -> 0 | H49: =[48]Summary!$E$6/100 -> 0 | I49: =[48]Summary!$E$10/100 -> 0 | J49: =[48]Summary!$E$14/100 -> 0 | K49: =[48]Summary!$C$40 -> 0 | L49: =[48]Summary!$C$54 -> 0 | M49: ='[48]Glbl Expsr'!$D$2 -> 0 | N49: ='[48]Glbl Expsr'!$D$3 -> 0 | O49: \\pim-cpt-statpro\SPC_602\Client\Profiles\PIM\Exports\EMHPBQ Derv Calc 6Apr2022.xlsx | P49: EMHPBQ Mandate
A50: SWGSWX | B50: =[49]Summary!$G$3 -> ≠ UT | C50: =[49]Summary!$E$1 -> 10 | D50: =[49]Summary!$C$34 -> 0.69521514 | E50: =[49]Summary!$E$34/100 -> 0.69521514 | F50: =[49]Summary!$C$36 | G50: =[49]Summary!$C$32 -> 0.70086344 | H50: =[49]Summary!$E$6/100 -> 0 | I50: =[49]Summary!$E$10/100 -> 0.020171587 | J50: =[49]Summary!$E$14/100 -> 0.15776626 | K50: =[49]Summary!$C$40 -> 0.99496796 | L50: =[49]Summary!$C$54 -> 0 | M50: ='[49]Glbl Expsr'!$D$2 -> 0.13254017 | N50: ='[49]Glbl Expsr'!$D$3 -> 0.13254017 | O50: \\pim-cpt-statpro\SPC_602\Client\Profiles\PIM\Exports\SWGSWX Derv Calc 6Apr2022.xlsx | P50: SWGSWX Mandate
A51: ASBTOS | B51: =[50]Summary!$G$3 -> ≠ UT | C51: =[50]Summary!$E$1 -> 9 | D51: =[50]Summary!$C$34 -> 0.48600155 | E51: =[50]Summary!$E$34/100 -> 0.48600155 | F51: =[50]Summary!$C$36 | G51: =[50]Summary!$C$32 -> 0.25839679 | H51: =[50]Summary!$E$6/100 -> 0.19864304 | I51: =[50]Summary!$E$10/100 -> 0 | J51: =[50]Summary!$E$14/100 -> 0 | K51: =[50]Summary!$C$40 -> 0.42661143 | L51: =[50]Summary!$C$54 -> 0 | M51: ='[50]Glbl Expsr'!$D$2 -> 1.0003738 | N51: ='[50]Glbl Expsr'!$D$3 -> 0.22442118 | O51: \\pim-cpt-statpro\SPC_602\Client\Profiles\PIM\Exports\ASBTOS Derv Calc 6Apr2022.xlsx | P51: ASBTOS Mandate
A52: MOMPRET | B52: =[51]Summary!$G$3 -> ≠ UT | C52: =[51]Summary!$E$1 -> 9 | D52: =[51]Summary!$C$34 -> 0.48881222 | E52: =[51]Summary!$E$34/100 -> 0.48881222 | F52: =[51]Summary!$C$36 | G52: =[51]Summary!$C$32 -> 0.36585764 | H52: =[51]Summary!$E$6/100 -> 0.19841458 | I52: =[51]Summary!$E$10/100 -> 0 | J52: =[51]Summary!$E$14/100 -> 0 | K52: =[51]Summary!$C$40 -> 0.42530382 | L52: =[51]Summary!$C$54 -> 0 | M52: ='[51]Glbl Expsr'!$D$2 -> 1.0281698 | N52: ='[51]Glbl Expsr'!$D$3 -> 0.22646763 | O52: \\pim-cpt-statpro\SPC_602\Client\Profiles\PIM\Exports\MOMPRET Derv Calc 6Apr2022.xlsx | P52: MOMPRET Mandate
A53: PSPAM | B53: =[52]Summary!$G$3 -> ≠ UT | C53: =[52]Summary!$E$1 -> 9 | D53: =[52]Summary!$C$34 -> 0.49519552 | E53: =[52]Summary!$E$34/100 -> 0.49519552 | F53: =[52]Summary!$C$36 | G53: =[52]Summary!$C$32 -> 0.25850493 | H53: =[52]Summary!$E$6/100 -> 0.19412024 | I53: =[52]Summary!$E$10/100 -> 0 | J53: =[52]Summary!$E$14/100 -> 0 | K53: =[52]Summary!$C$40 -> 0.41247377 | L53: =[52]Summary!$C$54 -> 0 | M53: ='[52]Glbl Expsr'!$D$2 -> 1.0412002 | N53: ='[52]Glbl Expsr'!$D$3 -> 0.2166133 | O53: \\pim-cpt-statpro\SPC_602\Client\Profiles\PIM\Exports\PSPAM Derv Calc 6Apr2022.xlsx | P53: PSPAM Mandate
A54: PLPRNA | B54: =[53]Summary!$G$3 -> ≠ UT | C54: =[53]Summary!$E$1 -> 9 | D54: =[53]Summary!$C$34 -> 0.49592282 | E54: =[53]Summary!$E$34/100 -> 0.49592282 | F54: =[53]Summary!$C$36 | G54: =[53]Summary!$C$32 -> 0.3511329 | H54: =[53]Summary!$E$6/100 -> 0.21370953 | I54: =[53]Summary!$E$10/100 -> 0 | J54: =[53]Summary!$E$14/100 -> 0 | K54: =[53]Summary!$C$40 -> 0.41970656 | L54: =[53]Summary!$C$54 -> 0 | M54: ='[53]Glbl Expsr'!$D$2 -> 1.058431 | N54: ='[53]Glbl Expsr'!$D$3 -> 0.22022183 | O54: \\pim-cpt-statpro\SPC_602\Client\Profiles\PIM\Exports\PLPRNA Derv Calc 6Apr2022.xlsx | P54: PLPRNA Mandate
A55: PORFGPR | B55: =[54]Summary!$G$3 -> ≠ UT | C55: =[54]Summary!$E$1 -> 9 | D55: =[54]Summary!$C$34 -> 0.52590718 | E55: =[54]Summary!$E$34/100 -> 0.52590718 | F55: =[54]Summary!$C$36 | G55: =[54]Summary!$C$32 -> 0.43251845 | H55: =[54]Summary!$E$6/100 -> 0.15955254 | I55: =[54]Summary!$E$10/100 -> 0 | J55: =[54]Summary!$E$14/100 -> 0 | K55: =[54]Summary!$C$40 -> 0.36624659 | L55: =[54]Summary!$C$54 -> 19.625628 | M55: ='[54]Glbl Expsr'!$D$2 -> 0.93497344 | N55: ='[54]Glbl Expsr'!$D$3 -> 0.18306944 | O55: \\pim-cpt-statpro\SPC_602\Client\Profiles\PIM\Exports\PORFGPR Derv Calc 6Apr2022.xlsx | P55: PORFGPR Mandate
A56: GMRETF | B56: =[55]Summary!$G$3 -> ≠ UT | C56: =[55]Summary!$E$1 -> 9 | D56: =[55]Summary!$C$34 -> 0.54325361 | E56: =[55]Summary!$E$34/100 -> 0.54325361 | F56: =[55]Summary!$C$36 | G56: =[55]Summary!$C$32 -> 0.44788333 | H56: =[55]Summary!$E$6/100 -> 0.16722989 | I56: =[55]Summary!$E$10/100 -> 0 | J56: =[55]Summary!$E$14/100 -> 0 | K56: =[55]Summary!$C$40 -> 0.37438532 | L56: =[55]Summary!$C$54 -> 19.668501 | M56: ='[55]Glbl Expsr'!$D$2 -> 0.86223606 | N56: ='[55]Glbl Expsr'!$D$3 -> 0.20501827 | O56: \\pim-cpt-statpro\SPC_602\Client\Profiles\PIM\Exports\GMRETF Derv Calc 6Apr2022.xlsx | P56: GMRETF Mandate
A57: GMRETF2 | B57: =[56]Summary!$G$3 -> ≠ UT | C57: =[56]Summary!$E$1 -> 9 | D57: =[56]Summary!$C$34 -> 0.54757375 | E57: =[56]Summary!$E$34/100 -> 0.54757375 | F57: =[56]Summary!$C$36 | G57: =[56]Summary!$C$32 -> 0.45606054 | H57: =[56]Summary!$E$6/100 -> 0.16554408 | I57: =[56]Summary!$E$10/100 -> 0 | J57: =[56]Summary!$E$14/100 -> 0 | K57: =[56]Summary!$C$40 -> 0.38361174 | L57: =[56]Summary!$C$54 -> 18.873765 | M57: ='[56]Glbl Expsr'!$D$2 -> 0.88747081 | N57: ='[56]Glbl Expsr'!$D$3 -> 0.22052143 | O57: \\pim-cpt-statpro\SPC_602\Client\Profiles\PIM\Exports\GMRETF2 Derv Calc 6Apr2022.xlsx | P57: GMRETF2 Mandate
A58: ELCIPF | B58: =[57]Summary!$G$3 -> ≠ UT | C58: =[57]Summary!$E$1 -> 8 | D58: =[57]Summary!$C$34 -> 0.020179498 | E58: =[57]Summary!$E$34/100 -> 0.020179498 | F58: =[57]Summary!$C$36 -> 0 | G58: =[57]Summary!$C$32 -> 0 | H58: =[57]Summary!$E$6/100 -> 0 | I58: =[57]Summary!$E$10/100 -> 0.033811283 | J58: =[57]Summary!$E$14/100 -> 0.18559155 | K58: =[57]Summary!$C$40 -> 0.99149454 | L58: =[57]Summary!$C$54 -> 0 | M58: ='[57]Glbl Expsr'!$D$2 -> 0.15218442 | N58: ='[57]Glbl Expsr'!$D$3 -> 0.15218442 | O58: \\pim-cpt-statpro\SPC_602\Client\Profiles\PIM\Exports\ELCIPF Derv Calc 6Apr2022.xlsx | P58: ELCIPF Mandate
A59: TSHMPF | B59: =[58]Summary!$G$3 -> ≠ UT | C59: =[58]Summary!$E$1 -> 8 | D59: =[58]Summary!$C$34 -> 0.036012353 | E59: =[58]Summary!$E$34/100 -> 0.036012353 | F59: =[58]Summary!$C$36 -> 0 | G59: =[58]Summary!$C$32 -> 0 | H59: =[58]Summary!$E$6/100 -> 0 | I59: =[58]Summary!$E$10/100 -> 0.038791986 | J59: =[58]Summary!$E$14/100 -> 0.19918968 | K59: =[58]Summary!$C$40 -> 0.99065849 | L59: =[58]Summary!$C$54 -> 0 | M59: ='[58]Glbl Expsr'!$D$2 -> 0.13466471 | N59: ='[58]Glbl Expsr'!$D$3 -> 0.13466471 | O59: \\pim-cpt-statpro\SPC_602\Client\Profiles\PIM\Exports\TSHMPF Derv Calc 6Apr2022.xlsx | P59: TSHMPF Mandate
A60: NFMWEQU | B60: =[59]Summary!$G$3 -> ≠ UT | C60: =[59]Summary!$E$1 -> 8 | D60: =[59]Summary!$C$34 -> 0.082315026 | E60: =[59]Summary!$E$34/100 -> 0.082315026 | F60: =[59]Summary!$C$36 -> 0 | G60: =[59]Summary!$C$32 -> 0 | H60: =[59]Summary!$E$6/100 -> 0 | I60: =[59]Summary!$E$10/100 -> 0.041456634 | J60: =[59]Summary!$E$14/100 -> 0.20559187 | K60: =[59]Summary!$C$40 -> 0.9929748 | L60: =[59]Summary!$C$54 -> 0 | M60: ='[59]Glbl Expsr'!$D$2 -> 0.12791244 | N60: ='[59]Glbl Expsr'!$D$3 -> 0.12791244 | O60: \\pim-cpt-statpro\SPC_602\Client\Profiles\PIM\Exports\NFMWEQU Derv Calc 6Apr2022.xlsx | P60: NFMWEQU Mandate
A61: MWPFEQU | B61: =[60]Summary!$G$3 -> ≠ UT | C61: =[60]Summary!$E$1 -> 7 | D61: =[60]Summary!$C$34 -> 0.092714644 | E61: =[60]Summary!$E$34/100 -> 0.092714644 | F61: =[60]Summary!$C$36 -> 0 | G61: =[60]Summary!$C$32 -> 0 | H61: =[60]Summary!$E$6/100 -> 0 | I61: =[60]Summary!$E$10/100 -> 0 | J61: =[60]Summary!$E$14/100 -> 0 | K61: =[60]Summary!$C$40 -> 0.99600668 | L61: =[60]Summary!$C$54 -> 0 | M61: ='[60]Glbl Expsr'!$D$2 -> 0.15441125 | N61: ='[60]Glbl Expsr'!$D$3 -> 0.15441125 | O61: \\pim-cpt-statpro\SPC_602\Client\Profiles\PIM\Exports\MWPFEQU Derv Calc 6Apr2022.xlsx | P61: MWPFEQU Mandate
A62: PPWEQU | B62: =[61]Summary!$G$3 -> ≠ UT | C62: =[61]Summary!$E$1 -> 7 | D62: =[61]Summary!$C$34 -> 0.10865402 | E62: =[61]Summary!$E$34/100 -> 0.10865402 | F62: =[61]Summary!$C$36 -> 0 | G62: =[61]Summary!$C$32 -> 0 | H62: =[61]Summary!$E$6/100 -> 0 | I62: =[61]Summary!$E$10/100 -> 0.038332914 | J62: =[61]Summary!$E$14/100 -> 0.19039019 | K62: =[61]Summary!$C$40 -> 0.99150557 | L62: =[61]Summary!$C$54 -> 0 | M62: ='[61]Glbl Expsr'!$D$2 -> 0.060655969 | N62: ='[61]Glbl Expsr'!$D$3 -> 0.060655969 | O62: \\pim-cpt-statpro\SPC_602\Client\Profiles\PIM\Exports\PPWEQU Derv Calc 6Apr2022.xlsx | P62: PPWEQU Mandate
A63: TOYCEF | B63: =[62]Summary!$G$3 -> ≠ UT | C63: =[62]Summary!$E$1 -> 7 | D63: =[62]Summary!$C$34 -> 0.18388094 | E63: =[62]Summary!$E$34/100 -> 0.18388094 | F63: =[62]Summary!$C$36 -> 0 | G63: =[62]Summary!$C$32 -> 0 | H63: =[62]Summary!$E$6/100 -> 0 | I63: =[62]Summary!$E$10/100 -> 0.018937928 | J63: =[62]Summary!$E$14/100 -> 0.15724512 | K63: =[62]Summary!$C$40 -> 0.99324049 | L63: =[62]Summary!$C$54 -> 0 | M63: ='[62]Glbl Expsr'!$D$2 -> 0.049272184 | N63: ='[62]Glbl Expsr'!$D$3 -> 0.049272184 | O63: \\pim-cpt-statpro\SPC_602\Client\Profiles\PIM\Exports\TOYCEF Derv Calc 6Apr2022.xlsx | P63: TOYCEF Mandate
A64: LIBTAA | B64: =[63]Summary!$G$3 -> ≠ UT | C64: =[63]Summary!$E$1 -> 6 | D64: =[63]Summary!$C$34 -> -9.8724884 | E64: =[63]Summary!$E$34/100 -> -9.8724884 | F64: =[63]Summary!$C$36 | G64: =[63]Summary!$C$32 -> 0 | H64: =[63]Summary!$E$6/100 -> 0 | I64: =[63]Summary!$E$10/100 -> 0 | J64: =[63]Summary!$E$14/100 -> 0 | K64: =[63]Summary!$C$40 -> 4.8229683 | L64: =[63]Summary!$C$54 -> 0 | M64: ='[63]Glbl Expsr'!$D$2 -> 4.8229683 | N64: ='[63]Glbl Expsr'!$D$3 -> 4.8229683 | O64: \\pim-cpt-statpro\SPC_602\Client\Profiles\PIM\Exports\LIBTAA Derv Calc 6Apr2022.xlsx | P64: LIBTAA Mandate
A65: NESEQU | B65: =[64]Summary!$G$3 -> ≠ UT | C65: =[64]Summary!$E$1 -> 5 | D65: =[64]Summary!$C$34 -> 0.32332707 | E65: =[64]Summary!$E$34/100 -> 0.32332707 | F65: =[64]Summary!$C$36 | G65: =[64]Summary!$C$32 -> 0.61037529 | H65: =[64]Summary!$E$6/100 -> 0 | I65: =[64]Summary!$E$10/100 -> 0.038329992 | J65: =[64]Summary!$E$14/100 -> 0.198451 | K65: =[64]Summary!$C$40 -> 0.99265782 | L65: =[64]Summary!$C$54 -> 0 | M65: ='[64]Glbl Expsr'!$D$2 -> 0.46525073 | N65: ='[64]Glbl Expsr'!$D$3 -> 0.46525073 | O65: \\pim-cpt-statpro\SPC_602\Client\Profiles\PIM\Exports\NESEQU Derv Calc 6Apr2022.xlsx | P65: NESEQU Mandate
A66: PPSNAM | B66: =[65]Summary!$G$3 -> ≠ UT | C66: =[65]Summary!$E$1 -> 5 | D66: =[65]Summary!$C$34 -> 0.34005022 | E66: =[65]Summary!$E$34/100 -> 0.34005022 | F66: =[65]Summary!$C$36 -> 0.14896869 | G66: =[65]Summary!$C$32 -> 0 | H66: =[65]Summary!$E$6/100 -> 0 | I66: =[65]Summary!$E$10/100 -> 0 | J66: =[65]Summary!$E$14/100 -> 0 | K66: =[65]Summary!$C$40 -> 2.2573325 | L66: =[65]Summary!$C$54 -> 20.716682 | M66: ='[65]Glbl Expsr'!$D$2 -> 2.2193856 | N66: ='[65]Glbl Expsr'!$D$3 -> 2.2193856 | O66: \\pim-cpt-statpro\SPC_602\Client\Profiles\PIM\Exports\PPSNAM Derv Calc 6Apr2022.xlsx | P66: PPSNAM Mandate
A67: ENGENMBF | B67: =[66]Summary!$G$3 -> ≠ UT | C67: =[66]Summary!$E$1 -> 4 | D67: =[66]Summary!$C$34 -> 0.026913899 | E67: =[66]Summary!$E$34/100 -> 0.026913899 | F67: =[66]Summary!$C$36 -> 0.53939459 | G67: =[66]Summary!$C$32 -> 0 | H67: =[66]Summary!$E$6/100 -> 0.18080561 | I67: =[66]Summary!$E$10/100 -> 0.0024552069 | J67: =[66]Summary!$E$14/100 -> 0.077266517 | K67: =[66]Summary!$C$40 -> 0.26617114 | L67: =[66]Summary!$C$54 -> 0 | M67: ='[66]Glbl Expsr'!$D$2 -> 0.40592791 | N67: ='[66]Glbl Expsr'!$D$3 -> 0.095009306 | O67: \\pim-cpt-statpro\SPC_602\Client\Profiles\PIM\Exports\ENGENMBF Derv Calc 6Apr2022.xlsx | P67: ENGENMBF Mandate
A68: PLMED | B68: =[67]Summary!$G$3 -> ≠ UT | C68: =[67]Summary!$E$1 -> 4 | D68: =[67]Summary!$C$34 -> 0.052054816 | E68: =[67]Summary!$E$34/100 -> 0.052054816 | F68: =[67]Summary!$C$36 -> 0.54928121 | G68: =[67]Summary!$C$32 -> 0 | H68: =[67]Summary!$E$6/100 -> 0.19617424 | I68: =[67]Summary!$E$10/100 -> 0.0024544533 | J68: =[67]Summary!$E$14/100 -> 0.0774701 | K68: =[67]Summary!$C$40 -> 0.23280053 | L68: =[67]Summary!$C$54 -> 0 | M68: ='[67]Glbl Expsr'!$D$2 -> 0.38805549 | N68: ='[67]Glbl Expsr'!$D$3 -> 0.077649449 | O68: \\pim-cpt-statpro\SPC_602\Client\Profiles\PIM\Exports\PLMED Derv Calc 6Apr2022.xlsx | P68: PLMED Mandate
A69: GAEMBF | B69: =[68]Summary!$G$3 -> ≠ UT | C69: =[68]Summary!$E$1 -> 4 | D69: =[68]Summary!$C$34 -> 0.066435256 | E69: =[68]Summary!$E$34/100 -> 0.066435256 | F69: =[68]Summary!$C$36 -> 0.53472296 | G69: =[68]Summary!$C$32 -> 0 | H69: =[68]Summary!$E$6/100 -> 0.18872322 | I69: =[68]Summary!$E$10/100 -> 0.0024727652 | J69: =[68]Summary!$E$14/100 -> 0.077776726 | K69: =[68]Summary!$C$40 -> 0.2334199 | L69: =[68]Summary!$C$54 -> 0 | M69: ='[68]Glbl Expsr'!$D$2 -> 0.38630358 | N69: ='[68]Glbl Expsr'!$D$3 -> 0.07708471 | O69: \\pim-cpt-statpro\SPC_602\Client\Profiles\PIM\Exports\GAEMBF Derv Calc 6Apr2022.xlsx | P69: GAEMBF Mandate
A70: PICPROV | B70: =[69]Summary!$G$3 -> ≠ UT | C70: =[69]Summary!$E$1 -> 0 | D70: =[69]Summary!$C$34 -> 0.00022616534 | E70: =[69]Summary!$E$34/100 -> 0.00022616534 | F70: =[69]Summary!$C$36 -> 0 | G70: =[69]Summary!$C$32 -> 0 | H70: =[69]Summary!$E$6/100 -> 0 | I70: =[69]Summary!$E$10/100 -> 0 | J70: =[69]Summary!$E$14/100 -> 0 | K70: =[69]Summary!$C$40 -> 0 | L70: =[69]Summary!$C$54 -> 0 | M70: ='[69]Glbl Expsr'!$D$2 -> 0 | N70: ='[69]Glbl Expsr'!$D$3 -> 0 | O70: \\pim-cpt-statpro\SPC_602\Client\Profiles\PIM\Exports\PICPROV Derv Calc 6Apr2022.xlsx | P70: PICPROV Mandate
A71: ECICBALC | B71: =[70]Summary!$G$3 -> ≠ UT | C71: =[70]Summary!$E$1 -> 0 | D71: =[70]Summary!$C$34 -> 0.0013665616 | E71: =[70]Summary!$E$34/100 -> 0.0013665616 | F71: =[70]Summary!$C$36 -> 0.20375182 | G71: =[70]Summary!$C$32 -> 0 | H71: =[70]Summary!$E$6/100 -> 0 | I71: =[70]Summary!$E$10/100 -> 0.17560309 | J71: =[70]Summary!$E$14/100 -> 0.41816658 | K71: =[70]Summary!$C$40 -> 0.79488162 | L71: =[70]Summary!$C$54 -> 28.54072 | M71: ='[70]Glbl Expsr'!$D$2 -> 0 | N71: ='[70]Glbl Expsr'!$D$3 -> 0 | O71: \\pim-cpt-statpro\SPC_602\Client\Profiles\PIM\Exports\ECICBALC Derv Calc 6Apr2022.xlsx | P71: ECICBALC Mandate
A72: SISLP | B72: =[71]Summary!$G$3 -> ≠ UT | C72: =[71]Summary!$E$1 -> 0 | D72: =[71]Summary!$C$34 -> 0.0033739815 | E72: =[71]Summary!$E$34/100 -> 0.0033739815 | F72: =[71]Summary!$C$36 -> 0.94846202 | G72: =[71]Summary!$C$32 -> 0 | H72: =[71]Summary!$E$6/100 -> 0 | I72: =[71]Summary!$E$10/100 -> 0 | J72: =[71]Summary!$E$14/100 -> 0 | K72: =[71]Summary!$C$40 -> 0 | L72: =[71]Summary!$C$54 -> 0 | M72: ='[71]Glbl Expsr'!$D$2 -> 0 | N72: ='[71]Glbl Expsr'!$D$3 -> 0 | O72: \\pim-cpt-statpro\SPC_602\Client\Profiles\PIM\Exports\SISLP Derv Calc 6Apr2022.xlsx | P72: SISLP Mandate
A73: SILEQF | B73: =[72]Summary!$G$3 -> ≠ UT | C73: =[72]Summary!$E$1 -> 0 | D73: =[72]Summary!$C$34 -> 0.0037735423 | E73: =[72]Summary!$E$34/100 -> 0.0037735423 | F73: =[72]Summary!$C$36 -> 0 | G73: =[72]Summary!$C$32 -> 0 | H73: =[72]Summary!$E$6/100 -> 0 | I73: =[72]Summary!$E$10/100 -> 0.40608401 | J73: =[72]Summary!$E$14/100 -> 0.91193662 | K73: =[72]Summary!$C$40 -> 0.99622646 | L73: =[72]Summary!$C$54 -> 0 | M73: ='[72]Glbl Expsr'!$D$2 -> 0 | N73: ='[72]Glbl Expsr'!$D$3 -> 0 | O73: \\pim-cpt-statpro\SPC_602\Client\Profiles\PIM\Exports\SILEQF Derv Calc 6Apr2022.xlsx | P73: SILEQF Mandate
A74: SHNIPF | B74: =[73]Summary!$G$3 -> ≠ UT | C74: =[73]Summary!$E$1 -> 0 | D74: =[73]Summary!$C$34 -> 0.24908775 | E74: =[73]Summary!$E$34/100 -> 0.24908775 | F74: =[73]Summary!$C$36 -> 0.69915416 | G74: =[73]Summary!$C$32 -> 0 | H74: =[73]Summary!$E$6/100 -> 0.084928238 | I74: =[73]Summary!$E$10/100 -> 0 | J74: =[73]Summary!$E$14/100 -> 0 | K74: =[73]Summary!$C$40 -> 0.051706024 | L74: =[73]Summary!$C$54 -> 0 | M74: ='[73]Glbl Expsr'!$D$2 -> 0 | N74: ='[73]Glbl Expsr'!$D$3 -> 0 | O74: \\pim-cpt-statpro\SPC_602\Client\Profiles\PIM\Exports\SHNIPF Derv Calc 6Apr2022.xlsx | P74: SHNIPF Mandate
A75: NGKINC | B75: =[74]Summary!$G$3 -> ≠ UT | C75: =[74]Summary!$E$1 -> 0 | D75: =[74]Summary!$C$34 -> 0.35447371 | E75: =[74]Summary!$E$34/100 -> 0.35447371 | F75: =[74]Summary!$C$36 -> 0.59734229 | G75: =[74]Summary!$C$32 -> 0 | H75: =[74]Summary!$E$6/100 -> 0.086169346 | I75: =[74]Summary!$E$10/100 -> 0 | J75: =[74]Summary!$E$14/100 -> 0 | K75: =[74]Summary!$C$40 -> 0.048135573 | L75: =[74]Summary!$C$54 -> 0 | M75: ='[74]Glbl Expsr'!$D$2 -> 0 | N75: ='[74]Glbl Expsr'!$D$3 -> 0 | O75: \\pim-cpt-statpro\SPC_602\Client\Profiles\PIM\Exports\NGKINC Derv Calc 6Apr2022.xlsx | P75: NGKINC Mandate
A76: AMMIPF | B76: =[75]Summary!$G$3 -> ≠ UT | C76: =[75]Summary!$E$1 -> 0 | D76: =[75]Summary!$C$34 -> 0.44461666 | E76: =[75]Summary!$E$34/100 -> 0.44461666 | F76: =[75]Summary!$C$36 -> 0.55538334 | G76: =[75]Summary!$C$32 -> 0 | H76: =[75]Summary!$E$6/100 -> 0.25836517 | I76: =[75]Summary!$E$10/100 -> 0 | J76: =[75]Summary!$E$14/100 -> 0 | K76: =[75]Summary!$C$40 -> 0 | L76: =[75]Summary!$C$54 -> 0 | M76: ='[75]Glbl Expsr'!$D$2 -> 0 | N76: ='[75]Glbl Expsr'!$D$3 -> 0 | O76: \\pim-cpt-statpro\SPC_602\Client\Profiles\PIM\Exports\AMMIPF Derv Calc 6Apr2022.xlsx | P76: AMMIPF Mandate
A77: MEDINC | B77: =[76]Summary!$G$3 -> ≠ UT | C77: =[76]Summary!$E$1 -> 0 | D77: =[76]Summary!$C$34 -> 0.53402459 | E77: =[76]Summary!$E$34/100 -> 0.53402459 | F77: =[76]Summary!$C$36 -> 0.32152803 | G77: =[76]Summary!$C$32 -> 0 | H77: =[76]Summary!$E$6/100 -> 0.11023489 | I77: =[76]Summary!$E$10/100 -> 0 | J77: =[76]Summary!$E$14/100 -> 0 | K77: =[76]Summary!$C$40 -> 0.094706446 | L77: =[76]Summary!$C$54 -> 0 | M77: ='[76]Glbl Expsr'!$D$2 -> 0 | N77: ='[76]Glbl Expsr'!$D$3 -> 0 | O77: \\pim-cpt-statpro\SPC_602\Client\Profiles\PIM\Exports\MEDINC Derv Calc 6Apr2022.xlsx | P77: MEDINC Mandate

Sheet Static
A1: 44181 | B1: Day of Reconciliation | D1: =HYPERLINK("C:\Users\hilton.netta\py","Back to py") -> Back to py
A2: 44190 | B2: Christmas Day
A3: 44191 | B3: Boxing Day
A4: 44197 | B4: New Year's Day
A5: 44277 | B5: Human Rights Day
A6: 44288 | B6: Good Friday
A7: 44291 | B7: Family Day
A8: 44313 | B8: Freedom Day
A9: 44317 | B9: International Workers' Day
A10: 44363 | B10: Youth Day (in South Africa)
A11: 44417 | B11: National Women's Day
A12: 44463 | B12: Heritage Day
A13: 44501 | B13: Election Day
... A29: 44921 | B29: Day of Goodwill

Sheet Summary
A1: =Data!$A$2&" ("&Data!$AK$2&")" -> 0 (44676) | B1: Current Exposure | C1: Market Value | E1: =COUNTIF(Data!$B:$B,"Derivatives")+COUNTIF(Data!$B:$B,"Forwards")+COUNTIF(Data!$B:$B,"Swaps") -> 0 | F1: ="derivative"&IF(E1=1,"","s") -> derivatives | G1: =HYPERLINK("J:\PProfile Operations\Legal\Legal and Compliance Framework\Hilton\Client Mandates\"&SUBSTITUTE(Data!$AK$2,"_C","")&" Rules.docx","Mandate") -> Mandate | H1: {="SA equity indices ("&SUMPRODUCT((Data!$C:$C="Equity Derivatives")*(Data!$W:$W="ZAR"))&")"} -> SA equity indices (0) | I1: {=IF(ISNA(MATCH(1,("Equity derivatives"=Data!C:C)*("ZAR"=Data!W:W),0)),"",INDEX(Data!D:D,MATCH(1,("Equity derivatives"=Data!C:C)*("ZAR"=Data!W:W),0)))} | J1: {=IF(COUNTA($I$1:I$1)<COUNTIFS(Data!$C:$C,"Equity derivatives",Data!$W:$W,"ZAR"),INDEX(Data!$D:$D,MATCH(I$1,Data!$D:$D,0)+1),"")} | K1: {=IF(COUNTA($I$1:J$1)<COUNTIFS(Data!$C:$C,"Equity derivatives",Data!$W:$W,"ZAR"),INDEX(Data!$D:$D,MATCH(J$1,Data!$D:$D,0)+1),"")} | L1: {=IF(COUNTA($I$1:K$1)<COUNTIFS(Data!$C:$C,"Equity derivatives",Data!$W:$W,"ZAR"),INDEX(Data!$D:$D,MATCH(K$1,Data!$D:$D,0)+1),"")} | M1: {=IF(COUNTA($I$1:L$1)<COUNTIFS(Data!$C:$C,"Equity derivatives",Data!$W:$W,"ZAR"),INDEX(Data!$D:$D,MATCH(L$1,Data!$D:$D,0)+1),"")} | N1: {=IF(COUNTA($I$1:M$1)<COUNTIFS(Data!$C:$C,"Equity derivatives",Data!$W:$W,"ZAR"),INDEX(Data!$D:$D,MATCH(M$1,Data!$D:$D,0)+1),"")} | O1: {=IF(COUNTA($I$1:N$1)<COUNTIFS(Data!$C:$C,"Equity derivatives",Data!$W:$W,"ZAR"),INDEX(Data!$D:$D,MATCH(N$1,Data!$D:$D,0)+1),"")} | P1: {=IF(COUNTA($I$1:O$1)<COUNTIFS(Data!$C:$C,"Equity derivatives",Data!$W:$W,"ZAR"),INDEX(Data!$D:$D,MATCH(O$1,Data!$D:$D,0)+1),"")} | Q1: {=IF(COUNTA($I$1:P$1)<COUNTIFS(Data!$C:$C,"Equity derivatives",Data!$W:$W,"ZAR"),INDEX(Data!$D:$D,MATCH(P$1,Data!$D:$D,0)+1),"")} | ... BH1: {=IF(COUNTA($I$1:BG$1)<COUNTIFS(Data!$C:$C,"Equity derivatives",Data!$W:$W,"ZAR"),INDEX(Data!$D:$D,MATCH(BG$1,Data!$D:$D,0)+1),"")}
A2: =HYPERLINK("https://pimportalprod2015.eagleaccess.com/Default.aspx","Derivative Cover "&TEXT(Data!$AJ$2,"dddd d mmmm yyyy")) -> Derivative Cover Saturday 0 January 1900 | B2: R | C2: % | F2: ASSET COVER CHECK | G2: {=CELL("filename")} -> C:\Users\hilton.netta\py\[derv - Copy.xlsx]Deltas | H2: =IF(ISNA(SUM(I2:BH2)),0,SUM(I2:BH2)) -> 0 | I2: =IF(I$1="","",INDEX(Data!$AH:$AH,MATCH(I$1,Data!$D:$D,0))/$B$4) | J2: =IF(J$1="","",INDEX(Data!$AH:$AH,MATCH(J$1,Data!$D:$D,0))/$B$4) | K2: =IF(K$1="","",INDEX(Data!$AH:$AH,MATCH(K$1,Data!$D:$D,0))/$B$4) | L2: =IF(L$1="","",INDEX(Data!$AH:$AH,MATCH(L$1,Data!$D:$D,0))/$B$4) | M2: =IF(M$1="","",INDEX(Data!$AH:$AH,MATCH(M$1,Data!$D:$D,0))/$B$4) | N2: =IF(N$1="","",INDEX(Data!$AH:$AH,MATCH(N$1,Data!$D:$D,0))/$B$4) | O2: =IF(O$1="","",INDEX(Data!$AH:$AH,MATCH(O$1,Data!$D:$D,0))/$B$4) | P2: =IF(P$1="","",INDEX(Data!$AH:$AH,MATCH(P$1,Data!$D:$D,0))/$B$4) | ... BH2: =IF(BH$1="","",INDEX(Data!$AH:$AH,MATCH(BH$1,Data!$D:$D,0))/$B$4)
A3: UT | E3: 0 | F3: Total direct SA bonds available to cover short exposures | G3: =_xlfn.XLOOKUP(Data!AK$2,[77]Funds!$A:$A,[77]Funds!$E:$E) -> #N/A
A4: Fund NAV | B4: =SUM(Data!$L:$L) -> 0 | C4: =SUM(Data!$N:$N)/100 -> 3137.8749 | E4: =IF(ISNA(MATCH($G4,Data!$E:$E,0)),0,_xlfn.XLOOKUP($G4,Data!$E:$E,Data!$AI:$AI))+IF(ISNA(MATCH(186,Data!$E:$E,0)),0,_xlfn.XLOOKUP(186,Data!$E:$E,Data!$AI:$AI)) -> 0 | F4: Total same or similar bonds available to cover short exposures | G4: R186 | H4: {="World equity indices ("&SUMPRODUCT((Data!$C:$C="Equity Derivatives")*(Data!$W:$W<>"ZAR"))&")"} -> World equity indices (0) | I4: {=IF(ISNA(MATCH(1,("Equity derivatives"=Data!C:C)*("ZAR"<>Data!W:W),0)),"",INDEX(Data!D:D,MATCH(1,("Equity derivatives"=Data!C:C)*("ZAR"<>Data!W:W),0)))} | J4: {=IF(COUNTA($I$4:I$4)<COUNTIFS(Data!$C:$C,"Equity derivatives",Data!$W:$W,"<>ZAR"),INDEX(Data!$D:$D,MATCH(I$4,Data!$D:$D,0)+1),"")} | K4: {=IF(COUNTA($I$4:J$4)<COUNTIFS(Data!$C:$C,"Equity derivatives",Data!$W:$W,"<>ZAR"),INDEX(Data!$D:$D,MATCH(J$4,Data!$D:$D,0)+1),"")} | L4: {=IF(COUNTA($I$4:K$4)<COUNTIFS(Data!$C:$C,"Equity derivatives",Data!$W:$W,"<>ZAR"),INDEX(Data!$D:$D,MATCH(K$4,Data!$D:$D,0)+1),"")} | M4: {=IF(COUNTA($I$4:L$4)<COUNTIFS(Data!$C:$C,"Equity derivatives",Data!$W:$W,"<>ZAR"),INDEX(Data!$D:$D,MATCH(L$4,Data!$D:$D,0)+1),"")} | N4: {=IF(COUNTA($I$4:M$4)<COUNTIFS(Data!$C:$C,"Equity derivatives",Data!$W:$W,"<>ZAR"),INDEX(Data!$D:$D,MATCH(M$4,Data!$D:$D,0)+1),"")} | O4: {=IF(COUNTA($I$4:N$4)<COUNTIFS(Data!$C:$C,"Equity derivatives",Data!$W:$W,"<>ZAR"),INDEX(Data!$D:$D,MATCH(N$4,Data!$D:$D,0)+1),"")} | P4: {=IF(COUNTA($I$4:O$4)<COUNTIFS(Data!$C:$C,"Equity derivatives",Data!$W:$W,"<>ZAR"),INDEX(Data!$D:$D,MATCH(O$4,Data!$D:$D,0)+1),"")} | Q4: {=IF(COUNTA($I$4:P$4)<COUNTIFS(Data!$C:$C,"Equity derivatives",Data!$W:$W,"<>ZAR"),INDEX(Data!$D:$D,MATCH(P$4,Data!$D:$D,0)+1),"")} | ... BH4: {=IF(COUNTA($I$4:BG$4)<COUNTIFS(Data!$C:$C,"Equity derivatives",Data!$W:$W,"<>ZAR"),INDEX(Data!$D:$D,MATCH(BG$4,Data!$D:$D,0)+1),"")}
E5: =MIN(0,$H$8*100) -> 0 | F5: Net short derivative exposure | H5: =IF(ISNA(SUM(I5:BH5)),0,SUM(I5:BH5)) -> 0 | I5: =IF(I$4="","",INDEX(Data!$AH:$AH,MATCH(I$4,Data!$D:$D,0))/$B$4) | J5: =IF(J$4="","",INDEX(Data!$AH:$AH,MATCH(J$4,Data!$D:$D,0))/$B$4) | K5: =IF(K$4="","",INDEX(Data!$AH:$AH,MATCH(K$4,Data!$D:$D,0))/$B$4) | L5: =IF(L$4="","",INDEX(Data!$AH:$AH,MATCH(L$4,Data!$D:$D,0))/$B$4) | M5: =IF(M$4="","",INDEX(Data!$AH:$AH,MATCH(M$4,Data!$D:$D,0))/$B$4) | N5: =IF(N$4="","",INDEX(Data!$AH:$AH,MATCH(N$4,Data!$D:$D,0))/$B$4) | O5: =IF(O$4="","",INDEX(Data!$AH:$AH,MATCH(O$4,Data!$D:$D,0))/$B$4) | P5: =IF(P$4="","",INDEX(Data!$AH:$AH,MATCH(P$4,Data!$D:$D,0))/$B$4) | ... BH5: =IF(BH$4="","",INDEX(Data!$AH:$AH,MATCH(BH$4,Data!$D:$D,0))/$B$4)
A6: Assets in liquid form | B6: =SUM(B7:B11) -> 0 | C6: =SUM(C7:C11) -> #DIV/0! | E6: =SUM(E3:E5) -> 0 | F6: =IF($E6>=0,"Adequate","INADEQUATE")&" short SA bond bond derivative cover [BN90 16(1)(a) & (b)]" -> Adequate short SA bond bond derivative cover [BN90 16(1)(a) & (b)]
A7: Cash (incl MMFs, excl margin) | B7: =SUMIF(Data!$B:$B,"CASH",Data!$AH:$AH)-SUMIF(Data!$E:$E,"SAFEX",Data!$AH:$AH)-SUMIF(Data!$E:$E,"VARMARG",Data!$AH:$AH) -> 0 | C7: =$B7/$B$4 -> #DIV/0! | H7: {="SA bond indices ("&SUMPRODUCT((Data!$C:$C="Bond Derivatives")*(Data!$W:$W="ZAR"))&")"} -> SA bond indices (0) | I7: {=IF(ISNA(MATCH(1,("Bond derivatives"=Data!C:C)*("ZAR"=Data!W:W),0)),"",INDEX(Data!D:D,MATCH(1,("Bond derivatives"=Data!C:C)*("ZAR"=Data!W:W),0)))} | J7: {=IF(I7<>"",IF(COUNTA($I$7:I$7)<COUNTIF(Data!$C:$C,"Bond Derivatives"),INDEX(Data!$D:$D,MATCH(I$7,Data!$D:$D,0)+1),""),"")} | K7: {=IF(COUNTA($I$7:J$7)<COUNTIF(Data!$C:$C,"Bond derivatives"),INDEX(Data!$D:$D,MATCH(J$7,Data!$D:$D,0)+1),"")} | L7: {=IF(COUNTA($I$7:K$7)<COUNTIF(Data!$C:$C,"Bond derivatives"),INDEX(Data!$D:$D,MATCH(K$7,Data!$D:$D,0)+1),"")} | M7: {=IF(COUNTA($I$7:L$7)<COUNTIF(Data!$C:$C,"Bond derivatives"),INDEX(Data!$D:$D,MATCH(L$7,Data!$D:$D,0)+1),"")} | N7: {=IF(COUNTA($I$7:M$7)<COUNTIF(Data!$C:$C,"Bond derivatives"),INDEX(Data!$D:$D,MATCH(M$7,Data!$D:$D,0)+1),"")} | O7: {=IF(COUNTA($I$7:N$7)<COUNTIF(Data!$C:$C,"Bond derivatives"),INDEX(Data!$D:$D,MATCH(N$7,Data!$D:$D,0)+1),"")} | P7: {=IF(COUNTA($I$7:O$7)<COUNTIF(Data!$C:$C,"Bond derivatives"),INDEX(Data!$D:$D,MATCH(O$7,Data!$D:$D,0)+1),"")} | Q7: {=IF(COUNTA($I$7:P$7)<COUNTIF(Data!$C:$C,"Bond derivatives"),INDEX(Data!$D:$D,MATCH(P$7,Data!$D:$D,0)+1),"")} | R7: {=IF(COUNTA($I$7:Q$7)<COUNTIF(Data!$C:$C,"Bond derivatives"),INDEX(Data!$D:$D,MATCH(Q$7,Data!$D:$D,0)+1),"")} | ... BH7: {=IF(COUNTA($I$7:BG$7)<COUNTIF(Data!$C:$C,"Bond derivatives"),INDEX(Data!$D:$D,MATCH(BG$7,Data!$D:$D,0)+1),"")}
A8: ="Money market instruments"&IF($A3="UT"," (excl CLNs and > 13 month bonds)","") -> Money market instruments (excl CLNs and > 13 month bonds) | B8: {=IF($A3="UT",SUMPRODUCT((Data!$B:$B="MONEY MARKET")*((Data!$P:$P<Data!$AJ$2+397)*(Data!$V:$V<>"CLN")),(Data!$AH:$AH)),SUMIF(Data!$B:$B,"MONEY MARKET",Data!$AH:$AH))} -> 0 | C8: =$B8/$B$4 -> #DIV/0! | E8: =SUM(BM!$V:$V) -> 0 | F8: Total direct MSCI ACWI assets available to cover short exposures | H8: =SUM(I8:BH8) -> 0 | I8: =IF(I$7="","",INDEX(Data!$AH:$AH,MATCH(I$7,Data!$D:$D,0))/$B$4) | J8: =IF(J$7="","",INDEX(Data!$AH:$AH,MATCH(J$7,Data!$D:$D,0))/$B$4) | K8: =IF(K$7="","",INDEX(Data!$AH:$AH,MATCH(K$7,Data!$D:$D,0))/$B$4) | L8: =IF(L$7="","",INDEX(Data!$AH:$AH,MATCH(L$7,Data!$D:$D,0))/$B$4) | M8: =IF(M$7="","",INDEX(Data!$AH:$AH,MATCH(M$7,Data!$D:$D,0))/$B$4) | N8: =IF(N$7="","",INDEX(Data!$AH:$AH,MATCH(N$7,Data!$D:$D,0))/$B$4) | O8: =IF(O$7="","",INDEX(Data!$AH:$AH,MATCH(O$7,Data!$D:$D,0))/$B$4) | P8: =IF(P$7="","",INDEX(Data!$AH:$AH,MATCH(P$7,Data!$D:$D,0))/$B$4) | ... BH8: =IF(BH$7="","",INDEX(Data!$AH:$AH,MATCH(BH$7,Data!$D:$D,0))/$B$4)
A9: Bonds (excl > 13 month bonds) | B9: {=IF($A3="UT",SUMPRODUCT((Data!$B:$B="BONDS")*((Data!$P:$P<Data!$AJ$2+397)*(Data!$V:$V<>"CLN")),(Data!$AH:$AH)),SUMIF(Data!$B:$B,"BONDS",Data!$AH:$AH))} -> 0 | C9: =$B9/$B$4 -> #DIV/0! | E9: =MIN(0,$H$5*100) -> 0 | F9: Net short derivative exposure
A10: SAFEX [BN90 19(2)] | B10: =SUMIF(Data!$E:$E,"SAFEX",Data!$AH:$AH) -> 0 | C10: =$B10/$B$4 -> #DIV/0! | E10: =SUM(E8:E9) -> 0 | F10: =IF($E10>=0,"Adequate","INADEQUATE")&" short MSCI derivative cover [BN90 16(1)(a) & (b)]" -> Adequate short MSCI derivative cover [BN90 16(1)(a) & (b)] | H10: {="World bond indices ("&SUMPRODUCT((Data!$C:$C="Bond Derivatives")*(Data!$W:$W<>"ZAR"))&")"} -> World bond indices (0) | I10: {=IF(ISNA(MATCH(1,("bond derivatives"=Data!C:C)*("ZAR"<>Data!W:W),0)),"",INDEX(Data!D:D,MATCH(1,("bond derivatives"=Data!C:C)*("ZAR"<>Data!W:W),0)))} | J10: {=IF(I10<>"",IF(COUNTA($I$10:I$10)<COUNTIF(Data!$C:$C,"Bond Derivatives"),INDEX(Data!$D:$D,MATCH(I$10,Data!$D:$D,0)+1),""),"")} | K10: {=IF(COUNTA($I$10:J$10)<COUNTIF(Data!$C:$C,"Bond Derivatives"),INDEX(Data!$D:$D,MATCH(J$10,Data!$D:$D,0)+1),"")} | L10: {=IF(COUNTA($I$10:K$10)<COUNTIF(Data!$C:$C,"Bond Derivatives"),INDEX(Data!$D:$D,MATCH(K$10,Data!$D:$D,0)+1),"")} | M10: {=IF(COUNTA($I$10:L$10)<COUNTIF(Data!$C:$C,"Bond Derivatives"),INDEX(Data!$D:$D,MATCH(L$10,Data!$D:$D,0)+1),"")} | N10: {=IF(COUNTA($I$10:M$10)<COUNTIF(Data!$C:$C,"Bond Derivatives"),INDEX(Data!$D:$D,MATCH(M$10,Data!$D:$D,0)+1),"")} | O10: {=IF(COUNTA($I$10:N$10)<COUNTIF(Data!$C:$C,"Bond Derivatives"),INDEX(Data!$D:$D,MATCH(N$10,Data!$D:$D,0)+1),"")} | P10: {=IF(COUNTA($I$10:O$10)<COUNTIF(Data!$C:$C,"Bond Derivatives"),INDEX(Data!$D:$D,MATCH(O$10,Data!$D:$D,0)+1),"")} | Q10: {=IF(COUNTA($I$10:P$10)<COUNTIF(Data!$C:$C,"Bond Derivatives"),INDEX(Data!$D:$D,MATCH(P$10,Data!$D:$D,0)+1),"")} | R10: {=IF(COUNTA($I$10:Q$10)<COUNTIF(Data!$C:$C,"Bond Derivatives"),INDEX(Data!$D:$D,MATCH(Q$10,Data!$D:$D,0)+1),"")} | ... BH10: {=IF(COUNTA($I$10:BG$10)<COUNTIF(Data!$C:$C,"Bond Derivatives"),INDEX(Data!$D:$D,MATCH(BG$10,Data!$D:$D,0)+1),"")}
A11: Variation Margin [BN90 19(2)] | B11: =SUMIF(Data!$E:$E,"VARMARG",Data!$AH:$AH) -> 0 | C11: =$B11/$B$4 -> #DIV/0! | H11: =SUM(I11:BH11) -> 0 | I11: =IF(I$10="","",INDEX(Data!$AH:$AH,MATCH(I$10,Data!$D:$D,0))/$B$4) | J11: =IF(J$10="","",INDEX(Data!$AH:$AH,MATCH(J$10,Data!$D:$D,0))/$B$4) | K11: =IF(K$10="","",INDEX(Data!$AH:$AH,MATCH(K$10,Data!$D:$D,0))/$B$4) | L11: =IF(L$10="","",INDEX(Data!$AH:$AH,MATCH(L$10,Data!$D:$D,0))/$B$4) | M11: =IF(M$10="","",INDEX(Data!$AH:$AH,MATCH(M$10,Data!$D:$D,0))/$B$4) | N11: =IF(N$10="","",INDEX(Data!$AH:$AH,MATCH(N$10,Data!$D:$D,0))/$B$4) | O11: =IF(O$10="","",INDEX(Data!$AH:$AH,MATCH(O$10,Data!$D:$D,0))/$B$4) | P11: =IF(P$10="","",INDEX(Data!$AH:$AH,MATCH(P$10,Data!$D:$D,0))/$B$4) | ... BH11: =IF(BH$10="","",INDEX(Data!$AH:$AH,MATCH(BH$10,Data!$D:$D,0))/$B$4)
E12: =SUMIF(BM!$A:$A,"J203",BM!$E:$E) -> 0 | F12: Total direct ALSI assets available to cover short exposures
A13: less Sold currency futures to be covered by cash [BN90 16(1)(i)] | B13: =SUM(B14:B14) -> 0 | C13: =SUM(C14:C14) -> #DIV/0! | E13: =MIN(0, $H$2*100) -> 0 | F13: Net short derivative exposure | H13: ="Currency futures ("&COUNTIF(Data!$C:$C,"Currency Derivatives")&")" -> Currency futures (0) | I13: =IF(ISNA(IF(ISNA(MATCH("Currency Derivatives",Data!$C:$C,0)),"",INDEX(Data!$D:$D,MATCH("Currency Derivatives",Data!$C:$C,0)))),"",IF(ISNA(MATCH("Currency Derivatives",Data!$C:$C,0)),"",INDEX(Data!$D:$D,MATCH("Currency Derivatives",Data!$C:$C,0)))) | J13: {=IF(COUNTA($I$13:I$13)<COUNTIF(Data!$C:$C,"Currency derivatives"),INDEX(Data!$D:$D,MATCH(I$13,Data!$D:$D,0)+1),"")} | K13: {=IF(COUNTA($I$13:J$13)<COUNTIF(Data!$C:$C,"Currency derivatives"),INDEX(Data!$D:$D,MATCH(J$13,Data!$D:$D,0)+1),"")} | L13: {=IF(COUNTA($I$13:K$13)<COUNTIF(Data!$C:$C,"Currency derivatives"),INDEX(Data!$D:$D,MATCH(K$13,Data!$D:$D,0)+1),"")} | M13: {=IF(COUNTA($I$13:L$13)<COUNTIF(Data!$C:$C,"Currency derivatives"),INDEX(Data!$D:$D,MATCH(L$13,Data!$D:$D,0)+1),"")} | N13: {=IF(COUNTA($I$13:M$13)<COUNTIF(Data!$C:$C,"Currency derivatives"),INDEX(Data!$D:$D,MATCH(M$13,Data!$D:$D,0)+1),"")} | O13: {=IF(COUNTA($I$13:N$13)<COUNTIF(Data!$C:$C,"Currency derivatives"),INDEX(Data!$D:$D,MATCH(N$13,Data!$D:$D,0)+1),"")} | P13: {=IF(COUNTA($I$13:O$13)<COUNTIF(Data!$C:$C,"Currency derivatives"),INDEX(Data!$D:$D,MATCH(O$13,Data!$D:$D,0)+1),"")} | Q13: {=IF(COUNTA($I$13:P$13)<COUNTIF(Data!$C:$C,"Currency derivatives"),INDEX(Data!$D:$D,MATCH(P$13,Data!$D:$D,0)+1),"")} | ... BH13: {=IF(COUNTA($I$13:BG$13)<COUNTIF(Data!$C:$C,"Currency derivatives"),INDEX(Data!$D:$D,MATCH(BG$13,Data!$D:$D,0)+1),"")}
A14: Currency Derivatives | B14: =IF(SUMIF(Data!$C:$C,$A14,Data!$AH:$AH)<0,SUMIF(Data!$C:$C,$A14,Data!$AH:$AH),0) -> 0 | C14: =$B14/$B$4 -> #DIV/0! | E14: =SUM(E12:E13) -> 0 | F14: =IF($E14>=0,"Adequate","INADEQUATE")&" short ALSI derivative cover [BN90 16(1)(a) & (b)]" -> Adequate short ALSI derivative cover [BN90 16(1)(a) & (b)] | H14: =SUM(I14:BH14) -> 0 | I14: =IF(I$13="","",INDEX(Data!$AH:$AH,MATCH(I$13,Data!$D:$D,0))/$B$4) | J14: =IF(J$13="","",INDEX(Data!$AH:$AH,MATCH(J$13,Data!$D:$D,0))/$B$4) | K14: =IF(K$13="","",INDEX(Data!$AH:$AH,MATCH(K$13,Data!$D:$D,0))/$B$4) | L14: =IF(L$13="","",INDEX(Data!$AH:$AH,MATCH(L$13,Data!$D:$D,0))/$B$4) | M14: =IF(M$13="","",INDEX(Data!$AH:$AH,MATCH(M$13,Data!$D:$D,0))/$B$4) | N14: =IF(N$13="","",INDEX(Data!$AH:$AH,MATCH(N$13,Data!$D:$D,0))/$B$4) | O14: =IF(O$13="","",INDEX(Data!$AH:$AH,MATCH(O$13,Data!$D:$D,0))/$B$4) | P14: =IF(P$13="","",INDEX(Data!$AH:$AH,MATCH(P$13,Data!$D:$D,0))/$B$4) | ... BH14: =IF(BH$13="","",INDEX(Data!$AH:$AH,MATCH(BH$13,Data!$D:$D,0))/$B$4)
A16: less Net negative MtM OTC derivative exposure [BN90 17(1)(a)] | B16: =SUM(B17:B19) -> #VALUE! | C16: =SUM(C17:C19) -> #DIV/0! | E16: ='Glbl Expsr'!$D$3 -> #DIV/0! | F16: Leverage (net effective exposure ÷ NAV) | H16: ="Currency forwards ("&COUNTIF(Data!$C:$C,"Forwards")&")" -> Currency forwards (0) | I16: =IF(ISNA(IF(ISNA(MATCH("Forwards",Data!$C:$C,0)),"",INDEX(Data!$D:$D,MATCH("Forwards",Data!$C:$C,0)))),"",IF(ISNA(MATCH("Forwards",Data!$C:$C,0)),"",INDEX(Data!$D:$D,MATCH("Forwards",Data!$C:$C,0)))) | J16: {=IF(COUNTA($I$16:I$16)<COUNTIF(Data!$C:$C,"Forwards"),INDEX(Data!$D:$D,MATCH(I$16,Data!$D:$D,0)+1),"")} | K16: {=IF(COUNTA($I$16:J$16)<COUNTIF(Data!$C:$C,"Forwards"),INDEX(Data!$D:$D,MATCH(J$16,Data!$D:$D,0)+1),"")} | L16: {=IF(COUNTA($I$16:K$16)<COUNTIF(Data!$C:$C,"Forwards"),INDEX(Data!$D:$D,MATCH(K$16,Data!$D:$D,0)+1),"")} | M16: {=IF(COUNTA($I$16:L$16)<COUNTIF(Data!$C:$C,"Forwards"),INDEX(Data!$D:$D,MATCH(L$16,Data!$D:$D,0)+1),"")} | N16: {=IF(COUNTA($I$16:M$16)<COUNTIF(Data!$C:$C,"Forwards"),INDEX(Data!$D:$D,MATCH(M$16,Data!$D:$D,0)+1),"")} | O16: {=IF(COUNTA($I$16:N$16)<COUNTIF(Data!$C:$C,"Forwards"),INDEX(Data!$D:$D,MATCH(N$16,Data!$D:$D,0)+1),"")} | P16: {=IF(COUNTA($I$16:O$16)<COUNTIF(Data!$C:$C,"Forwards"),INDEX(Data!$D:$D,MATCH(O$16,Data!$D:$D,0)+1),"")} | Q16: {=IF(COUNTA($I$16:P$16)<COUNTIF(Data!$C:$C,"Forwards"),INDEX(Data!$D:$D,MATCH(P$16,Data!$D:$D,0)+1),"")} | ... BH16: {=IF(COUNTA($I$16:BG$16)<COUNTIF(Data!$C:$C,"Forwards"),INDEX(Data!$D:$D,MATCH(BG$16,Data!$D:$D,0)+1),"")} | BI16: {=IF(COUNTA($I$1:BH$1)<COUNTIF(Data!$C:$C,"Swaps"),INDEX(Data!$D:$D,MATCH(BH$1,Data!$D:$D,0)+1),"")} | BJ16: {=IF(COUNTA($I$1:BI$1)<COUNTIF(Data!$C:$C,"Swaps"),INDEX(Data!$D:$D,MATCH(BI$1,Data!$D:$D,0)+1),"")} | BK16: {=IF(COUNTA($I$1:BJ$1)<COUNTIF(Data!$C:$C,"Swaps"),INDEX(Data!$D:$D,MATCH(BJ$1,Data!$D:$D,0)+1),"")} | BL16: {=IF(COUNTA($I$1:BK$1)<COUNTIF(Data!$C:$C,"Swaps"),INDEX(Data!$D:$D,MATCH(BK$1,Data!$D:$D,0)+1),"")} | BM16: {=IF(COUNTA($I$1:BL$1)<COUNTIF(Data!$C:$C,"Swaps"),INDEX(Data!$D:$D,MATCH(BL$1,Data!$D:$D,0)+1),"")} | BN16: {=IF(COUNTA($I$1:BM$1)<COUNTIF(Data!$C:$C,"Swaps"),INDEX(Data!$D:$D,MATCH(BM$1,Data!$D:$D,0)+1),"")} | BO16: {=IF(COUNTA($I$1:BN$1)<COUNTIF(Data!$C:$C,"Swaps"),INDEX(Data!$D:$D,MATCH(BN$1,Data!$D:$D,0)+1),"")} | BP16: {=IF(COUNTA($I$1:BO$1)<COUNTIF(Data!$C:$C,"Swaps"),INDEX(Data!$D:$D,MATCH(BO$1,Data!$D:$D,0)+1),"")} | ... DO16: {=IF(COUNTA($I$1:DN$1)<COUNTIF(Data!$C:$C,"Swaps"),INDEX(Data!$D:$D,MATCH(DN$1,Data!$D:$D,0)+1),"")}
A17: Forwards | B17: =MIN(0,SUMIF(Data!$C:$C,$A17,Data!$AH:$AH)) -> 0 | C17: =$B17/$B$4 -> #DIV/0! | H17: =SUM(I17:BH17) -> 0 | I17: =IF(I$16="","",INDEX(Data!$AH:$AH,MATCH(I$16,Data!$D:$D,0))/$B$4) | J17: =IF(J$16="","",INDEX(Data!$AH:$AH,MATCH(J$16,Data!$D:$D,0))/$B$4) | K17: =IF(K$16="","",INDEX(Data!$AH:$AH,MATCH(K$16,Data!$D:$D,0))/$B$4) | L17: =IF(L$16="","",INDEX(Data!$AH:$AH,MATCH(L$16,Data!$D:$D,0))/$B$4) | M17: =IF(M$16="","",INDEX(Data!$AH:$AH,MATCH(M$16,Data!$D:$D,0))/$B$4) | N17: =IF(N$16="","",INDEX(Data!$AH:$AH,MATCH(N$16,Data!$D:$D,0))/$B$4) | O17: =IF(O$16="","",INDEX(Data!$AH:$AH,MATCH(O$16,Data!$D:$D,0))/$B$4) | P17: =IF(P$16="","",INDEX(Data!$AH:$AH,MATCH(P$16,Data!$D:$D,0))/$B$4) | ... BH17: =IF(BH$16="","",INDEX(Data!$AH:$AH,MATCH(BH$16,Data!$D:$D,0))/$B$4)
A18: Swaps | B18: {=MIN(0,SUMPRODUCT((Data!$B$2:$B$1000="SWAPS")*((Data!$G$2:$G$1000)*(Data!$M$2:$M$1000))))/100} -> #VALUE! | C18: =$B18/$B$4 -> #VALUE!
A19: FRAs | B19: {=MIN(0,SUMPRODUCT((Data!$B$2:$B$1000="FORWARD RATE AGREEMENT")*((Data!$G$2:$G$1000)*(Data!$M$2:$M$1000))))/100} -> #VALUE! | C19: =$B19/$B$4 -> #VALUE! | F19: CASH COVER CHECK | H19: ="Swaps ("&COUNTIF(Data!$C:$C,"SWAPS")&")" -> Swaps (0) | I19: =IF(ISNA(IF(ISNA(MATCH("Swaps",Data!$C:$C,0)),"",INDEX(Data!$D:$D,MATCH("Swaps",Data!$C:$C,0)))),"",IF(ISNA(MATCH("Swaps",Data!$C:$C,0)),"",INDEX(Data!$D:$D,MATCH("Swaps",Data!$C:$C,0)))) | J19: {=IF(COUNTA($I$19:I$19)<COUNTIF(Data!$C:$C,"Swaps"),INDEX(Data!$D:$D,MATCH(I$19,Data!$D:$D,0)+1),"")} | K19: {=IF(COUNTA($I$19:J$19)<COUNTIF(Data!$C:$C,"Swaps"),INDEX(Data!$D:$D,MATCH(J$19,Data!$D:$D,0)+1),"")} | L19: {=IF(COUNTA($I$19:K$19)<COUNTIF(Data!$C:$C,"Swaps"),INDEX(Data!$D:$D,MATCH(K$19,Data!$D:$D,0)+1),"")} | M19: {=IF(COUNTA($I$19:L$19)<COUNTIF(Data!$C:$C,"Swaps"),INDEX(Data!$D:$D,MATCH(L$19,Data!$D:$D,0)+1),"")} | N19: {=IF(COUNTA($I$19:M$19)<COUNTIF(Data!$C:$C,"Swaps"),INDEX(Data!$D:$D,MATCH(M$19,Data!$D:$D,0)+1),"")} | O19: {=IF(COUNTA($I$19:N$19)<COUNTIF(Data!$C:$C,"Swaps"),INDEX(Data!$D:$D,MATCH(N$19,Data!$D:$D,0)+1),"")} | P19: {=IF(COUNTA($I$19:O$19)<COUNTIF(Data!$C:$C,"Swaps"),INDEX(Data!$D:$D,MATCH(O$19,Data!$D:$D,0)+1),"")} | Q19: {=IF(COUNTA($I$19:P$19)<COUNTIF(Data!$C:$C,"Swaps"),INDEX(Data!$D:$D,MATCH(P$19,Data!$D:$D,0)+1),"")} | ... BH19: {=IF(COUNTA($I$19:BG$19)<COUNTIF(Data!$C:$C,"Swaps"),INDEX(Data!$D:$D,MATCH(BG$19,Data!$D:$D,0)+1),"")} | BI19: {=IF(COUNTA($I$1:BH$1)<COUNTIF(Data!$C:$C,"Forward Rate Agreement"),INDEX(Data!$D:$D,MATCH(BH$1,Data!$D:$D,0)+1),"")} | BJ19: {=IF(COUNTA($I$1:BI$1)<COUNTIF(Data!$C:$C,"Forward Rate Agreements"),INDEX(Data!$D:$D,MATCH(BI$1,Data!$D:$D,0)+1),"")} | BK19: {=IF(COUNTA($I$1:BJ$1)<COUNTIF(Data!$C:$C,"Forward Rate Agreements"),INDEX(Data!$D:$D,MATCH(BJ$1,Data!$D:$D,0)+1),"")} | BL19: {=IF(COUNTA($I$1:BK$1)<COUNTIF(Data!$C:$C,"Forward Rate Agreements"),INDEX(Data!$D:$D,MATCH(BK$1,Data!$D:$D,0)+1),"")} | BM19: {=IF(COUNTA($I$1:BL$1)<COUNTIF(Data!$C:$C,"Forward Rate Agreements"),INDEX(Data!$D:$D,MATCH(BL$1,Data!$D:$D,0)+1),"")} | BN19: {=IF(COUNTA($I$1:BM$1)<COUNTIF(Data!$C:$C,"Forward Rate Agreements"),INDEX(Data!$D:$D,MATCH(BM$1,Data!$D:$D,0)+1),"")} | BO19: {=IF(COUNTA($I$1:BN$1)<COUNTIF(Data!$C:$C,"Forward Rate Agreements"),INDEX(Data!$D:$D,MATCH(BN$1,Data!$D:$D,0)+1),"")} | BP19: {=IF(COUNTA($I$1:BO$1)<COUNTIF(Data!$C:$C,"Forward Rate Agreements"),INDEX(Data!$D:$D,MATCH(BO$1,Data!$D:$D,0)+1),"")} | BQ19: {=IF(COUNTA($I$1:BP$1)<COUNTIF(Data!$C:$C,"Swaps"),INDEX(Data!$D:$D,MATCH(BP$1,Data!$D:$D,0)+1),"")} | BR19: {=IF(COUNTA($I$1:BQ$1)<COUNTIF(Data!$C:$C,"Swaps"),INDEX(Data!$D:$D,MATCH(BQ$1,Data!$D:$D,0)+1),"")} | BS19: {=IF(COUNTA($I$1:BR$1)<COUNTIF(Data!$C:$C,"Swaps"),INDEX(Data!$D:$D,MATCH(BR$1,Data!$D:$D,0)+1),"")} | BT19: {=IF(COUNTA($I$1:BS$1)<COUNTIF(Data!$C:$C,"Swaps"),INDEX(Data!$D:$D,MATCH(BS$1,Data!$D:$D,0)+1),"")} | BU19: {=IF(COUNTA($I$1:BT$1)<COUNTIF(Data!$C:$C,"Swaps"),INDEX(Data!$D:$D,MATCH(BT$1,Data!$D:$D,0)+1),"")} | BV19: {=IF(COUNTA($I$1:BU$1)<COUNTIF(Data!$C:$C,"Swaps"),INDEX(Data!$D:$D,MATCH(BU$1,Data!$D:$D,0)+1),"")} | BW19: {=IF(COUNTA($I$1:BV$1)<COUNTIF(Data!$C:$C,"Swaps"),INDEX(Data!$D:$D,MATCH(BV$1,Data!$D:$D,0)+1),"")}
E20: =$C6*100 -> #DIV/0! | F20: ="Cash, including cash value of options, available for long cover"&IF($A3="UT","",", and including underlying UT cash") -> Cash, including cash value of options, available for long cover | H20: =SUM(I20:BH20) -> 0 | I20: =IF(I$19="","",INDEX(Data!$AH:$AH,MATCH(I$19,Data!$D:$D,0))/$B$4) | J20: =IF(J$19="","",INDEX(Data!$AH:$AH,MATCH(J$19,Data!$D:$D,0))/$B$4) | K20: =IF(K$19="","",INDEX(Data!$AH:$AH,MATCH(K$19,Data!$D:$D,0))/$B$4) | L20: =IF(L$19="","",INDEX(Data!$AH:$AH,MATCH(L$19,Data!$D:$D,0))/$B$4) | M20: =IF(M$19="","",INDEX(Data!$AH:$AH,MATCH(M$19,Data!$D:$D,0))/$B$4) | N20: =IF(N$19="","",INDEX(Data!$AH:$AH,MATCH(N$19,Data!$D:$D,0))/$B$4) | O20: =IF(O$19="","",INDEX(Data!$AH:$AH,MATCH(O$19,Data!$D:$D,0))/$B$4) | P20: =IF(P$19="","",INDEX(Data!$AH:$AH,MATCH(P$19,Data!$D:$D,0))/$B$4) | ... BH20: =IF(BH$19="","",INDEX(Data!$AH:$AH,MATCH(BH$19,Data!$D:$D,0))/$B$4)
E21: =MIN(0,$H$11*100) -> 0 | F21: ="Net "&IF(E21<0,"short","long")&" currency derivatives, so "&IF(E21<0,"adequate","no")&" cash cover required" -> Net long currency derivatives, so no cash cover required
A22: =IF(B22>=0,"A","Ina")&"dequate cash cover for currency derivatives" -> #VALUE! | B22: =B6+B13+B16 -> #VALUE! | C22: =C6+C13+C16 -> #DIV/0! | E22: =SUM(E20:E21) -> #DIV/0! | F22: =IF($E22>=0,"Adequate","INADEQUATE")&" currency future cover [BN90 16(1)(i)]" -> #DIV/0! | H22: ="FRAs ("&COUNTIF(Data!$C:$C,"Forward Rate Agreement")&")" -> FRAs (0) | I22: =IF(ISNA(IF(ISNA(MATCH("Forward Rate Agreement",Data!$C:$C,0)),"",INDEX(Data!$D:$D,MATCH("Forward Rate Agreement",Data!$C:$C,0)))),"",IF(ISNA(MATCH("Forward Rate Agreement",Data!$C:$C,0)),"",INDEX(Data!$D:$D,MATCH("Forward Rate Agreement",Data!$C:$C,0)))) | J22: {=IF(COUNTA($I$22:I$22)<COUNTIF(Data!$C:$C,"Forward Rate Agreement"),INDEX(Data!$D:$D,MATCH(I$22,Data!$D:$D,0)+1),"")} | K22: {=IF(COUNTA($I$22:J$22)<COUNTIF(Data!$C:$C,"Forward Rate Agreement"),INDEX(Data!$D:$D,MATCH(J$22,Data!$D:$D,0)+1),"")} | L22: {=IF(COUNTA($I$22:K$22)<COUNTIF(Data!$C:$C,"Forward Rate Agreement"),INDEX(Data!$D:$D,MATCH(K$22,Data!$D:$D,0)+1),"")} | M22: {=IF(COUNTA($I$22:L$22)<COUNTIF(Data!$C:$C,"Forward Rate Agreement"),INDEX(Data!$D:$D,MATCH(L$22,Data!$D:$D,0)+1),"")} | N22: {=IF(COUNTA($I$22:M$22)<COUNTIF(Data!$C:$C,"Forward Rate Agreement"),INDEX(Data!$D:$D,MATCH(M$22,Data!$D:$D,0)+1),"")} | O22: {=IF(COUNTA($I$22:N$22)<COUNTIF(Data!$C:$C,"Forward Rate Agreement"),INDEX(Data!$D:$D,MATCH(N$22,Data!$D:$D,0)+1),"")} | P22: {=IF(COUNTA($I$22:O$22)<COUNTIF(Data!$C:$C,"Forward Rate Agreement"),INDEX(Data!$D:$D,MATCH(O$22,Data!$D:$D,0)+1),"")} | Q22: {=IF(COUNTA($I$22:P$22)<COUNTIF(Data!$C:$C,"Forward Rate Agreement"),INDEX(Data!$D:$D,MATCH(P$22,Data!$D:$D,0)+1),"")} | ... BH22: {=IF(COUNTA($I$22:BG$22)<COUNTIF(Data!$C:$C,"Forward Rate Agreement"),INDEX(Data!$D:$D,MATCH(BG$22,Data!$D:$D,0)+1),"")}
E23: =MIN(0,$H$14*100) -> 0 | F23: ="Net "&IF($E23>0,"positive","negative")&" MtM OTC forwards, so "&IF($E23>0,"no ","")&"cash cover required" -> Net negative MtM OTC forwards, so cash cover required | H23: =SUM(I23:BH23) -> 0 | I23: =IF(I$22="","",INDEX(Data!$AH:$AH,MATCH(I$22,Data!$D:$D,0))/$B$4) | J23: =IF(J$22="","",INDEX(Data!$AH:$AH,MATCH(J$22,Data!$D:$D,0))/$B$4) | K23: =IF(K$22="","",INDEX(Data!$AH:$AH,MATCH(K$22,Data!$D:$D,0))/$B$4) | L23: =IF(L$22="","",INDEX(Data!$AH:$AH,MATCH(L$22,Data!$D:$D,0))/$B$4) | M23: =IF(M$22="","",INDEX(Data!$AH:$AH,MATCH(M$22,Data!$D:$D,0))/$B$4) | N23: =IF(N$22="","",INDEX(Data!$AH:$AH,MATCH(N$22,Data!$D:$D,0))/$B$4) | O23: =IF(O$22="","",INDEX(Data!$AH:$AH,MATCH(O$22,Data!$D:$D,0))/$B$4) | P23: =IF(P$22="","",INDEX(Data!$AH:$AH,MATCH(P$22,Data!$D:$D,0))/$B$4) | ... BH23: =IF(BH$22="","",INDEX(Data!$AH:$AH,MATCH(BH$22,Data!$D:$D,0))/$B$4)
A24: less Bought futures or calls & sold puts to be covered by cash [BN90 16(1)(c)] | B24: =SUM(B25:B30) -> #VALUE! | C24: =SUM(C25:C30) -> #DIV/0! | E24: =MIN(0,B18/B$4)*100 -> #VALUE! | F24: ="Net "&IF($E24>0,"positive","negative")&" MtM OTC swaps, so "&IF($E24>0,"no ","")&"cash cover required" -> #VALUE!
A25: Equity Derivatives | B25: =IF(SUMIF(Data!$C:$C,"Equity Derivatives",Data!$AH:$AH)>=0,SUMIF(Data!$C:$C,"Equity Derivatives",Data!$AH:$AH),0) -> 0 | C25: =$B25/$B$4 -> #DIV/0! | E25: =MIN(0,B19/B$4)*100 -> #VALUE! | F25: ="Net "&IF($E25>0,"positive","negative")&" MtM OTC FRAs, so "&IF($E25>0,"no ","")&"cash cover required" -> #VALUE!
A26: excl MtM P&L on internationally listed derivatives | B26: =IF($H$5=0,0,-SUMIF(Data!$B:$B,"DERIVATIVES",Data!$AH:$AH)-SUMIF(Data!$B:$B,"UNKNOWN",Data!$AH:$AH)) -> 0 | C26: =$B26/$B$4 -> #DIV/0! | E26: =SUM(E22:E24) -> #DIV/0! | F26: =IF($E26>=0,"Adequate","INADEQUATE")&" OTC currency forward and swap cover [BN90 17(1)(a)]" -> #DIV/0!
A27: Effective equity exposure from swaps | B27: {=SUMPRODUCT((Data!$C$2:$C$1000="SWAPS")*((Data!$G$2:$G$1000)*(Data!$M$2:$M$1000))>0)} -> #VALUE! | C27: =$B27/$B$4 -> #VALUE! | E27: =MAX(0,($H$2+$H$5+C26)*100) -> #DIV/0! | F27: ="Net "&IF(E27>=0,"long","short")&" equity index, so adequate "&IF(E27>=0,"cash","similar asset")&" cover required" -> #DIV/0!
A28: excl MtM P&L on OTC swaps | B28: {=-SUMPRODUCT((Data!$C$2:$C$1000="SWAPS")*((Data!$AH$2:$AH$1000)))} -> 0 | C28: =$B28/$B$4 -> #DIV/0! | E28: =MAX(0,$H$8*100) -> 0 | F28: ="Net "&IF(E28>=0,"long","short")&" bond index, so adequate "&IF(E28>=0,"cash","similar asset")&" cover required" -> Net long bond index, so adequate cash cover required
A29: Currency Derivatives | B29: =IF(SUMIF(Data!$C:$C,$A29,Data!$AH:$AH)>=0,SUMIF(Data!$C:$C,$A29,Data!$AH:$AH),0) -> 0 | C29: =$B29/$B$4 -> #DIV/0!
A30: Bond Derivatives | B30: =IF(SUMIF(Data!$C:$C,$A30,Data!$AH:$AH)>=0,SUMIF(Data!$C:$C,$A30,Data!$AH:$AH),0) -> 0 | C30: =$B30/$B$4 -> #DIV/0! | E30: =SUM(C27:C28)*100 -> #VALUE! | F30: Effective equity exposure from swaps, after MtM
A32: =IF($A3="UT","","Cash from the "&COUNTIF(Data!$B:$B,"COLLECTIVE INVESTMENT SCHEMES")&" underlying UT"&IF(COUNTIF(Data!$B:$B,"COLLECTIVE INVESTMENT SCHEMES")=1,"","s")) | B32: =IF($A$3="UT",0,SUMIF(Data!$B:$B,"COLLECTIVE INVESTMENT SCHEMES",Data!$AH:$AH)) -> 0 | C32: =IF($A3="UT",0,$B32/$B$4) -> 0 | E32: =C32*100 -> 0
A34: =IF(B34>=0,"A","Ina")&"dequate cash cover for derivatives" -> #VALUE! | B34: =B22-B24+B32 -> #VALUE! | C34: =C22-C24+C32 -> #DIV/0! | E34: =E26-E27-E28-E29-E30+E32 -> #DIV/0! | F34: =IF($E34>=0,"Adequate","INADEQUATE")&" long derivative cash cover [BN90 16(1)(c)]" -> #DIV/0!
A36: =IF($A3="UT","The numbers above exclude these assets which don't qualify as AiLF for UTs: *","") -> The numbers above exclude these assets which don't qualify as AiLF for UTs: * | B36: =IF($A3="UT",SUM(B37:B38),"") -> 0 | C36: =IF($A3="UT",SUM(C37:C38),"") -> #DIV/0!
A37: =IF($A3="UT","Money Market","") -> Money Market | B37: {=IF($A3="UT",SUMIF(Data!$B:$B,"MONEY MARKET",Data!$AH:$AH)-SUMPRODUCT((Data!$B:$B="MONEY MARKET")*((Data!$P:$P<Data!$AJ$2+397)*(Data!$V:$V<>"CLN")),(Data!$AH:$AH)),"")} -> 0 | C37: =IF($A3="UT",B37/$B$4,"") -> #DIV/0!
A38: =IF($A3="UT","Bonds","") -> Bonds | B38: {=IF($A3="UT",SUMIF(Data!$B:$B,"BONDS",Data!$AH:$AH)-SUMPRODUCT((Data!$B:$B="BONDS")*((Data!$P:$P<Data!$AJ$2+397)*(Data!$V:$V<>"CLN")),(Data!$AH:$AH)),"")} -> 0 | C38: =IF($A3="UT",B38/$B$4,"") -> #DIV/0!
A40: Total equity, incl property equity | B40: =B42+B50 -> #VALUE! | C40: =C42+C50 -> #DIV/0!
A42: Total non-property equity | B42: =SUM(B43:B48) -> #VALUE! | C42: =SUM(C43:C48) -> #DIV/0!
A43: Equity futures and options | B43: {=SUMPRODUCT(('Glbl Expsr'!$H$2:$H$68)*('Glbl Expsr'!$I$2:$I$68)*('Glbl Expsr'!$J$2:$J$68)*('Glbl Expsr'!$L$2:$L$68)*('Glbl Expsr'!$O$2:$O$68))+$B$26} -> 0 | C43: {=SUMPRODUCT(('Glbl Expsr'!$H$2:$H$68)*('Glbl Expsr'!$I$2:$I$68)*('Glbl Expsr'!$J$2:$J$68)*('Glbl Expsr'!$L$2:$L$68)*('Glbl Expsr'!$O$2:$O$68))/SUM(Data!$L:$L)+$C$26} -> #DIV/0!
A44: Equity linked notes | B44: {=SUMPRODUCT(--(Data!$C$2:$C$1000="EQUITY LINKED NOTES"), (Data!$AH$2:$AH$1000))} -> 0 | C44: {=SUMPRODUCT(--(Data!$C$2:$C$1000="EQUITY LINKED NOTES"),(Data!$AI2:$AI1000))/100} -> 0
A45: Equity TRSs | B45: {=SUMPRODUCT((Data!$C$2:$C$1000="SWAPS")*((Data!$G$2:$G$1000)*(Data!$M$2:$M$1000)))} -> #VALUE! | C45: {=SUMPRODUCT((Data!$C$2:$C$1000="SWAPS")*((Data!$G$2:$G$1000)*(Data!$M$2:$M$1000)))/SUM(Data!$L:$L)} -> #VALUE!
A46: Direct equities, excl direct property equity | B46: {=SUMPRODUCT((Data!$B:$B="EQUITIES")*(Data!$X:$X<>"REAL ESTATE")*(Data!$V:$V<>"EQUITY - ELN"),(Data!$AH:$AH))} -> 0 | C46: {=SUMPRODUCT((Data!$B:$B="EQUITIES")*(Data!$X:$X<>"REAL ESTATE")*(Data!$V:$V<>"EQUITY - ELN"),(Data!$AI:$AI))/100} -> 0
A47: Direct preference shares | B47: =SUMIF(Data!$B:$B,"PREFERENCE SHARES",Data!$AH:$AH) -> 0 | C47: =SUMIF(Data!$B:$B,"PREFERENCE SHARES",Data!$AI:$AI)/100 -> 0
A48: Equity unit trusts | B48: {=SUMPRODUCT(--((Data!$B:$B="COLLECTIVE INVESTMENT SCHEMES")*(ISNUMBER(SEARCH("equity",Data!$D:$D))-ISNUMBER(SEARCH("property equity",Data!$D:$D))+ISNUMBER(SEARCH("balanced",Data!$D:$D)))>0),(Data!$AH:$AH))} -> 0 | C48: {=SUMPRODUCT(--((Data!$B:$B="COLLECTIVE INVESTMENT SCHEMES")*(ISNUMBER(SEARCH("equity",Data!$D:$D))-ISNUMBER(SEARCH("property equity",Data!$D:$D))+ISNUMBER(SEARCH("balanced",Data!$D:$D)))>0),(Data!$AI:$AI))/100} -> 0
A50: Total property equity | B50: =SUM(B51:B52) -> 0 | C50: =SUM(C51:C52) -> 0
A51: Direct property equity | B51: {=SUMPRODUCT((Data!$B:$B="EQUITIES")*(Data!$X:$X="REAL ESTATE"),(Data!$AH:$AH))} -> 0 | C51: {=SUMPRODUCT((Data!$B:$B="EQUITIES")*(Data!$X:$X="REAL ESTATE"),(Data!$AI:$AI))/100} -> 0
A52: Property equity unit trusts | B52: {=SUMPRODUCT(--((Data!$B:$B="COLLECTIVE INVESTMENT SCHEMES")*(ISNUMBER(SEARCH("property equity",Data!$D:$D)))>0),(Data!$AH:$AH))} -> 0 | C52: {=SUMPRODUCT(--((Data!$B:$B="COLLECTIVE INVESTMENT SCHEMES")*(ISNUMBER(SEARCH("property equity",Data!$D:$D)))>0),(Data!$AI:$AI))/100} -> 0
A54: Total foreign | B54: =SUM(B56,B63,B69,B73) -> 101.27 | C54: =SUM(C56,C63,C69) -> 1.0437708e+08 | D54: < 45%
A56: Direct foreign exposure excl foreign derivatives | B56: =SUM(B57:B61) -> 101.27 | C56: =SUM(C57:C61) -> 1.0437708e+08
A57: Direct foreign assets excl derivatives, cash, MMIs, 'SYNCASH', CISes | B57: {=SUMPRODUCT((Data!$B:$B<>"CASH")*(Data!$B:$B<>"MONEY MARKET")*(Data!$B:$B<>"DERIVATIVES")*(Data!$B:$B<>"COLLECTIVE INVESTMENT SCHEMES")*(Data!$W:$W<>"ZAR")*(Data!$T:$T<>"SYTH"),Data!$AH:$AH)} -> 101.27 | C57: {=SUMPRODUCT((Data!$B:$B<>"CASH")*(Data!$B:$B<>"MONEY MARKET")*(Data!$B:$B<>"DERIVATIVES")*(Data!$B:$B<>"COLLECTIVE INVESTMENT SCHEMES")*(Data!$W:$W<>"ZAR")*(Data!$T:$T<>"SYTH"),Data!$AI:$AI)} -> 1.0437708e+08
A58: {="Direct foreign cash excl 'SYNCASH' ("&SUMPRODUCT((Data!$B:$B="CASH")*(Data!$W:$W<>"ZAR")*(Data!$T:$T<>"SYTH"))&")"} -> Direct foreign cash excl 'SYNCASH' (0) | B58: {=SUMPRODUCT((Data!$B:$B="CASH")*(Data!$W:$W<>"ZAR")*(Data!$T:$T<>"SYTH"),Data!$AH:$AH)} -> 0 | C58: {=SUMPRODUCT((Data!$B:$B="CASH")*(Data!$W:$W<>"ZAR")*(Data!$T:$T<>"SYTH"),Data!$AI:$AI)} -> 0
A59: {="Direct foreign MMIs excl 'SYNCASH' ("&SUMPRODUCT((Data!$B:$B="MONEY MARKET")*(Data!$W:$W<>"ZAR")*(Data!$T:$T<>"SYTH"))&")"} -> Direct foreign MMIs excl 'SYNCASH' (0) | B59: {=SUMPRODUCT((Data!$B:$B="MONEY MARKET")*(Data!$W:$W<>"ZAR")*(Data!$T:$T<>"SYTH"),Data!$AH:$AH)} -> 0 | C59: {=SUMPRODUCT((Data!$B:$B="MONEY MARKET")*(Data!$W:$W<>"ZAR")*(Data!$T:$T<>"SYTH"),Data!$AI:$AI)} -> 0
A60: {="Global funds denominated as non-ZAR ("&SUMPRODUCT((Data!$B:$B="COLLECTIVE INVESTMENT SCHEMES")*(Data!$W:$W<>"ZAR")*(Data!$T:$T<>"SYTH"))&")"} -> Global funds denominated as non-ZAR (0) | B60: {=SUMPRODUCT((Data!$B:$B="COLLECTIVE INVESTMENT SCHEMES")*(Data!$W:$W<>"ZAR")*(Data!$T:$T<>"SYTH"),Data!$AH:$AH)} -> 0 | C60: {=SUMPRODUCT((Data!$B:$B="COLLECTIVE INVESTMENT SCHEMES")*(Data!$W:$W<>"ZAR")*(Data!$T:$T<>"SYTH"),Data!$AI:$AI)} -> 0
A61: {="Global funds denominated as ZAR ("&SUMPRODUCT((ISNUMBER(SEARCH("global",Data!$D:$D)))*(Data!$B:$B="COLLECTIVE INVESTMENT SCHEMES")*(Data!$W:$W="ZAR")*(Data!$T:$T<>"SYTH"))&")"} -> Global funds denominated as ZAR (0) | B61: {=SUMPRODUCT(Data!$AH:$AH,(ISNUMBER(SEARCH("global",Data!$D:$D)))*(Data!$B:$B="COLLECTIVE INVESTMENT SCHEMES")*(Data!$W:$W="ZAR")*(Data!$T:$T<>"SYTH"))} -> 0 | C61: {=SUMPRODUCT(Data!$AI:$AI,(ISNUMBER(SEARCH("global",Data!$D:$D)))*(Data!$B:$B="COLLECTIVE INVESTMENT SCHEMES")*(Data!$W:$W="ZAR")*(Data!$T:$T<>"SYTH"))} -> 0
A63: Indirect foreign exposure from derivatives | B63: =SUM(B64:B67) -> 0 | C63: =SUM(C64:C67) -> 0
A64: {="Foreign equity derivatives ("&SUMPRODUCT(--(Data!$C:$C="Equity Derivatives")*(Data!$W:$W<>"ZAR"))&")"} -> Foreign equity derivatives (0) | B64: {=SUMPRODUCT((Data!$C:$C="Equity derivatives")*(Data!$W:$W<>"ZAR"),Data!$AH:$AH)} -> 0 | C64: {=SUMPRODUCT((Data!$C:$C="Equity derivatives")*(Data!$W:$W<>"ZAR"),Data!$AI:$AI)} -> 0
A65: {="Foreign bond derivatives ("&SUMPRODUCT(--(Data!$C:$C="Bond Derivatives")*(Data!$W:$W<>"ZAR"))&")"} -> Foreign bond derivatives (0) | B65: {=SUMPRODUCT((Data!$C:$C="Bond derivatives")*(Data!$W:$W<>"ZAR"),Data!$AH:$AH)} -> 0 | C65: {=SUMPRODUCT((Data!$C:$C="Bond derivatives")*(Data!$W:$W<>"ZAR"),Data!$AI:$AI)} -> 0
A66: {="Foreign currency derivatives ("&SUMPRODUCT(--(Data!$C:$C="Currency Derivatives")*(Data!$W:$W<>"ZAR"))&")"} -> Foreign currency derivatives (0) | B66: {=SUMPRODUCT((Data!$C:$C="Currency derivatives")*(Data!$W:$W<>"ZAR"),Data!$AH:$AH)} -> 0 | C66: {=SUMPRODUCT((Data!$C:$C="Currency derivatives")*(Data!$W:$W<>"ZAR"),Data!$AI:$AI)} -> 0
A67: {="Foreign currency forwards ("&SUMPRODUCT(--(Data!$C:$C="Forwards")*(Data!$W:$W<>"ZAR"))&")"} -> Foreign currency forwards (0) | B67: {=SUMPRODUCT((Data!$C:$C="Forwards")*(Data!$W:$W<>"ZAR"),Data!$AH:$AH)} -> 0 | C67: {=SUMPRODUCT((Data!$C:$C="Forwards")*(Data!$W:$W<>"ZAR"),Data!$AI:$AI)} -> 0
A69: less Foreign cash | B69: =-SUM(B58:B59) -> 0 | C69: =-SUM(C58:C59) -> 0
A70: {="Direct foreign cash excl 'SYNCASH' ("&SUMPRODUCT((Data!$B:$B="CASH")*(Data!$W:$W<>"ZAR")*(Data!$T:$T<>"SYTH"))&")"} -> Direct foreign cash excl 'SYNCASH' (0) | B70: {=SUMPRODUCT((Data!$B:$B="CASH")*(Data!$W:$W<>"ZAR")*(Data!$T:$T<>"SYTH"),Data!$AH:$AH)} -> 0 | C70: {=SUMPRODUCT((Data!$B:$B="CASH")*(Data!$W:$W<>"ZAR")*(Data!$T:$T<>"SYTH"),Data!$AI:$AI)} -> 0
A71: {="Direct foreign MMIs excl 'SYNCASH' ("&SUMPRODUCT((Data!$B:$B="MONEY MARKET")*(Data!$W:$W<>"ZAR")*(Data!$T:$T<>"SYTH"))&")"} -> Direct foreign MMIs excl 'SYNCASH' (0) | B71: {=SUMPRODUCT((Data!$B:$B="MONEY MARKET")*(Data!$W:$W<>"ZAR")*(Data!$T:$T<>"SYTH"),Data!$AH:$AH)} -> 0 | C71: {=SUMPRODUCT((Data!$B:$B="MONEY MARKET")*(Data!$W:$W<>"ZAR")*(Data!$T:$T<>"SYTH"),Data!$AI:$AI)} -> 0
A73: "Additional foreign added by derivative" | B73: =B63+B69 -> 0 | C73: =C63+C69 -> 0
A76: Synthetic cash | B76: =SUM(B77:B78) -> 0 | C76: =SUM(C77:C78) -> 0
A77: {="ZAR 'SYNCASH' ("&SUMPRODUCT((Data!$W:$W="ZAR")*(Data!$T:$T="SYTH"))&")"} -> ZAR 'SYNCASH' (0) | B77: {=SUMPRODUCT((Data!$W:$W="ZAR")*(Data!$T:$T="SYTH"),(Data!$AH:$AH))} -> 0 | C77: {=SUMPRODUCT((Data!$W:$W="ZAR")*(Data!$T:$T="SYTH"),(Data!$AI:$AI))} -> 0
A78: {="Non-ZAR 'SYNCASH' ("&SUMPRODUCT((Data!$W:$W<>"ZAR")*(Data!$T:$T="SYTH"))&")"} -> Non-ZAR 'SYNCASH' (0) | B78: {=SUMPRODUCT((Data!$W:$W<>"ZAR")*(Data!$T:$T="SYTH"),(Data!$AH:$AH))} -> 0 | C78: {=SUMPRODUCT((Data!$W:$W<>"ZAR")*(Data!$T:$T="SYTH"),(Data!$AI:$AI))} -> 0

Sheet Glbl Expsr
A1: =Data!$A$2&" ("&Data!$AK$2&") Exposures "&TEXT(Data!$AJ$2,"d mmm yy") -> 0 (44676) Exposures 0 Jan 00 | C1: ZAR | D1: % NAV | F1: =_xlfn.XLOOKUP(Data!$AK$2,[77]Funds!$A:$A,[77]Funds!$E:$E) -> #N/A | G1: {="SA Equity Derivatives ("&SUMPRODUCT((Data!$C:$C="Equity Derivatives")*(Data!$W:$W="ZAR"))&")"} -> SA Equity Derivatives (0) | H1: Contracts Held | I1: Multiplier | J1: Market Price | K1: Nominal Exposure | L1: Delta | M1: Effective Exposure | N1: Gross Effective Exposure (%) | O1: Forex rate
A2: Global exposure (sum of the absolute effective exposures) | B2: a | C2: {=SUMPRODUCT(ABS(($H$2:$H$68))*($I$2:$I$68)*ABS(($J$2:$J$68))*ABS(($L$2:$L$68))*(O2:O68))+Summary!$B$26} -> 0 | D2: {=SUMPRODUCT(ABS(($H$2:$H$68))*($I$2:$I$68)*ABS(($J$2:$J$68))*ABS(($L$2:$L$68))*(O2:O68))/SUM(Data!$L:$L)+Summary!$C$26} -> #DIV/0! | G2: =Summary!I$1 | H2: =IF($G2<>"",INDEX(Data!$G:$G,MATCH($G2,Data!$D:$D,0)),0) -> 0 | I2: =IF($G2<>"",10,0) -> 0 | J2: =IF($G2<>"",INDEX(Data!$M:$M,MATCH($G2,Data!$D:$D,0)),0) -> 0 | K2: =PRODUCT($H2:$J2)*$O$53 -> 0 | L2: =IF($G2<>"",INDEX(Deltas!$E:$E,MATCH($G2,Deltas!$B:$B,0)),0) -> 0 | M2: =PRODUCT($H2:$J2,$L2) -> 0 | N2: =ABS(PRODUCT($H2:$J2,$L2))/Summary!$B$4*$O$53 -> #DIV/0! | O2: 1
A3: Net effective exposure (sum of the net effective exposures) | B3: b | C3: {=SUMPRODUCT(($H$2:$H$68)*($I$2:$I$68)*($J$2:$J$68)*($L$2:$L$68)*($O$2:$O$68))+Summary!$B$26} -> 0 | D3: {=SUMPRODUCT(($H$2:$H$68)*($I$2:$I$68)*($J$2:$J$68)*($L$2:$L$68)*($O$2:$O$68))/SUM(Data!$L:$L)+Summary!$C$26} -> #DIV/0! | G3: =Summary!J$1 | H3: =IF($G3<>"",INDEX(Data!$G:$G,MATCH($G3,Data!$D:$D,0)),0) -> 0 | I3: =IF($G3<>"",10,0) -> 0 | J3: =IF($G3<>"",INDEX(Data!$M:$M,MATCH($G3,Data!$D:$D,0)),0) -> 0 | K3: =PRODUCT($H3:$J3)*$O$53 -> 0 | L3: =IF($G3<>"",INDEX(Deltas!$E:$E,MATCH($G3,Deltas!$B:$B,0)),0) -> 0 | M3: =PRODUCT($H3:$J3,$L3) -> 0 | N3: =ABS(PRODUCT($H3:$J3,$L3))/Summary!$B$4*$O$53 -> #DIV/0! | O3: 1
A4: Liquid assets | B4: c | C4: =Summary!$B6 -> 0 | D4: =Summary!$B6/SUM(Data!$L:$L) -> #DIV/0! | G4: =Summary!K$1 | H4: =IF($G4<>"",INDEX(Data!$G:$G,MATCH($G4,Data!$D:$D,0)),0) -> 0 | I4: =IF($G4<>"",10,0) -> 0 | J4: =IF($G4<>"",INDEX(Data!$M:$M,MATCH($G4,Data!$D:$D,0)),0) -> 0 | K4: =PRODUCT($H4:$J4)*$O$53 -> 0 | L4: =IF($G4<>"",INDEX(Deltas!$E:$E,MATCH($G4,Deltas!$B:$B,0)),0) -> 0 | M4: =PRODUCT($H4:$J4,$L4) -> 0 | N4: =ABS(PRODUCT($H4:$J4,$L4))/Summary!$B$4*$O$53 -> #DIV/0! | O4: 1
A5: Liquid assets and collective investment schemes | B5: d | C5: =Summary!$B6+SUMIF(Data!$B:$B,"COLLECTIVE INVESTMENT SCHEMES",Data!$AH:$AH) -> 0 | D5: =(Summary!$B6+SUMIF(Data!$B:$B,"COLLECTIVE INVESTMENT SCHEMES",Data!$AH:$AH))/SUM(Data!$L:$L) -> #DIV/0! | G5: =Summary!L$1 | H5: =IF($G5<>"",INDEX(Data!$G:$G,MATCH($G5,Data!$D:$D,0)),0) -> 0 | I5: =IF($G5<>"",10,0) -> 0 | J5: =IF($G5<>"",INDEX(Data!$M:$M,MATCH($G5,Data!$D:$D,0)),0) -> 0 | K5: =PRODUCT($H5:$J5)*$O$53 -> 0 | L5: =IF($G5<>"",INDEX(Deltas!$E:$E,MATCH($G5,Deltas!$B:$B,0)),0) -> 0 | M5: =PRODUCT($H5:$J5,$L5) -> 0 | N5: =ABS(PRODUCT($H5:$J5,$L5))/Summary!$B$4*$O$53 -> #DIV/0! | O5: 1
G6: =Summary!M$1 | H6: =IF($G6<>"",INDEX(Data!$G:$G,MATCH($G6,Data!$D:$D,0)),0) -> 0 | I6: =IF($G6<>"",10,0) -> 0 | J6: =IF($G6<>"",INDEX(Data!$M:$M,MATCH($G6,Data!$D:$D,0)),0) -> 0 | K6: =PRODUCT($H6:$J6)*$O$53 -> 0 | L6: =IF($G6<>"",INDEX(Deltas!$E:$E,MATCH($G6,Deltas!$B:$B,0)),0) -> 0 | M6: =PRODUCT($H6:$J6,$L6) -> 0 | N6: =ABS(PRODUCT($H6:$J6,$L6))/Summary!$B$4*$O$53 -> #DIV/0! | O6: 1
A7: Liquid asset cover over global exposure (must be > 100%) | B7: c ÷ a | C7: =IF(C2=0,1,C4/C2) -> 1 | D7: =D4-D2 -> #DIV/0! | E7: c - a | G7: =Summary!N$1 | H7: =IF($G7<>"",INDEX(Data!$G:$G,MATCH($G7,Data!$D:$D,0)),0) -> 0 | I7: =IF($G7<>"",10,0) -> 0 | J7: =IF($G7<>"",INDEX(Data!$M:$M,MATCH($G7,Data!$D:$D,0)),0) -> 0 | K7: =PRODUCT($H7:$J7)*$O$53 -> 0 | L7: =IF($G7<>"",INDEX(Deltas!$E:$E,MATCH($G7,Deltas!$B:$B,0)),0) -> 0 | M7: =PRODUCT($H7:$J7,$L7) -> 0 | N7: =ABS(PRODUCT($H7:$J7,$L7))/Summary!$B$4*$O$53 -> #DIV/0! | O7: 1
A8: Liquid asset cover over net effective exposure (must be > 100%) | B8: c ÷ b | C8: =IF(C3=0,1,C4/C3) -> 1 | D8: =D4-D3 -> #DIV/0! | E8: c - b | G8: =Summary!O$1 | H8: =IF($G8<>"",INDEX(Data!$G:$G,MATCH($G8,Data!$D:$D,0)),0) -> 0 | I8: =IF($G8<>"",10,0) -> 0 | J8: =IF($G8<>"",INDEX(Data!$M:$M,MATCH($G8,Data!$D:$D,0)),0) -> 0 | K8: =PRODUCT($H8:$J8)*$O$53 -> 0 | L8: =IF($G8<>"",INDEX(Deltas!$E:$E,MATCH($G8,Deltas!$B:$B,0)),0) -> 0 | M8: =PRODUCT($H8:$J8,$L8) -> 0 | N8: =ABS(PRODUCT($H8:$J8,$L8))/Summary!$B$4*$O$53 -> #DIV/0! | O8: 1
G9: =Summary!P$1 | H9: =IF($G9<>"",INDEX(Data!$G:$G,MATCH($G9,Data!$D:$D,0)),0) -> 0 | I9: =IF($G9<>"",10,0) -> 0 | J9: =IF($G9<>"",INDEX(Data!$M:$M,MATCH($G9,Data!$D:$D,0)),0) -> 0 | K9: =PRODUCT($H9:$J9)*$O$53 -> 0 | L9: =IF($G9<>"",INDEX(Deltas!$E:$E,MATCH($G9,Deltas!$B:$B,0)),0) -> 0 | M9: =PRODUCT($H9:$J9,$L9) -> 0 | N9: =ABS(PRODUCT($H9:$J9,$L9))/Summary!$B$4*$O$53 -> #DIV/0! | O9: 1
A10: Liquid asset cover, incl CISes, over net effective exposure (must be > 100%) | B10: d ÷ a | C10: =IF(C2=0,1,C5/C2) -> 1 | D10: =D5-D2 -> #DIV/0! | E10: d - a | G10: =Summary!Q$1 | H10: =IF($G10<>"",INDEX(Data!$G:$G,MATCH($G10,Data!$D:$D,0)),0) -> 0 | I10: =IF($G10<>"",10,0) -> 0 | J10: =IF($G10<>"",INDEX(Data!$M:$M,MATCH($G10,Data!$D:$D,0)),0) -> 0 | K10: =PRODUCT($H10:$J10)*$O$53 -> 0 | L10: =IF($G10<>"",INDEX(Deltas!$E:$E,MATCH($G10,Deltas!$B:$B,0)),0) -> 0 | M10: =PRODUCT($H10:$J10,$L10) -> 0 | N10: =ABS(PRODUCT($H10:$J10,$L10))/Summary!$B$4*$O$53 -> #DIV/0! | O10: 1
A11: Liquid asset cover, incl CISes, over net effective exposure (must be > 100%) | B11: d ÷ b | C11: =IF(C3=0,1,C5/C3) -> 1 | D11: =D5-D3 -> #DIV/0! | E11: d - b | G11: =Summary!R$1 | H11: =IF($G11<>"",INDEX(Data!$G:$G,MATCH($G11,Data!$D:$D,0)),0) -> 0 | I11: =IF($G11<>"",10,0) -> 0 | J11: =IF($G11<>"",INDEX(Data!$M:$M,MATCH($G11,Data!$D:$D,0)),0) -> 0 | K11: =PRODUCT($H11:$J11)*$O$53 -> 0 | L11: =IF($G11<>"",INDEX(Deltas!$E:$E,MATCH($G11,Deltas!$B:$B,0)),0) -> 0 | M11: =PRODUCT($H11:$J11,$L11) -> 0 | N11: =ABS(PRODUCT($H11:$J11,$L11))/Summary!$B$4*$O$53 -> #DIV/0! | O11: 1
G12: =Summary!S$1 | H12: =IF($G12<>"",INDEX(Data!$G:$G,MATCH($G12,Data!$D:$D,0)),0) -> 0 | I12: =IF($G12<>"",10,0) -> 0 | J12: =IF($G12<>"",INDEX(Data!$M:$M,MATCH($G12,Data!$D:$D,0)),0) -> 0 | K12: =PRODUCT($H12:$J12)*$O$53 -> 0 | L12: =IF($G12<>"",INDEX(Deltas!$E:$E,MATCH($G12,Deltas!$B:$B,0)),0) -> 0 | M12: =PRODUCT($H12:$J12,$L12) -> 0 | N12: =ABS(PRODUCT($H12:$J12,$L12))/Summary!$B$4*$O$53 -> #DIV/0! | O12: 1
G13: =Summary!T$1 | H13: =IF($G13<>"",INDEX(Data!$G:$G,MATCH($G13,Data!$D:$D,0)),0) -> 0 | I13: =IF($G13<>"",10,0) -> 0 | J13: =IF($G13<>"",INDEX(Data!$M:$M,MATCH($G13,Data!$D:$D,0)),0) -> 0 | K13: =PRODUCT($H13:$J13)*$O$53 -> 0 | L13: =IF($G13<>"",INDEX(Deltas!$E:$E,MATCH($G13,Deltas!$B:$B,0)),0) -> 0 | M13: =PRODUCT($H13:$J13,$L13) -> 0 | N13: =ABS(PRODUCT($H13:$J13,$L13))/Summary!$B$4*$O$53 -> #DIV/0! | O13: 1
G14: =Summary!U$1 | H14: =IF($G14<>"",INDEX(Data!$G:$G,MATCH($G14,Data!$D:$D,0)),0) -> 0 | I14: =IF($G14<>"",10,0) -> 0 | J14: =IF($G14<>"",INDEX(Data!$M:$M,MATCH($G14,Data!$D:$D,0)),0) -> 0 | K14: =PRODUCT($H14:$J14)*$O$53 -> 0 | L14: =IF($G14<>"",INDEX(Deltas!$E:$E,MATCH($G14,Deltas!$B:$B,0)),0) -> 0 | M14: =PRODUCT($H14:$J14,$L14) -> 0 | N14: =ABS(PRODUCT($H14:$J14,$L14))/Summary!$B$4*$O$53 -> #DIV/0! | O14: 1
G15: =Summary!V$1 | H15: =IF($G15<>"",INDEX(Data!$G:$G,MATCH($G15,Data!$D:$D,0)),0) -> 0 | I15: =IF($G15<>"",10,0) -> 0 | J15: =IF($G15<>"",INDEX(Data!$M:$M,MATCH($G15,Data!$D:$D,0)),0) -> 0 | K15: =PRODUCT($H15:$J15)*$O$53 -> 0 | L15: =IF($G15<>"",INDEX(Deltas!$E:$E,MATCH($G15,Deltas!$B:$B,0)),0) -> 0 | M15: =PRODUCT($H15:$J15,$L15) -> 0 | N15: =ABS(PRODUCT($H15:$J15,$L15))/Summary!$B$4*$O$53 -> #DIV/0! | O15: 1
G16: =Summary!W$1 | H16: =IF($G16<>"",INDEX(Data!$G:$G,MATCH($G16,Data!$D:$D,0)),0) -> 0 | I16: =IF($G16<>"",10,0) -> 0 | J16: =IF($G16<>"",INDEX(Data!$M:$M,MATCH($G16,Data!$D:$D,0)),0) -> 0 | K16: =PRODUCT($H16:$J16)*$O$53 -> 0 | L16: =IF($G16<>"",INDEX(Deltas!$E:$E,MATCH($G16,Deltas!$B:$B,0)),0) -> 0 | M16: =PRODUCT($H16:$J16,$L16) -> 0 | N16: =ABS(PRODUCT($H16:$J16,$L16))/Summary!$B$4*$O$53 -> #DIV/0! | O16: 1
G17: =Summary!X$1 | H17: =IF($G17<>"",INDEX(Data!$G:$G,MATCH($G17,Data!$D:$D,0)),0) -> 0 | I17: =IF($G17<>"",10,0) -> 0 | J17: =IF($G17<>"",INDEX(Data!$M:$M,MATCH($G17,Data!$D:$D,0)),0) -> 0 | K17: =PRODUCT($H17:$J17)*$O$53 -> 0 | L17: =IF($G17<>"",INDEX(Deltas!$E:$E,MATCH($G17,Deltas!$B:$B,0)),0) -> 0 | M17: =PRODUCT($H17:$J17,$L17) -> 0 | N17: =ABS(PRODUCT($H17:$J17,$L17))/Summary!$B$4*$O$53 -> #DIV/0! | O17: 1
G18: ="Swaps ("&COUNTIF(Data!$C:$C,"Swaps")&")" -> Swaps (0)
G19: =Summary!I$16 | H19: =IF($G19<>"",INDEX(Data!$G:$G,MATCH($G19,Data!$D:$D,0)),0) -> 0 | I19: =IF($G19<>"",1,0) -> 0 | J19: =IF($G19<>"",INDEX(Data!$M:$M,MATCH($G19,Data!$D:$D,0)),0)/100 -> 0 | K19: =PRODUCT($H19,$J19)*$O$53 -> 0 | L19: =IF($G19<>"",1,0) -> 0 | M19: =PRODUCT($H19,$J19,$L19) -> 0 | N19: =ABS(PRODUCT($H19:$J19,$L19))/Summary!$B$4*$O$53 -> #DIV/0! | O19: 1
G20: =Summary!J$16 | H20: =IF($G20<>"",INDEX(Data!$G:$G,MATCH($G20,Data!$D:$D,0)),0) -> 0 | I20: =IF($G20<>"",1,0) -> 0 | J20: =IF($G20<>"",INDEX(Data!$M:$M,MATCH($G20,Data!$D:$D,0)),0)/100 -> 0 | K20: =PRODUCT($H20,$J20)*$O$53 -> 0 | L20: =IF($G20<>"",1,0) -> 0 | M20: =PRODUCT($H20,$J20,$L20) -> 0 | N20: =ABS(PRODUCT($H20:$J20,$L20))/Summary!$B$4*$O$53 -> #DIV/0! | O20: 1
G21: =Summary!K$16 | H21: =IF($G21<>"",INDEX(Data!$G:$G,MATCH($G21,Data!$D:$D,0)),0) -> 0 | I21: =IF($G21<>"",1,0) -> 0 | J21: =IF($G21<>"",INDEX(Data!$M:$M,MATCH($G21,Data!$D:$D,0)),0)/100 -> 0 | K21: =PRODUCT($H21,$J21)*$O$53 -> 0 | L21: =IF($G21<>"",1,0) -> 0 | M21: =PRODUCT($H21,$J21,$L21) -> 0 | N21: =ABS(PRODUCT($H21:$J21,$L21))/Summary!$B$4*$O$53 -> #DIV/0! | O21: 1
G22: =Summary!L$16 | H22: =IF($G22<>"",INDEX(Data!$G:$G,MATCH($G22,Data!$D:$D,0)),0) -> 0 | I22: =IF($G22<>"",1,0) -> 0 | J22: =IF($G22<>"",INDEX(Data!$M:$M,MATCH($G22,Data!$D:$D,0)),0)/100 -> 0 | K22: =PRODUCT($H22,$J22)*$O$53 -> 0 | L22: =IF($G22<>"",1,0) -> 0 | M22: =PRODUCT($H22:$J22,$L22) -> 0 | N22: =ABS(PRODUCT($H22:$J22,$L22))/Summary!$B$4*$O$53 -> #DIV/0! | O22: 1
G23: =Summary!M$16 | H23: =IF($G23<>"",INDEX(Data!$G:$G,MATCH($G23,Data!$D:$D,0)),0) -> 0 | I23: =IF($G23<>"",1,0) -> 0 | J23: =IF($G23<>"",INDEX(Data!$M:$M,MATCH($G23,Data!$D:$D,0)),0)/100 -> 0 | K23: =PRODUCT($H23,$J23)*$O$53 -> 0 | L23: =IF($G23<>"",1,0) -> 0 | M23: =PRODUCT($H23:$J23,$L23) -> 0 | N23: =ABS(PRODUCT($H23:$J23,$L23))/Summary!$B$4*$O$53 -> #DIV/0! | O23: 1
G24: =Summary!N$16 | H24: =IF($G24<>"",INDEX(Data!$G:$G,MATCH($G24,Data!$D:$D,0)),0) -> 0 | I24: =IF($G24<>"",1,0) -> 0 | J24: =IF($G24<>"",INDEX(Data!$M:$M,MATCH($G24,Data!$D:$D,0)),0)/100 -> 0 | K24: =PRODUCT($H24,$J24)*$O$53 -> 0 | L24: =IF($G24<>"",1,0) -> 0 | M24: =PRODUCT($H24:$J24,$L24) -> 0 | N24: =ABS(PRODUCT($H24:$J24,$L24))/Summary!$B$4*$O$53 -> #DIV/0! | O24: 1
G25: =Summary!O$16 | H25: =IF($G25<>"",INDEX(Data!$G:$G,MATCH($G25,Data!$D:$D,0)),0) -> 0 | I25: =IF($G25<>"",1,0) -> 0 | J25: =IF($G25<>"",INDEX(Data!$M:$M,MATCH($G25,Data!$D:$D,0)),0)/100 -> 0 | K25: =PRODUCT($H25,$J25)*$O$53 -> 0 | L25: =IF($G25<>"",1,0) -> 0 | M25: =PRODUCT($H25:$J25,$L25) -> 0 | N25: =ABS(PRODUCT($H25:$J25,$L25))/Summary!$B$4*$O$53 -> #DIV/0! | O25: 1
G26: =Summary!P$16 | H26: =IF($G26<>"",INDEX(Data!$G:$G,MATCH($G26,Data!$D:$D,0)),0) -> 0 | I26: =IF($G26<>"",1,0) -> 0 | J26: =IF($G26<>"",INDEX(Data!$M:$M,MATCH($G26,Data!$D:$D,0)),0)/100 -> 0 | K26: =PRODUCT($H26,$J26)*$O$53 -> 0 | L26: =IF($G26<>"",1,0) -> 0 | M26: =PRODUCT($H26:$J26,$L26) -> 0 | N26: =ABS(PRODUCT($H26:$J26,$L26))/Summary!$B$4*$O$53 -> #DIV/0! | O26: 1
G27: =Summary!Q$16 | H27: =IF($G27<>"",INDEX(Data!$G:$G,MATCH($G27,Data!$D:$D,0)),0) -> 0 | I27: =IF($G27<>"",1,0) -> 0 | J27: =IF($G27<>"",INDEX(Data!$M:$M,MATCH($G27,Data!$D:$D,0)),0)/100 -> 0 | K27: =PRODUCT($H27,$J27)*$O$53 -> 0 | L27: =IF($G27<>"",1,0) -> 0 | M27: =PRODUCT($H27:$J27,$L27) -> 0 | N27: =ABS(PRODUCT($H27:$J27,$L27))/Summary!$B$4*$O$53 -> #DIV/0! | O27: 1
G28: =Summary!R$16 | H28: =IF($G28<>"",INDEX(Data!$G:$G,MATCH($G28,Data!$D:$D,0)),0) -> 0 | I28: =IF($G28<>"",1,0) -> 0 | J28: =IF($G28<>"",INDEX(Data!$M:$M,MATCH($G28,Data!$D:$D,0)),0)/100 -> 0 | K28: =PRODUCT($H28,$J28)*$O$53 -> 0 | L28: =IF($G28<>"",1,0) -> 0 | M28: =PRODUCT($H28:$J28,$L28) -> 0 | N28: =ABS(PRODUCT($H28:$J28,$L28))/Summary!$B$4*$O$53 -> #DIV/0! | O28: 1
G29: =Summary!S$16 | H29: =IF($G29<>"",INDEX(Data!$G:$G,MATCH($G29,Data!$D:$D,0)),0) -> 0 | I29: =IF($G29<>"",1,0) -> 0 | J29: =IF($G29<>"",INDEX(Data!$M:$M,MATCH($G29,Data!$D:$D,0)),0)/100 -> 0 | K29: =PRODUCT($H29,$J29)*$O$53 -> 0 | L29: =IF($G29<>"",1,0) -> 0 | M29: =PRODUCT($H29:$J29,$L29) -> 0 | N29: =ABS(PRODUCT($H29:$J29,$L29))/Summary!$B$4*$O$53 -> #DIV/0! | O29: 1
G30: =Summary!T$16 | H30: =IF($G30<>"",INDEX(Data!$G:$G,MATCH($G30,Data!$D:$D,0)),0) -> 0 | I30: =IF($G30<>"",1,0) -> 0 | J30: =IF($G30<>"",INDEX(Data!$M:$M,MATCH($G30,Data!$D:$D,0)),0)/100 -> 0 | K30: =PRODUCT($H30,$J30)*$O$53 -> 0 | L30: =IF($G30<>"",1,0) -> 0 | M30: =PRODUCT($H30:$J30,$L30) -> 0 | N30: =ABS(PRODUCT($H30:$J30,$L30))/Summary!$B$4*$O$53 -> #DIV/0! | O30: 1
G31: =Summary!U$16 | H31: =IF($G31<>"",INDEX(Data!$G:$G,MATCH($G31,Data!$D:$D,0)),0) -> 0 | I31: =IF($G31<>"",1,0) -> 0 | J31: =IF($G31<>"",INDEX(Data!$M:$M,MATCH($G31,Data!$D:$D,0)),0)/100 -> 0 | K31: =PRODUCT($H31,$J31)*$O$53 -> 0 | L31: =IF($G31<>"",1,0) -> 0 | M31: =PRODUCT($H31:$J31,$L31) -> 0 | N31: =ABS(PRODUCT($H31:$J31,$L31))/Summary!$B$4*$O$53 -> #DIV/0! | O31: 1
G32: =Summary!V$16 | H32: =IF($G32<>"",INDEX(Data!$G:$G,MATCH($G32,Data!$D:$D,0)),0) -> 0 | I32: =IF($G32<>"",1,0) -> 0 | J32: =IF($G32<>"",INDEX(Data!$M:$M,MATCH($G32,Data!$D:$D,0)),0)/100 -> 0 | K32: =PRODUCT($H32,$J32)*$O$53 -> 0 | L32: =IF($G32<>"",1,0) -> 0 | M32: =PRODUCT($H32:$J32,$L32) -> 0 | N32: =ABS(PRODUCT($H32:$J32,$L32))/Summary!$B$4*$O$53 -> #DIV/0! | O32: 1
G33: =Summary!W$16 | H33: =IF($G33<>"",INDEX(Data!$G:$G,MATCH($G33,Data!$D:$D,0)),0) -> 0 | I33: =IF($G33<>"",1,0) -> 0 | J33: =IF($G33<>"",INDEX(Data!$M:$M,MATCH($G33,Data!$D:$D,0)),0)/100 -> 0 | K33: =PRODUCT($H33,$J33)*$O$53 -> 0 | L33: =IF($G33<>"",1,0) -> 0 | M33: =PRODUCT($H33:$J33,$L33) -> 0 | N33: =ABS(PRODUCT($H33:$J33,$L33))/Summary!$B$4*$O$53 -> #DIV/0! | O33: 1
G34: =Summary!X$16 | H34: =IF($G34<>"",INDEX(Data!$G:$G,MATCH($G34,Data!$D:$D,0)),0) -> 0 | I34: =IF($G34<>"",1,0) -> 0 | J34: =IF($G34<>"",INDEX(Data!$M:$M,MATCH($G34,Data!$D:$D,0)),0)/100 -> 0 | K34: =PRODUCT($H34,$J34)*$O$53 -> 0 | L34: =IF($G34<>"",1,0) -> 0 | M34: =PRODUCT($H34:$J34,$L34) -> 0 | N34: =ABS(PRODUCT($H34:$J34,$L34))/Summary!$B$4*$O$53 -> #DIV/0! | O34: 1
G35: ="Bond Derivatives ("&COUNTIF(Data!$C:$C,"Bond Derivatives")&")" -> Bond Derivatives (0)
G36: =Summary!I$7 | H36: =IF($G36<>"",INDEX(Data!$G:$G,MATCH($G36,Data!$D:$D,0)),0) -> 0 | I36: =IF($G36<>"",10,0) -> 0 | J36: =IF($G36<>"",INDEX(Data!$M:$M,MATCH($G36,Data!$D:$D,0)),0) -> 0 | K36: =PRODUCT($H36:$J36)*$O$53 -> 0 | L36: =IF($G36<>"",INDEX(Deltas!$E:$E,MATCH($G36,Deltas!$B:$B,0)),0) -> 0 | M36: =PRODUCT($H36:$J36,$L36)*$O$53 -> 0 | N36: =ABS(PRODUCT($H36:$J36,$L36))/Summary!$B$4*$O$53 -> #DIV/0! | O36: 1
G37: =Summary!J$7 | H37: =IF($G37<>"",INDEX(Data!$G:$G,MATCH($G37,Data!$D:$D,0)),0) -> 0 | I37: =IF($G37<>"",10,0) -> 0 | J37: =IF($G37<>"",INDEX(Data!$M:$M,MATCH($G37,Data!$D:$D,0)),0) -> 0 | K37: =PRODUCT($H37:$J37)*$O$53 -> 0 | L37: =IF($G37<>"",INDEX(Deltas!$E:$E,MATCH($G37,Deltas!$B:$B,0)),0) -> 0 | M37: =PRODUCT($H37:$J37,$L37)*$O$53 -> 0 | N37: =ABS(PRODUCT($H37:$J37,$L37))/Summary!$B$4*$O$53 -> #DIV/0! | O37: 1
G38: =Summary!K$7 | H38: =IF($G38<>"",INDEX(Data!$G:$G,MATCH($G38,Data!$D:$D,0)),0) -> 0 | I38: =IF($G38<>"",10,0) -> 0 | J38: =IF($G38<>"",INDEX(Data!$M:$M,MATCH($G38,Data!$D:$D,0)),0) -> 0 | K38: =PRODUCT($H38:$J38)*$O$53 -> 0 | L38: =IF($G38<>"",INDEX(Deltas!$E:$E,MATCH($G38,Deltas!$B:$B,0)),0) -> 0 | M38: =PRODUCT($H38:$J38,$L38)*$O$53 -> 0 | N38: =ABS(PRODUCT($H38:$J38,$L38))/Summary!$B$4*$O$53 -> #DIV/0! | O38: 1
G39: =Summary!L$7 | H39: =IF($G39<>"",INDEX(Data!$G:$G,MATCH($G39,Data!$D:$D,0)),0) -> 0 | I39: =IF($G39<>"",10,0) -> 0 | J39: =IF($G39<>"",INDEX(Data!$M:$M,MATCH($G39,Data!$D:$D,0)),0) -> 0 | K39: =PRODUCT($H39:$J39)*$O$53 -> 0 | L39: =IF($G39<>"",INDEX(Deltas!$E:$E,MATCH($G39,Deltas!$B:$B,0)),0) -> 0 | M39: =PRODUCT($H39:$J39,$L39)*$O$53 -> 0 | N39: =ABS(PRODUCT($H39:$J39,$L39))/Summary!$B$4*$O$53 -> #DIV/0! | O39: 1
G40: =Summary!M$7 | H40: =IF($G40<>"",INDEX(Data!$G:$G,MATCH($G40,Data!$D:$D,0)),0) -> 0 | I40: =IF($G40<>"",10,0) -> 0 | J40: =IF($G40<>"",INDEX(Data!$M:$M,MATCH($G40,Data!$D:$D,0)),0) -> 0 | K40: =PRODUCT($H40:$J40)*$O$53 -> 0 | L40: =IF($G40<>"",INDEX(Deltas!$E:$E,MATCH($G40,Deltas!$B:$B,0)),0) -> 0 | M40: =PRODUCT($H40:$J40,$L40)*$O$53 -> 0 | N40: =ABS(PRODUCT($H40:$J40,$L40))/Summary!$B$4*$O$53 -> #DIV/0! | O40: 1
G41: =Summary!N$7 | H41: =IF($G41<>"",INDEX(Data!$G:$G,MATCH($G41,Data!$D:$D,0)),0) -> 0 | I41: =IF($G41<>"",10,0) -> 0 | J41: =IF($G41<>"",INDEX(Data!$M:$M,MATCH($G41,Data!$D:$D,0)),0) -> 0 | K41: =PRODUCT($H41:$J41)*$O$53 -> 0 | L41: =IF($G41<>"",INDEX(Deltas!$E:$E,MATCH($G41,Deltas!$B:$B,0)),0) -> 0 | M41: =PRODUCT($H41:$J41,$L41)*$O$53 -> 0 | N41: =ABS(PRODUCT($H41:$J41,$L41))/Summary!$B$4*$O$53 -> #DIV/0! | O41: 1
G42: =Summary!O$7 | H42: =IF($G42<>"",INDEX(Data!$G:$G,MATCH($G42,Data!$D:$D,0)),0) -> 0 | I42: =IF($G42<>"",10,0) -> 0 | J42: =IF($G42<>"",INDEX(Data!$M:$M,MATCH($G42,Data!$D:$D,0)),0) -> 0 | K42: =PRODUCT($H42:$J42)*$O$53 -> 0 | L42: =IF($G42<>"",INDEX(Deltas!$E:$E,MATCH($G42,Deltas!$B:$B,0)),0) -> 0 | M42: =PRODUCT($H42:$J42,$L42)*$O$53 -> 0 | N42: =ABS(PRODUCT($H42:$J42,$L42))/Summary!$B$4*$O$53 -> #DIV/0! | O42: 1
G43: =Summary!P$7 | H43: =IF($G43<>"",INDEX(Data!$G:$G,MATCH($G43,Data!$D:$D,0)),0) -> 0 | I43: =IF($G43<>"",10,0) -> 0 | J43: =IF($G43<>"",INDEX(Data!$M:$M,MATCH($G43,Data!$D:$D,0)),0) -> 0 | K43: =PRODUCT($H43:$J43)*$O$53 -> 0 | L43: =IF($G43<>"",INDEX(Deltas!$E:$E,MATCH($G43,Deltas!$B:$B,0)),0) -> 0 | M43: =PRODUCT($H43:$J43,$L43)*$O$53 -> 0 | N43: =ABS(PRODUCT($H43:$J43,$L43))/Summary!$B$4*$O$53 -> #DIV/0! | O43: 1
G44: =Summary!Q$7 | H44: =IF($G44<>"",INDEX(Data!$G:$G,MATCH($G44,Data!$D:$D,0)),0) -> 0 | I44: =IF($G44<>"",10,0) -> 0 | J44: =IF($G44<>"",INDEX(Data!$M:$M,MATCH($G44,Data!$D:$D,0)),0) -> 0 | K44: =PRODUCT($H44:$J44)*$O$53 -> 0 | L44: =IF($G44<>"",INDEX(Deltas!$E:$E,MATCH($G44,Deltas!$B:$B,0)),0) -> 0 | M44: =PRODUCT($H44:$J44,$L44)*$O$53 -> 0 | N44: =ABS(PRODUCT($H44:$J44,$L44))/Summary!$B$4*$O$53 -> #DIV/0! | O44: 1
G45: =Summary!R$7 | H45: =IF($G45<>"",INDEX(Data!$G:$G,MATCH($G45,Data!$D:$D,0)),0) -> 0 | I45: =IF($G45<>"",10,0) -> 0 | J45: =IF($G45<>"",INDEX(Data!$M:$M,MATCH($G45,Data!$D:$D,0)),0) -> 0 | K45: =PRODUCT($H45:$J45)*$O$53 -> 0 | L45: =IF($G45<>"",INDEX(Deltas!$E:$E,MATCH($G45,Deltas!$B:$B,0)),0) -> 0 | M45: =PRODUCT($H45:$J45,$L45)*$O$53 -> 0 | N45: =ABS(PRODUCT($H45:$J45,$L45))/Summary!$B$4*$O$53 -> #DIV/0! | O45: 1
G46: =Summary!S$7 | H46: =IF($G46<>"",INDEX(Data!$G:$G,MATCH($G46,Data!$D:$D,0)),0) -> 0 | I46: =IF($G46<>"",10,0) -> 0 | J46: =IF($G46<>"",INDEX(Data!$M:$M,MATCH($G46,Data!$D:$D,0)),0) -> 0 | K46: =PRODUCT($H46:$J46)*$O$53 -> 0 | L46: =IF($G46<>"",INDEX(Deltas!$E:$E,MATCH($G46,Deltas!$B:$B,0)),0) -> 0 | M46: =PRODUCT($H46:$J46,$L46)*$O$53 -> 0 | N46: =ABS(PRODUCT($H46:$J46,$L46))/Summary!$B$4*$O$53 -> #DIV/0! | O46: 1
G47: =Summary!T$7 | H47: =IF($G47<>"",INDEX(Data!$G:$G,MATCH($G47,Data!$D:$D,0)),0) -> 0 | I47: =IF($G47<>"",10,0) -> 0 | J47: =IF($G47<>"",INDEX(Data!$M:$M,MATCH($G47,Data!$D:$D,0)),0) -> 0 | K47: =PRODUCT($H47:$J47)*$O$53 -> 0 | L47: =IF($G47<>"",INDEX(Deltas!$E:$E,MATCH($G47,Deltas!$B:$B,0)),0) -> 0 | M47: =PRODUCT($H47:$J47,$L47)*$O$53 -> 0 | N47: =ABS(PRODUCT($H47:$J47,$L47))/Summary!$B$4*$O$53 -> #DIV/0! | O47: 1
G48: =Summary!U$7 | H48: =IF($G48<>"",INDEX(Data!$G:$G,MATCH($G48,Data!$D:$D,0)),0) -> 0 | I48: =IF($G48<>"",10,0) -> 0 | J48: =IF($G48<>"",INDEX(Data!$M:$M,MATCH($G48,Data!$D:$D,0)),0) -> 0 | K48: =PRODUCT($H48:$J48)*$O$53 -> 0 | L48: =IF($G48<>"",INDEX(Deltas!$E:$E,MATCH($G48,Deltas!$B:$B,0)),0) -> 0 | M48: =PRODUCT($H48:$J48,$L48)*$O$53 -> 0 | N48: =ABS(PRODUCT($H48:$J48,$L48))/Summary!$B$4*$O$53 -> #DIV/0! | O48: 1
G49: =Summary!V$7 | H49: =IF($G49<>"",INDEX(Data!$G:$G,MATCH($G49,Data!$D:$D,0)),0) -> 0 | I49: =IF($G49<>"",10,0) -> 0 | J49: =IF($G49<>"",INDEX(Data!$M:$M,MATCH($G49,Data!$D:$D,0)),0) -> 0 | K49: =PRODUCT($H49:$J49)*$O$53 -> 0 | L49: =IF($G49<>"",INDEX(Deltas!$E:$E,MATCH($G49,Deltas!$B:$B,0)),0) -> 0 | M49: =PRODUCT($H49:$J49,$L49)*$O$53 -> 0 | N49: =ABS(PRODUCT($H49:$J49,$L49))/Summary!$B$4*$O$53 -> #DIV/0! | O49: 1
G50: =Summary!W$7 | H50: =IF($G50<>"",INDEX(Data!$G:$G,MATCH($G50,Data!$D:$D,0)),0) -> 0 | I50: =IF($G50<>"",10,0) -> 0 | J50: =IF($G50<>"",INDEX(Data!$M:$M,MATCH($G50,Data!$D:$D,0)),0) -> 0 | K50: =PRODUCT($H50:$J50)*$O$53 -> 0 | L50: =IF($G50<>"",INDEX(Deltas!$E:$E,MATCH($G50,Deltas!$B:$B,0)),0) -> 0 | M50: =PRODUCT($H50:$J50,$L50)*$O$53 -> 0 | N50: =ABS(PRODUCT($H50:$J50,$L50))/Summary!$B$4*$O$53 -> #DIV/0! | O50: 1
G51: =Summary!X$7 | H51: =IF($G51<>"",INDEX(Data!$G:$G,MATCH($G51,Data!$D:$D,0)),0) -> 0 | I51: =IF($G51<>"",10,0) -> 0 | J51: =IF($G51<>"",INDEX(Data!$M:$M,MATCH($G51,Data!$D:$D,0)),0) -> 0 | K51: =PRODUCT($H51:$J51)*$O$53 -> 0 | L51: =IF($G51<>"",INDEX(Deltas!$E:$E,MATCH($G51,Deltas!$B:$B,0)),0) -> 0 | M51: =PRODUCT($H51:$J51,$L51)*$O$53 -> 0 | N51: =ABS(PRODUCT($H51:$J51,$L51))/Summary!$B$4*$O$53 -> #DIV/0! | O51: 1
G52: {="Foreign Equity Derivatives ("&SUMPRODUCT((Data!$C:$C="Equity Derivatives")*(Data!$W:$W<>"ZAR"))&")"} -> Foreign Equity Derivatives (0)
G53: =Summary!I$4 | H53: =IF($G53<>"",INDEX(Data!$G:$G,MATCH($G53,Data!$D:$D,0)),0) -> 0 | I53: =IF($G53<>"",10,0) -> 0 | J53: =IF($G53<>"",INDEX(Data!$M:$M,MATCH($G53,Data!$D:$D,0)),0) -> 0 | K53: =PRODUCT($H53:$J53)*$O$53 -> 0 | L53: =IF($G53<>"",INDEX(Deltas!$E:$E,MATCH($G53,Deltas!$B:$B,0)),0) -> 0 | M53: =PRODUCT($H53:$J53,$L53) -> 0 | N53: =ABS(PRODUCT($H53:$J53,$L53))/Summary!$B$4*$O$53 -> #DIV/0! | O53: 15.58
G54: =Summary!J$4 | H54: =IF($G54<>"",INDEX(Data!$G:$G,MATCH($G54,Data!$D:$D,0)),0) -> 0 | I54: =IF($G54<>"",10,0) -> 0 | J54: =IF($G54<>"",INDEX(Data!$M:$M,MATCH($G54,Data!$D:$D,0)),0) -> 0 | K54: =PRODUCT($H54:$J54)*$O$53 -> 0 | L54: =IF($G54<>"",INDEX(Deltas!$E:$E,MATCH($G54,Deltas!$B:$B,0)),0) -> 0 | M54: =PRODUCT($H54:$J54,$L54) -> 0 | N54: =ABS(PRODUCT($H54:$J54,$L54))/Summary!$B$4*$O$53 -> #DIV/0! | O54: 15.58
G55: =Summary!K$4 | H55: =IF($G55<>"",INDEX(Data!$G:$G,MATCH($G55,Data!$D:$D,0)),0) -> 0 | I55: =IF($G55<>"",10,0) -> 0 | J55: =IF($G55<>"",INDEX(Data!$M:$M,MATCH($G55,Data!$D:$D,0)),0) -> 0 | K55: =PRODUCT($H55:$J55)*$O$53 -> 0 | L55: =IF($G55<>"",INDEX(Deltas!$E:$E,MATCH($G55,Deltas!$B:$B,0)),0) -> 0 | M55: =PRODUCT($H55:$J55,$L55) -> 0 | N55: =ABS(PRODUCT($H55:$J55,$L55))/Summary!$B$4*$O$53 -> #DIV/0! | O55: 15.58
G56: =Summary!L$4 | H56: =IF($G56<>"",INDEX(Data!$G:$G,MATCH($G56,Data!$D:$D,0)),0) -> 0 | I56: =IF($G56<>"",10,0) -> 0 | J56: =IF($G56<>"",INDEX(Data!$M:$M,MATCH($G56,Data!$D:$D,0)),0) -> 0 | K56: =PRODUCT($H56:$J56)*$O$53 -> 0 | L56: =IF($G56<>"",INDEX(Deltas!$E:$E,MATCH($G56,Deltas!$B:$B,0)),0) -> 0 | M56: =PRODUCT($H56:$J56,$L56) -> 0 | N56: =ABS(PRODUCT($H56:$J56,$L56))/Summary!$B$4*$O$53 -> #DIV/0! | O56: 15.58
G57: =Summary!M$4 | H57: =IF($G57<>"",INDEX(Data!$G:$G,MATCH($G57,Data!$D:$D,0)),0) -> 0 | I57: =IF($G57<>"",10,0) -> 0 | J57: =IF($G57<>"",INDEX(Data!$M:$M,MATCH($G57,Data!$D:$D,0)),0) -> 0 | K57: =PRODUCT($H57:$J57)*$O$53 -> 0 | L57: =IF($G57<>"",INDEX(Deltas!$E:$E,MATCH($G57,Deltas!$B:$B,0)),0) -> 0 | M57: =PRODUCT($H57:$J57,$L57) -> 0 | N57: =ABS(PRODUCT($H57:$J57,$L57))/Summary!$B$4*$O$53 -> #DIV/0! | O57: 15.58
G58: =Summary!N$4 | H58: =IF($G58<>"",INDEX(Data!$G:$G,MATCH($G58,Data!$D:$D,0)),0) -> 0 | I58: =IF($G58<>"",10,0) -> 0 | J58: =IF($G58<>"",INDEX(Data!$M:$M,MATCH($G58,Data!$D:$D,0)),0) -> 0 | K58: =PRODUCT($H58:$J58)*$O$53 -> 0 | L58: =IF($G58<>"",INDEX(Deltas!$E:$E,MATCH($G58,Deltas!$B:$B,0)),0) -> 0 | M58: =PRODUCT($H58:$J58,$L58) -> 0 | N58: =ABS(PRODUCT($H58:$J58,$L58))/Summary!$B$4*$O$53 -> #DIV/0! | O58: 15.58
G59: =Summary!O$4 | H59: =IF($G59<>"",INDEX(Data!$G:$G,MATCH($G59,Data!$D:$D,0)),0) -> 0 | I59: =IF($G59<>"",10,0) -> 0 | J59: =IF($G59<>"",INDEX(Data!$M:$M,MATCH($G59,Data!$D:$D,0)),0) -> 0 | K59: =PRODUCT($H59:$J59)*$O$53 -> 0 | L59: =IF($G59<>"",INDEX(Deltas!$E:$E,MATCH($G59,Deltas!$B:$B,0)),0) -> 0 | M59: =PRODUCT($H59:$J59,$L59) -> 0 | N59: =ABS(PRODUCT($H59:$J59,$L59))/Summary!$B$4*$O$53 -> #DIV/0! | O59: 15.58
G60: =Summary!P$4 | H60: =IF($G60<>"",INDEX(Data!$G:$G,MATCH($G60,Data!$D:$D,0)),0) -> 0 | I60: =IF($G60<>"",10,0) -> 0 | J60: =IF($G60<>"",INDEX(Data!$M:$M,MATCH($G60,Data!$D:$D,0)),0) -> 0 | K60: =PRODUCT($H60:$J60)*$O$53 -> 0 | L60: =IF($G60<>"",INDEX(Deltas!$E:$E,MATCH($G60,Deltas!$B:$B,0)),0) -> 0 | M60: =PRODUCT($H60:$J60,$L60) -> 0 | N60: =ABS(PRODUCT($H60:$J60,$L60))/Summary!$B$4*$O$53 -> #DIV/0! | O60: 15.58
G61: =Summary!Q$4 | H61: =IF($G61<>"",INDEX(Data!$G:$G,MATCH($G61,Data!$D:$D,0)),0) -> 0 | I61: =IF($G61<>"",10,0) -> 0 | J61: =IF($G61<>"",INDEX(Data!$M:$M,MATCH($G61,Data!$D:$D,0)),0) -> 0 | K61: =PRODUCT($H61:$J61)*$O$53 -> 0 | L61: =IF($G61<>"",INDEX(Deltas!$E:$E,MATCH($G61,Deltas!$B:$B,0)),0) -> 0 | M61: =PRODUCT($H61:$J61,$L61) -> 0 | N61: =ABS(PRODUCT($H61:$J61,$L61))/Summary!$B$4*$O$53 -> #DIV/0! | O61: 15.58
G62: =Summary!R$4 | H62: =IF($G62<>"",INDEX(Data!$G:$G,MATCH($G62,Data!$D:$D,0)),0) -> 0 | I62: =IF($G62<>"",10,0) -> 0 | J62: =IF($G62<>"",INDEX(Data!$M:$M,MATCH($G62,Data!$D:$D,0)),0) -> 0 | K62: =PRODUCT($H62:$J62)*$O$53 -> 0 | L62: =IF($G62<>"",INDEX(Deltas!$E:$E,MATCH($G62,Deltas!$B:$B,0)),0) -> 0 | M62: =PRODUCT($H62:$J62,$L62) -> 0 | N62: =ABS(PRODUCT($H62:$J62,$L62))/Summary!$B$4*$O$53 -> #DIV/0! | O62: 15.58
G63: =Summary!S$4 | H63: =IF($G63<>"",INDEX(Data!$G:$G,MATCH($G63,Data!$D:$D,0)),0) -> 0 | I63: =IF($G63<>"",10,0) -> 0 | J63: =IF($G63<>"",INDEX(Data!$M:$M,MATCH($G63,Data!$D:$D,0)),0) -> 0 | K63: =PRODUCT($H63:$J63)*$O$53 -> 0 | L63: =IF($G63<>"",INDEX(Deltas!$E:$E,MATCH($G63,Deltas!$B:$B,0)),0) -> 0 | M63: =PRODUCT($H63:$J63,$L63) -> 0 | N63: =ABS(PRODUCT($H63:$J63,$L63))/Summary!$B$4*$O$53 -> #DIV/0! | O63: 15.58
G64: =Summary!T$4 | H64: =IF($G64<>"",INDEX(Data!$G:$G,MATCH($G64,Data!$D:$D,0)),0) -> 0 | I64: =IF($G64<>"",10,0) -> 0 | J64: =IF($G64<>"",INDEX(Data!$M:$M,MATCH($G64,Data!$D:$D,0)),0) -> 0 | K64: =PRODUCT($H64:$J64)*$O$53 -> 0 | L64: =IF($G64<>"",INDEX(Deltas!$E:$E,MATCH($G64,Deltas!$B:$B,0)),0) -> 0 | M64: =PRODUCT($H64:$J64,$L64) -> 0 | N64: =ABS(PRODUCT($H64:$J64,$L64))/Summary!$B$4*$O$53 -> #DIV/0! | O64: 15.58
G65: =Summary!U$4 | H65: =IF($G65<>"",INDEX(Data!$G:$G,MATCH($G65,Data!$D:$D,0)),0) -> 0 | I65: =IF($G65<>"",10,0) -> 0 | J65: =IF($G65<>"",INDEX(Data!$M:$M,MATCH($G65,Data!$D:$D,0)),0) -> 0 | K65: =PRODUCT($H65:$J65)*$O$53 -> 0 | L65: =IF($G65<>"",INDEX(Deltas!$E:$E,MATCH($G65,Deltas!$B:$B,0)),0) -> 0 | M65: =PRODUCT($H65:$J65,$L65) -> 0 | N65: =ABS(PRODUCT($H65:$J65,$L65))/Summary!$B$4*$O$53 -> #DIV/0! | O65: 15.58
G66: =Summary!V$4 | H66: =IF($G66<>"",INDEX(Data!$G:$G,MATCH($G66,Data!$D:$D,0)),0) -> 0 | I66: =IF($G66<>"",10,0) -> 0 | J66: =IF($G66<>"",INDEX(Data!$M:$M,MATCH($G66,Data!$D:$D,0)),0) -> 0 | K66: =PRODUCT($H66:$J66)*$O$53 -> 0 | L66: =IF($G66<>"",INDEX(Deltas!$E:$E,MATCH($G66,Deltas!$B:$B,0)),0) -> 0 | M66: =PRODUCT($H66:$J66,$L66) -> 0 | N66: =ABS(PRODUCT($H66:$J66,$L66))/Summary!$B$4*$O$53 -> #DIV/0! | O66: 15.58
G67: =Summary!W$4 | H67: =IF($G67<>"",INDEX(Data!$G:$G,MATCH($G67,Data!$D:$D,0)),0) -> 0 | I67: =IF($G67<>"",10,0) -> 0 | J67: =IF($G67<>"",INDEX(Data!$M:$M,MATCH($G67,Data!$D:$D,0)),0) -> 0 | K67: =PRODUCT($H67:$J67)*$O$53 -> 0 | L67: =IF($G67<>"",INDEX(Deltas!$E:$E,MATCH($G67,Deltas!$B:$B,0)),0) -> 0 | M67: =PRODUCT($H67:$J67,$L67) -> 0 | N67: =ABS(PRODUCT($H67:$J67,$L67))/Summary!$B$4*$O$53 -> #DIV/0! | O67: 15.58
G68: =Summary!X$4 | H68: =IF($G68<>"",INDEX(Data!$G:$G,MATCH($G68,Data!$D:$D,0)),0) -> 0 | I68: =IF($G68<>"",10,0) -> 0 | J68: =IF($G68<>"",INDEX(Data!$M:$M,MATCH($G68,Data!$D:$D,0)),0) -> 0 | K68: =PRODUCT($H68:$J68)*$O$53 -> 0 | L68: =IF($G68<>"",INDEX(Deltas!$E:$E,MATCH($G68,Deltas!$B:$B,0)),0) -> 0 | M68: =PRODUCT($H68:$J68,$L68) -> 0 | N68: =ABS(PRODUCT($H68:$J68,$L68))/Summary!$B$4*$O$53 -> #DIV/0! | O68: 15.58

Sheet Data
B1: Entity Name | C1: Valuation First Level | D1: Valuation Second Level | E1: i Issue Name | F1: PrimaryAssetID | G1: Issue Description | H1: Original Nominal | I1: Clean Book Value | J1: Clean Market Value | K1: Accrued Income | L1: Dividend Receivable | M1: Sum of Market Value Income | N1: Market Price /Yield | O1: % of Total Market Value | P1: Next Coupon Date | Q1: Maturity Date | R1: Coupon | S1: Duration | T1: Modified Duration | U1: Investment Type | V1: Security Type | W1: Sub Security Type | X1: CCY | Y1: Sector | Z1: Supersector | AA1: Industry | AB1: Issuer Rating | AC1: Security Rating | AD1: NACA Yield | AE1: NACM Yield | AF1: Weighted Avg NACA Yield | AG1: Weighted Avg NACM Yield | AH1: Market Value % | AI1: Current Exposure | AJ1: Current Exposure % | AK1: i Position Effective Date | AL1: Entity ID | AM1: Weighted Average NACS Yield | AN1: Weighted Average Coupon | AO1: Weighted Modified Duration | AP1: Issuer | AQ1: ISIN Code | AR1: Ticker | AS1: =SUMPRODUCT((B:B = "DERIVATIVES")*(C:C = "UNKNOWN")) -> 0
A2: 0 | B2: GA Empolyees Medical BF | C2: BONDS | D2: Bonds (1 - 3 Years) | E2: Nedbank Group Ltd FRN NGT104 150125 JB3+450 | F2: NGT104 | G2: Nedbank Group Ltd FRN NGT104 150125 JB3+450 | H2: 5060000 | I2: 5188272.5 | J2: 5260376.2 | K2: 8620.16 | L2: 0 | M2: 5268996.4 | N2: 7.151458 | O2: 0.050480395 | P2: 44757 | Q2: 45672 | R2: 8.883 | S2: 0.22 | T2: 0.20481451 | U2: FI | V2: FI | W2: FRN | X2: ZAR | Y2: BANKS | AB2: AA | AD2: 7.279316 | AE2: 7.0471799 | AF2: 7.28 | AG2: 7.0471799 | AH2: 5.11 | AI2: 5268996.4 | AJ2: 0.01 | AK2: 44676 | AL2: GAEMBF | AM2: 7.15 | AN2: 8.88 | AO2: 0.2 | AP2: NEDBANK LTD | AQ2: ZAG000160441 | AR2: NGT104
A3: 1 | B3: GA Empolyees Medical BF | C3: BONDS | D3: Bonds (3 - 7 Years) | E3: LBK28 10.565% 150528 | F3: LBK28 | G3: LBK28 10.565% 150528 | H3: 2067120 | I3: 2097620.6 | J3: 1942828.6 | K3: 96929.81 | L3: 0 | M3: 2039758.4 | N3: 11.88 | O3: 0.019542206 | P3: 44697 | Q3: 46888 | R3: 10.565 | S3: 4.73 | T3: 4.4668326 | U3: FI | V3: FI | W3: VB | X3: ZAR | AB3: AA+ | AD3: 12.232836 | AE3: 11.596214 | AF3: 12.23 | AG3: 11.596214 | AH3: 1.98 | AI3: 2039758.4 | AJ3: 0 | AK3: 44676 | AL3: GAEMBF | AM3: 11.88 | AN3: 10.56 | AO3: 4.47 | AP3: LANDBANK | AQ3: ZAG000151275 | AR3: LBK28
A4: 2 | B4: GA Empolyees Medical BF | C4: BONDS | D4: Bonds (3 - 7 Years) | E4: RSA 10.50% R186 211226 | F4: R186 | G4: RSA 10.50% R186 211226 | H4: 17800000 | I4: 19872351 | J4: 19344885 | K4: 645189.04 | L4: 0 | M4: 19990074 | N4: 8.215 | O4: 0.19151785 | P4: 44733 | Q4: 46377 | R4: 10.5 | S4: 3.72 | T4: 3.5704067 | U4: FI | V4: FI | W4: VB | X4: ZAR | Y4: GOVI | AB4: AAA | AD4: 8.3837156 | AE4: 8.0778333 | AF4: 8.38 | AG4: 8.0778333 | AH4: 19.39 | AI4: 19990074 | AJ4: 0.05 | AK4: 44676 | AL4: GAEMBF | AM4: 8.21 | AN4: 10.5 | AO4: 3.57 | AP4: REP OF SOUTH AFRICA | AQ4: ZAG000016320 | AR4: R186
A5: 3 | B5: GA Empolyees Medical BF | C5: BONDS | D5: Bonds (3 - 7 Years) | E5: Standard Bank Group Ltd SBT107 Jb3+379 080427 | F5: SBT107 | G5: Standard Bank Group Ltd SBT107 Jb3+379 080427 | H5: 2130000 | I5: 2130000 | J5: 2132395.1 | K5: 9044.21 | L5: 0 | M5: 2141439.3 | N5: 8.031702 | O5: 0.020516374 | P5: 44750 | Q5: 46485 | R5: 8.157 | S5: 0.2 | T5: 0.092570486 | U5: FI | V5: FI | W5: FRN | X5: ZAR | Y5: BANKS | AB5: AA | AD5: 8.1929731 | AE5: 7.9005174 | AF5: 8.19 | AG5: 7.9005174 | AH5: 2.08 | AI5: 2141439.3 | AJ5: 0 | AK5: 44676 | AL5: GAEMBF | AM5: 8.03 | AN5: 8.16 | AO5: 0.09 | AP5: STANDARD BANK GROUP | AQ5: ZAG000184896 | AR5: SBT107
A6: 4 | B6: GA Empolyees Medical BF | C6: BONDS | D6: Bonds (7 - 12 Years) | E6: Transnet 10.50% TN30 091030 | F6: TN30 | G6: Transnet 10.50% TN30 091030 | H6: 2600000 | I6: 2574893.4 | J6: 2480031.6 | K6: 11219.18 | L6: 0 | M6: 2491250.8 | N6: 11.361 | O6: 0.023867794 | P6: 44844 | Q6: 47765 | R6: 10.5 | S6: 5.71 | T6: 5.4005014 | U6: FI | V6: FI | W6: VB | X6: ZAR | AB6: AA+ | AD6: 11.683681 | AE6: 11.101074 | AF6: 11.68 | AG6: 11.101074 | AH6: 2.42 | AI6: 2491250.8 | AJ6: 0.01 | AK6: 44676 | AL6: GAEMBF | AM6: 11.36 | AN6: 10.5 | AO6: 5.4 | AP6: TRANSNET SOC LTD | AQ6: ZAG000120312 | AR6: TN30
A7: 5 | B7: GA Empolyees Medical BF | C7: BONDS | D7: Bonds (Greater than 12 Years) | E7: R2048 8.75% 280248 | F7: R2048 | G7: R2048 8.75% 280248 | H7: 3600000 | I7: 2896561.4 | J7: 2944734.8 | K7: 49191.8 | L7: 0 | M7: 2993926.6 | N7: 10.86 | O7: 0.028683754 | P7: 44804 | Q7: 54116 | R7: 8.75 | S7: 9.19 | T7: 8.7159378 | U7: FI | V7: FI | W7: VB | X7: ZAR | Y7: GOVI | AB7: AAA | AD7: 11.154849 | AE7: 10.622145 | AF7: 11.15 | AG7: 10.622145 | AH7: 2.9 | AI7: 2993926.6 | AJ7: 0.01 | AK7: 44676 | AL7: GAEMBF | AM7: 10.86 | AN7: 8.75 | AO7: 8.72 | AP7: REP OF SOUTH AFRICA | AQ7: ZAG000096173 | AR7: R2048
A8: 6 | B8: GA Empolyees Medical BF | C8: BONDS | D8: Bonds (Greater than 12 Years) | E8: RSA 8.50% R2037 310137 | F8: R2037 | G8: RSA 8.50% R2037 310137 | H8: 3250000 | I8: 2726349 | J8: 2706025.7 | K8: 64332.19 | L8: 0 | M8: 2770357.9 | N8: 10.79 | O8: 0.026541821 | P8: 44774 | Q8: 50071 | R8: 8.5 | S8: 7.9 | T8: 7.4921091 | U8: FI | V8: FI | W8: VB | X8: ZAR | Y8: GOVI | AB8: AAA | AD8: 11.08106 | AE8: 10.555153 | AF8: 11.08 | AG8: 10.555153 | AH8: 2.69 | AI8: 2770357.9 | AJ8: 0.01 | AK8: 44676 | AL8: GAEMBF | AM8: 10.79 | AN8: 8.5 | AO8: 7.49 | AP8: REP OF SOUTH AFRICA | AQ8: ZAG000107012 | AR8: R2037
A9: 7 | B9: GA Empolyees Medical BF | C9: BONDS | D9: Inflation Linked Bonds | E9: I2038 2.25% 310138 | F9: I2038 | G9: I2038 2.25% 310138 | H9: 1960000 | I9: 2524917.8 | J9: 2538316 | K9: 16458.51 | L9: 0 | M9: 2554774.5 | N9: 3.89 | O9: 0.024476392 | P9: 44774 | Q9: 50436 | R9: 2.25 | S9: 12.94 | T9: 12.689944 | U9: FI | V9: FI | W9: ILB | X9: ZAR | Y9: GOVI | AB9: AAA | AD9: 3.9278302 | AE9: 3.8588444 | AF9: 3.93 | AG9: 3.8588444 | AH9: 2.48 | AI9: 2554774.5 | AJ9: 0.01 | AK9: 44676 | AL9: GAEMBF | AM9: 3.89 | AN9: 2.25 | AO9: 12.69 | AP9: REP OF SOUTH AFRICA | AQ9: ZAG000096595 | AR9: I2038
A10: 8 | B10: GA Empolyees Medical BF | C10: BONDS | D10: Inflation Linked Bonds | E10: I2046 2.50% 310346 | F10: I2046 | G10: I2046 2.50% 310346 | H10: 2140000 | I10: 2516926.1 | J10: 2532462.2 | K10: 5756.35 | L10: 0 | M10: 2538218.6 | N10: 3.9 | O10: 0.024317776 | P10: 44834 | Q10: 53417 | R10: 2.5 | S10: 17.21 | T10: 16.883952 | U10: FI | V10: FI | W10: ILB | X10: ZAR | Y10: GOVI | AB10: AAA | AD10: 3.938025 | AE10: 3.868685 | AF10: 3.94 | AG10: 3.868685 | AH10: 2.46 | AI10: 2538218.6 | AJ10: 0.01 | AK10: 44676 | AL10: GAEMBF | AM10: 3.9 | AN10: 2.5 | AO10: 16.88 | AP10: REP OF SOUTH AFRICA | AQ10: ZAG000106980 | AR10: I2046
A11: 9 | B11: GA Empolyees Medical BF | C11: BONDS | D11: Inflation Linked Bonds | E11: I2050 2.25% 2050 | F11: I2050 | G11: I2050 2.25% 2050 | H11: 2380000 | I11: 2870454.3 | J11: 2894730.9 | K11: 30276.69 | L11: 0 | M11: 2925007.5 | N11: 3.9 | O11: 0.028023465 | P11: 44742 | Q11: 55153 | R11: 2.5 | S11: 19.05 | T11: 18.686914 | U11: FI | V11: FI | W11: ILB | X11: ZAR | Y11: GOVI | AB11: AAA | AD11: 3.938025 | AE11: 3.868685 | AF11: 3.94 | AG11: 3.868685 | AH11: 2.84 | AI11: 2925007.5 | AJ11: 0.01 | AK11: 44676 | AL11: GAEMBF | AM11: 3.9 | AN11: 2.5 | AO11: 18.69 | AP11: REP OF SOUTH AFRICA | AQ11: ZAG000096603 | AR11: I2050
A12: 10 | B12: GA Empolyees Medical BF | C12: BONDS | D12: Inflation Linked Bonds | E12: RSA 1.875% I2033 280233 | F12: I2033 | G12: RSA 1.875% I2033 280233 | H12: 2260000 | I12: 2566170.5 | J12: 2558335.6 | K12: 9040.86 | L12: 0 | M12: 2567376.5 | N12: 3.82 | O12: 0.024597128 | P12: 44804 | Q12: 48638 | R12: 1.875 | S12: 9.71 | T12: 9.5250554 | U12: FI | V12: FI | W12: ILB | X12: ZAR | Y12: GOVI | AB12: AAA | AD12: 3.856481 | AE12: 3.7899493 | AF12: 3.86 | AG12: 3.7899493 | AH12: 2.49 | AI12: 2567376.5 | AJ12: 0.01 | AK12: 44676 | AL12: GAEMBF | AM12: 3.82 | AN12: 1.88 | AO12: 9.53 | AP12: REP OF SOUTH AFRICA | AQ12: ZAG000125998 | AR12: I2033
A13: 11 | B13: GA Empolyees Medical BF | C13: CASH | D13: Cash on Call | E13: Prescient Money Market Fund B3 | F13: PRMFB3 | G13: Prescient Money Market Fund B3 | H13: 3303338.1 | I13: 3303338.1 | J13: 3303338.1 | K13: 16262.6 | L13: 0 | M13: 3319600.7 | O13: 0.031803923 | P13: 40756 | Q13: 73020 | R13: 0 | U13: FI | V13: CIS | W13: CSH | X13: ZAR | AF13: 0 | AG13: 0 | AH13: 3.22 | AI13: 3319600.7 | AJ13: 0.01 | AK13: 44676 | AL13: GAEMBF | AM13: 0 | AN13: 0 | AO13: 0 | AQ13: ZAE000140885 | AR13: PRMFB3
A14: 12 | B14: GA Empolyees Medical BF | C14: CASH | D14: Safex Margin Deposits | E14: SAFEX Margin | F14: SAFEX | G14: Margin Account | H14: 1236404 | I14: 1236404 | J14: 1236404 | K14: 5346.98 | L14: 0 | M14: 1241751 | N14: 6.88 | O14: 0.011896778 | Q14: 55153 | R14: 6.88 | S14: 0.08 | T14: 0.002600675 | U14: ST | V14: CSH | W14: MARGIN | X14: ZAR | AF14: 0 | AG14: 0 | AH14: 1.2 | AI14: 1241751 | AJ14: 0 | AK14: 44676 | AL14: GAEMBF | AM14: 0 | AN14: 6.88 | AO14: 0 | AP14: SAFEX | AR14: SAFEX
A15: 13 | B15: GA Empolyees Medical BF | C15: CASH | D15: Traded Cash | E15: Interest on Cash ZAR | F15: INTRZAR | G15: Interest on Cash | H15: 0 | I15: 0 | J15: 0 | K15: 0 | L15: 0 | M15: 735.9 | O15: 7.0503982e-06 | S15: 0.08 | U15: CASH | V15: CSH | X15: ZAR | AD15: 5.116339 | AE15: 5.0001425 | AF15: 5.12 | AG15: 5.0001425 | AH15: 0 | AI15: 735.9 | AJ15: 0 | AK15: 44676 | AL15: GAEMBF | AM15: 5.05 | AN15: 0 | AO15: 0
A16: 14 | B16: GA Empolyees Medical BF | C16: CASH | D16: Traded Cash | E16: South African Rand | F16: CASHZAR | G16: South African Rand | H16: 538964.95 | I16: 538964.95 | J16: 538964.95 | K16: 0 | L16: 0 | M16: 538964.95 | O16: 0.005163633 | S16: 0.08 | U16: CASH | V16: CRNY | X16: ZAR | AD16: 5.116339 | AE16: 5.0001425 | AF16: 5.12 | AG16: 5.0001425 | AH16: 0.52 | AI16: 538964.95 | AJ16: 0 | AK16: 44676 | AL16: GAEMBF | AM16: 5.05 | AN16: 0 | AO16: 0 | AR16: ZAR
A17: 15 | B17: GA Empolyees Medical BF | C17: CASH | D17: Unsettled Cash | E17: Variation Margin | F17: VARMARG | H17: -459606.18 | I17: -459606.18 | J17: -459606.18 | K17: 0 | M17: -459606.18 | O17: -0.0044033246 | Q17: 73051 | R17: 0 | S17: 0.08 | U17: CASH | X17: ZAR | AD17: 5.116339 | AE17: 5.0001425 | AF17: 5.12 | AG17: 5.0001425 | AH17: -0.45 | AI17: -459606.18 | AJ17: 0 | AK17: 44676 | AL17: GAEMBF | AM17: 5.05 | AN17: 0 | AO17: 0
A18: 16 | B18: GA Empolyees Medical BF | C18: DERIVATIVES | D18: Equity Derivatives | E18: 15JUN22 ALSI | F18: 15JUN22 ALSI | G18: 15JUN22 ALSI | H18: 27 | I18: 0 | J18: 0 | K18: 0 | L18: 0 | M18: 0 | N18: 63316 | O18: 0 | Q18: 44727 | U18: FT | V18: DER | W18: IDXFT | X18: ZAR | AF18: 0 | AG18: 0 | AH18: 0 | AI18: 17095320 | AJ18: 0.04 | AK18: 44676 | AL18: GAEMBF | AM18: 0 | AN18: 0 | AO18: 0 | AQ18: ZAD000277663 | AR18: 15JUN22 ALSI
A19: 17 | B19: GA Empolyees Medical BF | C19: DERIVATIVES | D19: Equity Derivatives | E19: 15SEP22 ALSI | F19: 15SEP22 ALSI | G19: 15SEP22 ALSI | H19: -21 | I19: 0 | J19: 0 | K19: 0 | L19: 0 | M19: 0 | N19: 63354 | O19: 0 | Q19: 44819 | U19: FT | V19: DER | W19: IDXFT | X19: ZAR | AF19: 0 | AG19: 0 | AH19: 0 | AI19: -13304340 | AJ19: -0.03 | AK19: 44676 | AL19: GAEMBF | AM19: 0 | AN19: 0 | AO19: 0 | AQ19: ZAD000277671 | AR19: 15SEP22 ALSI
A20: 18 | B20: GA Empolyees Medical BF | C20: DERIVATIVES | D20: Equity Derivatives | E20: 15SEP22 ALSI 56000P | F20: 15SEP22 ALSI 56000P | G20: 15SEP22 ALSI 56000P | H20: -16 | I20: 0 | J20: 0 | K20: 0 | L20: 0 | M20: 0 | N20: 14773 | O20: 0 | Q20: 44819 | U20: OP | V20: DER | W20: IDXOP | X20: ZAR | AF20: 0 | AG20: 0 | AH20: 0 | AI20: 2171610.9 | AJ20: 0 | AK20: 44676 | AL20: GAEMBF | AM20: 0 | AN20: 0 | AO20: 0 | AQ20: ZADA00260281 | AR20: 15SEP22 ALSI 56000P
A21: 19 | B21: GA Empolyees Medical BF | C21: DERIVATIVES | D21: Equity Derivatives | E21: 15SEP22 ALSI 69000C | F21: 15SEP22 ALSI 69000C | G21: 15SEP22 ALSI 69000C | H21: 34 | I21: 0 | J21: 0 | K21: 0 | L21: 0 | M21: 0 | N21: 12029 | O21: 0 | Q21: 44819 | U21: OP | V21: DER | W21: IDXOP | X21: ZAR | AF21: 0 | AG21: 0 | AH21: 0 | AI21: 5739096.5 | AJ21: 0.01 | AK21: 44676 | AL21: GAEMBF | AM21: 0 | AN21: 0 | AO21: 0 | AQ21: ZADA00259275 | AR21: 15SEP22 ALSI 69000C
A22: 20 | B22: GA Empolyees Medical BF | C22: DERIVATIVES | D22: Equity Derivatives | E22: 15SEP22 ALSI 70000C | F22: 15SEP22 ALSI 70000C | G22: 15SEP22 ALSI 70000C | H22: 34 | I22: 0 | J22: 0 | K22: 0 | L22: 0 | M22: 0 | N22: 9541 | O22: 0 | Q22: 44819 | U22: OP | V22: DER | W22: IDXOP | X22: ZAR | AF22: 0 | AG22: 0 | AH22: 0 | AI22: 4859479.5 | AJ22: 0.01 | AK22: 44676 | AL22: GAEMBF | AM22: 0 | AN22: 0 | AO22: 0 | AQ22: ZADA00256511 | AR22: 15SEP22 ALSI 70000C
A23: 21 | B23: GA Empolyees Medical BF | C23: DERIVATIVES | D23: Equity Derivatives | E23: 15SEP22 ALSI 74000C | F23: 15SEP22 ALSI 74000C | G23: 15SEP22 ALSI 74000C | H23: -34 | I23: 0 | J23: 0 | K23: 0 | L23: 0 | M23: 0 | N23: 3904 | O23: 0 | Q23: 44819 | U23: OP | V23: DER | W23: IDXOP | X23: ZAR | AF23: 0 | AG23: 0 | AH23: 0 | AI23: -2384548.1 | AJ23: -0.01 | AK23: 44676 | AL23: GAEMBF | AM23: 0 | AN23: 0 | AO23: 0 | AQ23: ZADA00260075 | AR23: 15SEP22 ALSI 74000C
A24: 22 | B24: GA Empolyees Medical BF | C24: EQUITIES | D24: FINANCIALS | E24: Equites Property Fund Limited | F24: EQU | G24: Equites Property Fund Limited | H24: 25682 | I24: 530631.35 | J24: 552419.82 | K24: 0 | L24: 0 | M24: 552419.82 | N24: 2151 | O24: 0.0052925393 | U24: EQ | V24: EQ | W24: EQ | X24: ZAR | Y24: REAL ESTATE | Z24: FINANCIAL SERVICES | AA24: FINANCIALS | AF24: 0 | AG24: 0 | AH24: 0.54 | AI24: 552419.82 | AJ24: 0 | AK24: 44676 | AL24: GAEMBF | AM24: 0 | AN24: 0 | AO24: 0 | AQ24: ZAE000188843 | AR24: EQU
A25: 23 | B25: GA Empolyees Medical BF | C25: EQUITIES | D25: FINANCIALS | E25: Fortress Reit Limited A | F25: FFA | G25: Fortress Reit Limited A | H25: 44852 | I25: 604451.3 | J25: 557958.88 | K25: 0 | L25: 0 | M25: 557958.88 | N25: 1244 | O25: 0.0053456071 | U25: EQ | V25: EQ | W25: EQ | X25: ZAR | Y25: REAL ESTATE | Z25: FINANCIAL SERVICES | AA25: FINANCIALS | AF25: 0 | AG25: 0 | AH25: 0.54 | AI25: 557958.88 | AJ25: 0 | AK25: 44676 | AL25: GAEMBF | AM25: 0 | AN25: 0 | AO25: 0 | AQ25: ZAE000248498 | AR25: FFA
A26: 24 | B26: GA Empolyees Medical BF | C26: EQUITIES | D26: FINANCIALS | E26: Growthpoint Properties Ltd | F26: GRT | G26: Growthpoint Properties Ltd | H26: 128047 | I26: 1771445.5 | J26: 1776011.9 | K26: 0 | L26: 0 | M26: 1776011.9 | N26: 1387 | O26: 0.017015343 | U26: EQ | V26: EQ | W26: EQ | X26: ZAR | Y26: REAL ESTATE | Z26: FINANCIAL SERVICES | AA26: FINANCIALS | AF26: 0 | AG26: 0 | AH26: 1.72 | AI26: 1776011.9 | AJ26: 0 | AK26: 44676 | AL26: GAEMBF | AM26: 0 | AN26: 0 | AO26: 0 | AQ26: ZAE000179420 | AR26: GRT
A27: 25 | B27: GA Empolyees Medical BF | C27: EQUITIES | D27: FINANCIALS | E27: Hyprop Investments Ltd | F27: HYP | G27: Hyprop Investments Ltd | H27: 12989 | I27: 401915.55 | J27: 467604 | K27: 0 | L27: 0 | M27: 467604 | N27: 3600 | O27: 0.0044799489 | U27: EQ | V27: EQ | W27: EQ | X27: ZAR | Y27: REAL ESTATE | Z27: FINANCIAL SERVICES | AA27: FINANCIALS | AF27: 0 | AG27: 0 | AH27: 0.45 | AI27: 467604 | AJ27: 0 | AK27: 44676 | AL27: GAEMBF | AM27: 0 | AN27: 0 | AO27: 0 | AQ27: ZAE000190724 | AR27: HYP
A28: 26 | B28: GA Empolyees Medical BF | C28: EQUITIES | D28: FINANCIALS | E28: MAS PLC | F28: MSP | G28: MAS PLC | H28: 16238 | I28: 301985.94 | J28: 345544.64 | K28: 0 | L28: 0 | M28: 345544.64 | N28: 2128 | O28: 0.0033105412 | U28: EQ | V28: EQ | W28: EQ | X28: ZAR | Y28: REAL ESTATE | Z28: FINANCIAL SERVICES | AA28: FINANCIALS | AF28: 0 | AG28: 0 | AH28: 0.34 | AI28: 345544.64 | AJ28: 0 | AK28: 44676 | AL28: GAEMBF | AM28: 0 | AN28: 0 | AO28: 0 | AQ28: VGG5884M1041 | AR28: MSP
A29: 27 | B29: GA Empolyees Medical BF | C29: EQUITIES | D29: FINANCIALS | E29: Nepi Rockcastle PLC | F29: NRP | G29: Nepi Rockcastle PLC | H29: 17190 | I29: 1704757.7 | J29: 1625486.4 | K29: 0 | L29: 0 | M29: 1625486.4 | N29: 9456 | O29: 0.015573211 | U29: EQ | V29: EQ | W29: EQ | X29: ZAR | Y29: REAL ESTATE | Z29: FINANCIAL SERVICES | AA29: FINANCIALS | AF29: 0 | AG29: 0 | AH29: 1.58 | AI29: 1625486.4 | AJ29: 0 | AK29: 44676 | AL29: GAEMBF | AM29: 0 | AN29: 0 | AO29: 0 | AQ29: IM00BDD7WV31 | AR29: NRP
A30: 28 | B30: GA Empolyees Medical BF | C30: EQUITIES | D30: FINANCIALS | E30: Redefine Properties Limited | F30: RDF | G30: Redefine Properties Limited | H30: 257037 | I30: 1155086.9 | J30: 1123251.7 | K30: 0 | L30: 0 | M30: 1123251.7 | N30: 437 | O30: 0.010761478 | U30: EQ | V30: EQ | W30: EQ | X30: ZAR | Y30: REAL ESTATE | Z30: FINANCIAL SERVICES | AA30: FINANCIALS | AF30: 0 | AG30: 0 | AH30: 1.09 | AI30: 1123251.7 | AJ30: 0 | AK30: 44676 | AL30: GAEMBF | AM30: 0 | AN30: 0 | AO30: 0 | AQ30: ZAE000190252 | AR30: RDF
A31: 29 | B31: GA Empolyees Medical BF | C31: EQUITIES | D31: FINANCIALS | E31: Resilient REIT Limited | F31: RES | G31: Resilient Property Income Fund Ltd | H31: 12294 | I31: 705313.62 | J31: 709363.8 | K31: 0 | L31: 0 | M31: 709363.8 | N31: 5770 | O31: 0.0067961642 | U31: EQ | V31: EQ | W31: REIT | X31: ZAR | Y31: REAL ESTATE | Z31: FINANCIAL SERVICES | AA31: FINANCIALS | AF31: 0 | AG31: 0 | AH31: 0.69 | AI31: 709363.8 | AJ31: 0 | AK31: 44676 | AL31: GAEMBF | AM31: 0 | AN31: 0 | AO31: 0 | AQ31: ZAE000209557 | AR31: RES
A32: 30 | B32: GA Empolyees Medical BF | C32: EQUITIES | D32: FINANCIALS | E32: Sirius Real Estate Ltd | F32: SRE | G32: Sirius Real Estate Ltd | H32: 11334 | I32: 274665.3 | J32: 263855.52 | K32: 0 | L32: 0 | M32: 263855.52 | N32: 2328 | O32: 0.0025279066 | U32: EQ | V32: EQ | W32: EQ | X32: ZAR | Y32: REAL ESTATE | Z32: FINANCIAL SERVICES | AA32: FINANCIALS | AF32: 0 | AG32: 0 | AH32: 0.26 | AI32: 263855.52 | AJ32: 0 | AK32: 44676 | AL32: GAEMBF | AM32: 0 | AN32: 0 | AO32: 0 | AQ32: GG00B1W3VF54 | AR32: SRE
A33: 31 | B33: GA Empolyees Medical BF | C33: EQUITIES | D33: FINANCIALS | E33: Vukile Property Fund Ltd | F33: VKE | G33: Vukile Property Fund Ltd | H33: 33663 | I33: 411031.4 | J33: 447044.64 | K33: 0 | L33: 0 | M33: 447044.64 | N33: 1328 | O33: 0.0042829769 | U33: EQ | V33: EQ | W33: EQ | X33: ZAR | Y33: REAL ESTATE | Z33: FINANCIAL SERVICES | AA33: FINANCIALS | AF33: 0 | AG33: 0 | AH33: 0.43 | AI33: 447044.64 | AJ33: 0 | AK33: 44676 | AL33: GAEMBF | AM33: 0 | AN33: 0 | AO33: 0 | AQ33: ZAE000180865 | AR33: VKE
A34: 32 | B34: GA Empolyees Medical BF | C34: MONEY MARKET | D34: Money Market : Maturity (6-12) Months | E34: ABSA NCD 5.95% 220223 | F34: ABSAN220223A | G34: ABSA NCD 5.95% 220223 | H34: 6000000 | I34: 6000000 | J34: 5989479.1 | K34: 61619.18 | L34: 0 | M34: 6051098.2 | N34: 6.109894 | O34: 0.057973437 | P34: 44979 | Q34: 44979 | R34: 5.95 | S34: 0.83 | T34: 0.78758253 | U34: FI | V34: MM | W34: NCD | X34: ZAR | Y34: BANKS | AB34: AA+ | AD34: 6.1416908 | AE34: 5.9752997 | AF34: 6.14 | AG34: 5.9752997 | AH34: 5.87 | AI34: 6051098.2 | AJ34: 0.01 | AK34: 44676 | AL34: GAEMBF | AM34: 6.05 | AN34: 5.95 | AO34: 0.79 | AP34: ABSA BANK LTD | AQ34: ZAM000566470 | AR34: ABSAN220223A
A35: 33 | B35: GA Empolyees Medical BF | C35: MONEY MARKET | D35: Money Market : Maturity (6-12) Months | E35: Nedbank NCD 5.95% 140223 | F35: NEDN140223 | G35: Nedbank NCD 5.95% 140223 | H35: 10000000 | I35: 10000000 | J35: 9987251.3 | K35: 115739.73 | L35: 0 | M35: 10102991 | N35: 6.046006 | O35: 0.096793191 | P35: 44971 | Q35: 44971 | R35: 5.95 | S35: 0.81 | T35: 0.76807472 | U35: FI | V35: MM | W35: NCD | X35: ZAR | Y35: BANKS | AB35: AA | AD35: 6.08113 | AE35: 5.917944 | AF35: 6.08 | AG35: 5.917944 | AH35: 9.8 | AI35: 10102991 | AJ35: 0.02 | AK35: 44676 | AL35: GAEMBF | AM35: 5.99 | AN35: 5.95 | AO35: 0.77 | AP35: NEDBANK LTD | AQ35: ZAM000565282 | AR35: NEDN140223
A36: 34 | B36: GA Empolyees Medical BF | C36: MONEY MARKET | D36: Money Market : Maturity (6-12) Months | E36: Standard Bank NCD 5.325% 141222 | F36: STDN141222 | G36: Standard Bank NCD 5.325% 141222 | H36: 1000000 | I36: 1000000 | J36: 997571.49 | K36: 19403.42 | L36: 0 | M36: 1016974.9 | N36: 5.611812 | O36: 0.0097432777 | P36: 44909 | Q36: 44909 | R36: 5.325 | S36: 0.64 | T36: 0.61372511 | U36: FI | V36: MM | W36: NCD | X36: ZAR | Y36: BANKS | AB36: AA+ | AD36: 5.6689015 | AE36: 5.526733 | AF36: 5.67 | AG36: 5.526733 | AH36: 0.99 | AI36: 1016974.9 | AJ36: 0 | AK36: 44676 | AL36: GAEMBF | AM36: 5.59 | AN36: 5.33 | AO36: 0.61 | AP36: STANDARD BANK LTD | AQ36: ZAM000559558 | AR36: STDN141222
A37: 35 | B37: GA Empolyees Medical BF | C37: MONEY MARKET | D37: Money Market : Maturity (6-12) Months | E37: Standard Bank NCD 6.35% 310323 | F37: STDN310323 | G37: Standard Bank NCD 6.35% 310323 | H37: 2000000 | I37: 2000000 | J37: 2000761.5 | K37: 9046.58 | L37: 0 | M37: 2009808.1 | N37: 6.278215 | O37: 0.019255262 | P37: 45016 | Q37: 45016 | R37: 6.35 | S37: 0.93 | T37: 0.87759458 | U37: FI | V37: MM | W37: NCD | X37: ZAR | Y37: BANKS | AB37: AA+ | AD37: 6.2920086 | AE37: 6.1175325 | AF37: 6.29 | AG37: 6.1175325 | AH37: 1.95 | AI37: 2009808.1 | AJ37: 0 | AK37: 44676 | AL37: GAEMBF | AM37: 6.2 | AN37: 6.35 | AO37: 0.88 | AP37: STANDARD BANK LTD | AQ37: ZAM000571397 | AR37: STDN310323
A38: 36 | B38: GA Empolyees Medical BF | C38: MONEY MARKET | D38: Money Market : Maturity 12+ Months | E38: FirstRand NCD 6.43% 110523 | F38: FSRN110523 | G38: FirstRand NCD 6.43% 110523 | H38: 3000000 | I38: 3000000 | J38: 2997478 | K38: 7398.9 | L38: 0 | M38: 3004876.9 | N38: 6.500183 | O38: 0.028788665 | P38: 45057 | Q38: 45057 | R38: 6.43 | S38: 1.04 | T38: 0.97510732 | U38: FI | V38: MM | W38: NCD | X38: ZAR | Y38: BANKS | AB38: AA+ | AD38: 6.4916979 | AE38: 6.3061965 | AF38: 6.49 | AG38: 6.3061965 | AH38: 2.91 | AI38: 3004876.9 | AJ38: 0.01 | AK38: 44676 | AL38: GAEMBF | AM38: 6.39 | AN38: 6.43 | AO38: 0.98 | AP38: FIRSTRAND BANK LTD | AQ38: ZAM000572718 | AR38: FSRN110523
A39: 37 | B39: GA Empolyees Medical BF | C39: MONEY MARKET | D39: Money Market : Maturity 12+ Months | E39: Investec Tier1 FRN 12082024 Jb+425 | F39: INLV01 | G39: Investec Tier1 FRN 12082024 Jb+425 | H39: 2930000 | I39: 2968440.4 | J39: 3010266 | K39: 47972.29 | L39: 0 | M39: 3058238.3 | N39: 7.156159 | O39: 0.029299902 | P39: 44693 | Q39: 45516 | R39: 8.417 | S39: 0.04 | T39: 0.030256699 | U39: FI | V39: MM | W39: FRN | X39: ZAR | Y39: BANKS | AB39: AA | AC39: A- | AD39: 7.4063995 | AE39: 7.1662713 | AF39: 7.41 | AG39: 7.1662713 | AH39: 2.97 | AI39: 3058238.3 | AJ39: 0.01 | AK39: 44676 | AL39: GAEMBF | AM39: 7.27 | AN39: 8.42 | AO39: 0.03 | AP39: INVESTEC LTD | AQ39: ZAG000118647 | AR39: INLV01
A40: 38 | B40: GA Empolyees Medical BF | C40: MONEY MARKET | D40: Money Market : Maturity 12+ Months | E40: Standard bank NCD 6.51% 220224 | F40: STDN220224 | G40: Standard bank NCD 6.51% 220224 | H40: 5000000 | I40: 5000000 | J40: 4949019 | K40: 56182.19 | L40: 0 | M40: 5005201.2 | N40: 7.107226 | O40: 0.047953066 | P40: 44795 | Q40: 45344 | R40: 6.51 | S40: 1.73 | T40: 1.6746973 | U40: FI | V40: MM | W40: NCD | X40: ZAR | AB40: AA+ | AD40: 7.2335079 | AE40: 7.0042208 | AF40: 7.23 | AG40: 7.0042208 | AH40: 4.86 | AI40: 5005201.2 | AJ40: 0.01 | AK40: 44676 | AL40: GAEMBF | AM40: 7.11 | AN40: 6.51 | AO40: 1.67 | AP40: STANDARD BANK LTD | AQ40: ZAM000566447 | AR40: STDN220224
A41: 39 | B41: GA Empolyees Medical BF | C41: PREFERENCE SHARES | D41: Preference Shares | E41: Absa Bank Ltd Preference Shares | F41: ABSP | G41: Absa Bank Ltd Preference Shares | H41: 2766 | I41: 1915569.6 | J41: 2470038 | K41: 0 | L41: 0 | M41: 2470038 | N41: 89300 | O41: 0.023664562 | U41: EQ | V41: EQ | W41: PREF | X41: ZAR | AB41: AA+ | AF41: 0 | AG41: 0 | AH41: 2.4 | AI41: 2470038 | AJ41: 0.01 | AK41: 44676 | AL41: GAEMBF | AM41: 0 | AN41: 0 | AO41: 0 | AP41: ABSA BANK LTD | AQ41: ZAE000079810 | AR41: ABSP
A42: 40 | B42: GA Empolyees Medical BF | C42: PREFERENCE SHARES | D42: Preference Shares | E42: Investec Ltd Preference Share | F42: INPR | G42: Investec Ltd Preference Share | H42: 27806 | I42: 2030935.8 | J42: 2697182 | K42: 0 | L42: 0 | M42: 2697182 | N42: 9700 | O42: 0.025840749 | U42: EQ | V42: EQ | W42: PREF | X42: ZAR | AF42: 0 | AG42: 0 | AH42: 2.62 | AI42: 2697182 | AJ42: 0.01 | AK42: 44676 | AL42: GAEMBF | AM42: 0 | AN42: 0 | AO42: 0 | AQ42: ZAE000063814 | AR42: INPR
A43: 41 | B43: GA Empolyees Medical BF | C43: PREFERENCE SHARES | D43: Preference Shares | E43: Netcare Preference Share Ltd | F43: NTCP | G43: Netcare Preference Share Ltd | H43: 7516 | I43: 622880.84 | J43: 646376 | K43: 0 | L43: 0 | M43: 646376 | N43: 8600 | O43: 0.0061927003 | U43: EQ | V43: EQ | W43: PREF | X43: ZAR | AF43: 0 | AG43: 0 | AH43: 0.63 | AI43: 646376 | AJ43: 0 | AK43: 44676 | AL43: GAEMBF | AM43: 0 | AN43: 0 | AO43: 0 | AQ43: ZAE000081121 | AR43: NTCP
A44: 42 | B44: GA Empolyees Medical BF | C44: PREFERENCE SHARES | D44: Preference Shares | E44: Standard Bank Group Ltd Preference Shares | F44: SBPP | G44: Standard Bank Group Ltd Pref | H44: 25171 | I44: 1960392.4 | J44: 2342161.5 | K44: 0 | L44: 0 | M44: 2342161.5 | N44: 9305 | O44: 0.022439423 | U44: EQ | V44: EQ | W44: PREF | X44: ZAR | AB44: AA+ | AF44: 0 | AG44: 0 | AH44: 2.27 | AI44: 2342161.5 | AJ44: 0.01 | AK44: 44676 | AL44: GAEMBF | AM44: 0 | AN44: 0 | AO44: 0 | AP44: STANDARD BANK LTD | AQ44: ZAE000056339 | AR44: SBPP
A45: 43 | B45: GA Empolyees Medical BF | C45: PRIVATE COMPANY | D45: Private Company | E45: Prescient Clean Energy and Infrastructure Debt Fund Trust | F45: PIMEVOA | G45: Prescient Clean Energy and Infrastructure Debt Fund Trust | H45: 5172176.5 | I45: 5201302.8 | J45: 5180969.2 | K45: 0 | L45: 0 | M45: 5180969.2 | N45: 1.0017 | O45: 0.049637037 | U45: EQ | V45: PRIVATE COMP | W45: OTHER | X45: ZAR | AF45: 0 | AG45: 0 | AH45: 5.03 | AI45: 5180969.2 | AJ45: 0.01 | AK45: 44676 | AL45: GAEMBF | AM45: 0 | AN45: 0 | AO45: 0 | AR45: PIMEVOA
A46: 44 | B46: GA Empolyees Medical BF | C46: UNKNOWN | D46: UNKNOWN | E46: Synthetic Cash_15JUN22 ALSI | F46: 15JUN22 ALSI | G46: Synthetic Cash_15JUN22 ALSI | H46: 27 | J46: 0 | M46: 0 | O46: 0 | U46: SYTH | V46: SYNCASHFUT | W46: CASH | X46: ZAR | AF46: 0 | AG46: 0 | AH46: 0 | AI46: -17095320 | AJ46: -0.04 | AK46: 44676 | AL46: GAEMBF | AM46: 0 | AN46: 0 | AO46: 0 | AR46: SYNZAR
A47: 45 | B47: GA Empolyees Medical BF | C47: UNKNOWN | D47: UNKNOWN | E47: Synthetic Cash_15SEP22 ALSI | F47: 15SEP22 ALSI | G47: Synthetic Cash_15SEP22 ALSI | H47: -21 | J47: 0 | M47: 0 | O47: 0 | U47: SYTH | V47: SYNCASHFUT | W47: CASH | X47: ZAR | AF47: 0 | AG47: 0 | AH47: 0 | AI47: 13304340 | AJ47: 0.03 | AK47: 44676 | AL47: GAEMBF | AM47: 0 | AN47: 0 | AO47: 0 | AR47: SYNZAR
A48: 46 | B48: GA Empolyees Medical BF | C48: UNKNOWN | D48: UNKNOWN | E48: Synthetic Cash_15SEP22 ALSI 56000P | F48: 15SEP22 ALSI 56000P | G48: Synthetic Cash_15SEP22 ALSI 56000P | H48: -16 | J48: 0 | M48: 0 | O48: 0 | U48: SYTH | V48: SYNCASHOPT | W48: CASH | X48: ZAR | AF48: 0 | AG48: 0 | AH48: 0 | AI48: -2171610.9 | AJ48: 0 | AK48: 44676 | AL48: GAEMBF | AM48: 0 | AN48: 0 | AO48: 0 | AR48: SYNZAR
A49: 47 | B49: GA Empolyees Medical BF | C49: UNKNOWN | D49: UNKNOWN | E49: Synthetic Cash_15SEP22 ALSI 69000C | F49: 15SEP22 ALSI 69000C | G49: Synthetic Cash_15SEP22 ALSI 69000C | H49: 34 | J49: 0 | M49: 0 | O49: 0 | U49: SYTH | V49: SYNCASHOPT | W49: CASH | X49: ZAR | AF49: 0 | AG49: 0 | AH49: 0 | AI49: -5739096.5 | AJ49: -0.01 | AK49: 44676 | AL49: GAEMBF | AM49: 0 | AN49: 0 | AO49: 0 | AR49: SYNZAR
A50: 48 | B50: GA Empolyees Medical BF | C50: UNKNOWN | D50: UNKNOWN | E50: Synthetic Cash_15SEP22 ALSI 70000C | F50: 15SEP22 ALSI 70000C | G50: Synthetic Cash_15SEP22 ALSI 70000C | H50: 34 | J50: 0 | M50: 0 | O50: 0 | U50: SYTH | V50: SYNCASHOPT | W50: CASH | X50: ZAR | AF50: 0 | AG50: 0 | AH50: 0 | AI50: -4859479.5 | AJ50: -0.01 | AK50: 44676 | AL50: GAEMBF | AM50: 0 | AN50: 0 | AO50: 0 | AR50: SYNZAR
A51: 49 | B51: GA Empolyees Medical BF | C51: UNKNOWN | D51: UNKNOWN | E51: Synthetic Cash_15SEP22 ALSI 74000C | F51: 15SEP22 ALSI 74000C | G51: Synthetic Cash_15SEP22 ALSI 74000C | H51: -34 | J51: 0 | M51: 0 | O51: 0 | U51: SYTH | V51: SYNCASHOPT | W51: CASH | X51: ZAR | AF51: 0 | AG51: 0 | AH51: 0 | AI51: 2384548.1 | AJ51: 0.01 | AK51: 44676 | AL51: GAEMBF | AM51: 0 | AN51: 0 | AO51: 0 | AR51: SYNZAR

Sheet Deltas
B1: Entity Name | C1: i Issue Name | D1: Primary Asset ID | E1: Nominal Holding | F1: Delta | G1: Market Value | H1: Effective Exposure
A2: 0 | B2: GA Empolyees Medical BF | C2: 15JUN22 ALSI | D2: 15JUN22 ALSI | E2: 27 | F2: 1 | G2: 0 | H2: 17095320
A3: 1 | B3: GA Empolyees Medical BF | C3: 15SEP22 ALSI | D3: 15SEP22 ALSI | E3: -21 | F3: 1 | G3: 0 | H3: -13304340
A4: 2 | B4: GA Empolyees Medical BF | C4: 15SEP22 ALSI 56000P | D4: 15SEP22 ALSI 56000P | E4: -16 | F4: -0.21423 | G4: 0 | H4: 2171610.9
A5: 3 | B5: GA Empolyees Medical BF | C5: 15SEP22 ALSI 69000C | D5: 15SEP22 ALSI 69000C | E5: 34 | F5: 0.26643 | G5: 0 | H5: 5739096.5
A6: 4 | B6: GA Empolyees Medical BF | C6: 15SEP22 ALSI 70000C | D6: 15SEP22 ALSI 70000C | E6: 34 | F6: 0.2256 | G6: 0 | H6: 4859479.5
A7: 5 | B7: GA Empolyees Medical BF | C7: 15SEP22 ALSI 74000C | D7: 15SEP22 ALSI 74000C | E7: -34 | F7: 0.1107 | G7: 0 | H7: -2384548.1

Sheet BM
A1: BenchMark | B1: Type | C1: Constituent | D1: Weighting | I1: Fondsposition per | J1: 10.Jan.2020 | U1: =HYPERLINK("https://www.ishares.com/de/privatanleger/de/produkte/251882/ishares-msci-world-ucits-etf-acc-fund/1478358465952.ajax?fileType=csv&fileName=EUNL_holdings&dataType=fund","MSCI ACWI source data") -> MSCI ACWI source data
A2: ALBI | B2: Instrument | C2: 186 | D2: 16.4894 | E2: =SUMIF(Data!$E:$E,$C2,Data!$AI:$AI) -> 0
A3: ALBI | B3: Instrument | C3: 207 | D3: 3.4932 | E3: =SUMIF(Data!$E:$E,$C3,Data!$AI:$AI) -> 0 | I3: Emittententicker | J3: Name | K3: Anlageklasse | L3: Gewichtung (%) | M3: Kurs | N3: Nominale | O3: Marktwert | P3: Nominalwert | Q3: Sektor | R3: ISIN | S3: Börse | T3: Standort | U3: Marktwährung
A4: ALBI | B4: Instrument | C4: 209 | D4: 5.278 | E4: =SUMIF(Data!$E:$E,$C4,Data!$AI:$AI) -> 0 | I4: AAPL | J4: APPLE INC | K4: Aktien | L4: 3,09 | M4: 310,33 | N4: 2.424.947 | O4: 752.533.803 | P4: 752.533.802,51 | Q4: IT | R4: US0378331005 | S4: NASDAQ | T4: Vereinigte Staaten | U4: USD | V4: =SUMIF(Data!$E:$E,$I4,Data!$AI:$AI) -> 0
A5: ALBI | B5: Instrument | C5: 208 | D5: 3.7744 | E5: =SUMIF(Data!$E:$E,$C5,Data!$AI:$AI) -> 0 | I5: MSFT | J5: MICROSOFT CORP | K5: Aktien | L5: 2,59 | M5: 161,34 | N5: 3.902.293 | O5: 629.595.953 | P5: 629.595.952,62 | Q5: IT | R5: US5949181045 | S5: NASDAQ | T5: Vereinigte Staaten | U5: USD | V5: =SUMIF(Data!$E:$E,$I5,Data!$AI:$AI) -> 0
A6: ALBI | B6: Instrument | C6: DV22 | D6: 0.6599 | E6: =SUMIF(Data!$E:$E,$C6,Data!$AI:$AI) -> 0 | I6: AMZN | J6: AMAZON COM INC | K6: Aktien | L6: 1,74 | M6: 1.883,16 | N6: 225.342 | O6: 424.355.041 | P6: 424.355.040,72 | Q6: Zyklische Konsumgüter | R6: US0231351067 | S6: NASDAQ | T6: Vereinigte Staaten | U6: USD | V6: =SUMIF(Data!$E:$E,$I6,Data!$AI:$AI) -> 0
A7: ALBI | B7: Instrument | C7: DV23 | D7: 0.6891 | E7: =SUMIF(Data!$E:$E,$C7,Data!$AI:$AI) -> 0 | I7: FB | J7: FACEBOOK CLASS A INC | K7: Aktien | L7: 1,15 | M7: 218,06 | N7: 1.288.590 | O7: 280.989.935 | P7: 280.989.935,40 | Q7: Kommunikation | R7: US30303M1027 | S7: NASDAQ | T7: Vereinigte Staaten | U7: USD | V7: =SUMIF(Data!$E:$E,$I7,Data!$AI:$AI) -> 0
A8: ALBI | B8: Instrument | C8: ES33 | D8: 1.5447 | E8: =SUMIF(Data!$E:$E,$C8,Data!$AI:$AI) -> 0 | I8: GOOG | J8: ALPHABET INC CLASS C | K8: Aktien | L8: 0,99 | M8: 1.429,73 | N8: 168.382 | O8: 240.740.797 | P8: 240.740.796,86 | Q8: Kommunikation | R8: US02079K1079 | S8: NASDAQ | T8: Vereinigte Staaten | U8: USD | V8: =SUMIF(Data!$E:$E,$I8,Data!$AI:$AI) -> 0
A9: ALBI | B9: Instrument | C9: ES26 | D9: 1.6881 | E9: =SUMIF(Data!$E:$E,$C9,Data!$AI:$AI) -> 0 | I9: JPM | J9: JPMORGAN CHASE & CO | K9: Aktien | L9: 0,96 | M9: 136,07 | N9: 1.722.589 | O9: 234.392.685 | P9: 234.392.685,23 | Q9: Financials | R9: US46625H1005 | S9: New York Stock Exchange Inc. | T9: Vereinigte Staaten | U9: USD | V9: =SUMIF(Data!$E:$E,$I9,Data!$AI:$AI) -> 0
A10: ALBI | B10: Instrument | C10: ES23 | D10: 1.2486 | E10: =SUMIF(Data!$E:$E,$C10,Data!$AI:$AI) -> 0 | I10: GOOGL | J10: ALPHABET INC CLASS A | K10: Aktien | L10: 0,94 | M10: 1.428,96 | N10: 160.289 | O10: 229.046.569 | P10: 229.046.569,44 | Q10: Kommunikation | R10: US02079K3059 | S10: NASDAQ | T10: Vereinigte Staaten | U10: USD | V10: =SUMIF(Data!$E:$E,$I10,Data!$AI:$AI) -> 0
A11: ALBI | B11: Instrument | C11: 213 | D11: 6.4352 | E11: =SUMIF(Data!$E:$E,$C11,Data!$AI:$AI) -> 0 | I11: JNJ | J11: JOHNSON & JOHNSON | K11: Aktien | L11: 0,85 | M11: 145,06 | N11: 1.424.692 | O11: 206.665.822 | P11: 206.665.821,52 | Q11: Gesundheitsversorgung | R11: US4781601046 | S11: New York Stock Exchange Inc. | T11: Vereinigte Staaten | U11: USD | V11: =SUMIF(Data!$E:$E,$I11,Data!$AI:$AI) -> 0
A12: ALBI | B12: Instrument | C12: 214 | D12: 4.6957 | E12: =SUMIF(Data!$E:$E,$C12,Data!$AI:$AI) -> 0 | I12: V | J12: VISA INC CLASS A | K12: Aktien | L12: 0,74 | M12: 193,77 | N12: 935.117 | O12: 181.197.621 | P12: 181.197.621,09 | Q12: IT | R12: US92826C8394 | S12: New York Stock Exchange Inc. | T12: Vereinigte Staaten | U12: USD | V12: =SUMIF(Data!$E:$E,$I12,Data!$AI:$AI) -> 0
A13: ALBI | B13: Instrument | C13: 2023 | D13: 5.1942 | E13: =SUMIF(Data!$E:$E,$C13,Data!$AI:$AI) -> 0 | I13: NESN | J13: NESTLE SA | K13: Aktien | L13: 0,71 | M13: 105,77 | N13: 1.637.775 | O13: 173.226.364 | P13: 173.226.363,73 | Q13: Nichtzyklische Konsumgüter | R13: CH0038863350 | S13: Six Swiss Exchange Ag | T13: Schweiz | U13: CHF | V13: =SUMIF(Data!$E:$E,$I13,Data!$AI:$AI) -> 0
A14: ALBI | B14: Instrument | C14: 2048 | D14: 11.4225 | E14: =SUMIF(Data!$E:$E,$C14,Data!$AI:$AI) -> 0 | I14: PG | J14: PROCTER & GAMBLE | K14: Aktien | L14: 0,69 | M14: 123,97 | N14: 1.358.285 | O14: 168.386.591 | P14: 168.386.591,45 | Q14: Nichtzyklische Konsumgüter | R14: US7427181091 | S14: New York Stock Exchange Inc. | T14: Vereinigte Staaten | U14: USD | V14: =SUMIF(Data!$E:$E,$I14,Data!$AI:$AI) -> 0
A15: ALBI | B15: Instrument | C15: 2037 | D15: 7.0558 | E15: =SUMIF(Data!$E:$E,$C15,Data!$AI:$AI) -> 0 | I15: BAC | J15: BANK OF AMERICA CORP | K15: Aktien | L15: 0,68 | M15: 34,74 | N15: 4.788.406 | O15: 166.349.224 | P15: 166.349.224,44 | Q15: Financials | R15: US0605051046 | S15: New York Stock Exchange Inc. | T15: Vereinigte Staaten | U15: USD | V15: =SUMIF(Data!$E:$E,$I15,Data!$AI:$AI) -> 0
A16: ALBI | B16: Instrument | C16: 2030 | D16: 7.1749 | E16: =SUMIF(Data!$E:$E,$C16,Data!$AI:$AI) -> 0 | I16: BRKB | J16: BERKSHIRE HATHAWAY INC CLASS B | K16: Aktien | L16: 0,65 | M16: 226,62 | N16: 698.787 | O16: 158.359.110 | P16: 158.359.109,94 | Q16: Financials | R16: US0846707026 | S16: New York Stock Exchange Inc. | T16: Vereinigte Staaten | U16: USD | V16: =SUMIF(Data!$E:$E,$I16,Data!$AI:$AI) -> 0
A17: ALBI | B17: Instrument | C17: ES42 | D17: 0.8266 | E17: =SUMIF(Data!$E:$E,$C17,Data!$AI:$AI) -> 0 | I17: XOM | J17: EXXON MOBIL CORP | K17: Aktien | L17: 0,64 | M17: 69,14 | N17: 2.251.134 | O17: 155.643.405 | P17: 155.643.404,76 | Q17: Energie | R17: US30231G1022 | S17: New York Stock Exchange Inc. | T17: Vereinigte Staaten | U17: USD | V17: =SUMIF(Data!$E:$E,$I17,Data!$AI:$AI) -> 0
A18: ALBI | B18: Instrument | C18: 2032 | D18: 6.1326 | E18: =SUMIF(Data!$E:$E,$C18,Data!$AI:$AI) -> 0 | I18: MA | J18: MASTERCARD INC CLASS A | K18: Aktien | L18: 0,63 | M18: 311,17 | N18: 491.048 | O18: 152.799.406 | P18: 152.799.406,16 | Q18: IT | R18: US57636Q1040 | S18: New York Stock Exchange Inc. | T18: Vereinigte Staaten | U18: USD | V18: =SUMIF(Data!$E:$E,$I18,Data!$AI:$AI) -> 0
A19: ALBI | B19: Instrument | C19: 2044 | D19: 7.0828 | E19: =SUMIF(Data!$E:$E,$C19,Data!$AI:$AI) -> 0 | I19: UNH | J19: UNITEDHEALTH GROUP INC | K19: Aktien | L19: 0,62 | M19: 295,13 | N19: 511.206 | O19: 150.872.227 | P19: 150.872.226,78 | Q19: Gesundheitsversorgung | R19: US91324P1021 | S19: New York Stock Exchange Inc. | T19: Vereinigte Staaten | U19: USD | V19: =SUMIF(Data!$E:$E,$I19,Data!$AI:$AI) -> 0
A20: ALBI | B20: Instrument | C20: 2035 | D20: 4.7552 | E20: =SUMIF(Data!$E:$E,$C20,Data!$AI:$AI) -> 0 | I20: T | J20: AT&T INC | K20: Aktien | L20: 0,61 | M20: 38,57 | N20: 3.879.451 | O20: 149.630.425 | P20: 149.630.425,07 | Q20: Kommunikation | R20: US00206R1023 | S20: New York Stock Exchange Inc. | T20: Vereinigte Staaten | U20: USD | V20: =SUMIF(Data!$E:$E,$I20,Data!$AI:$AI) -> 0
A21: ALBI | B21: Instrument | C21: 2040 | D21: 4.3581 | E21: =SUMIF(Data!$E:$E,$C21,Data!$AI:$AI) -> 0 | I21: INTC | J21: INTEL CORPORATION CORP | K21: Aktien | L21: 0,58 | M21: 58,94 | N21: 2.398.081 | O21: 141.342.894 | P21: 141.342.894,14 | Q21: IT | R21: US4581401001 | S21: NASDAQ | T21: Vereinigte Staaten | U21: USD | V21: =SUMIF(Data!$E:$E,$I21,Data!$AI:$AI) -> 0
A22: ALBI | B22: Instrument | C22: AICASH | D22: 0 | E22: =SUMIF(Data!$E:$E,$C22,Data!$AI:$AI) -> 0 | I22: DIS | J22: WALT DISNEY | K22: Aktien | L22: 0,58 | M22: 144,62 | N22: 969.292 | O22: 140.179.009 | P22: 140.179.009,04 | Q22: Kommunikation | R22: US2546871060 | S22: New York Stock Exchange Inc. | T22: Vereinigte Staaten | U22: USD | V22: =SUMIF(Data!$E:$E,$I22,Data!$AI:$AI) -> 0
A23: ALBI01 | B23: Instrument | C23: 204 | D23: 44.0873 | E23: =SUMIF(Data!$E:$E,$C23,Data!$AI:$AI) -> 0 | I23: HD | J23: HOME DEPOT INC | K23: Aktien | L23: 0,54 | M23: 224,22 | N23: 591.299 | O23: 132.581.062 | P23: 132.581.061,78 | Q23: Zyklische Konsumgüter | R23: US4370761029 | S23: New York Stock Exchange Inc. | T23: Vereinigte Staaten | U23: USD | V23: =SUMIF(Data!$E:$E,$I23,Data!$AI:$AI) -> 0
A24: ALBI01 | B24: Instrument | C24: 207 | D24: 55.9126 | E24: =SUMIF(Data!$E:$E,$C24,Data!$AI:$AI) -> 0 | I24: VZ | J24: VERIZON COMMUNICATIONS INC | K24: Aktien | L24: 0,53 | M24: 58,99 | N24: 2.201.916 | O24: 129.891.025 | P24: 129.891.024,84 | Q24: Kommunikation | R24: US92343V1044 | S24: New York Stock Exchange Inc. | T24: Vereinigte Staaten | U24: USD | V24: =SUMIF(Data!$E:$E,$I24,Data!$AI:$AI) -> 0
A25: ALBI01 | B25: Instrument | C25: AICASH | D25: 0 | E25: =SUMIF(Data!$E:$E,$C25,Data!$AI:$AI) -> 0 | I25: ROG | J25: ROCHE HOLDING PAR AG | K25: Aktien | L25: 0,51 | M25: 329,21 | N25: 375.672 | O25: 123.673.577 | P25: 123.673.576,98 | Q25: Gesundheitsversorgung | R25: CH0012032048 | S25: Six Swiss Exchange Ag | T25: Schweiz | U25: CHF | V25: =SUMIF(Data!$E:$E,$I25,Data!$AI:$AI) -> 0
A26: BBG006Q42QL6 | B26: Instrument | C26: EGS60121C018 | D26: 5.8087 | E26: =SUMIF(Data!$E:$E,$C26,Data!$AI:$AI) -> 0 | I26: MRK | J26: MERCK & CO INC | K26: Aktien | L26: 0,51 | M26: 89,53 | N26: 1.375.827 | O26: 123.177.791 | P26: 123.177.791,31 | Q26: Gesundheitsversorgung | R26: US58933Y1055 | S26: New York Stock Exchange Inc. | T26: Vereinigte Staaten | U26: USD | V26: =SUMIF(Data!$E:$E,$I26,Data!$AI:$AI) -> 0
A27: BBG006Q42QL6 | B27: Instrument | C27: EGS691S1C011 | D27: 0.7944 | E27: =SUMIF(Data!$E:$E,$C27,Data!$AI:$AI) -> 0 | I27: KO | J27: COCA-COLA | K27: Aktien | L27: 0,50 | M27: 55,53 | N27: 2.184.327 | O27: 121.295.678 | P27: 121.295.678,31 | Q27: Nichtzyklische Konsumgüter | R27: US1912161007 | S27: New York Stock Exchange Inc. | T27: Vereinigte Staaten | U27: USD | V27: =SUMIF(Data!$E:$E,$I27,Data!$AI:$AI) -> 0
A28: BBG006Q42QL6 | B28: Instrument | C28: EGS74081C018 | D28: 5.2252 | E28: =SUMIF(Data!$E:$E,$C28,Data!$AI:$AI) -> 0 | I28: WFC | J28: WELLS FARGO | K28: Aktien | L28: 0,49 | M28: 52,50 | N28: 2.268.303 | O28: 119.085.908 | P28: 119.085.907,50 | Q28: Financials | R28: US9497461015 | S28: New York Stock Exchange Inc. | T28: Vereinigte Staaten | U28: USD | V28: =SUMIF(Data!$E:$E,$I28,Data!$AI:$AI) -> 0
A29: BBG006Q42QL6 | B29: Instrument | C29: KE0000000315 | D29: 0.8537 | E29: =SUMIF(Data!$E:$E,$C29,Data!$AI:$AI) -> 0 | I29: CVX | J29: CHEVRON CORP | K29: Aktien | L29: 0,49 | M29: 116,44 | N29: 1.020.318 | O29: 118.805.828 | P29: 118.805.827,92 | Q29: Energie | R29: US1667641005 | S29: New York Stock Exchange Inc. | T29: Vereinigte Staaten | U29: USD | V29: =SUMIF(Data!$E:$E,$I29,Data!$AI:$AI) -> 0
A30: BBG006Q42QL6 | B30: Instrument | C30: KE1000001402 | D30: 4.3754 | E30: =SUMIF(Data!$E:$E,$C30,Data!$AI:$AI) -> 0 | I30: PFE | J30: PFIZER INC | K30: Aktien | L30: 0,48 | M30: 39,49 | N30: 2.964.851 | O30: 117.081.966 | P30: 117.081.965,99 | Q30: Gesundheitsversorgung | R30: US7170811035 | S30: New York Stock Exchange Inc. | T30: Vereinigte Staaten | U30: USD | V30: =SUMIF(Data!$E:$E,$I30,Data!$AI:$AI) -> 0
A31: BBG006Q42QL6 | B31: Instrument | C31: KE1000001568 | D31: 0.3255 | E31: =SUMIF(Data!$E:$E,$C31,Data!$AI:$AI) -> 0 | I31: NOVN | J31: NOVARTIS AG | K31: Aktien | L31: 0,45 | M31: 94,16 | N31: 1.164.896 | O31: 109.685.147 | P31: 109.685.147,13 | Q31: Gesundheitsversorgung | R31: CH0012005267 | S31: Six Swiss Exchange Ag | T31: Schweiz | U31: CHF | V31: =SUMIF(Data!$E:$E,$I31,Data!$AI:$AI) -> 0
A32: BBG006Q42QL6 | B32: Instrument | C32: NGACCESS0005 | D32: 0.329 | E32: =SUMIF(Data!$E:$E,$C32,Data!$AI:$AI) -> 0 | I32: CMCSA | J32: COMCAST CORP CLASS A | K32: Aktien | L32: 0,45 | M32: 44,98 | N32: 2.427.203 | O32: 109.175.591 | P32: 109.175.590,94 | Q32: Kommunikation | R32: US20030N1019 | S32: NASDAQ | T32: Vereinigte Staaten | U32: USD | V32: =SUMIF(Data!$E:$E,$I32,Data!$AI:$AI) -> 0
A33: BBG006Q42QL6 | B33: Instrument | C33: NGDANGCEM008 | D33: 0.6906 | E33: =SUMIF(Data!$E:$E,$C33,Data!$AI:$AI) -> 0 | I33: CSCO | J33: CISCO SYSTEMS INC | K33: Aktien | L33: 0,44 | M33: 47,13 | N33: 2.291.677 | O33: 108.006.737 | P33: 108.006.737,01 | Q33: IT | R33: US17275R1023 | S33: NASDAQ | T33: Vereinigte Staaten | U33: USD | V33: =SUMIF(Data!$E:$E,$I33,Data!$AI:$AI) -> 0
A34: BBG006Q42QL6 | B34: Instrument | C34: NGGUARANTY06 | D34: 2.3453 | E34: =SUMIF(Data!$E:$E,$C34,Data!$AI:$AI) -> 0 | I34: PEP | J34: PEPSICO INC | K34: Aktien | L34: 0,42 | M34: 134,53 | N34: 753.738 | O34: 101.400.373 | P34: 101.400.373,14 | Q34: Nichtzyklische Konsumgüter | R34: US7134481081 | S34: NASDAQ | T34: Vereinigte Staaten | U34: USD | V34: =SUMIF(Data!$E:$E,$I34,Data!$AI:$AI) -> 0
A35: BBG006Q42QL6 | B35: Instrument | C35: NGZENITHBNK9 | D35: 2.8529 | E35: =SUMIF(Data!$E:$E,$C35,Data!$AI:$AI) -> 0 | I35: C | J35: CITIGROUP INC | K35: Aktien | L35: 0,40 | M35: 79,25 | N35: 1.217.677 | O35: 96.500.902 | P35: 96.500.902,25 | Q35: Financials | R35: US1729674242 | S35: New York Stock Exchange Inc. | T35: Vereinigte Staaten | U35: USD | V35: =SUMIF(Data!$E:$E,$I35,Data!$AI:$AI) -> 0
A36: BBG006Q42QL6 | B36: Instrument | C36: NGNESTLE0006 | D36: 1.3242 | E36: =SUMIF(Data!$E:$E,$C36,Data!$AI:$AI) -> 0 | I36: BA | J36: BOEING | K36: Aktien | L36: 0,39 | M36: 329,92 | N36: 286.697 | O36: 94.587.074 | P36: 94.587.074,24 | Q36: Industrie | R36: US0970231058 | S36: New York Stock Exchange Inc. | T36: Vereinigte Staaten | U36: USD | V36: =SUMIF(Data!$E:$E,$I36,Data!$AI:$AI) -> 0
A37: BBG006Q42QL6 | B37: Instrument | C37: NGWAPCO00002 | D37: 0.406 | E37: =SUMIF(Data!$E:$E,$C37,Data!$AI:$AI) -> 0 | I37: WMT | J37: WALMART INC | K37: Aktien | L37: 0,37 | M37: 116,38 | N37: 777.778 | O37: 90.517.804 | P37: 90.517.803,64 | Q37: Nichtzyklische Konsumgüter | R37: US9311421039 | S37: New York Stock Exchange Inc. | T37: Vereinigte Staaten | U37: USD | V37: =SUMIF(Data!$E:$E,$I37,Data!$AI:$AI) -> 0
A38: BBG006Q42QL6 | B38: Instrument | C38: NGFBNH000009 | D38: 0.4499 | E38: =SUMIF(Data!$E:$E,$C38,Data!$AI:$AI) -> 0 | I38: ADBE | J38: ADOBE INC | K38: Aktien | L38: 0,37 | M38: 339,81 | N38: 261.709 | O38: 88.931.335 | P38: 88.931.335,29 | Q38: IT | R38: US00724F1012 | S38: NASDAQ | T38: Vereinigte Staaten | U38: USD | V38: =SUMIF(Data!$E:$E,$I38,Data!$AI:$AI) -> 0
A39: BBG006Q42QL6 | B39: Instrument | C39: EGS37091C013 | D39: 1.1994 | E39: =SUMIF(Data!$E:$E,$C39,Data!$AI:$AI) -> 0 | I39: 7203 | J39: TOYOTA MOTOR CORP | K39: Aktien | L39: 0,35 | M39: 69,93 | N39: 1.231.200 | O39: 86.091.851 | P39: 86.091.851,04 | Q39: Zyklische Konsumgüter | R39: JP3633400001 | S39: Tokyo Stock Exchange | T39: Japan | U39: JPY | V39: =SUMIF(Data!$E:$E,$I39,Data!$AI:$AI) -> 0
A40: BBG006Q42QL6 | B40: Instrument | C40: KE0000000075 | D40: 0.5837 | E40: =SUMIF(Data!$E:$E,$C40,Data!$AI:$AI) -> 0 | I40: MCD | J40: MCDONALDS CORP | K40: Aktien | L40: 0,35 | M40: 207,27 | N40: 406.152 | O40: 84.183.125 | P40: 84.183.125,04 | Q40: Zyklische Konsumgüter | R40: US5801351017 | S40: New York Stock Exchange Inc. | T40: Vereinigte Staaten | U40: USD | V40: =SUMIF(Data!$E:$E,$I40,Data!$AI:$AI) -> 0
A41: BBG006Q42QL6 | B41: Instrument | C41: NGMOBIL00007 | D41: 0.1545 | E41: =SUMIF(Data!$E:$E,$C41,Data!$AI:$AI) -> 0 | I41: MDT | J41: MEDTRONIC PLC | K41: Aktien | L41: 0,34 | M41: 118,64 | N41: 705.786 | O41: 83.734.451 | P41: 83.734.451,04 | Q41: Gesundheitsversorgung | R41: IE00BTN1Y115 | S41: New York Stock Exchange Inc. | T41: Vereinigte Staaten | U41: USD | V41: =SUMIF(Data!$E:$E,$I41,Data!$AI:$AI) -> 0
A42: BBG006Q42QL6 | B42: Instrument | C42: SN0000000019 | D42: 1.9826 | E42: =SUMIF(Data!$E:$E,$C42,Data!$AI:$AI) -> 0 | I42: BMY | J42: BRISTOL MYERS SQUIBB | K42: Aktien | L42: 0,34 | M42: 65,23 | N42: 1.254.743 | O42: 81.846.886 | P42: 81.846.885,89 | Q42: Gesundheitsversorgung | R42: US1101221083 | S42: New York Stock Exchange Inc. | T42: Vereinigte Staaten | U42: USD | V42: =SUMIF(Data!$E:$E,$I42,Data!$AI:$AI) -> 0
A43: BBG006Q42QL6 | B43: Instrument | C43: ZW0009011199 | D43: 4.5946 | E43: =SUMIF(Data!$E:$E,$C43,Data!$AI:$AI) -> 0 | I43: HSBA | J43: HSBC HOLDINGS PLC | K43: Aktien | L43: 0,33 | M43: 7,64 | N43: 10.646.315 | O43: 81.286.407 | P43: 81.286.406,80 | Q43: Financials | R43: GB0005405286 | S43: London Stock Exchange | T43: Vereinigtes Königreich | U43: GBP | V43: =SUMIF(Data!$E:$E,$I43,Data!$AI:$AI) -> 0
A44: BBG006Q42QL6 | B44: Instrument | C44: EGS60041C018 | D44: 0.3585 | E44: =SUMIF(Data!$E:$E,$C44,Data!$AI:$AI) -> 0 | I44: CRM | J44: SALESFORCE.COM INC | K44: Aktien | L44: 0,33 | M44: 180,20 | N44: 449.099 | O44: 80.927.640 | P44: 80.927.639,80 | Q44: IT | R44: US79466L3024 | S44: New York Stock Exchange Inc. | T44: Vereinigte Staaten | U44: USD | V44: =SUMIF(Data!$E:$E,$I44,Data!$AI:$AI) -> 0
A45: BBG006Q42QL6 | B45: Instrument | C45: NGFCMB000005 | D45: 0.0724 | E45: =SUMIF(Data!$E:$E,$C45,Data!$AI:$AI) -> 0 | I45: ABT | J45: ABBOTT LABORATORIES | K45: Aktien | L45: 0,33 | M45: 85,36 | N45: 937.692 | O45: 80.041.389 | P45: 80.041.389,12 | Q45: Gesundheitsversorgung | R45: US0028241000 | S45: New York Stock Exchange Inc. | T45: Vereinigte Staaten | U45: USD | V45: =SUMIF(Data!$E:$E,$I45,Data!$AI:$AI) -> 0
A46: BBG006Q42QL6 | B46: Instrument | C46: NGSEPLAT0008 | D46: 0.3612 | E46: =SUMIF(Data!$E:$E,$C46,Data!$AI:$AI) -> 0 | I46: NFLX | J46: NETFLIX INC | K46: Aktien | L46: 0,32 | M46: 329,05 | N46: 237.036 | O46: 77.996.696 | P46: 77.996.695,80 | Q46: Kommunikation | R46: US64110L1061 | S46: NASDAQ | T46: Vereinigte Staaten | U46: USD | V46: =SUMIF(Data!$E:$E,$I46,Data!$AI:$AI) -> 0
A47: BBG006Q42QL6 | B47: Instrument | C47: TG0000000132 | D47: 1.3393 | E47: =SUMIF(Data!$E:$E,$C47,Data!$AI:$AI) -> 0 | I47: AMGN | J47: AMGEN INC | K47: Aktien | L47: 0,32 | M47: 238,26 | N47: 327.34 | O47: 77.992.028 | P47: 77.992.028,40 | Q47: Gesundheitsversorgung | R47: US0311621009 | S47: NASDAQ | T47: Vereinigte Staaten | U47: USD | V47: =SUMIF(Data!$E:$E,$I47,Data!$AI:$AI) -> 0
A48: BBG006Q42QL6 | B48: Instrument | C48: ZW0009012122 | D48: 1.1201 | E48: =SUMIF(Data!$E:$E,$C48,Data!$AI:$AI) -> 0 | I48: NVDA | J48: NVIDIA CORP | K48: Aktien | L48: 0,31 | M48: 244,32 | N48: 310.756 | O48: 75.923.906 | P48: 75.923.905,92 | Q48: IT | R48: US67066G1040 | S48: NASDAQ | T48: Vereinigte Staaten | U48: USD | V48: =SUMIF(Data!$E:$E,$I48,Data!$AI:$AI) -> 0
A49: BBG006Q42QL6 | B49: Instrument | C49: KE0000000323 | D49: 0.2058 | E49: =SUMIF(Data!$E:$E,$C49,Data!$AI:$AI) -> 0 | I49: SAP | J49: SAP | K49: Aktien | L49: 0,30 | M49: 137,54 | N49: 533.702 | O49: 73.405.734 | P49: 73.405.733,86 | Q49: IT | R49: DE0007164600 | S49: Xetra | T49: Deutschland | U49: EUR | V49: =SUMIF(Data!$E:$E,$I49,Data!$AI:$AI) -> 0
A50: BBG006Q42QL6 | B50: Instrument | C50: EGS305I1C011 | D50: 0.4764 | E50: =SUMIF(Data!$E:$E,$C50,Data!$AI:$AI) -> 0 | I50: PM | J50: PHILIP MORRIS INTERNATIONAL INC | K50: Aktien | L50: 0,30 | M50: 87,46 | N50: 827.17 | O50: 72.344.288 | P50: 72.344.288,20 | Q50: Nichtzyklische Konsumgüter | R50: US7181721090 | S50: New York Stock Exchange Inc. | T50: Vereinigte Staaten | U50: USD | V50: =SUMIF(Data!$E:$E,$I50,Data!$AI:$AI) -> 0
A51: BBG006Q42QL6 | B51: Instrument | C51: NGTOTAL00001 | D51: 0.5137 | E51: =SUMIF(Data!$E:$E,$C51,Data!$AI:$AI) -> 0 | I51: RDSA | J51: ROYAL DUTCH SHELL PLC | K51: Aktien | L51: 0,29 | M51: 29,56 | N51: 2.422.918 | O51: 71.627.372 | P51: 71.627.372,24 | Q51: Energie | R51: GB00B03MLX29 | S51: London Stock Exchange | T51: Vereinigtes Königreich | U51: GBP | V51: =SUMIF(Data!$E:$E,$I51,Data!$AI:$AI) -> 0
A52: BBG006Q42QL6 | B52: Instrument | C52: CI0000000030 | D52: 0.2939 | E52: =SUMIF(Data!$E:$E,$C52,Data!$AI:$AI) -> 0 | I52: 1299 | J52: AIA GROUP LTD | K52: Aktien | L52: 0,29 | M52: 11,07 | N52: 6.442.074 | O52: 71.333.908 | P52: 71.333.908,11 | Q52: Financials | R52: HK0000069689 | S52: Hong Kong Exchanges And Clearing Ltd | T52: Hongkong | U52: HKD | V52: =SUMIF(Data!$E:$E,$I52,Data!$AI:$AI) -> 0
A53: BBG006Q42QL6 | B53: Instrument | C53: EGS30031C016 | D53: 0.1728 | E53: =SUMIF(Data!$E:$E,$C53,Data!$AI:$AI) -> 0 | I53: FP | J53: TOTAL SA | K53: Aktien | L53: 0,29 | M53: 55,33 | N53: 1.287.367 | O53: 71.228.162 | P53: 71.228.161,98 | Q53: Energie | R53: FR0000120271 | S53: Nyse Euronext - Euronext Paris | T53: Frankreich | U53: EUR | V53: =SUMIF(Data!$E:$E,$I53,Data!$AI:$AI) -> 0
A54: BBG006Q42QL6 | B54: Instrument | C54: EGS30901C010 | D54: 1.1383 | E54: =SUMIF(Data!$E:$E,$C54,Data!$AI:$AI) -> 0 | I54: AZN | J54: ASTRAZENECA PLC | K54: Aktien | L54: 0,29 | M54: 99,85 | N54: 708.35 | O54: 70.726.993 | P54: 70.726.992,56 | Q54: Gesundheitsversorgung | R54: GB0009895292 | S54: London Stock Exchange | T54: Vereinigtes Königreich | U54: GBP | V54: =SUMIF(Data!$E:$E,$I54,Data!$AI:$AI) -> 0
A55: BBG006Q42QL6 | B55: Instrument | C55: EGS32221C011 | D55: 0.2804 | E55: =SUMIF(Data!$E:$E,$C55,Data!$AI:$AI) -> 0 | I55: TMO | J55: THERMO FISHER SCIENTIFIC INC | K55: Aktien | L55: 0,29 | M55: 328,73 | N55: 214.431 | O55: 70.489.903 | P55: 70.489.902,63 | Q55: Gesundheitsversorgung | R55: US8835561023 | S55: New York Stock Exchange Inc. | T55: Vereinigte Staaten | U55: USD | V55: =SUMIF(Data!$E:$E,$I55,Data!$AI:$AI) -> 0
A56: BBG006Q42QL6 | B56: Instrument | C56: EGS33041C012 | D56: 0.3913 | E56: =SUMIF(Data!$E:$E,$C56,Data!$AI:$AI) -> 0 | I56: ABBV | J56: ABBVIE INC | K56: Aktien | L56: 0,29 | M56: 89,06 | N56: 787.276 | O56: 70.114.801 | P56: 70.114.800,56 | Q56: Gesundheitsversorgung | R56: US00287Y1091 | S56: New York Stock Exchange Inc. | T56: Vereinigte Staaten | U56: USD | V56: =SUMIF(Data!$E:$E,$I56,Data!$AI:$AI) -> 0
A57: BBG006Q42QL6 | B57: Instrument | C57: EGS38081C013 | D57: 0.9574 | E57: =SUMIF(Data!$E:$E,$C57,Data!$AI:$AI) -> 0 | I57: NKE | J57: NIKE INC CLASS B | K57: Aktien | L57: 0,29 | M57: 100,90 | N57: 691.164 | O57: 69.738.448 | P57: 69.738.447,60 | Q57: Zyklische Konsumgüter | R57: US6541061031 | S57: New York Stock Exchange Inc. | T57: Vereinigte Staaten | U57: USD | V57: =SUMIF(Data!$E:$E,$I57,Data!$AI:$AI) -> 0
A58: BBG006Q42QL6 | B58: Instrument | C58: EGS380P1C010 | D58: 0.4692 | E58: =SUMIF(Data!$E:$E,$C58,Data!$AI:$AI) -> 0 | I58: ACN | J58: ACCENTURE PLC CLASS A | K58: Aktien | L58: 0,29 | M58: 207,66 | N58: 335.759 | O58: 69.723.714 | P58: 69.723.713,94 | Q58: IT | R58: IE00B4BNMY34 | S58: New York Stock Exchange Inc. | T58: Vereinigte Staaten | U58: USD | V58: =SUMIF(Data!$E:$E,$I58,Data!$AI:$AI) -> 0
A59: BBG006Q42QL6 | B59: Instrument | C59: EGS380S1C017 | D59: 1.0868 | E59: =SUMIF(Data!$E:$E,$C59,Data!$AI:$AI) -> 0 | I59: HON | J59: HONEYWELL INTERNATIONAL INC | K59: Aktien | L59: 0,29 | M59: 178,68 | N59: 389.579 | O59: 69.609.976 | P59: 69.609.975,72 | Q59: Industrie | R59: US4385161066 | S59: New York Stock Exchange Inc. | T59: Vereinigte Staaten | U59: USD | V59: =SUMIF(Data!$E:$E,$I59,Data!$AI:$AI) -> 0
A60: BBG006Q42QL6 | B60: Instrument | C60: EGS38201C017 | D60: 0.1754 | E60: =SUMIF(Data!$E:$E,$C60,Data!$AI:$AI) -> 0 | I60: COST | J60: COSTCO WHOLESALE CORP | K60: Aktien | L60: 0,29 | M60: 297,24 | N60: 233.838 | O60: 69.506.007 | P60: 69.506.007,12 | Q60: Nichtzyklische Konsumgüter | R60: US22160K1051 | S60: NASDAQ | T60: Vereinigte Staaten | U60: USD | V60: =SUMIF(Data!$E:$E,$I60,Data!$AI:$AI) -> 0
A61: BBG006Q42QL6 | B61: Instrument | C61: EGS38381C017 | D61: 0.0428 | E61: =SUMIF(Data!$E:$E,$C61,Data!$AI:$AI) -> 0 | I61: MC | J61: LVMH | K61: Aktien | L61: 0,29 | M61: 470,82 | N61: 147.528 | O61: 69.459.639 | P61: 69.459.638,61 | Q61: Zyklische Konsumgüter | R61: FR0000121014 | S61: Nyse Euronext - Euronext Paris | T61: Frankreich | U61: EUR | V61: =SUMIF(Data!$E:$E,$I61,Data!$AI:$AI) -> 0
A62: BBG006Q42QL6 | B62: Instrument | C62: EGS3C0O1C016 | D62: 0.7477 | E62: =SUMIF(Data!$E:$E,$C62,Data!$AI:$AI) -> 0 | I62: BP. | J62: BP PLC | K62: Aktien | L62: 0,28 | M62: 6,47 | N62: 10.648.225 | O62: 68.874.983 | P62: 68.874.983,38 | Q62: Energie | R62: GB0007980591 | S62: London Stock Exchange | T62: Vereinigtes Königreich | U62: GBP | V62: =SUMIF(Data!$E:$E,$I62,Data!$AI:$AI) -> 0
A63: BBG006Q42QL6 | B63: Instrument | C63: EGS3C251C013 | D63: 0.9489 | E63: =SUMIF(Data!$E:$E,$C63,Data!$AI:$AI) -> 0 | I63: ORCL | J63: ORACLE CORP | K63: Aktien | L63: 0,28 | M63: 54,45 | N63: 1.256.548 | O63: 68.419.039 | P63: 68.419.038,60 | Q63: IT | R63: US68389X1054 | S63: New York Stock Exchange Inc. | T63: Vereinigte Staaten | U63: USD | V63: =SUMIF(Data!$E:$E,$I63,Data!$AI:$AI) -> 0
A64: BBG006Q42QL6 | B64: Instrument | C64: EGS3D061C015 | D64: 0.1035 | E64: =SUMIF(Data!$E:$E,$C64,Data!$AI:$AI) -> 0 | I64: ASML | J64: ASML HOLDING NV | K64: Aktien | L64: 0,28 | M64: 298,51 | N64: 226.581 | O64: 67.636.379 | P64: 67.636.379,36 | Q64: IT | R64: NL0010273215 | S64: Euronext Amsterdam | T64: Niederlande | U64: EUR | V64: =SUMIF(Data!$E:$E,$I64,Data!$AI:$AI) -> 0
A65: BBG006Q42QL6 | B65: Instrument | C65: EGS3G0Z1C014 | D65: 1.6003 | E65: =SUMIF(Data!$E:$E,$C65,Data!$AI:$AI) -> 0 | I65: UNP | J65: UNION PACIFIC CORP | K65: Aktien | L65: 0,28 | M65: 177,94 | N65: 378.778 | O65: 67.399.757 | P65: 67.399.757,32 | Q65: Industrie | R65: US9078181081 | S65: New York Stock Exchange Inc. | T65: Vereinigte Staaten | U65: USD | V65: =SUMIF(Data!$E:$E,$I65,Data!$AI:$AI) -> 0
A66: BBG006Q42QL6 | B66: Instrument | C66: EGS42111C012 | D66: 2.3896 | E66: =SUMIF(Data!$E:$E,$C66,Data!$AI:$AI) -> 0 | I66: PYPL | J66: PAYPAL HOLDINGS INC | K66: Aktien | L66: 0,27 | M66: 112,93 | N66: 588.216 | O66: 66.427.233 | P66: 66.427.232,88 | Q66: IT | R66: US70450Y1038 | S66: NASDAQ | T66: Vereinigte Staaten | U66: USD | V66: =SUMIF(Data!$E:$E,$I66,Data!$AI:$AI) -> 0
A67: BBG006Q42QL6 | B67: Instrument | C67: EGS48031C016 | D67: 0.7267 | E67: =SUMIF(Data!$E:$E,$C67,Data!$AI:$AI) -> 0 | I67: UTX | J67: UNITED TECHNOLOGIES CORP | K67: Aktien | L67: 0,27 | M67: 151,86 | N67: 436.463 | O67: 66.281.271 | P67: 66.281.271,18 | Q67: Industrie | R67: US9130171096 | S67: New York Stock Exchange Inc. | T67: Vereinigte Staaten | U67: USD | V67: =SUMIF(Data!$E:$E,$I67,Data!$AI:$AI) -> 0
A68: BBG006Q42QL6 | B68: Instrument | C68: EGS60111C019 | D68: 0.0638 | E68: =SUMIF(Data!$E:$E,$C68,Data!$AI:$AI) -> 0 | I68: TXN | J68: TEXAS INSTRUMENT INC | K68: Aktien | L68: 0,27 | M68: 130,00 | N68: 506.74 | O68: 65.876.200 | P68: 65.876.200,00 | Q68: IT | R68: US8825081040 | S68: NASDAQ | T68: Vereinigte Staaten | U68: USD | V68: =SUMIF(Data!$E:$E,$I68,Data!$AI:$AI) -> 0
A69: BBG006Q42QL6 | B69: Instrument | C69: EGS60301C016 | D69: 0.2083 | E69: =SUMIF(Data!$E:$E,$C69,Data!$AI:$AI) -> 0 | I69: LLY | J69: ELI LILLY | K69: Aktien | L69: 0,27 | M69: 138,00 | N69: 475.438 | O69: 65.610.444 | P69: 65.610.444,00 | Q69: Gesundheitsversorgung | R69: US5324571083 | S69: New York Stock Exchange Inc. | T69: Vereinigte Staaten | U69: USD | V69: =SUMIF(Data!$E:$E,$I69,Data!$AI:$AI) -> 0
A70: BBG006Q42QL6 | B70: Instrument | C70: EGS65571C019 | D70: 0.298 | E70: =SUMIF(Data!$E:$E,$C70,Data!$AI:$AI) -> 0 | I70: IBM | J70: INTERNATIONAL BUSINESS MACHINES CO | K70: Aktien | L70: 0,27 | M70: 136,69 | N70: 477.236 | O70: 65.233.389 | P70: 65.233.388,84 | Q70: IT | R70: US4592001014 | S70: New York Stock Exchange Inc. | T70: Vereinigte Staaten | U70: USD | V70: =SUMIF(Data!$E:$E,$I70,Data!$AI:$AI) -> 0
A71: BBG006Q42QL6 | B71: Instrument | C71: EGS65591C017 | D71: 0.6376 | E71: =SUMIF(Data!$E:$E,$C71,Data!$AI:$AI) -> 0 | I71: NEE | J71: NEXTERA ENERGY INC | K71: Aktien | L71: 0,26 | M71: 243,55 | N71: 263.358 | O71: 64.140.841 | P71: 64.140.840,90 | Q71: Versorger | R71: US65339F1012 | S71: New York Stock Exchange Inc. | T71: Vereinigte Staaten | U71: USD | V71: =SUMIF(Data!$E:$E,$I71,Data!$AI:$AI) -> 0
A72: BBG006Q42QL6 | B72: Instrument | C72: EGS655L1C012 | D72: 0.1808 | E72: =SUMIF(Data!$E:$E,$C72,Data!$AI:$AI) -> 0 | I72: AVGO | J72: BROADCOM INC | K72: Aktien | L72: 0,26 | M72: 299,22 | N72: 213.632 | O72: 63.922.967 | P72: 63.922.967,04 | Q72: IT | R72: US11135F1012 | S72: NASDAQ | T72: Vereinigte Staaten | U72: USD | V72: =SUMIF(Data!$E:$E,$I72,Data!$AI:$AI) -> 0
A73: BBG006Q42QL6 | B73: Instrument | C73: EGS65851C015 | D73: 0.3771 | E73: =SUMIF(Data!$E:$E,$C73,Data!$AI:$AI) -> 0 | I73: GSK | J73: GLAXOSMITHKLINE PLC | K73: Aktien | L73: 0,26 | M73: 23,47 | N73: 2.681.654 | O73: 62.951.674 | P73: 62.951.673,99 | Q73: Gesundheitsversorgung | R73: GB0009252882 | S73: London Stock Exchange | T73: Vereinigtes Königreich | U73: GBP | V73: =SUMIF(Data!$E:$E,$I73,Data!$AI:$AI) -> 0
A74: BBG006Q42QL6 | B74: Instrument | C74: EGS673T1C012 | D74: 0.0624 | E74: =SUMIF(Data!$E:$E,$C74,Data!$AI:$AI) -> 0 | I74: SAN | J74: SANOFI SA | K74: Aktien | L74: 0,26 | M74: 103,04 | N74: 609.739 | O74: 62.830.172 | P74: 62.830.172,34 | Q74: Gesundheitsversorgung | R74: FR0000120578 | S74: Nyse Euronext - Euronext Paris | T74: Frankreich | U74: EUR | V74: =SUMIF(Data!$E:$E,$I74,Data!$AI:$AI) -> 0
A75: BBG006Q42QL6 | B75: Instrument | C75: EGS673Y1C015 | D75: 0.2043 | E75: =SUMIF(Data!$E:$E,$C75,Data!$AI:$AI) -> 0 | I75: RY | J75: ROYAL BANK OF CANADA | K75: Aktien | L75: 0,26 | M75: 79,91 | N75: 781.714 | O75: 62.470.038 | P75: 62.470.038,08 | Q75: Financials | R75: CA7800871021 | S75: Toronto Stock Exchange | T75: Kanada | U75: CAD | V75: =SUMIF(Data!$E:$E,$I75,Data!$AI:$AI) -> 0
A76: BBG006Q42QL6 | B76: Instrument | C76: EGS675S1C011 | D76: 0.0601 | E76: =SUMIF(Data!$E:$E,$C76,Data!$AI:$AI) -> 0 | I76: LIN | J76: LINDE PLC | K76: Aktien | L76: 0,26 | M76: 209,08 | N76: 298.636 | O76: 62.438.815 | P76: 62.438.814,88 | Q76: Materialien | R76: IE00BZ12WP82 | S76: New York Stock Exchange Inc. | T76: Vereinigte Staaten | U76: USD | V76: =SUMIF(Data!$E:$E,$I76,Data!$AI:$AI) -> 0
A77: BBG006Q42QL6 | B77: Instrument | C77: EGS69082C013 | D77: 0.8336 | E77: =SUMIF(Data!$E:$E,$C77,Data!$AI:$AI) -> 0 | I77: RDSB | J77: ROYAL DUTCH SHELL PLC CLASS B | K77: Aktien | L77: 0,25 | M77: 29,65 | N77: 2.022.543 | O77: 59.963.010 | P77: 59.963.009,87 | Q77: Energie | R77: GB00B03MM408 | S77: London Stock Exchange | T77: Vereinigtes Königreich | U77: GBP | V77: =SUMIF(Data!$E:$E,$I77,Data!$AI:$AI) -> 0
A78: BBG006Q42QL6 | B78: Instrument | C78: EGS69101C011 | D78: 0.8201 | E78: =SUMIF(Data!$E:$E,$C78,Data!$AI:$AI) -> 0 | I78: SBUX | J78: STARBUCKS CORP | K78: Aktien | L78: 0,24 | M78: 90,16 | N78: 660.622 | O78: 59.561.680 | P78: 59.561.679,52 | Q78: Zyklische Konsumgüter | R78: US8552441094 | S78: NASDAQ | T78: Vereinigte Staaten | U78: USD | V78: =SUMIF(Data!$E:$E,$I78,Data!$AI:$AI) -> 0
A79: BBG006Q42QL6 | B79: Instrument | C79: EGS691L1C018 | D79: 0.2731 | E79: =SUMIF(Data!$E:$E,$C79,Data!$AI:$AI) -> 0 | I79: USD | J79: USD CASH | K79: Geldmarkt | L79: 0,24 | M79: 100,00 | N79: 58.837.407 | O79: 58.837.407 | P79: 58.837.407,35 | Q79: Cash und/oder Derivate | R79: - | S79: - | T79: Vereinigte Staaten | U79: USD | V79: =SUMIF(Data!$E:$E,$I79,Data!$AI:$AI) -> 0
A80: BBG006Q42QL6 | B80: Instrument | C80: EGS693V1C014 | D80: 0.3643 | E80: =SUMIF(Data!$E:$E,$C80,Data!$AI:$AI) -> 0 | I80: NOVO B | J80: NOVO NORDISK CLASS B | K80: Aktien | L80: 0,24 | M80: 59,08 | N80: 991.797 | O80: 58.599.113 | P80: 58.599.113,39 | Q80: Gesundheitsversorgung | R80: DK0060534915 | S80: Omx Nordic Exchange Copenhagen A/S | T80: Dänemark | U80: DKK | V80: =SUMIF(Data!$E:$E,$I80,Data!$AI:$AI) -> 0
A81: BBG006Q42QL6 | B81: Instrument | C81: EGS694A1C018 | D81: 0.0364 | E81: =SUMIF(Data!$E:$E,$C81,Data!$AI:$AI) -> 0 | I81: QCOM | J81: QUALCOMM INC | K81: Aktien | L81: 0,24 | M81: 90,26 | N81: 645.789 | O81: 58.288.915 | P81: 58.288.915,14 | Q81: IT | R81: US7475251036 | S81: NASDAQ | T81: Vereinigte Staaten | U81: USD | V81: =SUMIF(Data!$E:$E,$I81,Data!$AI:$AI) -> 0
A82: BBG006Q42QL6 | B82: Instrument | C82: EGS70431C019 | D82: 0.0549 | E82: =SUMIF(Data!$E:$E,$C82,Data!$AI:$AI) -> 0 | I82: LMT | J82: LOCKHEED MARTIN CORP | K82: Aktien | L82: 0,23 | M82: 413,83 | N82: 136.833 | O82: 56.625.600 | P82: 56.625.600,39 | Q82: Industrie | R82: US5398301094 | S82: New York Stock Exchange Inc. | T82: Vereinigte Staaten | U82: USD | V82: =SUMIF(Data!$E:$E,$I82,Data!$AI:$AI) -> 0
A83: BBG006Q42QL6 | B83: Instrument | C83: EGS73541C012 | D83: 0.1032 | E83: =SUMIF(Data!$E:$E,$C83,Data!$AI:$AI) -> 0 | I83: ALV | J83: ALLIANZ | K83: Aktien | L83: 0,23 | M83: 244,77 | N83: 227.401 | O83: 55.662.043 | P83: 55.662.042,82 | Q83: Financials | R83: DE0008404005 | S83: Xetra | T83: Deutschland | U83: EUR | V83: =SUMIF(Data!$E:$E,$I83,Data!$AI:$AI) -> 0
A84: BBG006Q42QL6 | B84: Instrument | C84: EGS95001C011 | D84: 0.6737 | E84: =SUMIF(Data!$E:$E,$C84,Data!$AI:$AI) -> 0 | I84: MMM | J84: 3M | K84: Aktien | L84: 0,23 | M84: 180,47 | N84: 306.297 | O84: 55.277.420 | P84: 55.277.419,59 | Q84: Industrie | R84: US88579Y1010 | S84: New York Stock Exchange Inc. | T84: Vereinigte Staaten | U84: USD | V84: =SUMIF(Data!$E:$E,$I84,Data!$AI:$AI) -> 0
A85: BBG006Q42QL6 | B85: Instrument | C85: KE0000000216 | D85: 3.6055 | E85: =SUMIF(Data!$E:$E,$C85,Data!$AI:$AI) -> 0 | I85: AMT | J85: AMERICAN TOWER REIT CORP | K85: Aktien | L85: 0,23 | M85: 230,80 | N85: 238.829 | O85: 55.121.733 | P85: 55.121.733,20 | Q85: Immobilien | R85: US03027X1000 | S85: New York Stock Exchange Inc. | T85: Vereinigte Staaten | U85: USD | V85: =SUMIF(Data!$E:$E,$I85,Data!$AI:$AI) -> 0
A86: BBG006Q42QL6 | B86: Instrument | C86: KE0000000265 | D86: 0.1841 | E86: =SUMIF(Data!$E:$E,$C86,Data!$AI:$AI) -> 0 | I86: BATS | J86: BRITISH AMERICAN TOBACCO PLC | K86: Aktien | L86: 0,22 | M86: 45,48 | N86: 1.202.656 | O86: 54.692.779 | P86: 54.692.779,21 | Q86: Nichtzyklische Konsumgüter | R86: GB0002875804 | S86: London Stock Exchange | T86: Vereinigtes Königreich | U86: GBP | V86: =SUMIF(Data!$E:$E,$I86,Data!$AI:$AI) -> 0
A87: BBG006Q42QL6 | B87: Instrument | C87: KE0000000554 | D87: 1.5123 | E87: =SUMIF(Data!$E:$E,$C87,Data!$AI:$AI) -> 0 | I87: DGE | J87: DIAGEO PLC | K87: Aktien | L87: 0,22 | M87: 42,38 | N87: 1.288.328 | O87: 54.601.044 | P87: 54.601.044,45 | Q87: Nichtzyklische Konsumgüter | R87: GB0002374006 | S87: London Stock Exchange | T87: Vereinigtes Königreich | U87: GBP | V87: =SUMIF(Data!$E:$E,$I87,Data!$AI:$AI) -> 0
A88: BBG006Q42QL6 | B88: Instrument | C88: KE2000002192 | D88: 0.0863 | E88: =SUMIF(Data!$E:$E,$C88,Data!$AI:$AI) -> 0 | I88: GE | J88: GENERAL ELECTRIC | K88: Aktien | L88: 0,22 | M88: 11,67 | N88: 4.634.853 | O88: 54.088.735 | P88: 54.088.734,51 | Q88: Industrie | R88: US3696041033 | S88: New York Stock Exchange Inc. | T88: Vereinigte Staaten | U88: USD | V88: =SUMIF(Data!$E:$E,$I88,Data!$AI:$AI) -> 0
A89: BBG006Q42QL6 | B89: Instrument | C89: MA0000010019 | D89: 0.2359 | E89: =SUMIF(Data!$E:$E,$C89,Data!$AI:$AI) -> 0 | I89: TD | J89: TORONTO DOMINION | K89: Aktien | L89: 0,22 | M89: 55,93 | N89: 964.89 | O89: 53.968.486 | P89: 53.968.486,38 | Q89: Financials | R89: CA8911605092 | S89: Toronto Stock Exchange | T89: Kanada | U89: CAD | V89: =SUMIF(Data!$E:$E,$I89,Data!$AI:$AI) -> 0
A90: BBG006Q42QL6 | B90: Instrument | C90: MA0000010365 | D90: 0.7455 | E90: =SUMIF(Data!$E:$E,$C90,Data!$AI:$AI) -> 0 | I90: CBA | J90: COMMONWEALTH BANK OF AUSTRALIA | K90: Aktien | L90: 0,22 | M90: 56,97 | N90: 943.943 | O90: 53.776.787 | P90: 53.776.786,69 | Q90: Financials | R90: AU000000CBA7 | S90: Asx - All Markets | T90: Australien | U90: AUD | V90: =SUMIF(Data!$E:$E,$I90,Data!$AI:$AI) -> 0
A91: BBG006Q42QL6 | B91: Instrument | C91: MA0000010506 | D91: 0.9243 | E91: =SUMIF(Data!$E:$E,$C91,Data!$AI:$AI) -> 0 | I91: CSL | J91: CSL LTD | K91: Aktien | L91: 0,22 | M91: 206,68 | N91: 260.143 | O91: 53.766.775 | P91: 53.766.775,37 | Q91: Gesundheitsversorgung | R91: AU000000CSL8 | S91: Asx - All Markets | T91: Australien | U91: AUD | V91: =SUMIF(Data!$E:$E,$I91,Data!$AI:$AI) -> 0
A92: BBG006Q42QL6 | B92: Instrument | C92: MA0000010928 | D92: 0.4213 | E92: =SUMIF(Data!$E:$E,$C92,Data!$AI:$AI) -> 0 | I92: DHR | J92: DANAHER CORP | K92: Aktien | L92: 0,22 | M92: 158,12 | N92: 339.514 | O92: 53.683.954 | P92: 53.683.953,68 | Q92: Gesundheitsversorgung | R92: US2358511028 | S92: New York Stock Exchange Inc. | T92: Vereinigte Staaten | U92: USD | V92: =SUMIF(Data!$E:$E,$I92,Data!$AI:$AI) -> 0
A93: BBG006Q42QL6 | B93: Instrument | C93: MA0000011058 | D93: 1.6483 | E93: =SUMIF(Data!$E:$E,$C93,Data!$AI:$AI) -> 0 | I93: SIE | J93: SIEMENS N AG | K93: Aktien | L93: 0,22 | M93: 128,92 | N93: 411.189 | O93: 53.009.088 | P93: 53.009.087,84 | Q93: Industrie | R93: DE0007236101 | S93: Xetra | T93: Deutschland | U93: EUR | V93: =SUMIF(Data!$E:$E,$I93,Data!$AI:$AI) -> 0
A94: BBG006Q42QL6 | B94: Instrument | C94: MA0000011454 | D94: 0.1839 | E94: =SUMIF(Data!$E:$E,$C94,Data!$AI:$AI) -> 0 | I94: LOW | J94: LOWES COMPANIES INC | K94: Aktien | L94: 0,21 | M94: 121,00 | N94: 424.751 | O94: 51.394.871 | P94: 51.394.871,00 | Q94: Zyklische Konsumgüter | R94: US5486611073 | S94: New York Stock Exchange Inc. | T94: Vereinigte Staaten | U94: USD | V94: =SUMIF(Data!$E:$E,$I94,Data!$AI:$AI) -> 0
A95: BBG006Q42QL6 | B95: Instrument | C95: MA0000011488 | D95: 7.4994 | E95: =SUMIF(Data!$E:$E,$C95,Data!$AI:$AI) -> 0 | I95: 6758 | J95: SONY CORP | K95: Aktien | L95: 0,21 | M95: 71,59 | N95: 706.398 | O95: 50.568.451 | P95: 50.568.451,20 | Q95: Zyklische Konsumgüter | R95: JP3435000009 | S95: Tokyo Stock Exchange | T95: Japan | U95: JPY | V95: =SUMIF(Data!$E:$E,$I95,Data!$AI:$AI) -> 0
A96: BBG006Q42QL6 | B96: Instrument | C96: MA0000011512 | D96: 0.7279 | E96: =SUMIF(Data!$E:$E,$C96,Data!$AI:$AI) -> 0 | I96: CVS | J96: CVS HEALTH CORP | K96: Aktien | L96: 0,21 | M96: 72,11 | N96: 700.345 | O96: 50.501.878 | P96: 50.501.877,95 | Q96: Gesundheitsversorgung | R96: US1266501006 | S96: New York Stock Exchange Inc. | T96: Vereinigte Staaten | U96: USD | V96: =SUMIF(Data!$E:$E,$I96,Data!$AI:$AI) -> 0
A97: BBG006Q42QL6 | B97: Instrument | C97: MA0000011793 | D97: 0.2256 | E97: =SUMIF(Data!$E:$E,$C97,Data!$AI:$AI) -> 0 | I97: MO | J97: ALTRIA GROUP INC | K97: Aktien | L97: 0,20 | M97: 50,22 | N97: 991.117 | O97: 49.773.896 | P97: 49.773.895,74 | Q97: Nichtzyklische Konsumgüter | R97: US02209S1033 | S97: New York Stock Exchange Inc. | T97: Vereinigte Staaten | U97: USD | V97: =SUMIF(Data!$E:$E,$I97,Data!$AI:$AI) -> 0
A98: BBG006Q42QL6 | B98: Instrument | C98: MA0000011801 | D98: 0.5214 | E98: =SUMIF(Data!$E:$E,$C98,Data!$AI:$AI) -> 0 | I98: AXP | J98: AMERICAN EXPRESS | K98: Aktien | L98: 0,20 | M98: 127,28 | N98: 390.112 | O98: 49.653.455 | P98: 49.653.455,36 | Q98: Financials | R98: US0258161092 | S98: New York Stock Exchange Inc. | T98: Vereinigte Staaten | U98: USD | V98: =SUMIF(Data!$E:$E,$I98,Data!$AI:$AI) -> 0
A99: BBG006Q42QL6 | B99: Instrument | C99: MA0000011819 | D99: 0.2494 | E99: =SUMIF(Data!$E:$E,$C99,Data!$AI:$AI) -> 0 | I99: BKNG | J99: BOOKING HOLDINGS INC | K99: Aktien | L99: 0,20 | M99: 2.086,90 | N99: 23.095 | O99: 48.196.956 | P99: 48.196.955,50 | Q99: Zyklische Konsumgüter | R99: US09857L1089 | S99: NASDAQ | T99: Vereinigte Staaten | U99: USD | V99: =SUMIF(Data!$E:$E,$I99,Data!$AI:$AI) -> 0
A100: BBG006Q42QL6 | B100: Instrument | C100: MA0000011835 | D100: 1.1346 | E100: =SUMIF(Data!$E:$E,$C100,Data!$AI:$AI) -> 0 | I100: AIR | J100: AIRBUS GROUP | K100: Aktien | L100: 0,19 | M100: 149,39 | N100: 314.201 | O100: 46.937.754 | P100: 46.937.754,36 | Q100: Industrie | R100: NL0000235190 | S100: Nyse Euronext - Euronext Paris | T100: Frankreich | U100: EUR | V100: =SUMIF(Data!$E:$E,$I100,Data!$AI:$AI) -> 0
...
